{
  "type": "Feature",
  "properties": {
    "iso:country":"CM",
    "name:ara_x_preferred":[
        "\u0628\u0648\u063a\u0648"
    ],
    "name:ben_x_preferred":[
        "\u09ac\u09c1\u0997\u09cb"
    ],
    "name:ceb_x_preferred":[
        "Bogo"
    ],
    "name:dan_x_preferred":[
        "Bog\u00f8"
    ],
    "name:deu_x_preferred":[
        "Bogo"
    ],
    "name:dut_x_preferred":[
        "Bogo"
    ],
    "name:eng_x_preferred":[
        "Bogo"
    ],
    "name:fin_x_preferred":[
        "Bogo"
    ],
    "name:fra_x_preferred":[
        "Bogo"
    ],
    "name:fre_x_preferred":[
        "Bogo"
    ],
    "name:gre_x_preferred":[
        "\u039c\u03c0\u03cc\u03b3\u03ba\u03bf"
    ],
    "name:guj_x_preferred":[
        "\u0aac\u0acb\u0a97\u0acb"
    ],
    "name:hin_x_preferred":[
        "\u092c\u094b\u0917\u094b"
    ],
    "name:ind_x_preferred":[
        "Bogo"
    ],
    "name:ita_x_preferred":[
        "Bogo"
    ],
    "name:jpn_x_preferred":[
        "\u30dc\u30b4"
    ],
    "name:kan_x_preferred":[
        "\u0cac\u0cca\u0c97\u0ccb"
    ],
    "name:kor_x_preferred":[
        "\ubcf4\uace0"
    ],
    "name:lav_x_preferred":[
        "Boga"
    ],
    "name:lit_x_preferred":[
        "Bogas"
    ],
    "name:mar_x_preferred":[
        "\u092c\u094b\u0917\u094b"
    ],
    "name:may_x_preferred":[
        "Bogo"
    ],
    "name:nan_x_preferred":[
        "Bogo"
    ],
    "name:nld_x_preferred":[
        "Bogo"
    ],
    "name:nob_x_preferred":[
        "Bogo"
    ],
    "name:pol_x_preferred":[
        "Bogo"
    ],
    "name:por_x_preferred":[
        "Bogo"
    ],
    "name:rus_x_preferred":[
        "\u0411\u043e\u0433\u043e"
    ],
    "name:sin_x_preferred":[
        "\u0db6\u0ddc\u0d9c\u0ddd"
    ],
    "name:spa_x_preferred":[
        "Bogo"
    ],
    "name:swe_x_preferred":[
        "Bogo"
    ],
    "name:tam_x_preferred":[
        "\u0baa\u0bcb\u0b95\u0bcb"
    ],
    "name:tel_x_preferred":[
        "\u0c2c\u0c3e\u0c17\u0c4b"
    ],
    "name:tha_x_preferred":[
        "\u0e42\u0e1a\u0e01\u0e2d\u0e23\u0e4c"
    ],
    "name:tur_x_preferred":[
        "Bogo"
    ],
    "name:ukr_x_preferred":[
        "\u0411\u043e\u0433\u043e"
    ],
    "name:urd_x_preferred":[
        "\u0628\u0648\u062c\u0648"
    ],
    "name:vie_x_preferred":[
        "Bogo"
    ],
    "qs:gn_country":"CM",
    "qs:gn_fcode":"PPL",
    "qs:gn_pop":16952,
    "qs:name":"Bogo",
    "qs:name_adm0":"Cameroun",
    "qs:name_adm1":"Extreme-Nord",
    "qs:photos":0,
    "qs:photos_1k":0,
    "qs:photos_9k":1,
    "qs:photos_9r":1,
    "qs:photos_all":1,
    "qs:photos_sr":0,
    "qs:placetype":"Town",
    "qs:pop_sr":"6",
    "qs:woe_adm0":23424785,
    "wd:wordcount":80,
    "wof:name":"Bogo",
    "wof:placetype":"locality",
    "wof:population":16952
},
  "geometry": {"coordinates":[14.60928,10.7336],"type":"Point"}
}