{
  "type": "Feature",
  "properties": {
    "gn:admin1_code":"13.0",
    "gn:asciiname":"Ndogon",
    "gn:country_code":"CM",
    "gn:dem":596,
    "gn:feature_class":"P",
    "gn:feature_code":"PPL",
    "gn:name":"Ndogon",
    "gn:population":0,
    "gn:timezone":"Africa/Douala",
    "iso:country":"CM",
    "wof:name":"Ndogon",
    "wof:placetype":"locality"
},
  "geometry": {"coordinates":[14.35,8.05],"type":"Point"}
}