{
  "type": "Feature",
  "properties": {
    "gn:admin1_code":"9.0",
    "gn:asciiname":"Ayukaba",
    "gn:country_code":"CM",
    "gn:dem":74,
    "gn:feature_class":"P",
    "gn:feature_code":"PPL",
    "gn:name":"Ayukaba",
    "gn:population":0,
    "gn:timezone":"Africa/Douala",
    "iso:country":"CM",
    "wof:name":"Ayukaba",
    "wof:placetype":"locality"
},
  "geometry": {"coordinates":[9.1441,5.707],"type":"Point"}
}