{
  "type": "Feature",
  "properties": {
    "gn:admin1_code":"11.0",
    "gn:asciiname":"Ekoum Douma",
    "gn:country_code":"CM",
    "gn:dem":646,
    "gn:feature_class":"P",
    "gn:feature_code":"PPL",
    "gn:name":"Ekoum Douma",
    "gn:population":0,
    "gn:timezone":"Africa/Douala",
    "iso:country":"CM",
    "wof:name":"Ekoum Douma",
    "wof:placetype":"locality"
},
  "geometry": {"coordinates":[12.03333,4.15],"type":"Point"}
}