{
  "type": "Feature",
  "properties": {
    "gn:admin1_code":"7.0",
    "gn:asciiname":"Abonse",
    "gn:country_code":"CM",
    "gn:dem":465,
    "gn:feature_class":"P",
    "gn:feature_code":"PPL",
    "gn:name":"Abonse",
    "gn:population":0,
    "gn:timezone":"Africa/Douala",
    "iso:country":"CM",
    "name:und_x_variant":[
        "Abunshie",
        "Abonshe",
        "Abonse"
    ],
    "wof:name":"Abonse",
    "wof:placetype":"locality"
},
  "geometry": {"coordinates":[10.75,6.88333],"type":"Point"}
}