{
  "type": "Feature",
  "properties": {
    "gn:admin1_code":"12.0",
    "gn:asciiname":"Djoum-Djoum",
    "gn:country_code":"CM",
    "gn:dem":617,
    "gn:feature_class":"P",
    "gn:feature_code":"PPL",
    "gn:name":"Djoum-Djoum",
    "gn:population":0,
    "gn:timezone":"Africa/Douala",
    "iso:country":"CM",
    "name:und_x_variant":[
        "Dzoum Dzoum",
        "Djoum-Djoum"
    ],
    "wof:name":"Djoum-Djoum",
    "wof:placetype":"locality"
},
  "geometry": {"coordinates":[13.78506,10.3065],"type":"Point"}
}