{
  "type": "Feature",
  "properties": {
    "gn:admin1_code":"10.0",
    "gn:asciiname":"Samaki",
    "gn:country_code":"CM",
    "gn:dem":1048,
    "gn:feature_class":"P",
    "gn:feature_code":"PPL",
    "gn:name":"Samaki",
    "gn:population":0,
    "gn:timezone":"Africa/Douala",
    "iso:country":"CM",
    "wof:name":"Samaki",
    "wof:placetype":"locality"
},
  "geometry": {"coordinates":[14.15,6.46667],"type":"Point"}
}