{
  "type": "Feature",
  "properties": {
    "gn:admin1_code":"12.0",
    "gn:asciiname":"Djola",
    "gn:country_code":"CM",
    "gn:dem":384,
    "gn:feature_class":"P",
    "gn:feature_code":"PPL",
    "gn:name":"Djola",
    "gn:population":0,
    "gn:timezone":"Africa/Douala",
    "iso:country":"CM",
    "wof:name":"Djola",
    "wof:placetype":"locality"
},
  "geometry": {"coordinates":[14.40489,10.60579],"type":"Point"}
}