{
  "type": "Feature",
  "properties": {
    "gn:admin1_code":"12.0",
    "gn:asciiname":"Guidprat",
    "gn:country_code":"CM",
    "gn:dem":1053,
    "gn:feature_class":"P",
    "gn:feature_code":"PPL",
    "gn:name":"Guidprat",
    "gn:population":0,
    "gn:timezone":"Africa/Douala",
    "iso:country":"CM",
    "wof:name":"Guidprat",
    "wof:placetype":"locality"
},
  "geometry": {"coordinates":[13.81728,10.81227],"type":"Point"}
}