{
  "type": "Feature",
  "properties": {
    "gn:admin1_code":"13.0",
    "gn:asciiname":"Kona",
    "gn:country_code":"CM",
    "gn:dem":347,
    "gn:feature_class":"P",
    "gn:feature_code":"PPL",
    "gn:name":"Kona",
    "gn:population":0,
    "gn:timezone":"Africa/Douala",
    "iso:country":"CM",
    "wof:name":"Kona",
    "wof:placetype":"locality"
},
  "geometry": {"coordinates":[13.84726,9.80568],"type":"Point"}
}