{
  "type": "Feature",
  "properties": {
    "gn:admin1_code":"12.0",
    "gn:asciiname":"Mogoumaz",
    "gn:country_code":"CM",
    "gn:dem":868,
    "gn:feature_class":"P",
    "gn:feature_code":"PPL",
    "gn:name":"Mogoumaz",
    "gn:population":0,
    "gn:timezone":"Africa/Douala",
    "iso:country":"CM",
    "name:und_x_variant":[
        "Magouma",
        "Mogoumaz"
    ],
    "wof:name":"Mogoumaz",
    "wof:placetype":"locality"
},
  "geometry": {"coordinates":[13.76239,10.82099],"type":"Point"}
}