{
  "type": "Feature",
  "properties": {
    "gn:admin1_code":"13.0",
    "gn:asciiname":"Gonhe",
    "gn:country_code":"CM",
    "gn:dem":544,
    "gn:feature_class":"P",
    "gn:feature_code":"PPL",
    "gn:name":"Gonh\u00e9",
    "gn:population":0,
    "gn:timezone":"Africa/Douala",
    "iso:country":"CM",
    "wof:name":"Gonhe",
    "wof:placetype":"locality"
},
  "geometry": {"coordinates":[15.4495,7.4689],"type":"Point"}
}