{
  "type": "Feature",
  "properties": {
    "gn:admin1_code":"13.0",
    "gn:asciiname":"Lougahori",
    "gn:country_code":"CM",
    "gn:dem":288,
    "gn:feature_class":"P",
    "gn:feature_code":"PPL",
    "gn:name":"Lougahori",
    "gn:population":0,
    "gn:timezone":"Africa/Douala",
    "iso:country":"CM",
    "name:und_x_variant":[
        "Louggahori"
    ],
    "wof:name":"Lougahori",
    "wof:placetype":"locality"
},
  "geometry": {"coordinates":[13.258,9.45406],"type":"Point"}
}