{
  "type": "Feature",
  "properties": {
    "gn:admin1_code":"11.0",
    "gn:asciiname":"Nkolakono II",
    "gn:country_code":"CM",
    "gn:dem":669,
    "gn:feature_class":"P",
    "gn:feature_code":"PPL",
    "gn:name":"Nkolakono II",
    "gn:population":0,
    "gn:timezone":"Africa/Douala",
    "iso:country":"CM",
    "wof:name":"Nkolakono II",
    "wof:placetype":"locality"
},
  "geometry": {"coordinates":[11.31667,3.51667],"type":"Point"}
}