{
  "type": "Feature",
  "properties": {
    "gn:admin1_code":"11.0",
    "gn:asciiname":"Nkolekotking",
    "gn:country_code":"CM",
    "gn:dem":525,
    "gn:feature_class":"P",
    "gn:feature_code":"PPL",
    "gn:name":"Nkol\u00e9kotking",
    "gn:population":0,
    "gn:timezone":"Africa/Douala",
    "iso:country":"CM",
    "wof:name":"Nkolekotking",
    "wof:placetype":"locality"
},
  "geometry": {"coordinates":[11.16667,4.06667],"type":"Point"}
}