{
  "type": "Feature",
  "properties": {
    "gn:admin1_code":"9.0",
    "gn:asciiname":"Beka",
    "gn:country_code":"CM",
    "gn:dem":251,
    "gn:feature_class":"P",
    "gn:feature_code":"PPL",
    "gn:name":"Beka",
    "gn:population":0,
    "gn:timezone":"Africa/Douala",
    "iso:country":"CM",
    "name:bos_x_preferred":[
        "Beka"
    ],
    "name:ceb_x_preferred":[
        "Beka"
    ],
    "name:fra_x_preferred":[
        "Beka"
    ],
    "name:heb_x_preferred":[
        "\u05d1\u05e7\u05e2"
    ],
    "name:ind_x_preferred":[
        "Beka"
    ],
    "name:lav_x_preferred":[
        "Beka"
    ],
    "name:nld_x_preferred":[
        "Beka"
    ],
    "name:pol_x_preferred":[
        "Beka"
    ],
    "name:slk_x_preferred":[
        "Beka"
    ],
    "name:slv_x_preferred":[
        "Beka"
    ],
    "name:spa_x_preferred":[
        "Beka"
    ],
    "name:swe_x_preferred":[
        "Beka"
    ],
    "wof:name":"Beka",
    "wof:placetype":"locality"
},
  "geometry": {"coordinates":[9.703,5.3643],"type":"Point"}
}