{
  "type": "Feature",
  "properties": {
    "gn:admin1_code":"9.0",
    "gn:asciiname":"Beka",
    "gn:country_code":"CM",
    "gn:dem":251,
    "gn:feature_class":"P",
    "gn:feature_code":"PPL",
    "gn:name":"Beka",
    "gn:population":0,
    "gn:timezone":"Africa/Douala",
    "iso:country":"CM",
    "wof:name":"Beka",
    "wof:placetype":"locality"
},
  "geometry": {"coordinates":[9.703,5.3643],"type":"Point"}
}