{
  "type": "Feature",
  "properties": {
    "gn:admin1_code":"11.0",
    "gn:asciiname":"Mengonde",
    "gn:country_code":"CM",
    "gn:dem":570,
    "gn:feature_class":"P",
    "gn:feature_code":"PPL",
    "gn:name":"Mengond\u00e9",
    "gn:population":0,
    "gn:timezone":"Africa/Douala",
    "iso:country":"CM",
    "wof:name":"Mengonde",
    "wof:placetype":"locality"
},
  "geometry": {"coordinates":[12.08333,4.53333],"type":"Point"}
}