{
  "type": "Feature",
  "properties": {
    "gn:admin1_code":"7.0",
    "gn:asciiname":"Koubokam",
    "gn:country_code":"CM",
    "gn:dem":1385,
    "gn:feature_class":"P",
    "gn:feature_code":"PPL",
    "gn:name":"Koubokam",
    "gn:population":0,
    "gn:timezone":"Africa/Douala",
    "iso:country":"CM",
    "name:und_x_variant":[
        "K\u00fabokam",
        "Koubokam"
    ],
    "wof:name":"Koubokam",
    "wof:placetype":"locality"
},
  "geometry": {"coordinates":[10.68333,6.05],"type":"Point"}
}