{
  "type": "Feature",
  "properties": {
    "gn:admin1_code":"12.0",
    "gn:asciiname":"Mokoujek",
    "gn:country_code":"CM",
    "gn:dem":802,
    "gn:feature_class":"P",
    "gn:feature_code":"PPL",
    "gn:name":"Mokoujek",
    "gn:population":0,
    "gn:timezone":"Africa/Douala",
    "iso:country":"CM",
    "wof:name":"Mokoujek",
    "wof:placetype":"locality"
},
  "geometry": {"coordinates":[14.07373,10.7341],"type":"Point"}
}