{
  "type": "Feature",
  "properties": {
    "gn:admin1_code":"13.0",
    "gn:asciiname":"Homa Hamassioto",
    "gn:country_code":"CM",
    "gn:dem":236,
    "gn:feature_class":"P",
    "gn:feature_code":"PPL",
    "gn:name":"Homa Hamassioto",
    "gn:population":0,
    "gn:timezone":"Africa/Douala",
    "iso:country":"CM",
    "wof:name":"Homa Hamassioto",
    "wof:placetype":"locality"
},
  "geometry": {"coordinates":[13.91667,9.03508],"type":"Point"}
}