{
  "type": "Feature",
  "properties": {
    "gn:admin1_code":"11.0",
    "gn:asciiname":"Koudoukomo",
    "gn:country_code":"CM",
    "gn:dem":704,
    "gn:feature_class":"P",
    "gn:feature_code":"PPL",
    "gn:name":"Koudoukomo",
    "gn:population":0,
    "gn:timezone":"Africa/Douala",
    "iso:country":"CM",
    "wof:name":"Koudoukomo",
    "wof:placetype":"locality"
},
  "geometry": {"coordinates":[12.06667,3.55],"type":"Point"}
}