{
  "type": "Feature",
  "properties": {
    "gn:admin1_code":"12.0",
    "gn:asciiname":"Kantchouloum",
    "gn:country_code":"CM",
    "gn:dem":368,
    "gn:feature_class":"P",
    "gn:feature_code":"PPL",
    "gn:name":"Kantchouloum",
    "gn:population":0,
    "gn:timezone":"Africa/Douala",
    "iso:country":"CM",
    "wof:name":"Kantchouloum",
    "wof:placetype":"locality"
},
  "geometry": {"coordinates":[13.9423,11.2087],"type":"Point"}
}