{
  "type": "Feature",
  "properties": {
    "gn:admin1_code":"12.0",
    "gn:asciiname":"Louba Louba",
    "gn:country_code":"CM",
    "gn:dem":318,
    "gn:feature_class":"P",
    "gn:feature_code":"PPL",
    "gn:name":"Louba Louba",
    "gn:population":0,
    "gn:timezone":"Africa/Douala",
    "iso:country":"CM",
    "wof:name":"Louba Louba",
    "wof:placetype":"locality"
},
  "geometry": {"coordinates":[14.65706,10.95192],"type":"Point"}
}