{
  "type": "Feature",
  "properties": {
    "gn:admin1_code":"8.0",
    "gn:asciiname":"Bangou",
    "gn:country_code":"CM",
    "gn:dem":1838,
    "gn:feature_class":"P",
    "gn:feature_code":"PPL",
    "gn:name":"Bangou",
    "gn:population":0,
    "gn:timezone":"Africa/Douala",
    "iso:country":"CM",
    "name:eng_x_preferred":[
        "Bangou"
    ],
    "wof:name":"Bangou",
    "wof:placetype":"locality"
},
  "geometry": {"coordinates":[10.39563,5.24998],"type":"Point"}
}