{
  "type": "Feature",
  "properties": {
    "gn:admin1_code":"9.0",
    "gn:asciiname":"Bambe",
    "gn:country_code":"CM",
    "gn:dem":546,
    "gn:feature_class":"P",
    "gn:feature_code":"PPL",
    "gn:name":"Bambe",
    "gn:population":0,
    "gn:timezone":"Africa/Douala",
    "iso:country":"CM",
    "wof:name":"Bambe",
    "wof:placetype":"locality"
},
  "geometry": {"coordinates":[9.6325,5.2038],"type":"Point"}
}