{
  "type": "Feature",
  "properties": {
    "gn:admin1_code":"4.0",
    "gn:asciiname":"Lila",
    "gn:country_code":"CM",
    "gn:dem":584,
    "gn:feature_class":"P",
    "gn:feature_code":"PPL",
    "gn:name":"Lila",
    "gn:population":0,
    "gn:timezone":"Africa/Douala",
    "iso:country":"CM",
    "name:bos_x_preferred":[
        "Lila"
    ],
    "name:ceb_x_preferred":[
        "Lila"
    ],
    "name:deu_x_preferred":[
        "Lila"
    ],
    "name:fra_x_preferred":[
        "Lila"
    ],
    "name:glg_x_preferred":[
        "Lila"
    ],
    "name:heb_x_preferred":[
        "\u05dc\u05d9\u05dc\u05d4"
    ],
    "name:ita_x_preferred":[
        "Lila"
    ],
    "name:nld_x_preferred":[
        "Lila"
    ],
    "name:pol_x_preferred":[
        "Lila"
    ],
    "name:por_x_preferred":[
        "Lila"
    ],
    "name:rus_x_preferred":[
        "\u041b\u0438\u043b\u0430"
    ],
    "name:spa_x_preferred":[
        "Lila"
    ],
    "name:srp_x_preferred":[
        "\u041b\u0438\u043b\u0430"
    ],
    "name:swe_x_preferred":[
        "Lila"
    ],
    "name:ukr_x_preferred":[
        "\u041b\u0456\u043b\u0430"
    ],
    "wof:name":"Lila",
    "wof:placetype":"locality"
},
  "geometry": {"coordinates":[14.46667,4.13333],"type":"Point"}
}