{
  "type": "Feature",
  "properties": {
    "gn:admin1_code":"4.0",
    "gn:asciiname":"Lila",
    "gn:country_code":"CM",
    "gn:dem":584,
    "gn:feature_class":"P",
    "gn:feature_code":"PPL",
    "gn:name":"Lila",
    "gn:population":0,
    "gn:timezone":"Africa/Douala",
    "iso:country":"CM",
    "wof:name":"Lila",
    "wof:placetype":"locality"
},
  "geometry": {"coordinates":[14.46667,4.13333],"type":"Point"}
}