{
  "type": "Feature",
  "properties": {
    "gn:admin1_code":"12.0",
    "gn:asciiname":"Bougay",
    "gn:country_code":"CM",
    "gn:dem":336,
    "gn:feature_class":"P",
    "gn:feature_code":"PPL",
    "gn:name":"Bougay",
    "gn:population":0,
    "gn:timezone":"Africa/Douala",
    "iso:country":"CM",
    "name:und_x_variant":[
        "Bougaye",
        "Bougay"
    ],
    "wof:name":"Bougay",
    "wof:placetype":"locality"
},
  "geometry": {"coordinates":[15.11022,10.25645],"type":"Point"}
}