{
  "type": "Feature",
  "properties": {
    "gn:admin1_code":"11.0",
    "gn:asciiname":"Songwi",
    "gn:country_code":"CM",
    "gn:dem":918,
    "gn:feature_class":"P",
    "gn:feature_code":"PPL",
    "gn:name":"Songwi",
    "gn:population":0,
    "gn:timezone":"Africa/Douala",
    "iso:country":"CM",
    "wof:name":"Songwi",
    "wof:placetype":"locality"
},
  "geometry": {"coordinates":[12.25,5.85],"type":"Point"}
}