{
  "type": "Feature",
  "properties": {
    "gn:admin1_code":"14.0",
    "gn:asciiname":"Inguiridjang",
    "gn:country_code":"CM",
    "gn:dem":531,
    "gn:feature_class":"P",
    "gn:feature_code":"PPL",
    "gn:name":"Inguiridjang",
    "gn:population":0,
    "gn:timezone":"Africa/Douala",
    "iso:country":"CM",
    "wof:name":"Inguiridjang",
    "wof:placetype":"locality"
},
  "geometry": {"coordinates":[10.66667,2.35],"type":"Point"}
}