{
  "type": "Feature",
  "properties": {
    "gn:admin1_code":"12.0",
    "gn:asciiname":"Krenak Chia",
    "gn:country_code":"CM",
    "gn:dem":287,
    "gn:feature_class":"P",
    "gn:feature_code":"PPL",
    "gn:name":"Krenak Chia",
    "gn:population":0,
    "gn:timezone":"Africa/Douala",
    "iso:country":"CM",
    "name:und_x_variant":[
        "Krenak I",
        "Krenak Chia"
    ],
    "wof:name":"Krenak Chia",
    "wof:placetype":"locality"
},
  "geometry": {"coordinates":[14.56828,12.58445],"type":"Point"}
}