{
  "type": "Feature",
  "properties": {
    "gn:admin1_code":"13.0",
    "gn:asciiname":"Giding",
    "gn:country_code":"CM",
    "gn:dem":300,
    "gn:feature_class":"P",
    "gn:feature_code":"PPL",
    "gn:name":"Giding",
    "gn:population":0,
    "gn:timezone":"Africa/Douala",
    "iso:country":"CM",
    "wof:name":"Giding",
    "wof:placetype":"locality"
},
  "geometry": {"coordinates":[13.01865,8.64077],"type":"Point"}
}