{
  "type": "Feature",
  "properties": {
    "gn:admin1_code":"9.0",
    "gn:asciiname":"Diombe",
    "gn:country_code":"CM",
    "gn:dem":5,
    "gn:feature_class":"P",
    "gn:feature_code":"PPL",
    "gn:name":"Diombe",
    "gn:population":0,
    "gn:timezone":"Africa/Douala",
    "iso:country":"CM",
    "wof:name":"Diombe",
    "wof:placetype":"locality"
},
  "geometry": {"coordinates":[8.7303,4.6737],"type":"Point"}
}