{
  "type": "Feature",
  "properties": {
    "gn:admin1_code":"7.0",
    "gn:asciiname":"Bamtem Manjane",
    "gn:country_code":"CM",
    "gn:dem":1543,
    "gn:feature_class":"P",
    "gn:feature_code":"PPL",
    "gn:name":"Bamtem Manjan\u00e9",
    "gn:population":0,
    "gn:timezone":"Africa/Douala",
    "iso:country":"CM",
    "wof:name":"Bamtem Manjane",
    "wof:placetype":"locality"
},
  "geometry": {"coordinates":[10.25938,5.83481],"type":"Point"}
}