{
  "type": "Feature",
  "properties": {
    "gn:admin1_code":"5.0",
    "gn:asciiname":"Nlongo",
    "gn:country_code":"CM",
    "gn:dem":814,
    "gn:feature_class":"P",
    "gn:feature_code":"PPL",
    "gn:name":"Nlongo",
    "gn:population":0,
    "gn:timezone":"Africa/Douala",
    "iso:country":"CM",
    "wof:name":"Nlongo",
    "wof:placetype":"locality"
},
  "geometry": {"coordinates":[9.93333,4.95],"type":"Point"}
}