{
  "type": "Feature",
  "properties": {
    "gn:admin1_code":"12.0",
    "gn:asciiname":"Golomba",
    "gn:country_code":"CM",
    "gn:dem":667,
    "gn:feature_class":"P",
    "gn:feature_code":"PPL",
    "gn:name":"Golomba",
    "gn:population":0,
    "gn:timezone":"Africa/Douala",
    "iso:country":"CM",
    "wof:name":"Golomba",
    "wof:placetype":"locality"
},
  "geometry": {"coordinates":[13.97396,10.76335],"type":"Point"}
}