{
  "type": "Feature",
  "properties": {
    "gn:admin1_code":"4.0",
    "gn:asciiname":"Mbelebina",
    "gn:country_code":"CM",
    "gn:dem":822,
    "gn:feature_class":"P",
    "gn:feature_code":"PPL",
    "gn:name":"Mb\u00e9l\u00e9bina",
    "gn:population":0,
    "gn:timezone":"Africa/Douala",
    "iso:country":"CM",
    "wof:name":"Mbelebina",
    "wof:placetype":"locality"
},
  "geometry": {"coordinates":[14.53333,5.15],"type":"Point"}
}