{
  "type": "Feature",
  "properties": {
    "gn:admin1_code":"8.0",
    "gn:asciiname":"Famtoum",
    "gn:country_code":"CM",
    "gn:dem":1418,
    "gn:feature_class":"P",
    "gn:feature_code":"PPL",
    "gn:name":"Famtoum",
    "gn:population":0,
    "gn:timezone":"Africa/Douala",
    "iso:country":"CM",
    "name:fra_x_preferred":[
        "Famtoum"
    ],
    "wof:name":"Famtoum",
    "wof:placetype":"locality"
},
  "geometry": {"coordinates":[10.48481,5.30615],"type":"Point"}
}