{
  "type": "Feature",
  "properties": {
    "gn:admin1_code":"8.0",
    "gn:asciiname":"Ho",
    "gn:country_code":"CM",
    "gn:dem":1681,
    "gn:feature_class":"P",
    "gn:feature_code":"PPL",
    "gn:name":"Ho",
    "gn:population":0,
    "gn:timezone":"Africa/Douala",
    "iso:country":"CM",
    "name:hun_x_preferred":[
        "Ho"
    ],
    "name:ind_x_preferred":[
        "Ho"
    ],
    "name:spa_x_preferred":[
        "Ho"
    ],
    "name:vie_x_preferred":[
        "Ho"
    ],
    "wof:name":"Ho",
    "wof:placetype":"locality"
},
  "geometry": {"coordinates":[10.36745,5.30332],"type":"Point"}
}