{
  "type": "Feature",
  "properties": {
    "gn:admin1_code":"13.0",
    "gn:asciiname":"Tapawa",
    "gn:country_code":"CM",
    "gn:dem":403,
    "gn:feature_class":"P",
    "gn:feature_code":"PPL",
    "gn:name":"Tapawa",
    "gn:population":0,
    "gn:timezone":"Africa/Douala",
    "iso:country":"CM",
    "wof:name":"Tapawa",
    "wof:placetype":"locality"
},
  "geometry": {"coordinates":[13.47129,9.68036],"type":"Point"}
}