{
  "type": "Feature",
  "properties": {
    "gn:admin1_code":"13.0",
    "gn:asciiname":"Nibango",
    "gn:country_code":"CM",
    "gn:dem":205,
    "gn:feature_class":"P",
    "gn:feature_code":"PPL",
    "gn:name":"Nibango",
    "gn:population":0,
    "gn:timezone":"Africa/Douala",
    "iso:country":"CM",
    "wof:name":"Nibango",
    "wof:placetype":"locality"
},
  "geometry": {"coordinates":[13.51426,9.30504],"type":"Point"}
}