{
  "type": "Feature",
  "properties": {
    "gn:admin1_code":"12.0",
    "gn:asciiname":"Douelou",
    "gn:country_code":"CM",
    "gn:dem":293,
    "gn:feature_class":"P",
    "gn:feature_code":"PPL",
    "gn:name":"Dou\u00e9lou",
    "gn:population":0,
    "gn:timezone":"Africa/Douala",
    "iso:country":"CM",
    "name:und_x_variant":[
        "B\u00e9dehr",
        "Oueilonaga",
        "Dou\u00e9lou"
    ],
    "wof:name":"Douelou",
    "wof:placetype":"locality"
},
  "geometry": {"coordinates":[14.6114,12.65659],"type":"Point"}
}