{
  "type": "Feature",
  "properties": {
    "gn:admin1_code":"11.0",
    "gn:asciiname":"Onyie",
    "gn:country_code":"CM",
    "gn:dem":680,
    "gn:feature_class":"P",
    "gn:feature_code":"PPL",
    "gn:name":"Onyi\u00e9",
    "gn:population":0,
    "gn:timezone":"Africa/Douala",
    "iso:country":"CM",
    "wof:name":"Onyie",
    "wof:placetype":"locality"
},
  "geometry": {"coordinates":[11.75,3.63333],"type":"Point"}
}