{
  "type": "Feature",
  "properties": {
    "gn:admin1_code":"12.0",
    "gn:asciiname":"Roumgoji",
    "gn:country_code":"CM",
    "gn:dem":602,
    "gn:feature_class":"P",
    "gn:feature_code":"PPL",
    "gn:name":"Roumgoji",
    "gn:population":0,
    "gn:timezone":"Africa/Douala",
    "iso:country":"CM",
    "wof:name":"Roumgoji",
    "wof:placetype":"locality"
},
  "geometry": {"coordinates":[13.77299,10.48259],"type":"Point"}
}