{
  "type": "Feature",
  "properties": {
    "gn:admin1_code":"13.0",
    "gn:asciiname":"Lakawar",
    "gn:country_code":"CM",
    "gn:dem":413,
    "gn:feature_class":"P",
    "gn:feature_code":"PPL",
    "gn:name":"Lakawar",
    "gn:population":0,
    "gn:timezone":"Africa/Douala",
    "iso:country":"CM",
    "name:und_x_variant":[
        "Lakaor",
        "Lakawar"
    ],
    "wof:name":"Lakawar",
    "wof:placetype":"locality"
},
  "geometry": {"coordinates":[13.88333,10.05],"type":"Point"}
}