{
  "type": "Feature",
  "properties": {
    "gn:admin1_code":"12.0",
    "gn:asciiname":"Hola Danou",
    "gn:country_code":"CM",
    "gn:dem":352,
    "gn:feature_class":"P",
    "gn:feature_code":"PPL",
    "gn:name":"Hola Danou",
    "gn:population":0,
    "gn:timezone":"Africa/Douala",
    "iso:country":"CM",
    "wof:name":"Hola Danou",
    "wof:placetype":"locality"
},
  "geometry": {"coordinates":[14.45,10.81667],"type":"Point"}
}