{
  "type": "Feature",
  "properties": {
    "gn:admin1_code":"12.0",
    "gn:asciiname":"Boussaya",
    "gn:country_code":"CM",
    "gn:dem":288,
    "gn:feature_class":"P",
    "gn:feature_code":"PPL",
    "gn:name":"Boussaya",
    "gn:population":0,
    "gn:timezone":"Africa/Douala",
    "iso:country":"CM",
    "name:und_x_variant":[
        "Bousaya"
    ],
    "wof:name":"Boussaya",
    "wof:placetype":"locality"
},
  "geometry": {"coordinates":[14.35703,12.72116],"type":"Point"}
}