{
  "type": "Feature",
  "properties": {
    "gn:admin1_code":"11.0",
    "gn:asciiname":"Biamo",
    "gn:country_code":"CM",
    "gn:dem":479,
    "gn:feature_class":"P",
    "gn:feature_code":"PPL",
    "gn:name":"Biamo",
    "gn:population":0,
    "gn:timezone":"Africa/Douala",
    "iso:country":"CM",
    "wof:name":"Biamo",
    "wof:placetype":"locality"
},
  "geometry": {"coordinates":[11.21667,4.76667],"type":"Point"}
}