{
  "type": "Feature",
  "properties": {
    "gn:admin1_code":"12.0",
    "gn:asciiname":"Golongreon",
    "gn:country_code":"CM",
    "gn:dem":346,
    "gn:feature_class":"P",
    "gn:feature_code":"PPL",
    "gn:name":"Golongreon",
    "gn:population":0,
    "gn:timezone":"Africa/Douala",
    "iso:country":"CM",
    "wof:name":"Golongreon",
    "wof:placetype":"locality"
},
  "geometry": {"coordinates":[14.79259,10.24737],"type":"Point"}
}