{
  "type": "Feature",
  "properties": {
    "gn:admin1_code":"12.0",
    "gn:asciiname":"Wagza",
    "gn:country_code":"CM",
    "gn:dem":480,
    "gn:feature_class":"P",
    "gn:feature_code":"PPL",
    "gn:name":"Wagza",
    "gn:population":0,
    "gn:timezone":"Africa/Douala",
    "iso:country":"CM",
    "wof:name":"Wagza",
    "wof:placetype":"locality"
},
  "geometry": {"coordinates":[13.97157,10.94869],"type":"Point"}
}