{
  "type": "Feature",
  "properties": {
    "gn:admin1_code":"12.0",
    "gn:asciiname":"Doh",
    "gn:country_code":"CM",
    "gn:dem":291,
    "gn:feature_class":"P",
    "gn:feature_code":"PPL",
    "gn:name":"Doh",
    "gn:population":0,
    "gn:timezone":"Africa/Douala",
    "iso:country":"CM",
    "name:und_x_variant":[
        "Biang Do"
    ],
    "wof:name":"Doh",
    "wof:placetype":"locality"
},
  "geometry": {"coordinates":[14.60884,12.56748],"type":"Point"}
}