{
  "type": "Feature",
  "properties": {
    "gn:admin1_code":"8.0",
    "gn:asciiname":"Bangang Fokam",
    "gn:country_code":"CM",
    "gn:dem":1440,
    "gn:feature_class":"P",
    "gn:feature_code":"PPL",
    "gn:name":"Bangang Fokam",
    "gn:population":0,
    "gn:timezone":"Africa/Douala",
    "iso:country":"CM",
    "name:fra_x_preferred":[
        "Bangang Fokam"
    ],
    "wof:name":"Bangang Fokam",
    "wof:placetype":"locality"
},
  "geometry": {"coordinates":[10.51554,5.25079],"type":"Point"}
}