{
  "type": "Feature",
  "properties": {
    "gn:admin1_code":"11.0",
    "gn:asciiname":"Meyete",
    "gn:country_code":"CM",
    "gn:dem":789,
    "gn:feature_class":"P",
    "gn:feature_code":"PPL",
    "gn:name":"Meyete",
    "gn:population":0,
    "gn:timezone":"Africa/Douala",
    "iso:country":"CM",
    "wof:name":"Meyete",
    "wof:placetype":"locality"
},
  "geometry": {"coordinates":[12.13333,4.18333],"type":"Point"}
}