{
  "type": "Feature",
  "properties": {
    "gn:admin1_code":"5.0",
    "gn:asciiname":"Ebone",
    "gn:country_code":"CM",
    "gn:dem":621,
    "gn:feature_class":"P",
    "gn:feature_code":"PPL",
    "gn:name":"Ebon\u00e9",
    "gn:population":0,
    "gn:timezone":"Africa/Douala",
    "iso:country":"CM",
    "name:und_x_variant":[
        "Ebon\u00e9"
    ],
    "wof:name":"Ebone",
    "wof:placetype":"locality"
},
  "geometry": {"coordinates":[9.8991,4.8775],"type":"Point"}
}