{
  "type": "Feature",
  "properties": {
    "iso:country":"CM",
    "name:ceb_x_preferred":[
        "Yagoua"
    ],
    "name:deu_x_preferred":[
        "Yagoua"
    ],
    "name:eng_x_preferred":[
        "Yagoua"
    ],
    "name:fra_x_preferred":[
        "Yagoua"
    ],
    "name:heb_x_preferred":[
        "\u05d9\u05d2\u05d5\u05d0\u05d4"
    ],
    "name:hrv_x_preferred":[
        "Yagoua"
    ],
    "name:ita_x_preferred":[
        "Yagoua"
    ],
    "name:jpn_x_preferred":[
        "\u30e4\u30fc\u30b0\u30a2"
    ],
    "name:msa_x_preferred":[
        "Yagoua"
    ],
    "name:nan_x_preferred":[
        "Yagoua"
    ],
    "name:nld_x_preferred":[
        "Yagoua"
    ],
    "name:pol_x_preferred":[
        "Yagoua"
    ],
    "name:por_x_preferred":[
        "Yagoua"
    ],
    "name:spa_x_preferred":[
        "Yagoua"
    ],
    "name:swe_x_preferred":[
        "Yagoua"
    ],
    "name:unk_x_variant":[
        "J\u00e1gua"
    ],
    "name:urd_x_preferred":[
        "\u06cc\u06af\u0648\u06c1"
    ],
    "name:zho_x_preferred":[
        "\u4e9e\u74dc"
    ],
    "qs:gn_country":"CM",
    "qs:gn_fcode":"PPL",
    "qs:gn_pop":80235,
    "qs:name":"Yagoua",
    "qs:name_adm0":"Cameroun",
    "qs:name_adm1":"Extreme-Nord",
    "qs:photos":10,
    "qs:photos_1k":2,
    "qs:photos_9k":1,
    "qs:photos_9r":1,
    "qs:photos_all":10,
    "qs:photos_sr":1,
    "qs:placetype":"Town",
    "qs:pop_sr":"8",
    "qs:woe_adm0":23424785,
    "wd:elevation":356.0,
    "wd:wordcount":23,
    "wof:name":"Yagoua",
    "wof:placetype":"locality",
    "wof:population":80235
},
  "geometry": {"coordinates":[15.23288,10.34107],"type":"Point"}
}