{
  "type": "Feature",
  "properties": {
    "gn:admin1_code":"14.0",
    "gn:asciiname":"Bikoula",
    "gn:country_code":"CM",
    "gn:dem":706,
    "gn:feature_class":"P",
    "gn:feature_code":"PPL",
    "gn:name":"Bikoula",
    "gn:population":0,
    "gn:timezone":"Africa/Douala",
    "iso:country":"CM",
    "wof:name":"Bikoula",
    "wof:placetype":"locality"
},
  "geometry": {"coordinates":[12.41667,2.81667],"type":"Point"}
}