{
  "type": "Feature",
  "properties": {
    "gn:admin1_code":"12.0",
    "gn:asciiname":"Kassay",
    "gn:country_code":"CM",
    "gn:dem":336,
    "gn:feature_class":"P",
    "gn:feature_code":"PPL",
    "gn:name":"Kassay",
    "gn:population":0,
    "gn:timezone":"Africa/Douala",
    "iso:country":"CM",
    "name:und_x_variant":[
        "Kassel",
        "Kasse\u00ef",
        "Kassay"
    ],
    "wof:name":"Kassay",
    "wof:placetype":"locality"
},
  "geometry": {"coordinates":[14.77432,10.51916],"type":"Point"}
}