{
  "type": "Feature",
  "properties": {
    "gn:admin1_code":"12.0",
    "gn:asciiname":"Sero Abou",
    "gn:country_code":"CM",
    "gn:dem":289,
    "gn:feature_class":"P",
    "gn:feature_code":"PPL",
    "gn:name":"S\u00e9ro Abou",
    "gn:population":0,
    "gn:timezone":"Africa/Douala",
    "iso:country":"CM",
    "wof:name":"Sero Abou",
    "wof:placetype":"locality"
},
  "geometry": {"coordinates":[14.63517,12.74711],"type":"Point"}
}