{
  "type": "Feature",
  "properties": {
    "iso:country":"CM",
    "name:ceb_x_preferred":[
        "Kael\u00e9"
    ],
    "name:deu_x_preferred":[
        "Ka\u00e9l\u00e9"
    ],
    "name:eng_x_preferred":[
        "Ka\u00e9l\u00e9"
    ],
    "name:fra_x_preferred":[
        "Ka\u00e9l\u00e9"
    ],
    "name:heb_x_preferred":[
        "\u05e7\u05d0\u05dc\u05d4"
    ],
    "name:ita_x_preferred":[
        "Ka\u00e9l\u00e9"
    ],
    "name:jpn_x_preferred":[
        "\u30ab\u30a8\u30ec"
    ],
    "name:msa_x_preferred":[
        "Ka\u00e9l\u00e9"
    ],
    "name:nan_x_preferred":[
        "Ka\u00e9l\u00e9"
    ],
    "name:nld_x_preferred":[
        "Ka\u00e9l\u00e9"
    ],
    "name:pol_x_preferred":[
        "Ka\u00e9l\u00e9"
    ],
    "name:por_x_preferred":[
        "Ka\u00e9l\u00e9"
    ],
    "name:ron_x_preferred":[
        "Ka\u00e9l\u00e9"
    ],
    "name:spa_x_preferred":[
        "Ka\u00e9l\u00e9"
    ],
    "name:swe_x_preferred":[
        "Kael\u00e9"
    ],
    "name:zho_x_preferred":[
        "\u5361\u57c3\u840a"
    ],
    "qs:gn_country":"CM",
    "qs:gn_fcode":"PPL",
    "qs:gn_pop":25199,
    "qs:name":"Ka\u00e9l\u00e9",
    "qs:name_adm0":"Cameroun",
    "qs:name_adm1":"Extreme-Nord",
    "qs:photos":0,
    "qs:photos_1k":0,
    "qs:photos_9k":1,
    "qs:photos_9r":1,
    "qs:photos_all":11,
    "qs:photos_sr":0,
    "qs:placetype":"Town",
    "qs:pop_sr":"7",
    "qs:woe_adm0":23424785,
    "wd:wordcount":127,
    "wof:name":"Ka\u00e9l\u00e9",
    "wof:placetype":"locality",
    "wof:population":25199
},
  "geometry": {"coordinates":[14.45083,10.10917],"type":"Point"}
}