{
  "type": "Feature",
  "properties": {
    "gn:admin1_code":"13.0",
    "gn:asciiname":"Gao",
    "gn:country_code":"CM",
    "gn:dem":594,
    "gn:feature_class":"P",
    "gn:feature_code":"PPL",
    "gn:name":"Gao",
    "gn:population":0,
    "gn:timezone":"Africa/Douala",
    "iso:country":"CM",
    "name:afr_x_preferred":[
        "Gao"
    ],
    "name:ara_x_preferred":[
        "\u062c\u0627\u0648"
    ],
    "name:azb_x_preferred":[
        "\u0642\u0627\u0626\u0648"
    ],
    "name:bam_x_preferred":[
        "Gao"
    ],
    "name:bos_x_preferred":[
        "Gao"
    ],
    "name:bre_x_preferred":[
        "Gao"
    ],
    "name:bul_x_preferred":[
        "\u0413\u0430\u043e"
    ],
    "name:cat_x_preferred":[
        "Gao"
    ],
    "name:ces_x_preferred":[
        "Gao"
    ],
    "name:deu_x_preferred":[
        "Gao"
    ],
    "name:ell_x_preferred":[
        "\u0393\u03ba\u03ac\u03bf"
    ],
    "name:epo_x_preferred":[
        "Gao"
    ],
    "name:est_x_preferred":[
        "Gao"
    ],
    "name:eus_x_preferred":[
        "Gao"
    ],
    "name:fas_x_preferred":[
        "\u06af\u0627\u0626\u0648"
    ],
    "name:fin_x_preferred":[
        "Gao"
    ],
    "name:fra_x_preferred":[
        "Gao"
    ],
    "name:frr_x_preferred":[
        "Gao"
    ],
    "name:heb_x_preferred":[
        "\u05d2\u05d0\u05d5"
    ],
    "name:hun_x_preferred":[
        "Gao"
    ],
    "name:ile_x_preferred":[
        "Gao"
    ],
    "name:ind_x_preferred":[
        "Gao"
    ],
    "name:ita_x_preferred":[
        "Gao"
    ],
    "name:jpn_x_preferred":[
        "\u30ac\u30aa"
    ],
    "name:kab_x_preferred":[
        "Gao"
    ],
    "name:kat_x_preferred":[
        "\u10d2\u10d0\u10dd"
    ],
    "name:lat_x_preferred":[
        "Gagos"
    ],
    "name:lit_x_preferred":[
        "Gao"
    ],
    "name:nld_x_preferred":[
        "Gao"
    ],
    "name:nno_x_preferred":[
        "Gao"
    ],
    "name:nor_x_preferred":[
        "Gao"
    ],
    "name:pol_x_preferred":[
        "Gao"
    ],
    "name:por_x_preferred":[
        "Gao"
    ],
    "name:ron_x_preferred":[
        "Gao"
    ],
    "name:rus_x_preferred":[
        "\u0413\u0430\u043e"
    ],
    "name:scn_x_preferred":[
        "Gao"
    ],
    "name:sco_x_preferred":[
        "Gao"
    ],
    "name:slk_x_preferred":[
        "Gao"
    ],
    "name:slv_x_preferred":[
        "Gao"
    ],
    "name:spa_x_preferred":[
        "Gao"
    ],
    "name:srp_x_preferred":[
        "\u0413\u0430\u043e"
    ],
    "name:swe_x_preferred":[
        "Gao"
    ],
    "name:tha_x_preferred":[
        "\u0e01\u0e32\u0e42\u0e2d"
    ],
    "name:tur_x_preferred":[
        "Gao"
    ],
    "name:ukr_x_preferred":[
        "\u0413\u0430\u043e"
    ],
    "name:urd_x_preferred":[
        "\u06af\u0627\u0648"
    ],
    "name:vie_x_preferred":[
        "Gao"
    ],
    "name:war_x_preferred":[
        "Gao"
    ],
    "name:yor_x_preferred":[
        "Gao"
    ],
    "wof:name":"Gao",
    "wof:placetype":"locality"
},
  "geometry": {"coordinates":[15.1574,7.5722],"type":"Point"}
}