{
  "type": "Feature",
  "properties": {
    "gn:admin1_code":"9.0",
    "gn:asciiname":"Ndoye",
    "gn:country_code":"CM",
    "gn:dem":767,
    "gn:feature_class":"P",
    "gn:feature_code":"PPL",
    "gn:name":"Ndoye",
    "gn:population":0,
    "gn:timezone":"Africa/Douala",
    "iso:country":"CM",
    "name:fra_x_preferred":[
        "Ndoye"
    ],
    "wof:name":"Ndoye",
    "wof:placetype":"locality"
},
  "geometry": {"coordinates":[9.1544,5.0703],"type":"Point"}
}