{
  "type": "Feature",
  "properties": {
    "gn:admin1_code":"8.0",
    "gn:asciiname":"Ntio",
    "gn:country_code":"CM",
    "gn:dem":1518,
    "gn:feature_class":"P",
    "gn:feature_code":"PPL",
    "gn:name":"Ntio",
    "gn:population":0,
    "gn:timezone":"Africa/Douala",
    "iso:country":"CM",
    "wof:name":"Ntio",
    "wof:placetype":"locality"
},
  "geometry": {"coordinates":[10.24086,5.54948],"type":"Point"}
}