{
  "type": "Feature",
  "properties": {
    "gn:admin1_code":"10.0",
    "gn:asciiname":"Maloum Goura",
    "gn:country_code":"CM",
    "gn:dem":997,
    "gn:feature_class":"P",
    "gn:feature_code":"PPL",
    "gn:name":"Maloum Goura",
    "gn:population":0,
    "gn:timezone":"Africa/Douala",
    "iso:country":"CM",
    "wof:name":"Maloum Goura",
    "wof:placetype":"locality"
},
  "geometry": {"coordinates":[12.11521,6.83866],"type":"Point"}
}