{
  "type": "Feature",
  "properties": {
    "gn:admin1_code":"8.0",
    "gn:asciiname":"Makong II",
    "gn:country_code":"CM",
    "gn:dem":1348,
    "gn:feature_class":"P",
    "gn:feature_code":"PPL",
    "gn:name":"Makong II",
    "gn:population":0,
    "gn:timezone":"Africa/Douala",
    "iso:country":"CM",
    "wof:name":"Makong II",
    "wof:placetype":"locality"
},
  "geometry": {"coordinates":[10.0269,5.44879],"type":"Point"}
}