{
  "type": "Feature",
  "properties": {
    "gn:admin1_code":"11.0",
    "gn:asciiname":"Nio",
    "gn:country_code":"CM",
    "gn:dem":568,
    "gn:feature_class":"P",
    "gn:feature_code":"PPL",
    "gn:name":"Nio",
    "gn:population":0,
    "gn:timezone":"Africa/Douala",
    "iso:country":"CM",
    "name:cat_x_preferred":[
        "Ni\u014d"
    ],
    "name:ces_x_preferred":[
        "Ni\u00f3"
    ],
    "name:epo_x_preferred":[
        "Nioo"
    ],
    "name:eus_x_preferred":[
        "Nio"
    ],
    "name:fra_x_preferred":[
        "Ni\u014d"
    ],
    "name:hun_x_preferred":[
        "Nio"
    ],
    "name:ita_x_preferred":[
        "Nio"
    ],
    "name:jpn_x_preferred":[
        "\u91d1\u525b\u529b\u58eb"
    ],
    "name:kor_x_preferred":[
        "\uae08\uac15\uc5ed\uc0ac"
    ],
    "name:pol_x_preferred":[
        "Ni\u014d"
    ],
    "name:ron_x_preferred":[
        "Ni\u014d"
    ],
    "name:spa_x_preferred":[
        "Ni\u014d"
    ],
    "name:zho_x_preferred":[
        "\u91d1\u525b\u529b\u58eb"
    ],
    "wof:name":"Nio",
    "wof:placetype":"locality"
},
  "geometry": {"coordinates":[11.86667,4.43333],"type":"Point"}
}