{
  "type": "Feature",
  "properties": {
    "gn:admin1_code":"11.0",
    "gn:asciiname":"Nio",
    "gn:country_code":"CM",
    "gn:dem":568,
    "gn:feature_class":"P",
    "gn:feature_code":"PPL",
    "gn:name":"Nio",
    "gn:population":0,
    "gn:timezone":"Africa/Douala",
    "iso:country":"CM",
    "wof:name":"Nio",
    "wof:placetype":"locality"
},
  "geometry": {"coordinates":[11.86667,4.43333],"type":"Point"}
}