{
  "type": "Feature",
  "properties": {
    "gn:admin1_code":"5.0",
    "gn:asciiname":"Kombo Missipi",
    "gn:country_code":"CM",
    "gn:dem":1,
    "gn:feature_class":"P",
    "gn:feature_code":"PPL",
    "gn:name":"Kombo Missipi",
    "gn:population":0,
    "gn:timezone":"Africa/Douala",
    "iso:country":"CM",
    "wof:name":"Kombo Missipi",
    "wof:placetype":"locality"
},
  "geometry": {"coordinates":[9.69583,3.94389],"type":"Point"}
}