{
  "type": "Feature",
  "properties": {
    "gn:admin1_code":"14.0",
    "gn:asciiname":"Enyeng",
    "gn:country_code":"CM",
    "gn:dem":672,
    "gn:feature_class":"P",
    "gn:feature_code":"PPL",
    "gn:name":"Enyeng",
    "gn:population":0,
    "gn:timezone":"Africa/Douala",
    "iso:country":"CM",
    "wof:name":"Enyeng",
    "wof:placetype":"locality"
},
  "geometry": {"coordinates":[12.03333,3.23333],"type":"Point"}
}