{
  "type": "Feature",
  "properties": {
    "gn:admin1_code":"7.0",
    "gn:asciiname":"Mulafi",
    "gn:country_code":"CM",
    "gn:dem":1274,
    "gn:feature_class":"P",
    "gn:feature_code":"PPL",
    "gn:name":"Mulafi",
    "gn:population":0,
    "gn:timezone":"Africa/Douala",
    "iso:country":"CM",
    "name:fra_x_preferred":[
        "Mulafi"
    ],
    "wof:name":"Mulafi",
    "wof:placetype":"locality"
},
  "geometry": {"coordinates":[10.32771,5.83228],"type":"Point"}
}