{
  "type": "Feature",
  "properties": {
    "gn:admin1_code":"10.0",
    "gn:asciiname":"Serkounouma",
    "gn:country_code":"CM",
    "gn:dem":946,
    "gn:feature_class":"P",
    "gn:feature_code":"PPL",
    "gn:name":"Serkounouma",
    "gn:population":0,
    "gn:timezone":"Africa/Douala",
    "iso:country":"CM",
    "wof:name":"Serkounouma",
    "wof:placetype":"locality"
},
  "geometry": {"coordinates":[12.02828,6.6339],"type":"Point"}
}