{
  "type": "Feature",
  "properties": {
    "gn:admin1_code":"12.0",
    "gn:asciiname":"Mandoussa",
    "gn:country_code":"CM",
    "gn:dem":533,
    "gn:feature_class":"P",
    "gn:feature_code":"PPL",
    "gn:name":"Mandoussa",
    "gn:population":0,
    "gn:timezone":"Africa/Douala",
    "iso:country":"CM",
    "name:und_x_variant":[
        "Mondousa",
        "Mandoussa",
        "Mondouza"
    ],
    "wof:name":"Mandoussa",
    "wof:placetype":"locality"
},
  "geometry": {"coordinates":[13.8375,10.91189],"type":"Point"}
}