{
  "type": "Feature",
  "properties": {
    "gn:admin1_code":"12.0",
    "gn:asciiname":"Guidsalay",
    "gn:country_code":"CM",
    "gn:dem":733,
    "gn:feature_class":"P",
    "gn:feature_code":"PPL",
    "gn:name":"Guidsalay",
    "gn:population":0,
    "gn:timezone":"Africa/Douala",
    "iso:country":"CM",
    "wof:name":"Guidsalay",
    "wof:placetype":"locality"
},
  "geometry": {"coordinates":[13.87553,10.82912],"type":"Point"}
}