{
  "type": "Feature",
  "properties": {
    "gn:admin1_code":"4.0",
    "gn:asciiname":"Tounkoumbe",
    "gn:country_code":"CM",
    "gn:dem":633,
    "gn:feature_class":"P",
    "gn:feature_code":"PPL",
    "gn:name":"Tounkoumb\u00e9",
    "gn:population":0,
    "gn:timezone":"Africa/Douala",
    "iso:country":"CM",
    "wof:name":"Tounkoumbe",
    "wof:placetype":"locality"
},
  "geometry": {"coordinates":[13.58333,4.21667],"type":"Point"}
}