{
  "type": "Feature",
  "properties": {
    "gn:admin1_code":"10.0",
    "gn:asciiname":"Maloa",
    "gn:country_code":"CM",
    "gn:dem":1068,
    "gn:feature_class":"P",
    "gn:feature_code":"PPL",
    "gn:name":"Maloa",
    "gn:population":0,
    "gn:timezone":"Africa/Douala",
    "iso:country":"CM",
    "wof:name":"Maloa",
    "wof:placetype":"locality"
},
  "geometry": {"coordinates":[12.76794,6.99826],"type":"Point"}
}