{
  "type": "Feature",
  "properties": {
    "gn:admin1_code":"11.0",
    "gn:asciiname":"Zoalouma",
    "gn:country_code":"CM",
    "gn:dem":691,
    "gn:feature_class":"P",
    "gn:feature_code":"PPL",
    "gn:name":"Zoalouma",
    "gn:population":0,
    "gn:timezone":"Africa/Douala",
    "iso:country":"CM",
    "wof:name":"Zoalouma",
    "wof:placetype":"locality"
},
  "geometry": {"coordinates":[11.35,3.45],"type":"Point"}
}