{
  "type": "Feature",
  "properties": {
    "gn:admin1_code":"12.0",
    "gn:asciiname":"Palva",
    "gn:country_code":"CM",
    "gn:dem":532,
    "gn:feature_class":"P",
    "gn:feature_code":"PPL",
    "gn:name":"Palva",
    "gn:population":0,
    "gn:timezone":"Africa/Douala",
    "iso:country":"CM",
    "wof:name":"Palva",
    "wof:placetype":"locality"
},
  "geometry": {"coordinates":[13.88683,10.3499],"type":"Point"}
}