{
  "type": "Feature",
  "properties": {
    "gn:admin1_code":"12.0",
    "gn:asciiname":"Sera Hadya",
    "gn:country_code":"CM",
    "gn:dem":416,
    "gn:feature_class":"P",
    "gn:feature_code":"PPL",
    "gn:name":"Sera Hadya",
    "gn:population":0,
    "gn:timezone":"Africa/Douala",
    "iso:country":"CM",
    "wof:name":"Sera Hadya",
    "wof:placetype":"locality"
},
  "geometry": {"coordinates":[14.19795,10.99486],"type":"Point"}
}