{
  "type": "Feature",
  "properties": {
    "gn:admin1_code":"12.0",
    "gn:asciiname":"Meleri",
    "gn:country_code":"CM",
    "gn:dem":384,
    "gn:feature_class":"P",
    "gn:feature_code":"PPL",
    "gn:name":"M\u00e9l\u00e9ri",
    "gn:population":0,
    "gn:timezone":"Africa/Douala",
    "iso:country":"CM",
    "wof:name":"Meleri",
    "wof:placetype":"locality"
},
  "geometry": {"coordinates":[13.97027,11.14847],"type":"Point"}
}