{
  "type": "Feature",
  "properties": {
    "gn:admin1_code":"8.0",
    "gn:asciiname":"Menkechoum",
    "gn:country_code":"CM",
    "gn:dem":1075,
    "gn:feature_class":"P",
    "gn:feature_code":"PPL",
    "gn:name":"Menk\u00e9choum",
    "gn:population":0,
    "gn:timezone":"Africa/Douala",
    "iso:country":"CM",
    "wof:name":"Menkechoum",
    "wof:placetype":"locality"
},
  "geometry": {"coordinates":[10.63369,5.5397],"type":"Point"}
}