{
  "type": "Feature",
  "properties": {
    "gn:admin1_code":"14.0",
    "gn:asciiname":"Minkpwele",
    "gn:country_code":"CM",
    "gn:dem":732,
    "gn:feature_class":"P",
    "gn:feature_code":"PPL",
    "gn:name":"Minkpw\u00e9le",
    "gn:population":0,
    "gn:timezone":"Africa/Douala",
    "iso:country":"CM",
    "wof:name":"Minkpwele",
    "wof:placetype":"locality"
},
  "geometry": {"coordinates":[11.45,2.86667],"type":"Point"}
}