{
  "type": "Feature",
  "properties": {
    "gn:admin1_code":"12.0",
    "gn:asciiname":"Dimeo",
    "gn:country_code":"CM",
    "gn:dem":595,
    "gn:feature_class":"P",
    "gn:feature_code":"PPL",
    "gn:name":"Dim\u00e9o",
    "gn:population":0,
    "gn:timezone":"Africa/Douala",
    "iso:country":"CM",
    "wof:name":"Dimeo",
    "wof:placetype":"locality"
},
  "geometry": {"coordinates":[13.92718,10.55514],"type":"Point"}
}