{
  "type": "Feature",
  "properties": {
    "gn:admin1_code":"13.0",
    "gn:asciiname":"Djoungoundou",
    "gn:country_code":"CM",
    "gn:dem":280,
    "gn:feature_class":"P",
    "gn:feature_code":"PPL",
    "gn:name":"Djoungoundou",
    "gn:population":0,
    "gn:timezone":"Africa/Douala",
    "iso:country":"CM",
    "wof:name":"Djoungoundou",
    "wof:placetype":"locality"
},
  "geometry": {"coordinates":[13.80737,9.21465],"type":"Point"}
}