{
  "type": "Feature",
  "properties": {
    "gn:admin1_code":"14.0",
    "gn:asciiname":"Bengbis",
    "gn:cc2":"CM",
    "gn:country_code":"CM",
    "gn:dem":670,
    "gn:feature_class":"P",
    "gn:feature_code":"PPL",
    "gn:name":"Bengbis",
    "gn:population":0,
    "gn:timezone":"Africa/Douala",
    "iso:country":"CM",
    "name:und_x_variant":[
        "Bangeb\u012bs",
        "Benghia",
        "Bengbia",
        "Bengbis"
    ],
    "wof:name":"Bengbis",
    "wof:placetype":"locality"
},
  "geometry": {"coordinates":[12.45,3.45],"type":"Point"}
}