{
  "type": "Feature",
  "properties": {
    "gn:admin1_code":"12.0",
    "gn:asciiname":"Dangra",
    "gn:country_code":"CM",
    "gn:dem":734,
    "gn:feature_class":"P",
    "gn:feature_code":"PPL",
    "gn:name":"Dangra",
    "gn:population":0,
    "gn:timezone":"Africa/Douala",
    "iso:country":"CM",
    "wof:name":"Dangra",
    "wof:placetype":"locality"
},
  "geometry": {"coordinates":[13.54862,10.27988],"type":"Point"}
}