{
  "type": "Feature",
  "properties": {
    "gn:admin1_code":"12.0",
    "gn:asciiname":"Dagam",
    "gn:country_code":"CM",
    "gn:dem":776,
    "gn:feature_class":"P",
    "gn:feature_code":"PPL",
    "gn:name":"Dagam",
    "gn:population":0,
    "gn:timezone":"Africa/Douala",
    "iso:country":"CM",
    "wof:name":"Dagam",
    "wof:placetype":"locality"
},
  "geometry": {"coordinates":[13.87527,10.82449],"type":"Point"}
}