{
  "type": "Feature",
  "properties": {
    "gn:admin1_code":"8.0",
    "gn:asciiname":"Baloum",
    "gn:country_code":"CM",
    "gn:dem":1201,
    "gn:feature_class":"P",
    "gn:feature_code":"PPL",
    "gn:name":"Baloum",
    "gn:population":0,
    "gn:timezone":"Africa/Douala",
    "iso:country":"CM",
    "wof:name":"Baloum",
    "wof:placetype":"locality"
},
  "geometry": {"coordinates":[10.35327,5.63012],"type":"Point"}
}