{
  "type": "Feature",
  "properties": {
    "gn:admin1_code":"12.0",
    "gn:asciiname":"Adraman",
    "gn:country_code":"CM",
    "gn:dem":370,
    "gn:feature_class":"P",
    "gn:feature_code":"PPL",
    "gn:name":"Adraman",
    "gn:population":0,
    "gn:timezone":"Africa/Douala",
    "iso:country":"CM",
    "wof:name":"Adraman",
    "wof:placetype":"locality"
},
  "geometry": {"coordinates":[13.94009,11.19379],"type":"Point"}
}