{
  "type": "Feature",
  "properties": {
    "gn:admin1_code":"8.0",
    "gn:asciiname":"Fowaji",
    "gn:country_code":"CM",
    "gn:dem":1755,
    "gn:feature_class":"P",
    "gn:feature_code":"PPL",
    "gn:name":"Fowaji",
    "gn:population":0,
    "gn:timezone":"Africa/Douala",
    "iso:country":"CM",
    "wof:name":"Fowaji",
    "wof:placetype":"locality"
},
  "geometry": {"coordinates":[10.03333,5.53333],"type":"Point"}
}