{
  "type": "Feature",
  "properties": {
    "gn:admin1_code":"12.0",
    "gn:asciiname":"Mandjakma",
    "gn:country_code":"CM",
    "gn:dem":353,
    "gn:feature_class":"P",
    "gn:feature_code":"PPL",
    "gn:name":"Mandjakma",
    "gn:population":0,
    "gn:timezone":"Africa/Douala",
    "iso:country":"CM",
    "wof:name":"Mandjakma",
    "wof:placetype":"locality"
},
  "geometry": {"coordinates":[14.90344,10.01332],"type":"Point"}
}