{
  "type": "Feature",
  "properties": {
    "gn:admin1_code":"5.0",
    "gn:asciiname":"Ekom Nkam",
    "gn:country_code":"CM",
    "gn:dem":571,
    "gn:feature_class":"P",
    "gn:feature_code":"PPL",
    "gn:name":"Ekom Nkam",
    "gn:population":0,
    "gn:timezone":"Africa/Douala",
    "iso:country":"CM",
    "name:fra_x_preferred":[
        "Ekom Nkam"
    ],
    "wof:name":"Ekom Nkam",
    "wof:placetype":"locality"
},
  "geometry": {"coordinates":[10.01593,5.06365],"type":"Point"}
}