{
  "type": "Feature",
  "properties": {
    "gn:admin1_code":"8.0",
    "gn:asciiname":"Pounjiem",
    "gn:country_code":"CM",
    "gn:dem":1126,
    "gn:feature_class":"P",
    "gn:feature_code":"PPL",
    "gn:name":"Pounjiem",
    "gn:population":0,
    "gn:timezone":"Africa/Douala",
    "iso:country":"CM",
    "wof:name":"Pounjiem",
    "wof:placetype":"locality"
},
  "geometry": {"coordinates":[10.65882,5.58135],"type":"Point"}
}