{
  "type": "Feature",
  "properties": {
    "gn:admin1_code":"9.0",
    "gn:asciiname":"Poala",
    "gn:country_code":"CM",
    "gn:dem":1846,
    "gn:feature_class":"P",
    "gn:feature_code":"PPL",
    "gn:name":"Poala",
    "gn:population":0,
    "gn:timezone":"Africa/Douala",
    "iso:country":"CM",
    "name:und_x_variant":[
        "Poala-Nhia",
        "Poala"
    ],
    "wof:name":"Poala",
    "wof:placetype":"locality"
},
  "geometry": {"coordinates":[9.81577,5.05029],"type":"Point"}
}