{
  "type": "Feature",
  "properties": {
    "gn:admin1_code":"12.0",
    "gn:asciiname":"Tchanyare",
    "gn:country_code":"CM",
    "gn:dem":308,
    "gn:feature_class":"P",
    "gn:feature_code":"PPL",
    "gn:name":"Tchanyar\u00e9",
    "gn:population":0,
    "gn:timezone":"Africa/Douala",
    "iso:country":"CM",
    "name:und_x_variant":[
        "Tchagnar\u00e9",
        "Tchanyar\u00e9"
    ],
    "wof:name":"Tchanyare",
    "wof:placetype":"locality"
},
  "geometry": {"coordinates":[14.93832,11.20139],"type":"Point"}
}