{
  "type": "Feature",
  "properties": {
    "gn:admin1_code":"12.0",
    "gn:asciiname":"Ldamsay",
    "gn:country_code":"CM",
    "gn:dem":869,
    "gn:feature_class":"P",
    "gn:feature_code":"PPL",
    "gn:name":"Ldamsay",
    "gn:population":0,
    "gn:timezone":"Africa/Douala",
    "iso:country":"CM",
    "wof:name":"Ldamsay",
    "wof:placetype":"locality"
},
  "geometry": {"coordinates":[13.7897,10.7665],"type":"Point"}
}