{
  "type": "Feature",
  "properties": {
    "gn:admin1_code":"14.0",
    "gn:asciiname":"Minkomo",
    "gn:country_code":"CM",
    "gn:dem":608,
    "gn:feature_class":"P",
    "gn:feature_code":"PPL",
    "gn:name":"Minkomo",
    "gn:population":0,
    "gn:timezone":"Africa/Douala",
    "iso:country":"CM",
    "wof:name":"Minkomo",
    "wof:placetype":"locality"
},
  "geometry": {"coordinates":[11.26667,2.18333],"type":"Point"}
}