{
  "type": "Feature",
  "properties": {
    "gn:admin1_code":"13.0",
    "gn:asciiname":"Mboudja",
    "gn:country_code":"CM",
    "gn:dem":246,
    "gn:feature_class":"P",
    "gn:feature_code":"PPL",
    "gn:name":"Mboudja",
    "gn:population":0,
    "gn:timezone":"Africa/Douala",
    "iso:country":"CM",
    "wof:name":"Mboudja",
    "wof:placetype":"locality"
},
  "geometry": {"coordinates":[13.96861,9.62118],"type":"Point"}
}