{
  "type": "Feature",
  "properties": {
    "gn:admin1_code":"12.0",
    "gn:asciiname":"Lawan Gaori",
    "gn:country_code":"CM",
    "gn:dem":346,
    "gn:feature_class":"P",
    "gn:feature_code":"PPL",
    "gn:name":"Lawan Gaori",
    "gn:population":0,
    "gn:timezone":"Africa/Douala",
    "iso:country":"CM",
    "wof:name":"Lawan Gaori",
    "wof:placetype":"locality"
},
  "geometry": {"coordinates":[14.82574,10.21924],"type":"Point"}
}