{
  "type": "Feature",
  "properties": {
    "gn:admin1_code":"7.0",
    "gn:asciiname":"Bekeu",
    "gn:country_code":"CM",
    "gn:dem":1178,
    "gn:feature_class":"P",
    "gn:feature_code":"PPL",
    "gn:name":"Bekeu",
    "gn:population":0,
    "gn:timezone":"Africa/Douala",
    "iso:country":"CM",
    "wof:name":"Bekeu",
    "wof:placetype":"locality"
},
  "geometry": {"coordinates":[10.46792,5.9863],"type":"Point"}
}