{
  "type": "Feature",
  "properties": {
    "gn:admin1_code":"8.0",
    "gn:asciiname":"Menguea II",
    "gn:country_code":"CM",
    "gn:dem":1641,
    "gn:feature_class":"P",
    "gn:feature_code":"PPL",
    "gn:name":"Mengu\u00e9a II",
    "gn:population":0,
    "gn:timezone":"Africa/Douala",
    "iso:country":"CM",
    "wof:name":"Menguea II",
    "wof:placetype":"locality"
},
  "geometry": {"coordinates":[10.18633,5.57657],"type":"Point"}
}