{
  "type": "Feature",
  "properties": {
    "gn:admin1_code":"10.0",
    "gn:asciiname":"Malarba",
    "gn:country_code":"CM",
    "gn:dem":874,
    "gn:feature_class":"P",
    "gn:feature_code":"PPL",
    "gn:name":"Malarba",
    "gn:population":0,
    "gn:timezone":"Africa/Douala",
    "iso:country":"CM",
    "wof:name":"Malarba",
    "wof:placetype":"locality"
},
  "geometry": {"coordinates":[12.61533,6.5252],"type":"Point"}
}