{
  "type": "Feature",
  "properties": {
    "gn:admin1_code":"12.0",
    "gn:asciiname":"Malmandja",
    "gn:country_code":"CM",
    "gn:dem":290,
    "gn:feature_class":"P",
    "gn:feature_code":"PPL",
    "gn:name":"Malmandja",
    "gn:population":0,
    "gn:timezone":"Africa/Douala",
    "iso:country":"CM",
    "name:und_x_variant":[
        "Malmadja",
        "Malmandja"
    ],
    "wof:name":"Malmandja",
    "wof:placetype":"locality"
},
  "geometry": {"coordinates":[14.23308,12.41295],"type":"Point"}
}