{
  "type": "Feature",
  "properties": {
    "gn:admin1_code":"5.0",
    "gn:asciiname":"Tengde",
    "gn:country_code":"CM",
    "gn:dem":25,
    "gn:feature_class":"P",
    "gn:feature_code":"PPL",
    "gn:name":"Tengd\u00e9",
    "gn:population":0,
    "gn:timezone":"Africa/Douala",
    "iso:country":"CM",
    "wof:name":"Tengde",
    "wof:placetype":"locality"
},
  "geometry": {"coordinates":[9.44835,3.94593],"type":"Point"}
}