{
  "type": "Feature",
  "properties": {
    "gn:admin1_code":"12.0",
    "gn:asciiname":"Baouli Hamadou",
    "gn:country_code":"CM",
    "gn:dem":326,
    "gn:feature_class":"P",
    "gn:feature_code":"PPL",
    "gn:name":"Baouli Hamadou",
    "gn:population":0,
    "gn:timezone":"Africa/Douala",
    "iso:country":"CM",
    "wof:name":"Baouli Hamadou",
    "wof:placetype":"locality"
},
  "geometry": {"coordinates":[14.70041,10.76122],"type":"Point"}
}