{
  "type": "Feature",
  "properties": {
    "gn:admin1_code":"7.0",
    "gn:asciiname":"Besi",
    "gn:country_code":"CM",
    "gn:dem":1268,
    "gn:feature_class":"P",
    "gn:feature_code":"PPL",
    "gn:name":"Besi",
    "gn:population":0,
    "gn:timezone":"Africa/Douala",
    "iso:country":"CM",
    "name:und_x_variant":[
        "Bessi",
        "Besi"
    ],
    "wof:name":"Besi",
    "wof:placetype":"locality"
},
  "geometry": {"coordinates":[9.92417,5.81558],"type":"Point"}
}