{
  "type": "Feature",
  "properties": {
    "gn:admin1_code":"14.0",
    "gn:asciiname":"Dpoue",
    "gn:country_code":"CM",
    "gn:dem":683,
    "gn:feature_class":"P",
    "gn:feature_code":"PPL",
    "gn:name":"Dpou\u00e9",
    "gn:population":0,
    "gn:timezone":"Africa/Douala",
    "iso:country":"CM",
    "name:und_x_variant":[
        "Kpoui",
        "Dpou\u00e9"
    ],
    "wof:name":"Dpoue",
    "wof:placetype":"locality"
},
  "geometry": {"coordinates":[12.23333,2.96667],"type":"Point"}
}