{
  "type": "Feature",
  "properties": {
    "gn:admin1_code":"10.0",
    "gn:asciiname":"Zamana",
    "gn:country_code":"CM",
    "gn:dem":1400,
    "gn:feature_class":"P",
    "gn:feature_code":"PPL",
    "gn:name":"Zamana",
    "gn:population":0,
    "gn:timezone":"Africa/Douala",
    "iso:country":"CM",
    "wof:name":"Zamana",
    "wof:placetype":"locality"
},
  "geometry": {"coordinates":[13.68333,7.63333],"type":"Point"}
}