{
  "type": "Feature",
  "properties": {
    "gn:admin1_code":"13.0",
    "gn:asciiname":"Ngargou",
    "gn:country_code":"CM",
    "gn:dem":196,
    "gn:feature_class":"P",
    "gn:feature_code":"PPL",
    "gn:name":"Ngargou",
    "gn:population":0,
    "gn:timezone":"Africa/Douala",
    "iso:country":"CM",
    "wof:name":"Ngargou",
    "wof:placetype":"locality"
},
  "geometry": {"coordinates":[13.62469,9.28085],"type":"Point"}
}