{
  "type": "Feature",
  "properties": {
    "gn:admin1_code":"13.0",
    "gn:asciiname":"Pomla Mango",
    "gn:country_code":"CM",
    "gn:dem":237,
    "gn:feature_class":"P",
    "gn:feature_code":"PPL",
    "gn:name":"Pomla Mango",
    "gn:population":0,
    "gn:timezone":"Africa/Douala",
    "iso:country":"CM",
    "name:und_x_variant":[
        "Pomla-Manga",
        "Plomba Mangua",
        "Pomla Mango"
    ],
    "wof:name":"Pomla Mango",
    "wof:placetype":"locality"
},
  "geometry": {"coordinates":[13.3479,9.39895],"type":"Point"}
}