{
  "type": "Feature",
  "properties": {
    "gn:admin1_code":"8.0",
    "gn:asciiname":"Touopou",
    "gn:country_code":"CM",
    "gn:dem":1392,
    "gn:feature_class":"P",
    "gn:feature_code":"PPL",
    "gn:name":"Touopou",
    "gn:population":0,
    "gn:timezone":"Africa/Douala",
    "iso:country":"CM",
    "wof:name":"Touopou",
    "wof:placetype":"locality"
},
  "geometry": {"coordinates":[10.03005,5.41957],"type":"Point"}
}