{
  "type": "Feature",
  "properties": {
    "gn:admin1_code":"10.0",
    "gn:asciiname":"Mikai",
    "gn:country_code":"CM",
    "gn:dem":989,
    "gn:feature_class":"P",
    "gn:feature_code":"PPL",
    "gn:name":"Mikai",
    "gn:population":0,
    "gn:timezone":"Africa/Douala",
    "iso:country":"CM",
    "name:und_x_variant":[
        "Mike\u00ef",
        "Mikai"
    ],
    "wof:name":"Mikai",
    "wof:placetype":"locality"
},
  "geometry": {"coordinates":[13.05,7.16667],"type":"Point"}
}