{
  "type": "Feature",
  "properties": {
    "gn:admin1_code":"12.0",
    "gn:asciiname":"Gamangaz",
    "gn:country_code":"CM",
    "gn:dem":442,
    "gn:feature_class":"P",
    "gn:feature_code":"PPL",
    "gn:name":"Gamangaz",
    "gn:population":0,
    "gn:timezone":"Africa/Douala",
    "iso:country":"CM",
    "wof:name":"Gamangaz",
    "wof:placetype":"locality"
},
  "geometry": {"coordinates":[13.97481,10.97787],"type":"Point"}
}