{
  "type": "Feature",
  "properties": {
    "gn:admin1_code":"4.0",
    "gn:asciiname":"Melen",
    "gn:country_code":"CM",
    "gn:dem":666,
    "gn:feature_class":"P",
    "gn:feature_code":"PPL",
    "gn:name":"M\u00e9len",
    "gn:population":0,
    "gn:timezone":"Africa/Douala",
    "iso:country":"CM",
    "wof:name":"Melen",
    "wof:placetype":"locality"
},
  "geometry": {"coordinates":[12.61667,3.45],"type":"Point"}
}