{
  "type": "Feature",
  "properties": {
    "gn:admin1_code":"9.0",
    "gn:asciiname":"Mfunum",
    "gn:country_code":"CM",
    "gn:dem":208,
    "gn:feature_class":"P",
    "gn:feature_code":"PPL",
    "gn:name":"Mfunum",
    "gn:population":0,
    "gn:timezone":"Africa/Douala",
    "iso:country":"CM",
    "wof:name":"Mfunum",
    "wof:placetype":"locality"
},
  "geometry": {"coordinates":[8.9143,5.6054],"type":"Point"}
}