{
  "type": "Feature",
  "properties": {
    "gn:admin1_code":"9.0",
    "gn:asciiname":"Manta",
    "gn:country_code":"CM",
    "gn:dem":1189,
    "gn:feature_class":"P",
    "gn:feature_code":"PPL",
    "gn:name":"Manta",
    "gn:population":0,
    "gn:timezone":"Africa/Douala",
    "iso:country":"CM",
    "wof:name":"Manta",
    "wof:placetype":"locality"
},
  "geometry": {"coordinates":[9.7371,4.9745],"type":"Point"}
}