{
  "type": "Feature",
  "properties": {
    "gn:admin1_code":"5.0",
    "gn:asciiname":"Nkanjok",
    "gn:country_code":"CM",
    "gn:dem":106,
    "gn:feature_class":"P",
    "gn:feature_code":"PPL",
    "gn:name":"Nkanjok",
    "gn:population":0,
    "gn:timezone":"Africa/Douala",
    "iso:country":"CM",
    "name:und_x_variant":[
        "Kagendjok",
        "Tagndok",
        "Nkanjok"
    ],
    "wof:name":"Nkanjok",
    "wof:placetype":"locality"
},
  "geometry": {"coordinates":[10.43333,3.83333],"type":"Point"}
}