{
  "type": "Feature",
  "properties": {
    "gn:admin1_code":"4.0",
    "gn:asciiname":"Mbahankou",
    "gn:country_code":"CM",
    "gn:dem":732,
    "gn:feature_class":"P",
    "gn:feature_code":"PPL",
    "gn:name":"Mbahankou",
    "gn:population":0,
    "gn:timezone":"Africa/Douala",
    "iso:country":"CM",
    "wof:name":"Mbahankou",
    "wof:placetype":"locality"
},
  "geometry": {"coordinates":[13.03333,4.35],"type":"Point"}
}