{
  "type": "Feature",
  "properties": {
    "gn:admin1_code":"13.0",
    "gn:asciiname":"Oura Bagoni",
    "gn:country_code":"CM",
    "gn:dem":279,
    "gn:feature_class":"P",
    "gn:feature_code":"PPL",
    "gn:name":"Oura Bagoni",
    "gn:population":0,
    "gn:timezone":"Africa/Douala",
    "iso:country":"CM",
    "wof:name":"Oura Bagoni",
    "wof:placetype":"locality"
},
  "geometry": {"coordinates":[13.88138,9.0392],"type":"Point"}
}