{
  "type": "Feature",
  "properties": {
    "gn:admin1_code":"12.0",
    "gn:asciiname":"Am Talia",
    "gn:country_code":"CM",
    "gn:dem":304,
    "gn:feature_class":"P",
    "gn:feature_code":"PPL",
    "gn:name":"Am Talia",
    "gn:population":0,
    "gn:timezone":"Africa/Douala",
    "iso:country":"CM",
    "wof:name":"Am Talia",
    "wof:placetype":"locality"
},
  "geometry": {"coordinates":[14.49963,11.39028],"type":"Point"}
}