{
  "type": "Feature",
  "properties": {
    "gn:admin1_code":"0.0",
    "gn:asciiname":"Minlaa",
    "gn:country_code":"CM",
    "gn:dem":677,
    "gn:feature_class":"P",
    "gn:feature_code":"PPL",
    "gn:name":"Minlaa",
    "gn:population":0,
    "gn:timezone":"Africa/Douala",
    "iso:country":"CM",
    "wof:name":"Minlaa",
    "wof:placetype":"locality"
},
  "geometry": {"coordinates":[12.48333,3.65],"type":"Point"}
}