{
  "type": "Feature",
  "properties": {
    "gn:admin1_code":"12.0",
    "gn:asciiname":"Bourmagwe",
    "gn:country_code":"CM",
    "gn:dem":306,
    "gn:feature_class":"P",
    "gn:feature_code":"PPL",
    "gn:name":"Bourmagw\u00e9",
    "gn:population":0,
    "gn:timezone":"Africa/Douala",
    "iso:country":"CM",
    "name:und_x_variant":[
        "Bourmagoui",
        "Bourmagw\u00e9"
    ],
    "wof:name":"Bourmagwe",
    "wof:placetype":"locality"
},
  "geometry": {"coordinates":[14.93999,11.35763],"type":"Point"}
}