{
  "type": "Feature",
  "properties": {
    "gn:admin1_code":"12.0",
    "gn:asciiname":"Bava",
    "gn:country_code":"CM",
    "gn:dem":523,
    "gn:feature_class":"P",
    "gn:feature_code":"PPL",
    "gn:name":"Bava",
    "gn:population":0,
    "gn:timezone":"Africa/Douala",
    "iso:country":"CM",
    "wof:name":"Bava",
    "wof:placetype":"locality"
},
  "geometry": {"coordinates":[13.93056,10.86772],"type":"Point"}
}