{
  "type": "Feature",
  "properties": {
    "gn:admin1_code":"14.0",
    "gn:asciiname":"Mesok",
    "gn:country_code":"CM",
    "gn:dem":746,
    "gn:feature_class":"P",
    "gn:feature_code":"PPL",
    "gn:name":"Mesok",
    "gn:population":0,
    "gn:timezone":"Africa/Douala",
    "iso:country":"CM",
    "wof:name":"Mesok",
    "wof:placetype":"locality"
},
  "geometry": {"coordinates":[11.35,3.08333],"type":"Point"}
}