{
  "type": "Feature",
  "properties": {
    "gn:admin1_code":"13.0",
    "gn:asciiname":"Kouman",
    "gn:country_code":"CM",
    "gn:dem":540,
    "gn:feature_class":"P",
    "gn:feature_code":"PPL",
    "gn:name":"Kouman",
    "gn:population":0,
    "gn:timezone":"Africa/Douala",
    "iso:country":"CM",
    "wof:name":"Kouman",
    "wof:placetype":"locality"
},
  "geometry": {"coordinates":[15.10703,7.6833],"type":"Point"}
}