{
  "type": "Feature",
  "properties": {
    "gn:admin1_code":"5.0",
    "gn:asciiname":"Minkwele",
    "gn:country_code":"CM",
    "gn:dem":8,
    "gn:feature_class":"P",
    "gn:feature_code":"PPL",
    "gn:name":"Minkw\u00e9l\u00e9",
    "gn:population":0,
    "gn:timezone":"Africa/Douala",
    "iso:country":"CM",
    "wof:name":"Minkwele",
    "wof:placetype":"locality"
},
  "geometry": {"coordinates":[9.6086,4.1006],"type":"Point"}
}