{
  "type": "Feature",
  "properties": {
    "gn:admin1_code":"8.0",
    "gn:asciiname":"Mbou",
    "gn:country_code":"CM",
    "gn:dem":1527,
    "gn:feature_class":"P",
    "gn:feature_code":"PPL",
    "gn:name":"Mbou",
    "gn:population":0,
    "gn:timezone":"Africa/Douala",
    "iso:country":"CM",
    "wof:name":"Mbou",
    "wof:placetype":"locality"
},
  "geometry": {"coordinates":[10.36352,5.38678],"type":"Point"}
}