{
  "type": "Feature",
  "properties": {
    "gn:admin1_code":"9.0",
    "gn:asciiname":"Talangaye",
    "gn:country_code":"CM",
    "gn:dem":400,
    "gn:feature_class":"P",
    "gn:feature_code":"PPL",
    "gn:name":"Talangaye",
    "gn:population":0,
    "gn:timezone":"Africa/Douala",
    "iso:country":"CM",
    "name:und_x_variant":[
        "Talangayi",
        "Talangaje",
        "Talanj\u00e9",
        "Talanganye",
        "Talangaye"
    ],
    "wof:name":"Talangaye",
    "wof:placetype":"locality"
},
  "geometry": {"coordinates":[9.38247,5.14984],"type":"Point"}
}