{
  "type": "Feature",
  "properties": {
    "gn:admin1_code":"14.0",
    "gn:asciiname":"Oyak",
    "gn:country_code":"CM",
    "gn:dem":716,
    "gn:feature_class":"P",
    "gn:feature_code":"PPL",
    "gn:name":"Oyak",
    "gn:population":0,
    "gn:timezone":"Africa/Douala",
    "iso:country":"CM",
    "wof:name":"Oyak",
    "wof:placetype":"locality"
},
  "geometry": {"coordinates":[11.68333,3.16667],"type":"Point"}
}