{
  "type": "Feature",
  "properties": {
    "gn:admin1_code":"0.0",
    "gn:asciiname":"Seebaya",
    "gn:country_code":"CM",
    "gn:dem":291,
    "gn:feature_class":"P",
    "gn:feature_code":"PPL",
    "gn:name":"Seebaya",
    "gn:population":0,
    "gn:timezone":"Africa/Ndjamena",
    "iso:country":"CM",
    "wof:name":"Seebaya",
    "wof:placetype":"locality"
},
  "geometry": {"coordinates":[14.95652,12.57942],"type":"Point"}
}