{
  "type": "Feature",
  "properties": {
    "gn:admin1_code":"13.0",
    "gn:asciiname":"Agorma",
    "gn:country_code":"CM",
    "gn:dem":236,
    "gn:feature_class":"P",
    "gn:feature_code":"PPL",
    "gn:name":"Agorma",
    "gn:population":0,
    "gn:timezone":"Africa/Douala",
    "iso:country":"CM",
    "wof:name":"Agorma",
    "wof:placetype":"locality"
},
  "geometry": {"coordinates":[13.71667,8.83333],"type":"Point"}
}