{
  "type": "Feature",
  "properties": {
    "gn:admin1_code":"8.0",
    "gn:asciiname":"Kamdeng",
    "gn:country_code":"CM",
    "gn:dem":1595,
    "gn:feature_class":"P",
    "gn:feature_code":"PPL",
    "gn:name":"Kamdeng",
    "gn:population":0,
    "gn:timezone":"Africa/Douala",
    "iso:country":"CM",
    "wof:name":"Kamdeng",
    "wof:placetype":"locality"
},
  "geometry": {"coordinates":[10.44553,5.32996],"type":"Point"}
}