{
  "type": "Feature",
  "properties": {
    "gn:admin1_code":"12.0",
    "gn:asciiname":"Bela",
    "gn:country_code":"CM",
    "gn:dem":291,
    "gn:feature_class":"P",
    "gn:feature_code":"PPL",
    "gn:name":"B\u00e9la",
    "gn:population":0,
    "gn:timezone":"Africa/Douala",
    "iso:country":"CM",
    "name:bos_x_preferred":[
        "Bela"
    ],
    "name:cat_x_preferred":[
        "Bela"
    ],
    "name:ceb_x_preferred":[
        "Bela"
    ],
    "name:deu_x_preferred":[
        "Bela"
    ],
    "name:eus_x_preferred":[
        "Bela"
    ],
    "name:fra_x_preferred":[
        "Bela"
    ],
    "name:heb_x_preferred":[
        "\u05d1\u05dc\u05e2"
    ],
    "name:hrv_x_preferred":[
        "Bela"
    ],
    "name:ita_x_preferred":[
        "Bela"
    ],
    "name:nld_x_preferred":[
        "Bela"
    ],
    "name:pol_x_preferred":[
        "Bela"
    ],
    "name:por_x_preferred":[
        "Bela"
    ],
    "name:slv_x_preferred":[
        "Bela"
    ],
    "name:srp_x_preferred":[
        "\u0411\u0435\u043b\u0430"
    ],
    "name:swe_x_preferred":[
        "Bela"
    ],
    "name:tgl_x_preferred":[
        "Bela"
    ],
    "wof:name":"Bela",
    "wof:placetype":"locality"
},
  "geometry": {"coordinates":[14.73333,12.16667],"type":"Point"}
}