{
  "type": "Feature",
  "properties": {
    "gn:admin1_code":"12.0",
    "gn:asciiname":"Marafin",
    "gn:country_code":"CM",
    "gn:dem":293,
    "gn:feature_class":"P",
    "gn:feature_code":"PPL",
    "gn:name":"Marafin",
    "gn:population":0,
    "gn:timezone":"Africa/Douala",
    "iso:country":"CM",
    "name:und_x_variant":[
        "Marfain",
        "Marafin",
        "Marfa\u00efn"
    ],
    "wof:name":"Marafin",
    "wof:placetype":"locality"
},
  "geometry": {"coordinates":[14.71073,12.35361],"type":"Point"}
}