{
  "type": "Feature",
  "properties": {
    "gn:admin1_code":"13.0",
    "gn:asciiname":"Baylara",
    "gn:country_code":"CM",
    "gn:dem":533,
    "gn:feature_class":"P",
    "gn:feature_code":"PPL",
    "gn:name":"Baylara",
    "gn:population":0,
    "gn:timezone":"Africa/Douala",
    "iso:country":"CM",
    "wof:name":"Baylara",
    "wof:placetype":"locality"
},
  "geometry": {"coordinates":[15.2568,7.7771],"type":"Point"}
}