{
  "type": "Feature",
  "properties": {
    "gn:admin1_code":"13.0",
    "gn:asciiname":"Godi",
    "gn:country_code":"CM",
    "gn:dem":230,
    "gn:feature_class":"P",
    "gn:feature_code":"PPL",
    "gn:name":"Godi",
    "gn:population":0,
    "gn:timezone":"Africa/Douala",
    "iso:country":"CM",
    "name:ceb_x_preferred":[
        "Godi"
    ],
    "name:fra_x_preferred":[
        "Godi"
    ],
    "name:nld_x_preferred":[
        "Godi"
    ],
    "name:swe_x_preferred":[
        "Godi"
    ],
    "name:wln_x_preferred":[
        "Godi"
    ],
    "wof:name":"Godi",
    "wof:placetype":"locality"
},
  "geometry": {"coordinates":[14.19,8.7908],"type":"Point"}
}