{
  "type": "Feature",
  "properties": {
    "gn:admin1_code":"8.0",
    "gn:asciiname":"Ndou'ndou",
    "gn:country_code":"CM",
    "gn:dem":1285,
    "gn:feature_class":"P",
    "gn:feature_code":"PPL",
    "gn:name":"Ndou\u2019 ndou",
    "gn:population":0,
    "gn:timezone":"Africa/Douala",
    "iso:country":"CM",
    "name:fra_x_preferred":[
        "Ndou\u2019 ndou"
    ],
    "wof:name":"Ndou'ndou",
    "wof:placetype":"locality"
},
  "geometry": {"coordinates":[10.56779,5.15494],"type":"Point"}
}