{
  "type": "Feature",
  "properties": {
    "gn:admin1_code":"13.0",
    "gn:asciiname":"Gore",
    "gn:country_code":"CM",
    "gn:dem":288,
    "gn:feature_class":"P",
    "gn:feature_code":"PPL",
    "gn:name":"Gor\u00e9",
    "gn:population":0,
    "gn:timezone":"Africa/Douala",
    "iso:country":"CM",
    "name:bos_x_preferred":[
        "Gore"
    ],
    "name:cat_x_preferred":[
        "Gore"
    ],
    "name:ceb_x_preferred":[
        "Gore"
    ],
    "name:ces_x_preferred":[
        "Gore"
    ],
    "name:deu_x_preferred":[
        "Gore"
    ],
    "name:fas_x_preferred":[
        "\u06af\u0648\u0631"
    ],
    "name:fin_x_preferred":[
        "Gore"
    ],
    "name:fra_x_preferred":[
        "Gore"
    ],
    "name:heb_x_preferred":[
        "\u05d2\u05d5\u05e8"
    ],
    "name:ita_x_preferred":[
        "Gore"
    ],
    "name:lit_x_preferred":[
        "Gore"
    ],
    "name:nld_x_preferred":[
        "Gore"
    ],
    "name:pol_x_preferred":[
        "Gore"
    ],
    "name:por_x_preferred":[
        "Gore"
    ],
    "name:rus_x_preferred":[
        "\u0413\u043e\u0440\u0435"
    ],
    "name:slv_x_preferred":[
        "Gore"
    ],
    "name:spa_x_preferred":[
        "Gore"
    ],
    "name:srp_x_preferred":[
        "\u0413\u043e\u0440\u0435"
    ],
    "name:swe_x_preferred":[
        "Gore"
    ],
    "name:ukr_x_preferred":[
        "\u0413\u043e\u0440\u0435"
    ],
    "name:vol_x_preferred":[
        "Gore"
    ],
    "wof:name":"Gore",
    "wof:placetype":"locality"
},
  "geometry": {"coordinates":[13.82844,9.17752],"type":"Point"}
}