{
  "type": "Feature",
  "properties": {
    "gn:admin1_code":"13.0",
    "gn:asciiname":"Gore",
    "gn:country_code":"CM",
    "gn:dem":288,
    "gn:feature_class":"P",
    "gn:feature_code":"PPL",
    "gn:name":"Gor\u00e9",
    "gn:population":0,
    "gn:timezone":"Africa/Douala",
    "iso:country":"CM",
    "wof:name":"Gore",
    "wof:placetype":"locality"
},
  "geometry": {"coordinates":[13.82844,9.17752],"type":"Point"}
}