{
  "type": "Feature",
  "properties": {
    "gn:admin1_code":"4.0",
    "gn:asciiname":"Dioula Kangoy",
    "gn:country_code":"CM",
    "gn:dem":540,
    "gn:feature_class":"P",
    "gn:feature_code":"PPL",
    "gn:name":"Dioula Kangoy",
    "gn:population":0,
    "gn:timezone":"Africa/Douala",
    "iso:country":"CM",
    "name:und_x_variant":[
        "Dioula",
        "Dioula Kangoy"
    ],
    "wof:name":"Dioula Kangoy",
    "wof:placetype":"locality"
},
  "geometry": {"coordinates":[15.35,2.25],"type":"Point"}
}