{
  "type": "Feature",
  "properties": {
    "gn:admin1_code":"12.0",
    "gn:asciiname":"Gamdama",
    "gn:country_code":"CM",
    "gn:dem":328,
    "gn:feature_class":"P",
    "gn:feature_code":"PPL",
    "gn:name":"Gamdama",
    "gn:population":0,
    "gn:timezone":"Africa/Douala",
    "iso:country":"CM",
    "wof:name":"Gamdama",
    "wof:placetype":"locality"
},
  "geometry": {"coordinates":[15.23959,10.29689],"type":"Point"}
}