{
  "type": "Feature",
  "properties": {
    "gn:admin1_code":"4.0",
    "gn:asciiname":"Monay",
    "gn:country_code":"CM",
    "gn:dem":745,
    "gn:feature_class":"P",
    "gn:feature_code":"PPL",
    "gn:name":"Monay",
    "gn:population":0,
    "gn:timezone":"Africa/Douala",
    "iso:country":"CM",
    "name:ara_x_preferred":[
        "\u0645\u0648\u0646\u0627\u064a"
    ],
    "name:cat_x_preferred":[
        "Monay"
    ],
    "name:ceb_x_preferred":[
        "Monay"
    ],
    "name:deu_x_preferred":[
        "Monay"
    ],
    "name:eus_x_preferred":[
        "Monay"
    ],
    "name:fra_x_preferred":[
        "Monay"
    ],
    "name:hun_x_preferred":[
        "Monay"
    ],
    "name:ita_x_preferred":[
        "Monay"
    ],
    "name:lat_x_preferred":[
        "Monay"
    ],
    "name:msa_x_preferred":[
        "Monay"
    ],
    "name:nld_x_preferred":[
        "Monay"
    ],
    "name:oci_x_preferred":[
        "Monay"
    ],
    "name:pms_x_preferred":[
        "Monay"
    ],
    "name:pol_x_preferred":[
        "Monay"
    ],
    "name:por_x_preferred":[
        "Monay"
    ],
    "name:slk_x_preferred":[
        "Monay"
    ],
    "name:spa_x_preferred":[
        "Monay"
    ],
    "name:swe_x_preferred":[
        "Monay"
    ],
    "name:ukr_x_preferred":[
        "\u041c\u043e\u043d\u0435"
    ],
    "name:und_x_variant":[
        "Monnay",
        "Money",
        "Monay"
    ],
    "name:uzb_x_preferred":[
        "Monay"
    ],
    "name:vie_x_preferred":[
        "Monay"
    ],
    "name:vol_x_preferred":[
        "Monay"
    ],
    "name:war_x_preferred":[
        "Monay"
    ],
    "name:zho_x_preferred":[
        "\u83ab\u5948"
    ],
    "wof:name":"Monay",
    "wof:placetype":"locality"
},
  "geometry": {"coordinates":[14.08333,5.78333],"type":"Point"}
}