{
  "type": "Feature",
  "properties": {
    "gn:admin1_code":"13.0",
    "gn:asciiname":"Singba",
    "gn:country_code":"CM",
    "gn:dem":628,
    "gn:feature_class":"P",
    "gn:feature_code":"PPL",
    "gn:name":"Singba",
    "gn:population":0,
    "gn:timezone":"Africa/Douala",
    "iso:country":"CM",
    "wof:name":"Singba",
    "wof:placetype":"locality"
},
  "geometry": {"coordinates":[13.32432,8.32216],"type":"Point"}
}