{
  "type": "Feature",
  "properties": {
    "gn:admin1_code":"13.0",
    "gn:asciiname":"Tingle",
    "gn:country_code":"CM",
    "gn:dem":290,
    "gn:feature_class":"P",
    "gn:feature_code":"PPL",
    "gn:name":"Tingl\u00e9",
    "gn:population":0,
    "gn:timezone":"Africa/Douala",
    "iso:country":"CM",
    "name:ast_x_preferred":[
        "Tingle"
    ],
    "name:fin_x_preferred":[
        "Tingle"
    ],
    "name:fra_x_preferred":[
        "Tingle"
    ],
    "name:jpn_x_preferred":[
        "\u30c1\u30f3\u30af\u30eb"
    ],
    "name:rus_x_preferred":[
        "\u0422\u0438\u043d\u0433\u043b"
    ],
    "name:spa_x_preferred":[
        "Tingle"
    ],
    "name:zho_x_preferred":[
        "\u91d1\u514b\u723e"
    ],
    "wof:name":"Tingle",
    "wof:placetype":"locality"
},
  "geometry": {"coordinates":[13.06694,8.59017],"type":"Point"}
}