{
  "type": "Feature",
  "properties": {
    "gn:admin1_code":"13.0",
    "gn:asciiname":"Ouro Gertogal",
    "gn:country_code":"CM",
    "gn:dem":229,
    "gn:feature_class":"P",
    "gn:feature_code":"PPL",
    "gn:name":"Ouro Gertogal",
    "gn:population":0,
    "gn:timezone":"Africa/Douala",
    "iso:country":"CM",
    "name:und_x_variant":[
        "Ouro Guertogal",
        "Ouro Gertogal"
    ],
    "wof:name":"Ouro Gertogal",
    "wof:placetype":"locality"
},
  "geometry": {"coordinates":[13.71667,8.88333],"type":"Point"}
}