{
  "type": "Feature",
  "properties": {
    "gn:admin1_code":"4.0",
    "gn:asciiname":"Badoume",
    "gn:country_code":"CM",
    "gn:dem":716,
    "gn:feature_class":"P",
    "gn:feature_code":"PPL",
    "gn:name":"Badoum\u00e9",
    "gn:population":0,
    "gn:timezone":"Africa/Douala",
    "iso:country":"CM",
    "wof:name":"Badoume",
    "wof:placetype":"locality"
},
  "geometry": {"coordinates":[12.98333,4.36667],"type":"Point"}
}