{
  "type": "Feature",
  "properties": {
    "gn:admin1_code":"12.0",
    "gn:asciiname":"Bigdi",
    "gn:country_code":"CM",
    "gn:dem":328,
    "gn:feature_class":"P",
    "gn:feature_code":"PPL",
    "gn:name":"Bigdi",
    "gn:population":0,
    "gn:timezone":"Africa/Douala",
    "iso:country":"CM",
    "name:und_x_variant":[
        "B\u00efkdi",
        "Bigdi"
    ],
    "wof:name":"Bigdi",
    "wof:placetype":"locality"
},
  "geometry": {"coordinates":[15.18443,10.03002],"type":"Point"}
}