{
  "type": "Feature",
  "properties": {
    "gn:admin1_code":"8.0",
    "gn:asciiname":"Njikan",
    "gn:country_code":"CM",
    "gn:dem":1192,
    "gn:feature_class":"P",
    "gn:feature_code":"PPL",
    "gn:name":"Njikan",
    "gn:population":0,
    "gn:timezone":"Africa/Douala",
    "iso:country":"CM",
    "wof:name":"Njikan",
    "wof:placetype":"locality"
},
  "geometry": {"coordinates":[10.74224,5.8306],"type":"Point"}
}