{
  "type": "Feature",
  "properties": {
    "gn:admin1_code":"11.0",
    "gn:asciiname":"Esse",
    "gn:country_code":"CM",
    "gn:dem":648,
    "gn:feature_class":"P",
    "gn:feature_code":"PPL",
    "gn:name":"Ess\u00e9",
    "gn:population":0,
    "gn:timezone":"Africa/Douala",
    "iso:country":"CM",
    "name:ceb_x_preferred":[
        "Esse"
    ],
    "name:deu_x_preferred":[
        "Esse"
    ],
    "name:fra_x_preferred":[
        "Esse"
    ],
    "name:ita_x_preferred":[
        "Esse"
    ],
    "name:nld_x_preferred":[
        "Esse"
    ],
    "name:por_x_preferred":[
        "Esse"
    ],
    "name:slk_x_preferred":[
        "Esse"
    ],
    "name:spa_x_preferred":[
        "Esse"
    ],
    "name:swe_x_preferred":[
        "Esse"
    ],
    "name:uzb_x_preferred":[
        "Esse"
    ],
    "wof:name":"Esse",
    "wof:placetype":"locality"
},
  "geometry": {"coordinates":[11.88333,4.08333],"type":"Point"}
}