{
  "type": "Feature",
  "properties": {
    "gn:admin1_code":"5.0",
    "gn:asciiname":"Yato",
    "gn:country_code":"CM",
    "gn:dem":24,
    "gn:feature_class":"P",
    "gn:feature_code":"PPL",
    "gn:name":"Yato",
    "gn:population":0,
    "gn:timezone":"Africa/Douala",
    "iso:country":"CM",
    "wof:name":"Yato",
    "wof:placetype":"locality"
},
  "geometry": {"coordinates":[9.5587,4.1532],"type":"Point"}
}