{
  "type": "Feature",
  "properties": {
    "gn:admin1_code":"12.0",
    "gn:asciiname":"Gay Gay Koumaire",
    "gn:country_code":"CM",
    "gn:dem":356,
    "gn:feature_class":"P",
    "gn:feature_code":"PPL",
    "gn:name":"Gay Gay Kouma\u00efr\u00e9",
    "gn:population":0,
    "gn:timezone":"Africa/Douala",
    "iso:country":"CM",
    "name:und_x_variant":[
        "Gay Gay Koumahir\u00e9",
        "Gay Gay Kouma\u00efr\u00e9"
    ],
    "wof:name":"Gay Gay Koumaire",
    "wof:placetype":"locality"
},
  "geometry": {"coordinates":[14.56681,10.48454],"type":"Point"}
}