{
  "type": "Feature",
  "properties": {
    "gn:admin1_code":"12.0",
    "gn:asciiname":"Panay",
    "gn:country_code":"CM",
    "gn:dem":635,
    "gn:feature_class":"P",
    "gn:feature_code":"PPL",
    "gn:name":"Panay",
    "gn:population":0,
    "gn:timezone":"Africa/Douala",
    "iso:country":"CM",
    "wof:name":"Panay",
    "wof:placetype":"locality"
},
  "geometry": {"coordinates":[13.63593,10.15831],"type":"Point"}
}