{
  "type": "Feature",
  "properties": {
    "gn:admin1_code":"12.0",
    "gn:asciiname":"Panay",
    "gn:country_code":"CM",
    "gn:dem":635,
    "gn:feature_class":"P",
    "gn:feature_code":"PPL",
    "gn:name":"Panay",
    "gn:population":0,
    "gn:timezone":"Africa/Douala",
    "iso:country":"CM",
    "name:afr_x_preferred":[
        "Panay"
    ],
    "name:aze_x_preferred":[
        "Panay"
    ],
    "name:bcl_x_preferred":[
        "Panay"
    ],
    "name:bel_x_preferred":[
        "\u041f\u0430\u043d\u0430\u0439"
    ],
    "name:bos_x_preferred":[
        "Panay"
    ],
    "name:bre_x_preferred":[
        "Panay"
    ],
    "name:cat_x_preferred":[
        "Panay"
    ],
    "name:ceb_x_preferred":[
        "Panay"
    ],
    "name:ces_x_preferred":[
        "Panaj"
    ],
    "name:cym_x_preferred":[
        "Panay"
    ],
    "name:deu_x_preferred":[
        "Panay"
    ],
    "name:ell_x_preferred":[
        "\u03a0\u03b1\u03bd\u03ac\u03b9"
    ],
    "name:epo_x_preferred":[
        "Panajo"
    ],
    "name:est_x_preferred":[
        "Panay"
    ],
    "name:eus_x_preferred":[
        "Panay"
    ],
    "name:fas_x_preferred":[
        "\u067e\u0627\u0646\u0627\u06cc"
    ],
    "name:fin_x_preferred":[
        "Panay"
    ],
    "name:fra_x_preferred":[
        "Panay"
    ],
    "name:glg_x_preferred":[
        "Panay"
    ],
    "name:hin_x_preferred":[
        "\u092a\u0928\u093e\u092f"
    ],
    "name:hrv_x_preferred":[
        "Panay"
    ],
    "name:hun_x_preferred":[
        "Panay"
    ],
    "name:ilo_x_preferred":[
        "Panay"
    ],
    "name:ind_x_preferred":[
        "Panay"
    ],
    "name:ita_x_preferred":[
        "Panay"
    ],
    "name:jpn_x_preferred":[
        "\u30d1\u30ca\u30a4\u5cf6"
    ],
    "name:kat_x_preferred":[
        "\u10de\u10d0\u10dc\u10d0\u10d8"
    ],
    "name:kir_x_preferred":[
        "\u041f\u0430\u043d\u0430\u0439"
    ],
    "name:kor_x_preferred":[
        "\ud30c\ub098\uc774\uc12c"
    ],
    "name:lit_x_preferred":[
        "Panajus"
    ],
    "name:mrj_x_preferred":[
        "\u041f\u0430\u043d\u0430\u0439"
    ],
    "name:nld_x_preferred":[
        "Panay"
    ],
    "name:nno_x_preferred":[
        "Panay"
    ],
    "name:nor_x_preferred":[
        "Panay"
    ],
    "name:pol_x_preferred":[
        "Panay"
    ],
    "name:por_x_preferred":[
        "Panay"
    ],
    "name:rus_x_preferred":[
        "\u041f\u0430\u043d\u0430\u0439"
    ],
    "name:spa_x_preferred":[
        "Panay"
    ],
    "name:srp_x_preferred":[
        "\u041f\u0430\u043d\u0430\u0458"
    ],
    "name:swe_x_preferred":[
        "Panay"
    ],
    "name:tgl_x_preferred":[
        "Panay"
    ],
    "name:tha_x_preferred":[
        "\u0e1b\u0e32\u0e44\u0e19\u0e22\u0e4c"
    ],
    "name:ukr_x_preferred":[
        "\u041f\u0430\u043d\u0430\u0439"
    ],
    "name:vie_x_preferred":[
        "Panay"
    ],
    "name:war_x_preferred":[
        "Panay"
    ],
    "name:zho_x_preferred":[
        "\u73ed\u4e43\u5c9b"
    ],
    "wof:name":"Panay",
    "wof:placetype":"locality"
},
  "geometry": {"coordinates":[13.63593,10.15831],"type":"Point"}
}