{
  "type": "Feature",
  "properties": {
    "gn:admin1_code":"5.0",
    "gn:asciiname":"Mabobe",
    "gn:country_code":"CM",
    "gn:dem":142,
    "gn:feature_class":"P",
    "gn:feature_code":"PPL",
    "gn:name":"Mabob\u00e9",
    "gn:population":0,
    "gn:timezone":"Africa/Douala",
    "iso:country":"CM",
    "wof:name":"Mabobe",
    "wof:placetype":"locality"
},
  "geometry": {"coordinates":[9.9293,4.6306],"type":"Point"}
}