{
  "type": "Feature",
  "properties": {
    "gn:admin1_code":"7.0",
    "gn:asciiname":"Tanti",
    "gn:country_code":"CM",
    "gn:dem":1406,
    "gn:feature_class":"P",
    "gn:feature_code":"PPL",
    "gn:name":"Tanti",
    "gn:population":0,
    "gn:timezone":"Africa/Douala",
    "iso:country":"CM",
    "wof:name":"Tanti",
    "wof:placetype":"locality"
},
  "geometry": {"coordinates":[10.13288,5.91332],"type":"Point"}
}