{
  "type": "Feature",
  "properties": {
    "gn:admin1_code":"12.0",
    "gn:asciiname":"Bazoza",
    "gn:country_code":"CM",
    "gn:dem":738,
    "gn:feature_class":"P",
    "gn:feature_code":"PPL",
    "gn:name":"Bazoza",
    "gn:population":0,
    "gn:timezone":"Africa/Douala",
    "iso:country":"CM",
    "wof:name":"Bazoza",
    "wof:placetype":"locality"
},
  "geometry": {"coordinates":[13.98431,10.83963],"type":"Point"}
}