{
  "type": "Feature",
  "properties": {
    "gn:admin1_code":"10.0",
    "gn:asciiname":"Malat",
    "gn:country_code":"CM",
    "gn:dem":1090,
    "gn:feature_class":"P",
    "gn:feature_code":"PPL",
    "gn:name":"Malat",
    "gn:population":0,
    "gn:timezone":"Africa/Douala",
    "iso:country":"CM",
    "name:msa_x_preferred":[
        "Malat"
    ],
    "name:ukr_x_preferred":[
        "\u041c\u0430\u043b\u0430\u0442"
    ],
    "wof:name":"Malat",
    "wof:placetype":"locality"
},
  "geometry": {"coordinates":[13.58333,7.38333],"type":"Point"}
}