{
  "type": "Feature",
  "properties": {
    "gn:admin1_code":"9.0",
    "gn:asciiname":"Masuma",
    "gn:country_code":"CM",
    "gn:dem":152,
    "gn:feature_class":"P",
    "gn:feature_code":"PPL",
    "gn:name":"Masuma",
    "gn:population":0,
    "gn:timezone":"Africa/Douala",
    "iso:country":"CM",
    "name:und_x_variant":[
        "Massuma",
        "Masuma"
    ],
    "wof:name":"Masuma",
    "wof:placetype":"locality"
},
  "geometry": {"coordinates":[9.3605,4.28076],"type":"Point"}
}