{
  "type": "Feature",
  "properties": {
    "gn:admin1_code":"7.0",
    "gn:asciiname":"Ngembo",
    "gn:country_code":"CM",
    "gn:dem":1306,
    "gn:feature_class":"P",
    "gn:feature_code":"PPL",
    "gn:name":"Ngembo",
    "gn:population":0,
    "gn:timezone":"Africa/Douala",
    "iso:country":"CM",
    "name:fra_x_preferred":[
        "Ngembo"
    ],
    "wof:name":"Ngembo",
    "wof:placetype":"locality"
},
  "geometry": {"coordinates":[10.03763,5.96387],"type":"Point"}
}