{
  "type": "Feature",
  "properties": {
    "gn:admin1_code":"8.0",
    "gn:asciiname":"Nkoussam",
    "gn:country_code":"CM",
    "gn:dem":1159,
    "gn:feature_class":"P",
    "gn:feature_code":"PPL",
    "gn:name":"Nkoussam",
    "gn:population":0,
    "gn:timezone":"Africa/Douala",
    "iso:country":"CM",
    "name:fra_x_preferred":[
        "Koussam"
    ],
    "name:fra_x_variant":[
        "Nkoussam"
    ],
    "wof:name":"Nkoussam",
    "wof:placetype":"locality"
},
  "geometry": {"coordinates":[10.9291,5.82022],"type":"Point"}
}