{
  "type": "Feature",
  "properties": {
    "gn:admin1_code":"14.0",
    "gn:asciiname":"Ngonebemeu",
    "gn:country_code":"CM",
    "gn:dem":652,
    "gn:feature_class":"P",
    "gn:feature_code":"PPL",
    "gn:name":"Ngon\u00e9bemeu",
    "gn:population":0,
    "gn:timezone":"Africa/Douala",
    "iso:country":"CM",
    "wof:name":"Ngonebemeu",
    "wof:placetype":"locality"
},
  "geometry": {"coordinates":[12.26667,3.46667],"type":"Point"}
}