{
  "type": "Feature",
  "properties": {
    "gn:admin1_code":"8.0",
    "gn:asciiname":"Ndenkeng",
    "gn:country_code":"CM",
    "gn:dem":1735,
    "gn:feature_class":"P",
    "gn:feature_code":"PPL",
    "gn:name":"Ndenkeng",
    "gn:population":0,
    "gn:timezone":"Africa/Douala",
    "iso:country":"CM",
    "wof:name":"Ndenkeng",
    "wof:placetype":"locality"
},
  "geometry": {"coordinates":[10.34017,5.25026],"type":"Point"}
}