{
  "type": "Feature",
  "properties": {
    "gn:admin1_code":"10.0",
    "gn:asciiname":"Sarki Mata",
    "gn:country_code":"CM",
    "gn:dem":585,
    "gn:feature_class":"P",
    "gn:feature_code":"PPL",
    "gn:name":"Sarki Mata",
    "gn:population":0,
    "gn:timezone":"Africa/Douala",
    "iso:country":"CM",
    "wof:name":"Sarki Mata",
    "wof:placetype":"locality"
},
  "geometry": {"coordinates":[12.56667,7.88333],"type":"Point"}
}