{
  "type": "Feature",
  "properties": {
    "gn:admin1_code":"8.0",
    "gn:asciiname":"Tsego",
    "gn:country_code":"CM",
    "gn:dem":1534,
    "gn:feature_class":"P",
    "gn:feature_code":"PPL",
    "gn:name":"Ts\u00e9go",
    "gn:population":0,
    "gn:timezone":"Africa/Douala",
    "iso:country":"CM",
    "name:fra_x_preferred":[
        "Tse Ngo"
    ],
    "name:und_x_variant":[
        "Ts\u00e9go"
    ],
    "wof:name":"Tsego",
    "wof:placetype":"locality"
},
  "geometry": {"coordinates":[10.45973,5.40733],"type":"Point"}
}