{
  "type": "Feature",
  "properties": {
    "gn:admin1_code":"9.0",
    "gn:asciiname":"Bai Bikom",
    "gn:country_code":"CM",
    "gn:dem":130,
    "gn:feature_class":"P",
    "gn:feature_code":"PPL",
    "gn:name":"Bai Bikom",
    "gn:population":0,
    "gn:timezone":"Africa/Douala",
    "iso:country":"CM",
    "wof:name":"Bai Bikom",
    "wof:placetype":"locality"
},
  "geometry": {"coordinates":[9.3344,4.5551],"type":"Point"}
}