{
  "type": "Feature",
  "properties": {
    "gn:admin1_code":"8.0",
    "gn:asciiname":"Mbing",
    "gn:country_code":"CM",
    "gn:dem":1650,
    "gn:feature_class":"P",
    "gn:feature_code":"PPL",
    "gn:name":"Mbing",
    "gn:population":0,
    "gn:timezone":"Africa/Douala",
    "iso:country":"CM",
    "wof:name":"Mbing",
    "wof:placetype":"locality"
},
  "geometry": {"coordinates":[10.01612,5.54316],"type":"Point"}
}