{
  "type": "Feature",
  "properties": {
    "gn:admin1_code":"10.0",
    "gn:asciiname":"Medjanba",
    "gn:country_code":"CM",
    "gn:dem":860,
    "gn:feature_class":"P",
    "gn:feature_code":"PPL",
    "gn:name":"Medjanba",
    "gn:population":0,
    "gn:timezone":"Africa/Douala",
    "iso:country":"CM",
    "name:und_x_variant":[
        "Manjambi",
        "Medjamba",
        "Medjanba"
    ],
    "wof:name":"Medjanba",
    "wof:placetype":"locality"
},
  "geometry": {"coordinates":[12.55809,6.3462],"type":"Point"}
}