{
  "type": "Feature",
  "properties": {
    "gn:admin1_code":"12.0",
    "gn:asciiname":"Ouro Goygoy",
    "gn:country_code":"CM",
    "gn:dem":368,
    "gn:feature_class":"P",
    "gn:feature_code":"PPL",
    "gn:name":"Ouro Goygoy",
    "gn:population":0,
    "gn:timezone":"Africa/Douala",
    "iso:country":"CM",
    "wof:name":"Ouro Goygoy",
    "wof:placetype":"locality"
},
  "geometry": {"coordinates":[14.30948,10.95751],"type":"Point"}
}