{
  "type": "Feature",
  "properties": {
    "gn:admin1_code":"0.0",
    "gn:asciiname":"Nkoumadjap III",
    "gn:country_code":"CM",
    "gn:dem":650,
    "gn:feature_class":"P",
    "gn:feature_code":"PPL",
    "gn:name":"Nkoumadjap III",
    "gn:population":0,
    "gn:timezone":"Africa/Douala",
    "iso:country":"CM",
    "wof:name":"Nkoumadjap III",
    "wof:placetype":"locality"
},
  "geometry": {"coordinates":[12.13333,3.35],"type":"Point"}
}