{
  "type": "Feature",
  "properties": {
    "gn:admin1_code":"10.0",
    "gn:asciiname":"Mayo Dabi",
    "gn:country_code":"CM",
    "gn:dem":999,
    "gn:feature_class":"P",
    "gn:feature_code":"PPL",
    "gn:name":"Mayo Dabi",
    "gn:population":0,
    "gn:timezone":"Africa/Douala",
    "iso:country":"CM",
    "wof:name":"Mayo Dabi",
    "wof:placetype":"locality"
},
  "geometry": {"coordinates":[14.51667,6.95],"type":"Point"}
}