{
  "type": "Feature",
  "properties": {
    "gn:admin1_code":"11.0",
    "gn:asciiname":"Nloudou",
    "gn:country_code":"CM",
    "gn:dem":457,
    "gn:feature_class":"P",
    "gn:feature_code":"PPL",
    "gn:name":"Nloudou",
    "gn:population":0,
    "gn:timezone":"Africa/Douala",
    "iso:country":"CM",
    "wof:name":"Nloudou",
    "wof:placetype":"locality"
},
  "geometry": {"coordinates":[11.13333,4.13333],"type":"Point"}
}