{
  "type": "Feature",
  "properties": {
    "gn:admin1_code":"13.0",
    "gn:asciiname":"Wala",
    "gn:country_code":"CM",
    "gn:dem":404,
    "gn:feature_class":"P",
    "gn:feature_code":"PPL",
    "gn:name":"Wala",
    "gn:population":0,
    "gn:timezone":"Africa/Douala",
    "iso:country":"CM",
    "name:ceb_x_preferred":[
        "Wala"
    ],
    "name:deu_x_preferred":[
        "Wala"
    ],
    "name:fra_x_preferred":[
        "Wala"
    ],
    "name:swe_x_preferred":[
        "Wala"
    ],
    "name:tgl_x_preferred":[
        "Wala"
    ],
    "name:und_x_variant":[
        "Oala",
        "Dala"
    ],
    "wof:name":"Wala",
    "wof:placetype":"locality"
},
  "geometry": {"coordinates":[13.61053,9.85904],"type":"Point"}
}