{
  "type": "Feature",
  "properties": {
    "gn:admin1_code":"13.0",
    "gn:asciiname":"Tako",
    "gn:country_code":"CM",
    "gn:dem":451,
    "gn:feature_class":"P",
    "gn:feature_code":"PPL",
    "gn:name":"Tako",
    "gn:population":0,
    "gn:timezone":"Africa/Douala",
    "iso:country":"CM",
    "wof:name":"Tako",
    "wof:placetype":"locality"
},
  "geometry": {"coordinates":[13.10803,8.49407],"type":"Point"}
}