{
  "type": "Feature",
  "properties": {
    "gn:admin1_code":"13.0",
    "gn:asciiname":"Tako",
    "gn:country_code":"CM",
    "gn:dem":451,
    "gn:feature_class":"P",
    "gn:feature_code":"PPL",
    "gn:name":"Tako",
    "gn:population":0,
    "gn:timezone":"Africa/Douala",
    "iso:country":"CM",
    "name:ceb_x_preferred":[
        "Tako"
    ],
    "name:deu_x_preferred":[
        "Tako"
    ],
    "name:jpn_x_preferred":[
        "\u30bf\u30b3"
    ],
    "name:rus_x_preferred":[
        "\u0422\u0430\u043a\u043e"
    ],
    "name:swe_x_preferred":[
        "Tako"
    ],
    "name:ukr_x_preferred":[
        "\u0422\u0430\u043a\u043e"
    ],
    "wof:name":"Tako",
    "wof:placetype":"locality"
},
  "geometry": {"coordinates":[13.10803,8.49407],"type":"Point"}
}