{
  "type": "Feature",
  "properties": {
    "gn:admin1_code":"12.0",
    "gn:asciiname":"Gouroum",
    "gn:country_code":"CM",
    "gn:dem":329,
    "gn:feature_class":"P",
    "gn:feature_code":"PPL",
    "gn:name":"Gouroum",
    "gn:population":0,
    "gn:timezone":"Africa/Douala",
    "iso:country":"CM",
    "wof:name":"Gouroum",
    "wof:placetype":"locality"
},
  "geometry": {"coordinates":[15.4291,10.10186],"type":"Point"}
}