{
  "type": "Feature",
  "properties": {
    "gn:admin1_code":"11.0",
    "gn:asciiname":"Ndjombe",
    "gn:country_code":"CM",
    "gn:dem":684,
    "gn:feature_class":"P",
    "gn:feature_code":"PPL",
    "gn:name":"Ndjomb\u00e9",
    "gn:population":0,
    "gn:timezone":"Africa/Douala",
    "iso:country":"CM",
    "wof:name":"Ndjombe",
    "wof:placetype":"locality"
},
  "geometry": {"coordinates":[12.66667,4.81667],"type":"Point"}
}