{
  "type": "Feature",
  "properties": {
    "gn:admin1_code":"13.0",
    "gn:asciiname":"Goudje",
    "gn:country_code":"CM",
    "gn:dem":319,
    "gn:feature_class":"P",
    "gn:feature_code":"PPL",
    "gn:name":"Goudj\u00e9",
    "gn:population":0,
    "gn:timezone":"Africa/Douala",
    "iso:country":"CM",
    "wof:name":"Goudje",
    "wof:placetype":"locality"
},
  "geometry": {"coordinates":[13.78333,9.58333],"type":"Point"}
}