{
  "type": "Feature",
  "properties": {
    "gn:admin1_code":"8.0",
    "gn:asciiname":"Panzou",
    "gn:country_code":"CM",
    "gn:dem":1011,
    "gn:feature_class":"P",
    "gn:feature_code":"PPL",
    "gn:name":"Panzou",
    "gn:population":0,
    "gn:timezone":"Africa/Douala",
    "iso:country":"CM",
    "name:fra_x_preferred":[
        "Panzou"
    ],
    "wof:name":"Panzou",
    "wof:placetype":"locality"
},
  "geometry": {"coordinates":[10.60861,5.4147],"type":"Point"}
}