{
  "type": "Feature",
  "properties": {
    "gn:admin1_code":"7.0",
    "gn:asciiname":"Ntambeng",
    "gn:country_code":"CM",
    "gn:dem":1257,
    "gn:feature_class":"P",
    "gn:feature_code":"PPL",
    "gn:name":"Ntambeng",
    "gn:population":0,
    "gn:timezone":"Africa/Douala",
    "iso:country":"CM",
    "name:fra_x_preferred":[
        "Ntambeng"
    ],
    "wof:name":"Ntambeng",
    "wof:placetype":"locality"
},
  "geometry": {"coordinates":[10.12995,5.99449],"type":"Point"}
}