{
  "type": "Feature",
  "properties": {
    "gn:admin1_code":"14.0",
    "gn:asciiname":"Biwong",
    "gn:country_code":"CM",
    "gn:dem":620,
    "gn:feature_class":"P",
    "gn:feature_code":"PPL",
    "gn:name":"Biwong",
    "gn:population":0,
    "gn:timezone":"Africa/Douala",
    "iso:country":"CM",
    "name:und_x_variant":[
        "Bivong",
        "Biwong"
    ],
    "wof:name":"Biwong",
    "wof:placetype":"locality"
},
  "geometry": {"coordinates":[11.35,2.76667],"type":"Point"}
}