{
  "type": "Feature",
  "properties": {
    "gn:admin1_code":"12.0",
    "gn:asciiname":"Douban Arabe",
    "gn:country_code":"CM",
    "gn:dem":289,
    "gn:feature_class":"P",
    "gn:feature_code":"PPL",
    "gn:name":"Douban Arabe",
    "gn:population":0,
    "gn:timezone":"Africa/Douala",
    "iso:country":"CM",
    "name:und_x_variant":[
        "Douban",
        "Douban Arabe"
    ],
    "wof:name":"Douban Arabe",
    "wof:placetype":"locality"
},
  "geometry": {"coordinates":[14.78291,12.63001],"type":"Point"}
}