{
  "type": "Feature",
  "properties": {
    "gn:admin1_code":"12.0",
    "gn:asciiname":"Bro",
    "gn:country_code":"CM",
    "gn:dem":675,
    "gn:feature_class":"P",
    "gn:feature_code":"PPL",
    "gn:name":"Bro",
    "gn:population":0,
    "gn:timezone":"Africa/Douala",
    "iso:country":"CM",
    "name:ceb_x_preferred":[
        "Bro"
    ],
    "name:dan_x_preferred":[
        "Bro"
    ],
    "name:deu_x_preferred":[
        "Bro"
    ],
    "name:fas_x_preferred":[
        "\u0628\u0631\u0648"
    ],
    "name:fin_x_preferred":[
        "Bro"
    ],
    "name:nld_x_preferred":[
        "Bro"
    ],
    "name:nor_x_preferred":[
        "Bro"
    ],
    "name:swe_x_preferred":[
        "Bro"
    ],
    "wof:name":"Bro",
    "wof:placetype":"locality"
},
  "geometry": {"coordinates":[13.99775,10.81057],"type":"Point"}
}