{
  "type": "Feature",
  "properties": {
    "gn:admin1_code":"12.0",
    "gn:asciiname":"Mour",
    "gn:country_code":"CM",
    "gn:dem":294,
    "gn:feature_class":"P",
    "gn:feature_code":"PPL",
    "gn:name":"Mour",
    "gn:population":0,
    "gn:timezone":"Africa/Douala",
    "iso:country":"CM",
    "name:und_x_variant":[
        "Mour-Fellatah",
        "Mour"
    ],
    "wof:name":"Mour",
    "wof:placetype":"locality"
},
  "geometry": {"coordinates":[14.74363,12.20221],"type":"Point"}
}