{
  "type": "Feature",
  "properties": {
    "gn:admin1_code":"13.0",
    "gn:asciiname":"Gang Na",
    "gn:country_code":"CM",
    "gn:dem":890,
    "gn:feature_class":"P",
    "gn:feature_code":"PPL",
    "gn:name":"Gang Na",
    "gn:population":0,
    "gn:timezone":"Africa/Douala",
    "iso:country":"CM",
    "wof:name":"Gang Na",
    "wof:placetype":"locality"
},
  "geometry": {"coordinates":[14.06667,7.61667],"type":"Point"}
}