{
  "type": "Feature",
  "properties": {
    "gn:admin1_code":"12.0",
    "gn:asciiname":"Boungay",
    "gn:country_code":"CM",
    "gn:dem":706,
    "gn:feature_class":"P",
    "gn:feature_code":"PPL",
    "gn:name":"Boungay",
    "gn:population":0,
    "gn:timezone":"Africa/Douala",
    "iso:country":"CM",
    "wof:name":"Boungay",
    "wof:placetype":"locality"
},
  "geometry": {"coordinates":[14.03977,10.90542],"type":"Point"}
}