{
  "type": "Feature",
  "properties": {
    "gn:admin1_code":"12.0",
    "gn:asciiname":"Mre",
    "gn:country_code":"CM",
    "gn:dem":305,
    "gn:feature_class":"P",
    "gn:feature_code":"PPL",
    "gn:name":"Mre",
    "gn:population":0,
    "gn:timezone":"Africa/Douala",
    "iso:country":"CM",
    "wof:name":"Mre",
    "wof:placetype":"locality"
},
  "geometry": {"coordinates":[15.0056,11.7028],"type":"Point"}
}