{
  "type": "Feature",
  "properties": {
    "gn:admin1_code":"7.0",
    "gn:asciiname":"Numben",
    "gn:country_code":"CM",
    "gn:dem":768,
    "gn:feature_class":"P",
    "gn:feature_code":"PPL",
    "gn:name":"Numben",
    "gn:population":0,
    "gn:timezone":"Africa/Douala",
    "iso:country":"CM",
    "wof:name":"Numben",
    "wof:placetype":"locality"
},
  "geometry": {"coordinates":[9.825,5.8687],"type":"Point"}
}