{
  "type": "Feature",
  "properties": {
    "gn:admin1_code":"5.0",
    "gn:asciiname":"Tangui",
    "gn:country_code":"CM",
    "gn:dem":82,
    "gn:feature_class":"P",
    "gn:feature_code":"PPL",
    "gn:name":"Tangui",
    "gn:population":0,
    "gn:timezone":"Africa/Douala",
    "iso:country":"CM",
    "wof:name":"Tangui",
    "wof:placetype":"locality"
},
  "geometry": {"coordinates":[9.6092,4.5388],"type":"Point"}
}