{
  "type": "Feature",
  "properties": {
    "gn:admin1_code":"13.0",
    "gn:asciiname":"Guiguidje",
    "gn:country_code":"CM",
    "gn:dem":324,
    "gn:feature_class":"P",
    "gn:feature_code":"PPL",
    "gn:name":"Guiguidj\u00e9",
    "gn:population":0,
    "gn:timezone":"Africa/Douala",
    "iso:country":"CM",
    "name:und_x_variant":[
        "Guigdj\u00e9",
        "Gigidj\u00e9",
        "Guiguidj\u00e9"
    ],
    "wof:name":"Guiguidje",
    "wof:placetype":"locality"
},
  "geometry": {"coordinates":[14.6164,8.6599],"type":"Point"}
}