{
  "type": "Feature",
  "properties": {
    "gn:admin1_code":"13.0",
    "gn:asciiname":"Ndip",
    "gn:country_code":"CM",
    "gn:dem":1290,
    "gn:feature_class":"P",
    "gn:feature_code":"PPL",
    "gn:name":"Ndip",
    "gn:population":0,
    "gn:timezone":"Africa/Douala",
    "iso:country":"CM",
    "wof:name":"Ndip",
    "wof:placetype":"locality"
},
  "geometry": {"coordinates":[14.48333,7.16667],"type":"Point"}
}