{
  "type": "Feature",
  "properties": {
    "gn:admin1_code":"13.0",
    "gn:asciiname":"Ouro Deri",
    "gn:country_code":"CM",
    "gn:dem":370,
    "gn:feature_class":"P",
    "gn:feature_code":"PPL",
    "gn:name":"Ouro D\u00e9ri",
    "gn:population":0,
    "gn:timezone":"Africa/Douala",
    "iso:country":"CM",
    "wof:name":"Ouro Deri",
    "wof:placetype":"locality"
},
  "geometry": {"coordinates":[13.78854,9.79301],"type":"Point"}
}