{
  "type": "Feature",
  "properties": {
    "gn:admin1_code":"10.0",
    "gn:asciiname":"Ngang Lara",
    "gn:country_code":"CM",
    "gn:dem":890,
    "gn:feature_class":"P",
    "gn:feature_code":"PPL",
    "gn:name":"Ngang Lara",
    "gn:population":0,
    "gn:timezone":"Africa/Douala",
    "iso:country":"CM",
    "wof:name":"Ngang Lara",
    "wof:placetype":"locality"
},
  "geometry": {"coordinates":[12.8263,6.58134],"type":"Point"}
}