{
  "type": "Feature",
  "properties": {
    "gn:admin1_code":"12.0",
    "gn:asciiname":"Bagalaf",
    "gn:country_code":"CM",
    "gn:dem":350,
    "gn:feature_class":"P",
    "gn:feature_code":"PPL",
    "gn:name":"Bagalaf",
    "gn:population":0,
    "gn:timezone":"Africa/Douala",
    "iso:country":"CM",
    "wof:name":"Bagalaf",
    "wof:placetype":"locality"
},
  "geometry": {"coordinates":[14.53314,10.69611],"type":"Point"}
}