{
  "type": "Feature",
  "properties": {
    "gn:admin1_code":"8.0",
    "gn:asciiname":"Menzi",
    "gn:country_code":"CM",
    "gn:dem":1344,
    "gn:feature_class":"P",
    "gn:feature_code":"PPL",
    "gn:name":"M\u00e8nzi",
    "gn:population":0,
    "gn:timezone":"Africa/Douala",
    "iso:country":"CM",
    "name:und_x_variant":[
        "M\u00e8nzi",
        "M\u00e8nzi II"
    ],
    "wof:name":"Menzi",
    "wof:placetype":"locality"
},
  "geometry": {"coordinates":[10.45916,5.48241],"type":"Point"}
}