{
  "type": "Feature",
  "properties": {
    "gn:admin1_code":"14.0",
    "gn:asciiname":"Mvamedjap Fong",
    "gn:country_code":"CM",
    "gn:dem":688,
    "gn:feature_class":"P",
    "gn:feature_code":"PPL",
    "gn:name":"Mvam\u00e9djap Fong",
    "gn:population":0,
    "gn:timezone":"Africa/Douala",
    "iso:country":"CM",
    "wof:name":"Mvamedjap Fong",
    "wof:placetype":"locality"
},
  "geometry": {"coordinates":[11.58333,3.06667],"type":"Point"}
}