{
  "type": "Feature",
  "properties": {
    "gn:admin1_code":"7.0",
    "gn:asciiname":"Bananka",
    "gn:country_code":"CM",
    "gn:dem":1368,
    "gn:feature_class":"P",
    "gn:feature_code":"PPL",
    "gn:name":"Bananka",
    "gn:population":0,
    "gn:timezone":"Africa/Douala",
    "iso:country":"CM",
    "wof:name":"Bananka",
    "wof:placetype":"locality"
},
  "geometry": {"coordinates":[9.71259,6.04684],"type":"Point"}
}