{
  "type": "Feature",
  "properties": {
    "gn:admin1_code":"4.0",
    "gn:asciiname":"Mwapak",
    "gn:country_code":"CM",
    "gn:dem":585,
    "gn:feature_class":"P",
    "gn:feature_code":"PPL",
    "gn:name":"Mwapak",
    "gn:population":0,
    "gn:timezone":"Africa/Douala",
    "iso:country":"CM",
    "name:und_x_variant":[
        "Moapak",
        "Mwapak"
    ],
    "wof:name":"Mwapak",
    "wof:placetype":"locality"
},
  "geometry": {"coordinates":[14.71667,3.43333],"type":"Point"}
}