{
  "type": "Feature",
  "properties": {
    "gn:admin1_code":"12.0",
    "gn:asciiname":"Bia",
    "gn:country_code":"CM",
    "gn:dem":358,
    "gn:feature_class":"P",
    "gn:feature_code":"PPL",
    "gn:name":"Bia",
    "gn:population":0,
    "gn:timezone":"Africa/Douala",
    "iso:country":"CM",
    "wof:name":"Bia",
    "wof:placetype":"locality"
},
  "geometry": {"coordinates":[14.09262,11.16888],"type":"Point"}
}