{
  "type": "Feature",
  "properties": {
    "gn:admin1_code":"8.0",
    "gn:asciiname":"Mouwe",
    "gn:country_code":"CM",
    "gn:dem":1582,
    "gn:feature_class":"P",
    "gn:feature_code":"PPL",
    "gn:name":"Mouw\u00e8",
    "gn:population":0,
    "gn:timezone":"Africa/Douala",
    "iso:country":"CM",
    "wof:name":"Mouwe",
    "wof:placetype":"locality"
},
  "geometry": {"coordinates":[10.39566,5.35966],"type":"Point"}
}