{
  "type": "Feature",
  "properties": {
    "gn:admin1_code":"12.0",
    "gn:asciiname":"Mazigat",
    "gn:country_code":"CM",
    "gn:dem":586,
    "gn:feature_class":"P",
    "gn:feature_code":"PPL",
    "gn:name":"Mazigat",
    "gn:population":0,
    "gn:timezone":"Africa/Douala",
    "iso:country":"CM",
    "wof:name":"Mazigat",
    "wof:placetype":"locality"
},
  "geometry": {"coordinates":[13.8154,10.52798],"type":"Point"}
}