{
  "type": "Feature",
  "properties": {
    "gn:admin1_code":"12.0",
    "gn:asciiname":"Ouro Zangui",
    "gn:country_code":"CM",
    "gn:dem":362,
    "gn:feature_class":"P",
    "gn:feature_code":"PPL",
    "gn:name":"Ouro Zangui",
    "gn:population":0,
    "gn:timezone":"Africa/Douala",
    "iso:country":"CM",
    "wof:name":"Ouro Zangui",
    "wof:placetype":"locality"
},
  "geometry": {"coordinates":[14.52203,10.51119],"type":"Point"}
}