{
  "type": "Feature",
  "properties": {
    "gn:admin1_code":"4.0",
    "gn:asciiname":"Nkolkwa",
    "gn:country_code":"CM",
    "gn:dem":725,
    "gn:feature_class":"P",
    "gn:feature_code":"PPL",
    "gn:name":"Nkolkwa",
    "gn:population":0,
    "gn:timezone":"Africa/Douala",
    "iso:country":"CM",
    "wof:name":"Nkolkwa",
    "wof:placetype":"locality"
},
  "geometry": {"coordinates":[12.71667,3.51667],"type":"Point"}
}