{
  "type": "Feature",
  "properties": {
    "gn:admin1_code":"9.0",
    "gn:asciiname":"New Madie",
    "gn:country_code":"CM",
    "gn:dem":1148,
    "gn:feature_class":"P",
    "gn:feature_code":"PPL",
    "gn:name":"New Madie",
    "gn:population":0,
    "gn:timezone":"Africa/Douala",
    "iso:country":"CM",
    "wof:name":"New Madie",
    "wof:placetype":"locality"
},
  "geometry": {"coordinates":[9.2216,4.9873],"type":"Point"}
}