{
  "type": "Feature",
  "properties": {
    "gn:admin1_code":"13.0",
    "gn:asciiname":"Aoudi",
    "gn:country_code":"CM",
    "gn:dem":385,
    "gn:feature_class":"P",
    "gn:feature_code":"PPL",
    "gn:name":"Aoudi",
    "gn:population":0,
    "gn:timezone":"Africa/Douala",
    "iso:country":"CM",
    "wof:name":"Aoudi",
    "wof:placetype":"locality"
},
  "geometry": {"coordinates":[12.31667,8.35],"type":"Point"}
}