{
  "type": "Feature",
  "properties": {
    "gn:admin1_code":"8.0",
    "gn:asciiname":"Melang Mefou",
    "gn:country_code":"CM",
    "gn:dem":1502,
    "gn:feature_class":"P",
    "gn:feature_code":"PPL",
    "gn:name":"Melang Mefou",
    "gn:population":0,
    "gn:timezone":"Africa/Douala",
    "iso:country":"CM",
    "name:fra_x_preferred":[
        "Melang Mefou"
    ],
    "wof:name":"Melang Mefou",
    "wof:placetype":"locality"
},
  "geometry": {"coordinates":[10.38505,5.37832],"type":"Point"}
}