{
  "type": "Feature",
  "properties": {
    "gn:admin1_code":"12.0",
    "gn:asciiname":"Chagama",
    "gn:country_code":"CM",
    "gn:dem":287,
    "gn:feature_class":"P",
    "gn:feature_code":"PPL",
    "gn:name":"Chagama",
    "gn:population":0,
    "gn:timezone":"Africa/Douala",
    "iso:country":"CM",
    "name:fas_x_preferred":[
        "\u0686\u0627\u06af\u0627\u0645\u0627"
    ],
    "name:pol_x_preferred":[
        "Cha-gama"
    ],
    "name:und_x_variant":[
        "Ourochagama"
    ],
    "wof:name":"Chagama",
    "wof:placetype":"locality"
},
  "geometry": {"coordinates":[14.36629,12.46709],"type":"Point"}
}