{
  "type": "Feature",
  "properties": {
    "gn:admin1_code":"4.0",
    "gn:asciiname":"Pater",
    "gn:country_code":"CM",
    "gn:dem":662,
    "gn:feature_class":"P",
    "gn:feature_code":"PPL",
    "gn:name":"Pat\u00e9r",
    "gn:population":0,
    "gn:timezone":"Africa/Douala",
    "iso:country":"CM",
    "name:bre_x_preferred":[
        "Pater"
    ],
    "name:deu_x_preferred":[
        "Pater"
    ],
    "name:fra_x_preferred":[
        "Pater"
    ],
    "name:ita_x_preferred":[
        "Pater"
    ],
    "name:pol_x_preferred":[
        "Pater"
    ],
    "name:rus_x_preferred":[
        "\u041f\u0430\u0442\u0435\u0440"
    ],
    "name:slk_x_preferred":[
        "Pater"
    ],
    "name:slv_x_preferred":[
        "Pater"
    ],
    "name:spa_x_preferred":[
        "Pater"
    ],
    "wof:name":"Pater",
    "wof:placetype":"locality"
},
  "geometry": {"coordinates":[15.06667,3.81667],"type":"Point"}
}