{
  "type": "Feature",
  "properties": {
    "gn:admin1_code":"10.0",
    "gn:asciiname":"Baran",
    "gn:country_code":"CM",
    "gn:dem":1411,
    "gn:feature_class":"P",
    "gn:feature_code":"PPL",
    "gn:name":"Baran",
    "gn:population":0,
    "gn:timezone":"Africa/Douala",
    "iso:country":"CM",
    "name:deu_x_preferred":[
        "Baran"
    ],
    "name:fra_x_preferred":[
        "Baran"
    ],
    "name:ita_x_preferred":[
        "Baran"
    ],
    "name:nld_x_preferred":[
        "Baran"
    ],
    "name:pol_x_preferred":[
        "Baran"
    ],
    "name:rus_x_preferred":[
        "\u0411\u0430\u0440\u0430\u043d"
    ],
    "name:slk_x_preferred":[
        "Baran"
    ],
    "name:swe_x_preferred":[
        "Baran"
    ],
    "name:ukr_x_preferred":[
        "\u0411\u0430\u0440\u0430\u043d"
    ],
    "wof:name":"Baran",
    "wof:placetype":"locality"
},
  "geometry": {"coordinates":[13.73333,7.63333],"type":"Point"}
}