{
  "type": "Feature",
  "properties": {
    "gn:admin1_code":"8.0",
    "gn:asciiname":"Ngwa",
    "gn:country_code":"CM",
    "gn:dem":1349,
    "gn:feature_class":"P",
    "gn:feature_code":"PPL",
    "gn:name":"Ngwa",
    "gn:population":0,
    "gn:timezone":"Africa/Douala",
    "iso:country":"CM",
    "name:cat_x_preferred":[
        "Ngwes"
    ],
    "name:por_x_preferred":[
        "Ngwa"
    ],
    "name:und_x_variant":[
        "Bangoa",
        "Bangwa",
        "Ngwa"
    ],
    "wof:name":"Ngwa",
    "wof:placetype":"locality"
},
  "geometry": {"coordinates":[10.48097,5.20134],"type":"Point"}
}