{
  "type": "Feature",
  "properties": {
    "gn:admin1_code":"12.0",
    "gn:asciiname":"Mbougouane",
    "gn:country_code":"CM",
    "gn:dem":748,
    "gn:feature_class":"P",
    "gn:feature_code":"PPL",
    "gn:name":"Mbougouane",
    "gn:population":0,
    "gn:timezone":"Africa/Douala",
    "iso:country":"CM",
    "wof:name":"Mbougouane",
    "wof:placetype":"locality"
},
  "geometry": {"coordinates":[13.6956,10.55535],"type":"Point"}
}