{
  "type": "Feature",
  "properties": {
    "gn:admin1_code":"8.0",
    "gn:asciiname":"Netam",
    "gn:country_code":"CM",
    "gn:dem":1270,
    "gn:feature_class":"P",
    "gn:feature_code":"PPL",
    "gn:name":"Netam",
    "gn:population":0,
    "gn:timezone":"Africa/Douala",
    "iso:country":"CM",
    "wof:name":"Netam",
    "wof:placetype":"locality"
},
  "geometry": {"coordinates":[10.58611,5.13059],"type":"Point"}
}