{
  "type": "Feature",
  "properties": {
    "gn:admin1_code":"9.0",
    "gn:asciiname":"Araru",
    "gn:country_code":"CM",
    "gn:dem":168,
    "gn:feature_class":"P",
    "gn:feature_code":"PPL",
    "gn:name":"Araru",
    "gn:population":0,
    "gn:timezone":"Africa/Douala",
    "iso:country":"CM",
    "wof:name":"Araru",
    "wof:placetype":"locality"
},
  "geometry": {"coordinates":[9.01491,5.60257],"type":"Point"}
}