{
  "type": "Feature",
  "properties": {
    "gn:admin1_code":"5.0",
    "gn:asciiname":"Mandjibo",
    "gn:country_code":"CM",
    "gn:dem":550,
    "gn:feature_class":"P",
    "gn:feature_code":"PPL",
    "gn:name":"Mandjibo",
    "gn:population":0,
    "gn:timezone":"Africa/Douala",
    "iso:country":"CM",
    "name:fra_x_preferred":[
        "Manjibo"
    ],
    "name:fra_x_variant":[
        "Mandjibo"
    ],
    "wof:name":"Mandjibo",
    "wof:placetype":"locality"
},
  "geometry": {"coordinates":[10.03724,5.01147],"type":"Point"}
}