{
  "type": "Feature",
  "properties": {
    "gn:admin1_code":"8.0",
    "gn:asciiname":"Njouwong",
    "gn:country_code":"CM",
    "gn:dem":1494,
    "gn:feature_class":"P",
    "gn:feature_code":"PPL",
    "gn:name":"Njouwong",
    "gn:population":0,
    "gn:timezone":"Africa/Douala",
    "iso:country":"CM",
    "wof:name":"Njouwong",
    "wof:placetype":"locality"
},
  "geometry": {"coordinates":[10.30677,5.43491],"type":"Point"}
}