{
  "type": "Feature",
  "properties": {
    "gn:admin1_code":"12.0",
    "gn:asciiname":"Kodogou",
    "gn:country_code":"CM",
    "gn:dem":335,
    "gn:feature_class":"P",
    "gn:feature_code":"PPL",
    "gn:name":"Kodogou",
    "gn:population":0,
    "gn:timezone":"Africa/Douala",
    "iso:country":"CM",
    "wof:name":"Kodogou",
    "wof:placetype":"locality"
},
  "geometry": {"coordinates":[14.08596,11.25625],"type":"Point"}
}