{
  "type": "Feature",
  "properties": {
    "gn:admin1_code":"12.0",
    "gn:asciiname":"Mandoz",
    "gn:country_code":"CM",
    "gn:dem":811,
    "gn:feature_class":"P",
    "gn:feature_code":"PPL",
    "gn:name":"Mandoz",
    "gn:population":0,
    "gn:timezone":"Africa/Douala",
    "iso:country":"CM",
    "wof:name":"Mandoz",
    "wof:placetype":"locality"
},
  "geometry": {"coordinates":[13.85616,10.71043],"type":"Point"}
}