{
  "type": "Feature",
  "properties": {
    "gn:admin1_code":"13.0",
    "gn:asciiname":"Balche",
    "gn:country_code":"CM",
    "gn:dem":363,
    "gn:feature_class":"P",
    "gn:feature_code":"PPL",
    "gn:name":"Balch\u00e9",
    "gn:population":0,
    "gn:timezone":"Africa/Douala",
    "iso:country":"CM",
    "wof:name":"Balche",
    "wof:placetype":"locality"
},
  "geometry": {"coordinates":[13.46041,8.49325],"type":"Point"}
}