{
  "type": "Feature",
  "properties": {
    "gn:admin1_code":"8.0",
    "gn:asciiname":"Ngbang",
    "gn:country_code":"CM",
    "gn:dem":1495,
    "gn:feature_class":"P",
    "gn:feature_code":"PPL",
    "gn:name":"Ngbang",
    "gn:population":0,
    "gn:timezone":"Africa/Douala",
    "iso:country":"CM",
    "wof:name":"Ngbang",
    "wof:placetype":"locality"
},
  "geometry": {"coordinates":[10.22753,5.45861],"type":"Point"}
}