{
  "type": "Feature",
  "properties": {
    "gn:admin1_code":"12.0",
    "gn:asciiname":"Ouro Boulode",
    "gn:country_code":"CM",
    "gn:dem":503,
    "gn:feature_class":"P",
    "gn:feature_code":"PPL",
    "gn:name":"Ouro Boulod\u00e9",
    "gn:population":0,
    "gn:timezone":"Africa/Douala",
    "iso:country":"CM",
    "wof:name":"Ouro Boulode",
    "wof:placetype":"locality"
},
  "geometry": {"coordinates":[13.87753,10.41797],"type":"Point"}
}