{
  "type": "Feature",
  "properties": {
    "gn:admin1_code":"12.0",
    "gn:asciiname":"Goizinak",
    "gn:country_code":"CM",
    "gn:dem":302,
    "gn:feature_class":"P",
    "gn:feature_code":"PPL",
    "gn:name":"Go\u00efzinak",
    "gn:population":0,
    "gn:timezone":"Africa/Douala",
    "iso:country":"CM",
    "wof:name":"Goizinak",
    "wof:placetype":"locality"
},
  "geometry": {"coordinates":[15.11491,11.51017],"type":"Point"}
}