{
  "type": "Feature",
  "properties": {
    "gn:admin1_code":"12.0",
    "gn:asciiname":"Baliak",
    "gn:country_code":"CM",
    "gn:dem":759,
    "gn:feature_class":"P",
    "gn:feature_code":"PPL",
    "gn:name":"Baliak",
    "gn:population":0,
    "gn:timezone":"Africa/Douala",
    "iso:country":"CM",
    "wof:name":"Baliak",
    "wof:placetype":"locality"
},
  "geometry": {"coordinates":[13.93483,10.65581],"type":"Point"}
}