{
  "type": "Feature",
  "properties": {
    "gn:admin1_code":"5.0",
    "gn:asciiname":"Djouki",
    "gn:country_code":"CM",
    "gn:dem":35,
    "gn:feature_class":"P",
    "gn:feature_code":"PPL",
    "gn:name":"Djouki",
    "gn:population":0,
    "gn:timezone":"Africa/Douala",
    "iso:country":"CM",
    "name:und_x_variant":[
        "Njuki",
        "Njouki",
        "Djouki"
    ],
    "wof:name":"Djouki",
    "wof:placetype":"locality"
},
  "geometry": {"coordinates":[9.6226,4.1445],"type":"Point"}
}