{
  "type": "Feature",
  "properties": {
    "gn:admin1_code":"11.0",
    "gn:asciiname":"Lekoubek",
    "gn:country_code":"CM",
    "gn:dem":488,
    "gn:feature_class":"P",
    "gn:feature_code":"PPL",
    "gn:name":"L\u00e9koubek",
    "gn:population":0,
    "gn:timezone":"Africa/Douala",
    "iso:country":"CM",
    "wof:name":"Lekoubek",
    "wof:placetype":"locality"
},
  "geometry": {"coordinates":[11.48333,4.38333],"type":"Point"}
}