{
  "type": "Feature",
  "properties": {
    "gn:admin1_code":"8.0",
    "gn:asciiname":"Ndandut",
    "gn:country_code":"CM",
    "gn:dem":1149,
    "gn:feature_class":"P",
    "gn:feature_code":"PPL",
    "gn:name":"Ndandut",
    "gn:population":0,
    "gn:timezone":"Africa/Douala",
    "iso:country":"CM",
    "wof:name":"Ndandut",
    "wof:placetype":"locality"
},
  "geometry": {"coordinates":[10.54666,5.19655],"type":"Point"}
}