{
  "type": "Feature",
  "properties": {
    "gn:admin1_code":"13.0",
    "gn:asciiname":"Mbotilgou",
    "gn:country_code":"CM",
    "gn:dem":502,
    "gn:feature_class":"P",
    "gn:feature_code":"PPL",
    "gn:name":"Mbotilgou",
    "gn:population":0,
    "gn:timezone":"Africa/Douala",
    "iso:country":"CM",
    "wof:name":"Mbotilgou",
    "wof:placetype":"locality"
},
  "geometry": {"coordinates":[13.43333,9.56667],"type":"Point"}
}