{
  "type": "Feature",
  "properties": {
    "gn:admin1_code":"14.0",
    "gn:asciiname":"Melondo",
    "gn:country_code":"CM",
    "gn:dem":713,
    "gn:feature_class":"P",
    "gn:feature_code":"PPL",
    "gn:name":"M\u00e9londo",
    "gn:population":0,
    "gn:timezone":"Africa/Douala",
    "iso:country":"CM",
    "wof:name":"Melondo",
    "wof:placetype":"locality"
},
  "geometry": {"coordinates":[12.48333,3.46667],"type":"Point"}
}