{
  "type": "Feature",
  "properties": {
    "gn:admin1_code":"5.0",
    "gn:asciiname":"Makakan",
    "gn:country_code":"CM",
    "gn:dem":392,
    "gn:feature_class":"P",
    "gn:feature_code":"PPL",
    "gn:name":"Makakan",
    "gn:population":0,
    "gn:timezone":"Africa/Douala",
    "iso:country":"CM",
    "wof:name":"Makakan",
    "wof:placetype":"locality"
},
  "geometry": {"coordinates":[10.28333,4.81667],"type":"Point"}
}