{
  "type": "Feature",
  "properties": {
    "gn:admin1_code":"8.0",
    "gn:asciiname":"Nkoumangba",
    "gn:country_code":"CM",
    "gn:dem":1164,
    "gn:feature_class":"P",
    "gn:feature_code":"PPL",
    "gn:name":"Nkoumangba",
    "gn:population":0,
    "gn:timezone":"Africa/Douala",
    "iso:country":"CM",
    "name:fra_x_preferred":[
        "Nkoumangba"
    ],
    "wof:name":"Nkoumangba",
    "wof:placetype":"locality"
},
  "geometry": {"coordinates":[10.62955,5.78615],"type":"Point"}
}