{
  "type": "Feature",
  "properties": {
    "gn:admin1_code":"14.0",
    "gn:asciiname":"Minkoo",
    "gn:country_code":"CM",
    "gn:dem":669,
    "gn:feature_class":"P",
    "gn:feature_code":"PPL",
    "gn:name":"Minkoo",
    "gn:population":0,
    "gn:timezone":"Africa/Douala",
    "iso:country":"CM",
    "wof:name":"Minkoo",
    "wof:placetype":"locality"
},
  "geometry": {"coordinates":[12.66667,2.63333],"type":"Point"}
}