{
  "type": "Feature",
  "properties": {
    "gn:admin1_code":"5.0",
    "gn:asciiname":"Bonandam",
    "gn:country_code":"CM",
    "gn:dem":227,
    "gn:feature_class":"P",
    "gn:feature_code":"PPL",
    "gn:name":"Bonandam",
    "gn:population":0,
    "gn:timezone":"Africa/Douala",
    "iso:country":"CM",
    "wof:name":"Bonandam",
    "wof:placetype":"locality"
},
  "geometry": {"coordinates":[9.8384,4.7235],"type":"Point"}
}