{
  "type": "Feature",
  "properties": {
    "gn:admin1_code":"10.0",
    "gn:asciiname":"Sarki Hai",
    "gn:country_code":"CM",
    "gn:dem":615,
    "gn:feature_class":"P",
    "gn:feature_code":"PPL",
    "gn:name":"Sarki Ha\u00ef",
    "gn:population":0,
    "gn:timezone":"Africa/Douala",
    "iso:country":"CM",
    "wof:name":"Sarki Hai",
    "wof:placetype":"locality"
},
  "geometry": {"coordinates":[12.15,7.61667],"type":"Point"}
}