{
  "type": "Feature",
  "properties": {
    "gn:admin1_code":"4.0",
    "gn:asciiname":"Ntimbe",
    "gn:country_code":"CM",
    "gn:dem":736,
    "gn:feature_class":"P",
    "gn:feature_code":"PPL",
    "gn:name":"Ntimb\u00e9",
    "gn:population":0,
    "gn:timezone":"Africa/Douala",
    "iso:country":"CM",
    "wof:name":"Ntimbe",
    "wof:placetype":"locality"
},
  "geometry": {"coordinates":[13.05,3.83333],"type":"Point"}
}