{
  "type": "Feature",
  "properties": {
    "gn:admin1_code":"13.0",
    "gn:asciiname":"Kapkana",
    "gn:country_code":"CM",
    "gn:dem":796,
    "gn:feature_class":"P",
    "gn:feature_code":"PPL",
    "gn:name":"Kapkana",
    "gn:population":0,
    "gn:timezone":"Africa/Douala",
    "iso:country":"CM",
    "wof:name":"Kapkana",
    "wof:placetype":"locality"
},
  "geometry": {"coordinates":[13.42798,10.00153],"type":"Point"}
}