{
  "type": "Feature",
  "properties": {
    "gn:admin1_code":"13.0",
    "gn:asciiname":"Gachire",
    "gn:country_code":"CM",
    "gn:dem":562,
    "gn:feature_class":"P",
    "gn:feature_code":"PPL",
    "gn:name":"Gachir\u00e9",
    "gn:population":0,
    "gn:timezone":"Africa/Douala",
    "iso:country":"CM",
    "wof:name":"Gachire",
    "wof:placetype":"locality"
},
  "geometry": {"coordinates":[13.30538,9.91721],"type":"Point"}
}