{
  "type": "Feature",
  "properties": {
    "gn:admin1_code":"9.0",
    "gn:asciiname":"Bangang",
    "gn:country_code":"CM",
    "gn:dem":228,
    "gn:feature_class":"P",
    "gn:feature_code":"PPL",
    "gn:name":"Bangang",
    "gn:population":0,
    "gn:timezone":"Africa/Douala",
    "iso:country":"CM",
    "wof:name":"Bangang",
    "wof:placetype":"locality"
},
  "geometry": {"coordinates":[9.8876,5.6061],"type":"Point"}
}