{
  "type": "Feature",
  "properties": {
    "gn:admin1_code":"8.0",
    "gn:asciiname":"Zemekong",
    "gn:country_code":"CM",
    "gn:dem":1428,
    "gn:feature_class":"P",
    "gn:feature_code":"PPL",
    "gn:name":"Zemekong",
    "gn:population":0,
    "gn:timezone":"Africa/Douala",
    "iso:country":"CM",
    "wof:name":"Zemekong",
    "wof:placetype":"locality"
},
  "geometry": {"coordinates":[10.22769,5.47443],"type":"Point"}
}