{
  "type": "Feature",
  "properties": {
    "gn:admin1_code":"12.0",
    "gn:asciiname":"Nguetchewe",
    "gn:country_code":"CM",
    "gn:dem":427,
    "gn:feature_class":"P",
    "gn:feature_code":"PPL",
    "gn:name":"Nguetch\u00e9w\u00e9",
    "gn:population":0,
    "gn:timezone":"Africa/Douala",
    "iso:country":"CM",
    "name:und_x_variant":[
        "Ngu\u00e9ch\u00e9w\u00e9",
        "Nguetch\u00e9w\u00e9",
        "Ng\u00e9ch\u00e9w\u00e9",
        "Ngach\u00e9v\u00e9",
        "Ngu\u00e9tch\u00e9ou\u00e9"
    ],
    "wof:name":"Nguetchewe",
    "wof:placetype":"locality"
},
  "geometry": {"coordinates":[13.94151,10.99841],"type":"Point"}
}