{
  "type": "Feature",
  "properties": {
    "gn:admin1_code":"9.0",
    "gn:asciiname":"Temzem",
    "gn:country_code":"CM",
    "gn:dem":2430,
    "gn:feature_class":"P",
    "gn:feature_code":"PPL",
    "gn:name":"Temzem",
    "gn:population":0,
    "gn:timezone":"Africa/Douala",
    "iso:country":"CM",
    "wof:name":"Temzem",
    "wof:placetype":"locality"
},
  "geometry": {"coordinates":[10.03706,5.63479],"type":"Point"}
}