{
  "type": "Feature",
  "properties": {
    "gn:admin1_code":"12.0",
    "gn:asciiname":"Sarma",
    "gn:country_code":"CM",
    "gn:dem":431,
    "gn:feature_class":"P",
    "gn:feature_code":"PPL",
    "gn:name":"Sarma",
    "gn:population":0,
    "gn:timezone":"Africa/Douala",
    "iso:country":"CM",
    "wof:name":"Sarma",
    "wof:placetype":"locality"
},
  "geometry": {"coordinates":[14.28919,10.40718],"type":"Point"}
}