{
  "type": "Feature",
  "properties": {
    "gn:admin1_code":"12.0",
    "gn:asciiname":"Sarma",
    "gn:country_code":"CM",
    "gn:dem":431,
    "gn:feature_class":"P",
    "gn:feature_code":"PPL",
    "gn:name":"Sarma",
    "gn:population":0,
    "gn:timezone":"Africa/Douala",
    "iso:country":"CM",
    "name:ceb_x_preferred":[
        "Sarma"
    ],
    "name:deu_x_preferred":[
        "Sarma"
    ],
    "name:fra_x_preferred":[
        "Sarma"
    ],
    "name:ita_x_preferred":[
        "Sarma"
    ],
    "name:jpn_x_preferred":[
        "\u30b5\u30eb\u30de"
    ],
    "name:lav_x_preferred":[
        "Sarma"
    ],
    "name:nld_x_preferred":[
        "Sarma"
    ],
    "name:pol_x_preferred":[
        "Sarma"
    ],
    "name:scn_x_preferred":[
        "Sarma"
    ],
    "name:swe_x_preferred":[
        "Dolmar#Sarma"
    ],
    "wof:name":"Sarma",
    "wof:placetype":"locality"
},
  "geometry": {"coordinates":[14.28919,10.40718],"type":"Point"}
}