{
  "type": "Feature",
  "properties": {
    "gn:admin1_code":"4.0",
    "gn:asciiname":"Kobi",
    "gn:country_code":"CM",
    "gn:dem":615,
    "gn:feature_class":"P",
    "gn:feature_code":"PPL",
    "gn:name":"Kobi",
    "gn:population":0,
    "gn:timezone":"Africa/Douala",
    "iso:country":"CM",
    "name:ceb_x_preferred":[
        "Kobi"
    ],
    "name:deu_x_preferred":[
        "Kobi"
    ],
    "name:est_x_preferred":[
        "Kobi"
    ],
    "name:jpn_x_preferred":[
        "\u30b3\u30d3\u30fc"
    ],
    "name:rus_x_preferred":[
        "\u041a\u043e\u0431\u0438"
    ],
    "name:swe_x_preferred":[
        "Kobi"
    ],
    "name:tgl_x_preferred":[
        "Kobi"
    ],
    "name:ukr_x_preferred":[
        "\u041a\u043e\u0431\u0456"
    ],
    "wof:name":"Kobi",
    "wof:placetype":"locality"
},
  "geometry": {"coordinates":[14.69636,4.19688],"type":"Point"}
}