{
  "type": "Feature",
  "properties": {
    "gn:admin1_code":"8.0",
    "gn:asciiname":"Mila",
    "gn:country_code":"CM",
    "gn:dem":1630,
    "gn:feature_class":"P",
    "gn:feature_code":"PPL",
    "gn:name":"Mila",
    "gn:population":0,
    "gn:timezone":"Africa/Douala",
    "iso:country":"CM",
    "name:ceb_x_preferred":[
        "Mila"
    ],
    "name:deu_x_preferred":[
        "Mila"
    ],
    "name:fra_x_preferred":[
        "Mila"
    ],
    "name:heb_x_preferred":[
        "\u05de\u05d9\u05dc\u05d4"
    ],
    "name:hun_x_preferred":[
        "Mila"
    ],
    "name:ita_x_preferred":[
        "Mila"
    ],
    "name:lit_x_preferred":[
        "Mila"
    ],
    "name:msa_x_preferred":[
        "Mila"
    ],
    "name:nld_x_preferred":[
        "Mila"
    ],
    "name:oci_x_preferred":[
        "Mila"
    ],
    "name:pol_x_preferred":[
        "Mila"
    ],
    "name:por_x_preferred":[
        "Mila"
    ],
    "name:ron_x_preferred":[
        "Mila"
    ],
    "name:rus_x_preferred":[
        "\u041c\u0438\u043b\u0430"
    ],
    "name:spa_x_preferred":[
        "Mila"
    ],
    "name:swe_x_preferred":[
        "Mila"
    ],
    "name:und_x_variant":[
        "Mila\u2019 I"
    ],
    "wof:name":"Mila",
    "wof:placetype":"locality"
},
  "geometry": {"coordinates":[10.21754,5.42875],"type":"Point"}
}