{
  "type": "Feature",
  "properties": {
    "gn:admin1_code":"8.0",
    "gn:asciiname":"Mila",
    "gn:country_code":"CM",
    "gn:dem":1630,
    "gn:feature_class":"P",
    "gn:feature_code":"PPL",
    "gn:name":"Mila",
    "gn:population":0,
    "gn:timezone":"Africa/Douala",
    "iso:country":"CM",
    "name:und_x_variant":[
        "Mila\u2019 I"
    ],
    "wof:name":"Mila",
    "wof:placetype":"locality"
},
  "geometry": {"coordinates":[10.21754,5.42875],"type":"Point"}
}