{
  "type": "Feature",
  "properties": {
    "gn:admin1_code":"12.0",
    "gn:asciiname":"Vourkaza",
    "gn:country_code":"CM",
    "gn:dem":687,
    "gn:feature_class":"P",
    "gn:feature_code":"PPL",
    "gn:name":"Vourkaza",
    "gn:population":0,
    "gn:timezone":"Africa/Douala",
    "iso:country":"CM",
    "wof:name":"Vourkaza",
    "wof:placetype":"locality"
},
  "geometry": {"coordinates":[13.81932,10.9754],"type":"Point"}
}