{
  "type": "Feature",
  "properties": {
    "gn:admin1_code":"7.0",
    "gn:asciiname":"Zang Tabi",
    "gn:country_code":"CM",
    "gn:dem":1364,
    "gn:feature_class":"P",
    "gn:feature_code":"PPL",
    "gn:name":"Zang Tabi",
    "gn:population":0,
    "gn:timezone":"Africa/Douala",
    "iso:country":"CM",
    "wof:name":"Zang Tabi",
    "wof:placetype":"locality"
},
  "geometry": {"coordinates":[9.9136,5.9458],"type":"Point"}
}