{
  "type": "Feature",
  "properties": {
    "gn:admin1_code":"11.0",
    "gn:asciiname":"Nkoayos",
    "gn:country_code":"CM",
    "gn:dem":559,
    "gn:feature_class":"P",
    "gn:feature_code":"PPL",
    "gn:name":"Nkoayos",
    "gn:population":0,
    "gn:timezone":"Africa/Douala",
    "iso:country":"CM",
    "wof:name":"Nkoayos",
    "wof:placetype":"locality"
},
  "geometry": {"coordinates":[11.76667,4.31667],"type":"Point"}
}