{
  "type": "Feature",
  "properties": {
    "gn:admin1_code":"8.0",
    "gn:asciiname":"Batoussop",
    "gn:country_code":"CM",
    "gn:dem":1409,
    "gn:feature_class":"P",
    "gn:feature_code":"PPL",
    "gn:name":"Batoussop",
    "gn:population":0,
    "gn:timezone":"Africa/Douala",
    "iso:country":"CM",
    "wof:name":"Batoussop",
    "wof:placetype":"locality"
},
  "geometry": {"coordinates":[10.27914,5.55245],"type":"Point"}
}