{
  "type": "Feature",
  "properties": {
    "gn:admin1_code":"12.0",
    "gn:asciiname":"Damba",
    "gn:country_code":"CM",
    "gn:dem":289,
    "gn:feature_class":"P",
    "gn:feature_code":"PPL",
    "gn:name":"Damba",
    "gn:population":0,
    "gn:timezone":"Africa/Douala",
    "iso:country":"CM",
    "wof:name":"Damba",
    "wof:placetype":"locality"
},
  "geometry": {"coordinates":[14.6731,12.30119],"type":"Point"}
}