{
  "type": "Feature",
  "properties": {
    "gn:admin1_code":"12.0",
    "gn:asciiname":"Gadala",
    "gn:country_code":"CM",
    "gn:dem":682,
    "gn:feature_class":"P",
    "gn:feature_code":"PPL",
    "gn:name":"Gadala",
    "gn:population":0,
    "gn:timezone":"Africa/Douala",
    "iso:country":"CM",
    "wof:name":"Gadala",
    "wof:placetype":"locality"
},
  "geometry": {"coordinates":[13.82658,10.59664],"type":"Point"}
}