{
  "type": "Feature",
  "properties": {
    "gn:admin1_code":"8.0",
    "gn:asciiname":"Ka'afo",
    "gn:country_code":"CM",
    "gn:dem":1706,
    "gn:feature_class":"P",
    "gn:feature_code":"PPL",
    "gn:name":"Ka\u2019afo",
    "gn:population":0,
    "gn:timezone":"Africa/Douala",
    "iso:country":"CM",
    "name:fra_x_preferred":[
        "Kafo"
    ],
    "name:und_x_variant":[
        "Ka\u2019afo"
    ],
    "wof:name":"Ka'afo",
    "wof:placetype":"locality"
},
  "geometry": {"coordinates":[10.41085,5.30905],"type":"Point"}
}