{
  "type": "Feature",
  "properties": {
    "gn:admin1_code":"12.0",
    "gn:asciiname":"Mougalam",
    "gn:country_code":"CM",
    "gn:dem":295,
    "gn:feature_class":"P",
    "gn:feature_code":"PPL",
    "gn:name":"Mougalam",
    "gn:population":0,
    "gn:timezone":"Africa/Douala",
    "iso:country":"CM",
    "wof:name":"Mougalam",
    "wof:placetype":"locality"
},
  "geometry": {"coordinates":[14.89432,12.31752],"type":"Point"}
}