{
  "type": "Feature",
  "properties": {
    "gn:admin1_code":"12.0",
    "gn:asciiname":"Mayo Houdo",
    "gn:country_code":"CM",
    "gn:dem":370,
    "gn:feature_class":"P",
    "gn:feature_code":"PPL",
    "gn:name":"Mayo Houdo",
    "gn:population":0,
    "gn:timezone":"Africa/Douala",
    "iso:country":"CM",
    "name:und_x_variant":[
        "Mayo Oudo",
        "Mayo Houdo"
    ],
    "wof:name":"Mayo Houdo",
    "wof:placetype":"locality"
},
  "geometry": {"coordinates":[14.69169,10.22974],"type":"Point"}
}