{
  "type": "Feature",
  "properties": {
    "gn:admin1_code":"9.0",
    "gn:asciiname":"Baro",
    "gn:country_code":"CM",
    "gn:dem":254,
    "gn:feature_class":"P",
    "gn:feature_code":"PPL",
    "gn:name":"Baro",
    "gn:population":0,
    "gn:timezone":"Africa/Douala",
    "iso:country":"CM",
    "name:und_x_variant":[
        "Baru",
        "Baro"
    ],
    "wof:name":"Baro",
    "wof:placetype":"locality"
},
  "geometry": {"coordinates":[9.2115,5.27454],"type":"Point"}
}