{
  "type": "Feature",
  "properties": {
    "gn:admin1_code":"14.0",
    "gn:asciiname":"Adjap",
    "gn:country_code":"CM",
    "gn:dem":641,
    "gn:feature_class":"P",
    "gn:feature_code":"PPL",
    "gn:name":"Adjap",
    "gn:population":0,
    "gn:timezone":"Africa/Douala",
    "iso:country":"CM",
    "wof:name":"Adjap",
    "wof:placetype":"locality"
},
  "geometry": {"coordinates":[10.85,3.05],"type":"Point"}
}