{
  "type": "Feature",
  "properties": {
    "gn:admin1_code":"7.0",
    "gn:asciiname":"Baba II",
    "gn:country_code":"CM",
    "gn:dem":1649,
    "gn:feature_class":"P",
    "gn:feature_code":"PPL",
    "gn:name":"Baba II",
    "gn:population":0,
    "gn:timezone":"Africa/Douala",
    "iso:country":"CM",
    "wof:name":"Baba II",
    "wof:placetype":"locality"
},
  "geometry": {"coordinates":[10.10619,5.8623],"type":"Point"}
}