{
  "type": "Feature",
  "properties": {
    "gn:admin1_code":"8.0",
    "gn:asciiname":"Fombap",
    "gn:country_code":"CM",
    "gn:dem":727,
    "gn:feature_class":"P",
    "gn:feature_code":"PPL",
    "gn:name":"Fombap",
    "gn:population":0,
    "gn:timezone":"Africa/Douala",
    "iso:country":"CM",
    "name:fra_x_preferred":[
        "Fombap"
    ],
    "wof:name":"Fombap",
    "wof:placetype":"locality"
},
  "geometry": {"coordinates":[10.0076,5.32203],"type":"Point"}
}