{
  "type": "Feature",
  "properties": {
    "gn:admin1_code":"8.0",
    "gn:asciiname":"Makang",
    "gn:country_code":"CM",
    "gn:dem":1494,
    "gn:feature_class":"P",
    "gn:feature_code":"PPL",
    "gn:name":"Makang",
    "gn:population":0,
    "gn:timezone":"Africa/Douala",
    "iso:country":"CM",
    "wof:name":"Makang",
    "wof:placetype":"locality"
},
  "geometry": {"coordinates":[10.163,5.48116],"type":"Point"}
}