{
  "type": "Feature",
  "properties": {
    "gn:admin1_code":"5.0",
    "gn:asciiname":"Mbanga Mpongo",
    "gn:country_code":"CM",
    "gn:dem":289,
    "gn:feature_class":"P",
    "gn:feature_code":"PPL",
    "gn:name":"Mbanga Mpongo",
    "gn:population":0,
    "gn:timezone":"Africa/Douala",
    "iso:country":"CM",
    "wof:name":"Mbanga Mpongo",
    "wof:placetype":"locality"
},
  "geometry": {"coordinates":[9.95,4.66667],"type":"Point"}
}