{
  "type": "Feature",
  "properties": {
    "gn:admin1_code":"13.0",
    "gn:asciiname":"Anski",
    "gn:country_code":"CM",
    "gn:dem":432,
    "gn:feature_class":"P",
    "gn:feature_code":"PPL",
    "gn:name":"Anski",
    "gn:population":0,
    "gn:timezone":"Africa/Douala",
    "iso:country":"CM",
    "wof:name":"Anski",
    "wof:placetype":"locality"
},
  "geometry": {"coordinates":[13.5524,9.65446],"type":"Point"}
}