{
  "type": "Feature",
  "properties": {
    "gn:admin1_code":"12.0",
    "gn:asciiname":"Badra",
    "gn:country_code":"CM",
    "gn:dem":290,
    "gn:feature_class":"P",
    "gn:feature_code":"PPL",
    "gn:name":"Badra",
    "gn:population":0,
    "gn:timezone":"Africa/Douala",
    "iso:country":"CM",
    "name:ceb_x_preferred":[
        "Badra"
    ],
    "name:deu_x_preferred":[
        "Badra"
    ],
    "name:fas_x_preferred":[
        "\u0628\u062f\u0631\u0647"
    ],
    "name:fra_x_preferred":[
        "Badra"
    ],
    "name:ind_x_preferred":[
        "Badra"
    ],
    "name:ita_x_preferred":[
        "Badra"
    ],
    "name:nld_x_preferred":[
        "Badra"
    ],
    "name:pol_x_preferred":[
        "Badra"
    ],
    "name:rus_x_preferred":[
        "\u0411\u0430\u0434\u0440\u0430"
    ],
    "name:swe_x_preferred":[
        "Badra"
    ],
    "wof:name":"Badra",
    "wof:placetype":"locality"
},
  "geometry": {"coordinates":[14.43549,12.44768],"type":"Point"}
}