{
  "type": "Feature",
  "properties": {
    "gn:admin1_code":"8.0",
    "gn:asciiname":"Nkouchou'nsen",
    "gn:country_code":"CM",
    "gn:dem":1142,
    "gn:feature_class":"P",
    "gn:feature_code":"PPL",
    "gn:name":"Nkouchou\u2019ns\u00e9n",
    "gn:population":0,
    "gn:timezone":"Africa/Douala",
    "iso:country":"CM",
    "name:fra_x_preferred":[
        "Nkouchounsen"
    ],
    "name:und_x_variant":[
        "Nkouchou\u2019ns\u00e9n"
    ],
    "wof:name":"Nkouchou'nsen",
    "wof:placetype":"locality"
},
  "geometry": {"coordinates":[10.8787,5.68061],"type":"Point"}
}