{
  "type": "Feature",
  "properties": {
    "gn:admin1_code":"13.0",
    "gn:asciiname":"Tonkolo",
    "gn:country_code":"CM",
    "gn:dem":353,
    "gn:feature_class":"P",
    "gn:feature_code":"PPL",
    "gn:name":"Tonkolo",
    "gn:population":0,
    "gn:timezone":"Africa/Douala",
    "iso:country":"CM",
    "wof:name":"Tonkolo",
    "wof:placetype":"locality"
},
  "geometry": {"coordinates":[13.93635,9.88695],"type":"Point"}
}