{
  "type": "Feature",
  "properties": {
    "gn:admin1_code":"13.0",
    "gn:asciiname":"Mayel Yeram",
    "gn:country_code":"CM",
    "gn:dem":367,
    "gn:feature_class":"P",
    "gn:feature_code":"PPL",
    "gn:name":"Mayel Yeram",
    "gn:population":0,
    "gn:timezone":"Africa/Douala",
    "iso:country":"CM",
    "name:und_x_variant":[
        "Mayo Yeram"
    ],
    "wof:name":"Mayel Yeram",
    "wof:placetype":"locality"
},
  "geometry": {"coordinates":[13.65697,9.68813],"type":"Point"}
}