{
  "type": "Feature",
  "properties": {
    "gn:admin1_code":"7.0",
    "gn:asciiname":"Matazu-Matadjong",
    "gn:country_code":"CM",
    "gn:dem":247,
    "gn:feature_class":"P",
    "gn:feature_code":"PPL",
    "gn:name":"Matazu-Matadjong",
    "gn:population":0,
    "gn:timezone":"Africa/Douala",
    "iso:country":"CM",
    "wof:name":"Matazu-Matadjong",
    "wof:placetype":"locality"
},
  "geometry": {"coordinates":[9.7707,6.6361],"type":"Point"}
}