{
  "type": "Feature",
  "properties": {
    "gn:admin1_code":"5.0",
    "gn:asciiname":"Bonindi",
    "gn:country_code":"CM",
    "gn:dem":11,
    "gn:feature_class":"P",
    "gn:feature_code":"PPL",
    "gn:name":"Bonindi",
    "gn:population":0,
    "gn:timezone":"Africa/Douala",
    "iso:country":"CM",
    "wof:name":"Bonindi",
    "wof:placetype":"locality"
},
  "geometry": {"coordinates":[9.8257,4.2815],"type":"Point"}
}