{
  "type": "Feature",
  "properties": {
    "gn:admin1_code":"12.0",
    "gn:asciiname":"Maborda",
    "gn:country_code":"CM",
    "gn:dem":671,
    "gn:feature_class":"P",
    "gn:feature_code":"PPL",
    "gn:name":"Maborda",
    "gn:population":0,
    "gn:timezone":"Africa/Douala",
    "iso:country":"CM",
    "wof:name":"Maborda",
    "wof:placetype":"locality"
},
  "geometry": {"coordinates":[13.95835,10.64157],"type":"Point"}
}