{
  "type": "Feature",
  "properties": {
    "gn:admin1_code":"12.0",
    "gn:asciiname":"Djireib",
    "gn:country_code":"CM",
    "gn:dem":289,
    "gn:feature_class":"P",
    "gn:feature_code":"PPL",
    "gn:name":"Djireib",
    "gn:population":0,
    "gn:timezone":"Africa/Douala",
    "iso:country":"CM",
    "name:und_x_variant":[
        "Djiraib",
        "Djireib"
    ],
    "wof:name":"Djireib",
    "wof:placetype":"locality"
},
  "geometry": {"coordinates":[14.43897,12.62398],"type":"Point"}
}