{
  "type": "Feature",
  "properties": {
    "gn:admin1_code":"10.0",
    "gn:asciiname":"Djombi Deux",
    "gn:country_code":"CM",
    "gn:dem":901,
    "gn:feature_class":"P",
    "gn:feature_code":"PPL",
    "gn:name":"Djombi Deux",
    "gn:population":0,
    "gn:timezone":"Africa/Douala",
    "iso:country":"CM",
    "name:eng_x_preferred":[
        "Djombi Two"
    ],
    "name:fra_x_preferred":[
        "Djombi Deux"
    ],
    "wof:name":"Djombi Deux",
    "wof:placetype":"locality"
},
  "geometry": {"coordinates":[12.6247,6.72794],"type":"Point"}
}