{
  "type": "Feature",
  "properties": {
    "gn:admin1_code":"11.0",
    "gn:asciiname":"Biba",
    "gn:country_code":"CM",
    "gn:dem":687,
    "gn:feature_class":"P",
    "gn:feature_code":"PPL",
    "gn:name":"Biba",
    "gn:population":0,
    "gn:timezone":"Africa/Douala",
    "iso:country":"CM",
    "name:fin_x_preferred":[
        "Biba"
    ],
    "name:fra_x_preferred":[
        "Biba"
    ],
    "name:por_x_preferred":[
        "Biba"
    ],
    "wof:name":"Biba",
    "wof:placetype":"locality"
},
  "geometry": {"coordinates":[12.21667,4.03333],"type":"Point"}
}