{
  "type": "Feature",
  "properties": {
    "gn:admin1_code":"12.0",
    "gn:asciiname":"Daguene",
    "gn:country_code":"CM",
    "gn:dem":293,
    "gn:feature_class":"P",
    "gn:feature_code":"PPL",
    "gn:name":"Dagu\u00e9n\u00e9",
    "gn:population":0,
    "gn:timezone":"Africa/Douala",
    "iso:country":"CM",
    "wof:name":"Daguene",
    "wof:placetype":"locality"
},
  "geometry": {"coordinates":[14.75224,12.23632],"type":"Point"}
}