{
  "type": "Feature",
  "properties": {
    "gn:admin1_code":"14.0",
    "gn:asciiname":"Bisombo",
    "gn:country_code":"CM",
    "gn:dem":634,
    "gn:feature_class":"P",
    "gn:feature_code":"PPL",
    "gn:name":"Bisombo",
    "gn:population":0,
    "gn:timezone":"Africa/Douala",
    "iso:country":"CM",
    "name:und_x_variant":[
        "Bissambo",
        "Bissombo",
        "Bisombo"
    ],
    "wof:name":"Bisombo",
    "wof:placetype":"locality"
},
  "geometry": {"coordinates":[12.46667,3.28333],"type":"Point"}
}