{
  "type": "Feature",
  "properties": {
    "gn:admin1_code":"12.0",
    "gn:asciiname":"Polgue",
    "gn:country_code":"CM",
    "gn:dem":333,
    "gn:feature_class":"P",
    "gn:feature_code":"PPL",
    "gn:name":"Polgu\u00e9",
    "gn:population":0,
    "gn:timezone":"Africa/Douala",
    "iso:country":"CM",
    "name:und_x_variant":[
        "Polg\u00e9",
        "Polgu\u00e9"
    ],
    "wof:name":"Polgue",
    "wof:placetype":"locality"
},
  "geometry": {"coordinates":[15.51634,9.96926],"type":"Point"}
}