{
  "type": "Feature",
  "properties": {
    "gn:admin1_code":"8.0",
    "gn:asciiname":"Wang",
    "gn:country_code":"CM",
    "gn:dem":1559,
    "gn:feature_class":"P",
    "gn:feature_code":"PPL",
    "gn:name":"Wang",
    "gn:population":0,
    "gn:timezone":"Africa/Douala",
    "iso:country":"CM",
    "name:ceb_x_preferred":[
        "Wang"
    ],
    "name:ces_x_preferred":[
        "Wang"
    ],
    "name:deu_x_preferred":[
        "Wang"
    ],
    "name:fra_x_preferred":[
        "Wang"
    ],
    "name:heb_x_preferred":[
        "\u05d5\u05d0\u05e0\u05d2"
    ],
    "name:ind_x_preferred":[
        "Wang"
    ],
    "name:ita_x_preferred":[
        "Wang"
    ],
    "name:nld_x_preferred":[
        "Wang"
    ],
    "name:nor_x_preferred":[
        "Wang"
    ],
    "name:pol_x_preferred":[
        "Wang"
    ],
    "name:por_x_preferred":[
        "Wang"
    ],
    "name:rus_x_preferred":[
        "\u0412\u0430\u043d\u0433"
    ],
    "name:swe_x_preferred":[
        "Wang"
    ],
    "name:tha_x_preferred":[
        "\u0e27\u0e31\u0e07"
    ],
    "name:und_x_variant":[
        "Bahouan",
        "Bawang"
    ],
    "name:vol_x_preferred":[
        "Wang"
    ],
    "wof:name":"Wang",
    "wof:placetype":"locality"
},
  "geometry": {"coordinates":[10.37241,5.3659],"type":"Point"}
}