{
  "type": "Feature",
  "properties": {
    "gn:admin1_code":"8.0",
    "gn:asciiname":"Wang",
    "gn:country_code":"CM",
    "gn:dem":1559,
    "gn:feature_class":"P",
    "gn:feature_code":"PPL",
    "gn:name":"Wang",
    "gn:population":0,
    "gn:timezone":"Africa/Douala",
    "iso:country":"CM",
    "name:und_x_variant":[
        "Bahouan",
        "Bawang"
    ],
    "wof:name":"Wang",
    "wof:placetype":"locality"
},
  "geometry": {"coordinates":[10.37241,5.3659],"type":"Point"}
}