{
  "type": "Feature",
  "properties": {
    "gn:admin1_code":"9.0",
    "gn:asciiname":"Ifunia",
    "gn:country_code":"CM",
    "gn:dem":11,
    "gn:feature_class":"P",
    "gn:feature_code":"PPL",
    "gn:name":"Ifunia",
    "gn:population":0,
    "gn:timezone":"Africa/Douala",
    "iso:country":"CM",
    "wof:name":"Ifunia",
    "wof:placetype":"locality"
},
  "geometry": {"coordinates":[8.586,4.6993],"type":"Point"}
}