{
  "type": "Feature",
  "properties": {
    "gn:admin1_code":"4.0",
    "gn:asciiname":"Kouem-Kouem",
    "gn:country_code":"CM",
    "gn:dem":677,
    "gn:feature_class":"P",
    "gn:feature_code":"PPL",
    "gn:name":"Kouem-Kouem",
    "gn:population":0,
    "gn:timezone":"Africa/Douala",
    "iso:country":"CM",
    "wof:name":"Kouem-Kouem",
    "wof:placetype":"locality"
},
  "geometry": {"coordinates":[14.21667,3.98333],"type":"Point"}
}