{
  "type": "Feature",
  "properties": {
    "gn:admin1_code":"10.0",
    "gn:asciiname":"Bidjan",
    "gn:country_code":"CM",
    "gn:dem":890,
    "gn:feature_class":"P",
    "gn:feature_code":"PPL",
    "gn:name":"Bidjan",
    "gn:population":0,
    "gn:timezone":"Africa/Douala",
    "iso:country":"CM",
    "wof:name":"Bidjan",
    "wof:placetype":"locality"
},
  "geometry": {"coordinates":[12.37295,6.75625],"type":"Point"}
}