{
  "type": "Feature",
  "properties": {
    "gn:admin1_code":"8.0",
    "gn:asciiname":"Nguemou",
    "gn:country_code":"CM",
    "gn:dem":1117,
    "gn:feature_class":"P",
    "gn:feature_code":"PPL",
    "gn:name":"Nguemou",
    "gn:population":0,
    "gn:timezone":"Africa/Douala",
    "iso:country":"CM",
    "wof:name":"Nguemou",
    "wof:placetype":"locality"
},
  "geometry": {"coordinates":[10.60665,5.63636],"type":"Point"}
}