{
  "type": "Feature",
  "properties": {
    "gn:admin1_code":"13.0",
    "gn:asciiname":"Sasa",
    "gn:country_code":"CM",
    "gn:dem":591,
    "gn:feature_class":"P",
    "gn:feature_code":"PPL",
    "gn:name":"Sasa",
    "gn:population":0,
    "gn:timezone":"Africa/Douala",
    "iso:country":"CM",
    "name:ara_x_preferred":[
        "\u0633\u0639\u0633\u0639"
    ],
    "name:ceb_x_preferred":[
        "Sasa"
    ],
    "name:deu_x_preferred":[
        "Sasa"
    ],
    "name:epo_x_preferred":[
        "Sasa"
    ],
    "name:fra_x_preferred":[
        "Sasa"
    ],
    "name:hrv_x_preferred":[
        "Sasa"
    ],
    "name:ita_x_preferred":[
        "Sasa"
    ],
    "name:jpn_x_preferred":[
        "\u30b5\u30b5"
    ],
    "name:sqi_x_preferred":[
        "Sasa"
    ],
    "name:srp_x_preferred":[
        "\u0421\u0430\u0441\u0430"
    ],
    "name:swe_x_preferred":[
        "Sasa"
    ],
    "wof:name":"Sasa",
    "wof:placetype":"locality"
},
  "geometry": {"coordinates":[13.76667,7.73333],"type":"Point"}
}