{
  "type": "Feature",
  "properties": {
    "gn:admin1_code":"8.0",
    "gn:asciiname":"Wassa",
    "gn:country_code":"CM",
    "gn:dem":1397,
    "gn:feature_class":"P",
    "gn:feature_code":"PPL",
    "gn:name":"Wassa",
    "gn:population":0,
    "gn:timezone":"Africa/Douala",
    "iso:country":"CM",
    "name:fra_x_preferred":[
        "Wassa"
    ],
    "wof:name":"Wassa",
    "wof:placetype":"locality"
},
  "geometry": {"coordinates":[10.27489,5.46748],"type":"Point"}
}