{
  "type": "Feature",
  "properties": {
    "iso:country":"CM",
    "name:ceb_x_preferred":[
        "Mundemba"
    ],
    "name:deu_x_preferred":[
        "Mundemba"
    ],
    "name:dut_x_preferred":[
        "Mundemba"
    ],
    "name:eng_x_preferred":[
        "Mundemba"
    ],
    "name:fra_x_preferred":[
        "Mundemba"
    ],
    "name:fre_x_preferred":[
        "Mudemba"
    ],
    "name:ger_x_preferred":[
        "Mundemba"
    ],
    "name:heb_x_preferred":[
        "\u05de\u05d5\u05e0\u05d3\u05de\u05d1\u05d4"
    ],
    "name:ita_x_preferred":[
        "Mundemba"
    ],
    "name:may_x_preferred":[
        "Mudemba"
    ],
    "name:msa_x_preferred":[
        "Mudemba"
    ],
    "name:pol_x_preferred":[
        "Mundemba"
    ],
    "name:swe_x_preferred":[
        "Mundemba"
    ],
    "name:unk_x_variant":[
        "Ndian"
    ],
    "qs:gn_country":"CM",
    "qs:gn_fcode":"PPL",
    "qs:gn_pop":11912,
    "qs:name":"Mundemba",
    "qs:name_adm0":"Cameroun",
    "qs:name_adm1":"Sud-Ouest",
    "qs:photos":0,
    "qs:photos_1k":0,
    "qs:photos_9k":1,
    "qs:photos_9r":2,
    "qs:photos_all":42,
    "qs:photos_sr":0,
    "qs:placetype":"Town",
    "qs:pop_sr":"6",
    "qs:woe_adm0":23424785,
    "wd:wordcount":760,
    "wof:name":"Mundemba",
    "wof:placetype":"locality",
    "wof:population":11912
},
  "geometry": {"coordinates":[8.8724,4.9479],"type":"Point"}
}