{
  "type": "Feature",
  "properties": {
    "gn:admin1_code":"14.0",
    "gn:asciiname":"Ewot",
    "gn:country_code":"CM",
    "gn:dem":663,
    "gn:feature_class":"P",
    "gn:feature_code":"PPL",
    "gn:name":"\u00c9wot",
    "gn:population":0,
    "gn:timezone":"Africa/Douala",
    "iso:country":"CM",
    "wof:name":"Ewot",
    "wof:placetype":"locality"
},
  "geometry": {"coordinates":[12.41667,3.38333],"type":"Point"}
}