{
  "type": "Feature",
  "properties": {
    "gn:admin1_code":"14.0",
    "gn:asciiname":"Yos",
    "gn:country_code":"CM",
    "gn:dem":557,
    "gn:feature_class":"P",
    "gn:feature_code":"PPL",
    "gn:name":"Yos",
    "gn:population":0,
    "gn:timezone":"Africa/Douala",
    "iso:country":"CM",
    "wof:name":"Yos",
    "wof:placetype":"locality"
},
  "geometry": {"coordinates":[11.06667,2.25],"type":"Point"}
}