{
  "type": "Feature",
  "properties": {
    "gn:admin1_code":"11.0",
    "gn:asciiname":"Bissaga",
    "gn:country_code":"CM",
    "gn:dem":659,
    "gn:feature_class":"P",
    "gn:feature_code":"PPL",
    "gn:name":"Bissaga",
    "gn:population":0,
    "gn:timezone":"Africa/Douala",
    "iso:country":"CM",
    "wof:name":"Bissaga",
    "wof:placetype":"locality"
},
  "geometry": {"coordinates":[12.13333,4.68333],"type":"Point"}
}