{
  "type": "Feature",
  "properties": {
    "gn:admin1_code":"11.0",
    "gn:asciiname":"Nkolekabeli",
    "gn:country_code":"CM",
    "gn:dem":690,
    "gn:feature_class":"P",
    "gn:feature_code":"PPL",
    "gn:name":"Nkolekab\u00e9li",
    "gn:population":0,
    "gn:timezone":"Africa/Douala",
    "iso:country":"CM",
    "wof:name":"Nkolekabeli",
    "wof:placetype":"locality"
},
  "geometry": {"coordinates":[11.78333,3.45],"type":"Point"}
}