{
  "type": "Feature",
  "properties": {
    "gn:admin1_code":"8.0",
    "gn:asciiname":"Mbepehe",
    "gn:country_code":"CM",
    "gn:dem":1295,
    "gn:feature_class":"P",
    "gn:feature_code":"PPL",
    "gn:name":"Mbep\u00e8h\u00e9",
    "gn:population":0,
    "gn:timezone":"Africa/Douala",
    "iso:country":"CM",
    "wof:name":"Mbepehe",
    "wof:placetype":"locality"
},
  "geometry": {"coordinates":[10.28835,5.68482],"type":"Point"}
}