{
  "type": "Feature",
  "properties": {
    "gn:admin1_code":"12.0",
    "gn:asciiname":"Idao",
    "gn:country_code":"CM",
    "gn:dem":392,
    "gn:feature_class":"P",
    "gn:feature_code":"PPL",
    "gn:name":"Idao",
    "gn:population":0,
    "gn:timezone":"Africa/Douala",
    "iso:country":"CM",
    "wof:name":"Idao",
    "wof:placetype":"locality"
},
  "geometry": {"coordinates":[14.36359,10.57067],"type":"Point"}
}