{
  "type": "Feature",
  "properties": {
    "gn:admin1_code":"12.0",
    "gn:asciiname":"Ngonfela",
    "gn:country_code":"CM",
    "gn:dem":289,
    "gn:feature_class":"P",
    "gn:feature_code":"PPL",
    "gn:name":"Ngonf\u00e9la",
    "gn:population":0,
    "gn:timezone":"Africa/Douala",
    "iso:country":"CM",
    "name:und_x_variant":[
        "Gounf\u00e9la",
        "Ngonf\u00e9la",
        "Gounfela"
    ],
    "wof:name":"Ngonfela",
    "wof:placetype":"locality"
},
  "geometry": {"coordinates":[14.67788,12.27543],"type":"Point"}
}