{
  "type": "Feature",
  "properties": {
    "gn:admin1_code":"12.0",
    "gn:asciiname":"Ngouambli",
    "gn:country_code":"CM",
    "gn:dem":620,
    "gn:feature_class":"P",
    "gn:feature_code":"PPL",
    "gn:name":"Ngouambli",
    "gn:population":0,
    "gn:timezone":"Africa/Douala",
    "iso:country":"CM",
    "wof:name":"Ngouambli",
    "wof:placetype":"locality"
},
  "geometry": {"coordinates":[13.98672,10.66057],"type":"Point"}
}