{
  "type": "Feature",
  "properties": {
    "gn:admin1_code":"8.0",
    "gn:asciiname":"Wouong III",
    "gn:country_code":"CM",
    "gn:dem":1307,
    "gn:feature_class":"P",
    "gn:feature_code":"PPL",
    "gn:name":"Wouong III",
    "gn:population":0,
    "gn:timezone":"Africa/Douala",
    "iso:country":"CM",
    "wof:name":"Wouong III",
    "wof:placetype":"locality"
},
  "geometry": {"coordinates":[10.35865,5.54739],"type":"Point"}
}