{
  "type": "Feature",
  "properties": {
    "gn:admin1_code":"10.0",
    "gn:asciiname":"Kouroum",
    "gn:country_code":"CM",
    "gn:dem":781,
    "gn:feature_class":"P",
    "gn:feature_code":"PPL",
    "gn:name":"Kouroum",
    "gn:population":0,
    "gn:timezone":"Africa/Douala",
    "iso:country":"CM",
    "wof:name":"Kouroum",
    "wof:placetype":"locality"
},
  "geometry": {"coordinates":[11.39093,6.42721],"type":"Point"}
}