{
  "type": "Feature",
  "properties": {
    "gn:admin1_code":"8.0",
    "gn:asciiname":"Fambe",
    "gn:country_code":"CM",
    "gn:dem":1267,
    "gn:feature_class":"P",
    "gn:feature_code":"PPL",
    "gn:name":"Fambe",
    "gn:population":0,
    "gn:timezone":"Africa/Douala",
    "iso:country":"CM",
    "wof:name":"Fambe",
    "wof:placetype":"locality"
},
  "geometry": {"coordinates":[10.57739,5.14232],"type":"Point"}
}