{
  "type": "Feature",
  "properties": {
    "gn:admin1_code":"13.0",
    "gn:asciiname":"Bougwi",
    "gn:country_code":"CM",
    "gn:dem":1131,
    "gn:feature_class":"P",
    "gn:feature_code":"PPL",
    "gn:name":"Bougwi",
    "gn:population":0,
    "gn:timezone":"Africa/Douala",
    "iso:country":"CM",
    "wof:name":"Bougwi",
    "wof:placetype":"locality"
},
  "geometry": {"coordinates":[14.93333,7.25],"type":"Point"}
}