{
  "type": "Feature",
  "properties": {
    "gn:admin1_code":"13.0",
    "gn:asciiname":"Lapeo",
    "gn:country_code":"CM",
    "gn:dem":377,
    "gn:feature_class":"P",
    "gn:feature_code":"PPL",
    "gn:name":"Lapeo",
    "gn:population":0,
    "gn:timezone":"Africa/Douala",
    "iso:country":"CM",
    "wof:name":"Lapeo",
    "wof:placetype":"locality"
},
  "geometry": {"coordinates":[12.48624,8.51873],"type":"Point"}
}