{
  "type": "Feature",
  "properties": {
    "gn:admin1_code":"5.0",
    "gn:asciiname":"Ehyengue",
    "gn:cc2":"CM",
    "gn:country_code":"CM",
    "gn:dem":1,
    "gn:feature_class":"P",
    "gn:feature_code":"PPL",
    "gn:name":"Ehyengu\u00e9",
    "gn:population":0,
    "gn:timezone":"Africa/Douala",
    "iso:country":"CM",
    "name:und_x_variant":[
        "Ehyango\u00e9",
        "Ehyengu\u00e9"
    ],
    "wof:name":"Ehyengue",
    "wof:placetype":"locality"
},
  "geometry": {"coordinates":[9.88583,3.31167],"type":"Point"}
}