{
  "type": "Feature",
  "properties": {
    "gn:admin1_code":"12.0",
    "gn:asciiname":"Gawar",
    "gn:country_code":"CM",
    "gn:dem":572,
    "gn:feature_class":"P",
    "gn:feature_code":"PPL",
    "gn:name":"Gawar",
    "gn:population":0,
    "gn:timezone":"Africa/Douala",
    "iso:country":"CM",
    "name:fra_x_preferred":[
        "Gawar"
    ],
    "name:und_x_variant":[
        "Gauar",
        "Gaouar",
        "Gawar"
    ],
    "wof:name":"Gawar",
    "wof:placetype":"locality"
},
  "geometry": {"coordinates":[13.83638,10.51092],"type":"Point"}
}