{
  "type": "Feature",
  "properties": {
    "gn:admin1_code":"8.0",
    "gn:asciiname":"Mamba",
    "gn:country_code":"CM",
    "gn:dem":781,
    "gn:feature_class":"P",
    "gn:feature_code":"PPL",
    "gn:name":"Mamba",
    "gn:population":0,
    "gn:timezone":"Africa/Douala",
    "iso:country":"CM",
    "wof:name":"Mamba",
    "wof:placetype":"locality"
},
  "geometry": {"coordinates":[10.97614,5.91563],"type":"Point"}
}