{
  "type": "Feature",
  "properties": {
    "gn:admin1_code":"11.0",
    "gn:asciiname":"Ekanga",
    "gn:country_code":"CM",
    "gn:dem":662,
    "gn:feature_class":"P",
    "gn:feature_code":"PPL",
    "gn:name":"Ekanga",
    "gn:population":0,
    "gn:timezone":"Africa/Douala",
    "iso:country":"CM",
    "wof:name":"Ekanga",
    "wof:placetype":"locality"
},
  "geometry": {"coordinates":[12.33333,4.46667],"type":"Point"}
}