{
  "type": "Feature",
  "properties": {
    "gn:admin1_code":"8.0",
    "gn:asciiname":"Nchout-Monoun",
    "gn:country_code":"CM",
    "gn:dem":1213,
    "gn:feature_class":"P",
    "gn:feature_code":"PPL",
    "gn:name":"Nchout-Monoun",
    "gn:population":0,
    "gn:timezone":"Africa/Douala",
    "iso:country":"CM",
    "wof:name":"Nchout-Monoun",
    "wof:placetype":"locality"
},
  "geometry": {"coordinates":[10.53548,5.66606],"type":"Point"}
}