{
  "type": "Feature",
  "properties": {
    "gn:admin1_code":"9.0",
    "gn:asciiname":"Ninong",
    "gn:country_code":"CM",
    "gn:dem":1475,
    "gn:feature_class":"P",
    "gn:feature_code":"PPL",
    "gn:name":"Ninong",
    "gn:population":0,
    "gn:timezone":"Africa/Douala",
    "iso:country":"CM",
    "wof:name":"Ninong",
    "wof:placetype":"locality"
},
  "geometry": {"coordinates":[9.7749,5.0386],"type":"Point"}
}