{
  "type": "Feature",
  "properties": {
    "gn:admin1_code":"10.0",
    "gn:asciiname":"Arnado Niakoum",
    "gn:country_code":"CM",
    "gn:dem":933,
    "gn:feature_class":"P",
    "gn:feature_code":"PPL",
    "gn:name":"Arnado Niakoum",
    "gn:population":0,
    "gn:timezone":"Africa/Douala",
    "iso:country":"CM",
    "wof:name":"Arnado Niakoum",
    "wof:placetype":"locality"
},
  "geometry": {"coordinates":[11.91667,6.51667],"type":"Point"}
}