{
  "type": "Feature",
  "properties": {
    "gn:admin1_code":"11.0",
    "gn:asciiname":"Nkolavolo I",
    "gn:country_code":"CM",
    "gn:dem":672,
    "gn:feature_class":"P",
    "gn:feature_code":"PPL",
    "gn:name":"Nkolavolo I",
    "gn:population":0,
    "gn:timezone":"Africa/Douala",
    "iso:country":"CM",
    "wof:name":"Nkolavolo I",
    "wof:placetype":"locality"
},
  "geometry": {"coordinates":[11.86667,4.06667],"type":"Point"}
}