{
  "type": "Feature",
  "properties": {
    "gn:admin1_code":"12.0",
    "gn:asciiname":"Paldok",
    "gn:country_code":"CM",
    "gn:dem":748,
    "gn:feature_class":"P",
    "gn:feature_code":"PPL",
    "gn:name":"Paldok",
    "gn:population":0,
    "gn:timezone":"Africa/Douala",
    "iso:country":"CM",
    "wof:name":"Paldok",
    "wof:placetype":"locality"
},
  "geometry": {"coordinates":[13.86562,10.76091],"type":"Point"}
}