{
  "type": "Feature",
  "properties": {
    "gn:admin1_code":"12.0",
    "gn:asciiname":"Djoubao",
    "gn:country_code":"CM",
    "gn:dem":397,
    "gn:feature_class":"P",
    "gn:feature_code":"PPL",
    "gn:name":"Djoubao",
    "gn:population":0,
    "gn:timezone":"Africa/Douala",
    "iso:country":"CM",
    "wof:name":"Djoubao",
    "wof:placetype":"locality"
},
  "geometry": {"coordinates":[14.36935,10.45042],"type":"Point"}
}