{
  "type": "Feature",
  "properties": {
    "gn:admin1_code":"10.0",
    "gn:asciiname":"Bissouna",
    "gn:country_code":"CM",
    "gn:dem":1031,
    "gn:feature_class":"P",
    "gn:feature_code":"PPL",
    "gn:name":"Bissouna",
    "gn:population":0,
    "gn:timezone":"Africa/Douala",
    "iso:country":"CM",
    "name:und_x_variant":[
        "Bissoum\u00e9",
        "Bissouna"
    ],
    "wof:name":"Bissouna",
    "wof:placetype":"locality"
},
  "geometry": {"coordinates":[13.11667,7.08333],"type":"Point"}
}