{
  "type": "Feature",
  "properties": {
    "gn:admin1_code":"8.0",
    "gn:asciiname":"Nkouloum",
    "gn:country_code":"CM",
    "gn:dem":748,
    "gn:feature_class":"P",
    "gn:feature_code":"PPL",
    "gn:name":"Nkouloum",
    "gn:population":0,
    "gn:timezone":"Africa/Douala",
    "iso:country":"CM",
    "wof:name":"Nkouloum",
    "wof:placetype":"locality"
},
  "geometry": {"coordinates":[11.05,6.16667],"type":"Point"}
}