{
  "type": "Feature",
  "properties": {
    "gn:admin1_code":"13.0",
    "gn:asciiname":"Sanguere-Paul",
    "gn:country_code":"CM",
    "gn:dem":222,
    "gn:feature_class":"P",
    "gn:feature_code":"PPL",
    "gn:name":"Sangu\u00e9r\u00e9-Paul",
    "gn:population":0,
    "gn:timezone":"Africa/Douala",
    "iso:country":"CM",
    "wof:name":"Sanguere-Paul",
    "wof:placetype":"locality"
},
  "geometry": {"coordinates":[13.45958,9.28164],"type":"Point"}
}