{
  "type": "Feature",
  "properties": {
    "gn:admin1_code":"9.0",
    "gn:asciiname":"Mekedembeng",
    "gn:country_code":"CM",
    "gn:dem":610,
    "gn:feature_class":"P",
    "gn:feature_code":"PPL",
    "gn:name":"Mekedembeng",
    "gn:population":0,
    "gn:timezone":"Africa/Douala",
    "iso:country":"CM",
    "wof:name":"Mekedembeng",
    "wof:placetype":"locality"
},
  "geometry": {"coordinates":[9.6774,4.89209],"type":"Point"}
}