{
  "type": "Feature",
  "properties": {
    "gn:admin1_code":"7.0",
    "gn:asciiname":"Menda",
    "gn:country_code":"CM",
    "gn:dem":323,
    "gn:feature_class":"P",
    "gn:feature_code":"PPL",
    "gn:name":"Menda",
    "gn:population":0,
    "gn:timezone":"Africa/Douala",
    "iso:country":"CM",
    "name:ceb_x_preferred":[
        "Menda"
    ],
    "name:swe_x_preferred":[
        "Menda"
    ],
    "wof:name":"Menda",
    "wof:placetype":"locality"
},
  "geometry": {"coordinates":[9.605,5.9129],"type":"Point"}
}