{
  "type": "Feature",
  "properties": {
    "gn:admin1_code":"4.0",
    "gn:asciiname":"Diaglassi",
    "gn:country_code":"CM",
    "gn:dem":728,
    "gn:feature_class":"P",
    "gn:feature_code":"PPL",
    "gn:name":"Diaglassi",
    "gn:population":0,
    "gn:timezone":"Africa/Douala",
    "iso:country":"CM",
    "wof:name":"Diaglassi",
    "wof:placetype":"locality"
},
  "geometry": {"coordinates":[13.28333,4.15],"type":"Point"}
}