{
  "type": "Feature",
  "properties": {
    "gn:admin1_code":"14.0",
    "gn:asciiname":"Mintom",
    "gn:country_code":"CM",
    "gn:dem":617,
    "gn:feature_class":"P",
    "gn:feature_code":"PPL",
    "gn:name":"Mintom",
    "gn:population":0,
    "gn:timezone":"Africa/Douala",
    "iso:country":"CM",
    "wof:name":"Mintom",
    "wof:placetype":"locality"
},
  "geometry": {"coordinates":[10.96667,2.95],"type":"Point"}
}