{
  "type": "Feature",
  "properties": {
    "gn:admin1_code":"12.0",
    "gn:asciiname":"Mbozo",
    "gn:country_code":"CM",
    "gn:dem":482,
    "gn:feature_class":"P",
    "gn:feature_code":"PPL",
    "gn:name":"Mbozo",
    "gn:population":0,
    "gn:timezone":"Africa/Douala",
    "iso:country":"CM",
    "wof:name":"Mbozo",
    "wof:placetype":"locality"
},
  "geometry": {"coordinates":[14.15343,10.67273],"type":"Point"}
}