{
  "type": "Feature",
  "properties": {
    "gn:admin1_code":"9.0",
    "gn:asciiname":"Manta",
    "gn:country_code":"CM",
    "gn:dem":356,
    "gn:feature_class":"P",
    "gn:feature_code":"PPL",
    "gn:name":"Manta",
    "gn:population":0,
    "gn:timezone":"Africa/Douala",
    "iso:country":"CM",
    "name:ceb_x_preferred":[
        "Manta"
    ],
    "name:deu_x_preferred":[
        "Manta"
    ],
    "name:eus_x_preferred":[
        "Manta"
    ],
    "name:fin_x_preferred":[
        "Manta"
    ],
    "name:fra_x_preferred":[
        "Manta"
    ],
    "name:heb_x_preferred":[
        "\u05de\u05e0\u05d8\u05d4"
    ],
    "name:hun_x_preferred":[
        "Manta"
    ],
    "name:hye_x_preferred":[
        "\u0544\u0561\u0576\u057f\u0561"
    ],
    "name:ind_x_preferred":[
        "Manta"
    ],
    "name:ita_x_preferred":[
        "Manta"
    ],
    "name:jpn_x_preferred":[
        "\u30de\u30f3\u30bf"
    ],
    "name:lav_x_preferred":[
        "Manta"
    ],
    "name:lmo_x_preferred":[
        "Manta"
    ],
    "name:nds_x_preferred":[
        "Manta"
    ],
    "name:nld_x_preferred":[
        "Manta"
    ],
    "name:nor_x_preferred":[
        "Manta"
    ],
    "name:pol_x_preferred":[
        "Manta"
    ],
    "name:por_x_preferred":[
        "Manta"
    ],
    "name:ron_x_preferred":[
        "Manta"
    ],
    "name:rus_x_preferred":[
        "\u041c\u0430\u043d\u0442\u0430"
    ],
    "name:scn_x_preferred":[
        "Manta"
    ],
    "name:spa_x_preferred":[
        "Manta"
    ],
    "name:swe_x_preferred":[
        "Manta"
    ],
    "name:tur_x_preferred":[
        "Manta"
    ],
    "name:ukr_x_preferred":[
        "\u041c\u0430\u043d\u0442\u0430"
    ],
    "name:vie_x_preferred":[
        "Manta"
    ],
    "name:vol_x_preferred":[
        "Manta"
    ],
    "wof:name":"Manta",
    "wof:placetype":"locality"
},
  "geometry": {"coordinates":[9.5998,5.9738],"type":"Point"}
}