{
  "type": "Feature",
  "properties": {
    "gn:admin1_code":"12.0",
    "gn:asciiname":"Warade",
    "gn:country_code":"CM",
    "gn:dem":376,
    "gn:feature_class":"P",
    "gn:feature_code":"PPL",
    "gn:name":"Warad\u00e9",
    "gn:population":0,
    "gn:timezone":"Africa/Douala",
    "iso:country":"CM",
    "name:und_x_variant":[
        "Warad\u00e9",
        "Ouarad\u00e9"
    ],
    "wof:name":"Warade",
    "wof:placetype":"locality"
},
  "geometry": {"coordinates":[13.95175,11.1463],"type":"Point"}
}