{
  "type": "Feature",
  "properties": {
    "gn:admin1_code":"4.0",
    "gn:asciiname":"Boni",
    "gn:country_code":"CM",
    "gn:dem":657,
    "gn:feature_class":"P",
    "gn:feature_code":"PPL",
    "gn:name":"Boni",
    "gn:population":0,
    "gn:timezone":"Africa/Douala",
    "iso:country":"CM",
    "name:ceb_x_preferred":[
        "Boni"
    ],
    "name:deu_x_preferred":[
        "Boni"
    ],
    "name:fas_x_preferred":[
        "\u0628\u0648\u0646\u06cc"
    ],
    "name:fra_x_preferred":[
        "Boni"
    ],
    "name:ita_x_preferred":[
        "Boni"
    ],
    "name:nld_x_preferred":[
        "Boni"
    ],
    "name:pol_x_preferred":[
        "Boni"
    ],
    "name:por_x_preferred":[
        "Boni"
    ],
    "name:rus_x_preferred":[
        "\u0411\u043e\u043d\u0438"
    ],
    "name:srp_x_preferred":[
        "\u0411\u043e\u043d\u0438"
    ],
    "name:swe_x_preferred":[
        "Boni"
    ],
    "name:und_x_variant":[
        "Nboni"
    ],
    "wof:name":"Boni",
    "wof:placetype":"locality"
},
  "geometry": {"coordinates":[13.61667,4.53333],"type":"Point"}
}