{
  "type": "Feature",
  "properties": {
    "gn:admin1_code":"11.0",
    "gn:asciiname":"Minkouma",
    "gn:country_code":"CM",
    "gn:dem":572,
    "gn:feature_class":"P",
    "gn:feature_code":"PPL",
    "gn:name":"Minkouma",
    "gn:population":0,
    "gn:timezone":"Africa/Douala",
    "iso:country":"CM",
    "wof:name":"Minkouma",
    "wof:placetype":"locality"
},
  "geometry": {"coordinates":[11.78333,4.38333],"type":"Point"}
}