{
  "type": "Feature",
  "properties": {
    "gn:admin1_code":"13.0",
    "gn:asciiname":"Kalao",
    "gn:country_code":"CM",
    "gn:dem":247,
    "gn:feature_class":"P",
    "gn:feature_code":"PPL",
    "gn:name":"Kalao",
    "gn:population":0,
    "gn:timezone":"Africa/Douala",
    "iso:country":"CM",
    "name:und_x_variant":[
        "Kala"
    ],
    "wof:name":"Kalao",
    "wof:placetype":"locality"
},
  "geometry": {"coordinates":[13.88576,9.58947],"type":"Point"}
}