{
  "type": "Feature",
  "properties": {
    "gn:admin1_code":"14.0",
    "gn:asciiname":"Mbebe",
    "gn:country_code":"CM",
    "gn:dem":73,
    "gn:feature_class":"P",
    "gn:feature_code":"PPL",
    "gn:name":"Mb\u00e9b\u00e9",
    "gn:population":0,
    "gn:timezone":"Africa/Douala",
    "iso:country":"CM",
    "name:swa_x_preferred":[
        "Mbebe"
    ],
    "wof:name":"Mbebe",
    "wof:placetype":"locality"
},
  "geometry": {"coordinates":[10.11667,3.38333],"type":"Point"}
}