{
  "type": "Feature",
  "properties": {
    "gn:admin1_code":"8.0",
    "gn:asciiname":"Fopwanga",
    "gn:country_code":"CM",
    "gn:dem":805,
    "gn:feature_class":"P",
    "gn:feature_code":"PPL",
    "gn:name":"Fopwanga",
    "gn:population":0,
    "gn:timezone":"Africa/Douala",
    "iso:country":"CM",
    "name:fra_x_preferred":[
        "Fopwanga"
    ],
    "name:und_x_variant":[
        "Fopouanga"
    ],
    "wof:name":"Fopwanga",
    "wof:placetype":"locality"
},
  "geometry": {"coordinates":[10.20157,5.03368],"type":"Point"}
}