{
  "type": "Feature",
  "properties": {
    "gn:admin1_code":"8.0",
    "gn:asciiname":"Nketloum",
    "gn:country_code":"CM",
    "gn:dem":1140,
    "gn:feature_class":"P",
    "gn:feature_code":"PPL",
    "gn:name":"Nketloum",
    "gn:population":0,
    "gn:timezone":"Africa/Douala",
    "iso:country":"CM",
    "wof:name":"Nketloum",
    "wof:placetype":"locality"
},
  "geometry": {"coordinates":[10.68273,5.51876],"type":"Point"}
}