{
  "type": "Feature",
  "properties": {
    "gn:admin1_code":"8.0",
    "gn:asciiname":"Mbie II",
    "gn:country_code":"CM",
    "gn:dem":1467,
    "gn:feature_class":"P",
    "gn:feature_code":"PPL",
    "gn:name":"Mbie II",
    "gn:population":0,
    "gn:timezone":"Africa/Douala",
    "iso:country":"CM",
    "wof:name":"Mbie II",
    "wof:placetype":"locality"
},
  "geometry": {"coordinates":[10.24311,5.56791],"type":"Point"}
}