{
  "type": "Feature",
  "properties": {
    "gn:admin1_code":"13.0",
    "gn:asciiname":"Goboum",
    "gn:country_code":"CM",
    "gn:dem":494,
    "gn:feature_class":"P",
    "gn:feature_code":"PPL",
    "gn:name":"Goboum",
    "gn:population":0,
    "gn:timezone":"Africa/Douala",
    "iso:country":"CM",
    "wof:name":"Goboum",
    "wof:placetype":"locality"
},
  "geometry": {"coordinates":[13.80075,10.15876],"type":"Point"}
}