{
  "type": "Feature",
  "properties": {
    "gn:admin1_code":"7.0",
    "gn:asciiname":"Batabi",
    "gn:country_code":"CM",
    "gn:dem":889,
    "gn:feature_class":"P",
    "gn:feature_code":"PPL",
    "gn:name":"Batabi",
    "gn:population":0,
    "gn:timezone":"Africa/Douala",
    "iso:country":"CM",
    "name:und_x_variant":[
        "Batebi",
        "Batabi"
    ],
    "wof:name":"Batabi",
    "wof:placetype":"locality"
},
  "geometry": {"coordinates":[9.7401,6.183],"type":"Point"}
}