{
  "type": "Feature",
  "properties": {
    "gn:admin1_code":"11.0",
    "gn:asciiname":"Djampa",
    "gn:country_code":"CM",
    "gn:dem":908,
    "gn:feature_class":"P",
    "gn:feature_code":"PPL",
    "gn:name":"Djampa",
    "gn:population":0,
    "gn:timezone":"Africa/Douala",
    "iso:country":"CM",
    "wof:name":"Djampa",
    "wof:placetype":"locality"
},
  "geometry": {"coordinates":[12.35,5.65],"type":"Point"}
}