{
  "type": "Feature",
  "properties": {
    "gn:admin1_code":"8.0",
    "gn:asciiname":"Mamben",
    "gn:country_code":"CM",
    "gn:dem":1173,
    "gn:feature_class":"P",
    "gn:feature_code":"PPL",
    "gn:name":"Mamben",
    "gn:population":0,
    "gn:timezone":"Africa/Douala",
    "iso:country":"CM",
    "name:fra_x_preferred":[
        "Mambain"
    ],
    "name:fra_x_variant":[
        "Mamben"
    ],
    "wof:name":"Mamben",
    "wof:placetype":"locality"
},
  "geometry": {"coordinates":[10.89795,5.7105],"type":"Point"}
}