{
  "type": "Feature",
  "properties": {
    "gn:country":"CM",
    "gn:fcode":"PPL",
    "gn:pop":2000,
    "iso:country":"CM",
    "name:eng_x_preferred":[
        "Somi\u00e9"
    ],
    "name:fre_x_preferred":[
        "Somi\u00e9"
    ],
    "name:unk_x_variant":[
        "Ndeba"
    ],
    "qs:name":"Somi\u00e9",
    "qs:photos_9r":0,
    "qs:photos_sr":0,
    "qs:pop_sr":"3",
    "wd:wordcount":76,
    "wof:name":"Somi\u00e9",
    "wof:placetype":"locality",
    "wof:population":2000
},
  "geometry": {"coordinates":[11.43299,6.45843],"type":"Point"}
}