{
  "type": "Feature",
  "properties": {
    "gn:admin1_code":"11.0",
    "gn:asciiname":"Ken",
    "gn:country_code":"CM",
    "gn:dem":519,
    "gn:feature_class":"P",
    "gn:feature_code":"PPL",
    "gn:name":"Ken",
    "gn:population":0,
    "gn:timezone":"Africa/Douala",
    "iso:country":"CM",
    "name:aze_x_preferred":[
        "Ken"
    ],
    "name:cat_x_preferred":[
        "Ken"
    ],
    "name:ceb_x_preferred":[
        "Ken"
    ],
    "name:deu_x_preferred":[
        "Ken"
    ],
    "name:fra_x_preferred":[
        "Ken"
    ],
    "name:kaz_x_preferred":[
        "\u041a\u0435\u043d"
    ],
    "name:nld_x_preferred":[
        "Ken"
    ],
    "name:pol_x_preferred":[
        "Ken"
    ],
    "name:por_x_preferred":[
        "Ken"
    ],
    "name:rus_x_preferred":[
        "\u041a\u0435\u043d"
    ],
    "name:spa_x_preferred":[
        "Ken"
    ],
    "name:srp_x_preferred":[
        "\u041a\u0435\u043d"
    ],
    "name:swe_x_preferred":[
        "Ken"
    ],
    "name:tha_x_preferred":[
        "\u0e40\u0e04\u0e47\u0e19"
    ],
    "name:ukr_x_preferred":[
        "\u041a\u0435\u043d"
    ],
    "name:vie_x_preferred":[
        "Ken"
    ],
    "name:zho_x_preferred":[
        "Ken"
    ],
    "wof:name":"Ken",
    "wof:placetype":"locality"
},
  "geometry": {"coordinates":[11.15,4.83333],"type":"Point"}
}