{
  "type": "Feature",
  "properties": {
    "gn:admin1_code":"11.0",
    "gn:asciiname":"Ken",
    "gn:country_code":"CM",
    "gn:dem":519,
    "gn:feature_class":"P",
    "gn:feature_code":"PPL",
    "gn:name":"Ken",
    "gn:population":0,
    "gn:timezone":"Africa/Douala",
    "iso:country":"CM",
    "wof:name":"Ken",
    "wof:placetype":"locality"
},
  "geometry": {"coordinates":[11.15,4.83333],"type":"Point"}
}