{
  "type": "Feature",
  "properties": {
    "gn:admin1_code":"12.0",
    "gn:asciiname":"Wouyang",
    "gn:country_code":"CM",
    "gn:dem":472,
    "gn:feature_class":"P",
    "gn:feature_code":"PPL",
    "gn:name":"Wouyang",
    "gn:population":0,
    "gn:timezone":"Africa/Douala",
    "iso:country":"CM",
    "wof:name":"Wouyang",
    "wof:placetype":"locality"
},
  "geometry": {"coordinates":[14.13965,10.42997],"type":"Point"}
}