{
  "type": "Feature",
  "properties": {
    "gn:admin1_code":"5.0",
    "gn:asciiname":"Bayis",
    "gn:country_code":"CM",
    "gn:dem":49,
    "gn:feature_class":"P",
    "gn:feature_code":"PPL",
    "gn:name":"Bayis",
    "gn:population":0,
    "gn:timezone":"Africa/Douala",
    "iso:country":"CM",
    "wof:name":"Bayis",
    "wof:placetype":"locality"
},
  "geometry": {"coordinates":[9.8142,4.1107],"type":"Point"}
}