{
  "type": "Feature",
  "properties": {
    "gn:admin1_code":"8.0",
    "gn:asciiname":"Nkouke",
    "gn:country_code":"CM",
    "gn:dem":1409,
    "gn:feature_class":"P",
    "gn:feature_code":"PPL",
    "gn:name":"Nkouk\u00e9",
    "gn:population":0,
    "gn:timezone":"Africa/Douala",
    "iso:country":"CM",
    "wof:name":"Nkouke",
    "wof:placetype":"locality"
},
  "geometry": {"coordinates":[10.37275,5.44745],"type":"Point"}
}