{
  "type": "Feature",
  "properties": {
    "gn:admin1_code":"8.0",
    "gn:asciiname":"Saamaya",
    "gn:country_code":"CM",
    "gn:dem":1554,
    "gn:feature_class":"P",
    "gn:feature_code":"PPL",
    "gn:name":"Saamaya",
    "gn:population":0,
    "gn:timezone":"Africa/Douala",
    "iso:country":"CM",
    "name:fra_x_preferred":[
        "Fo Nou Saamaya"
    ],
    "name:fra_x_variant":[
        "Saamaya"
    ],
    "wof:name":"Saamaya",
    "wof:placetype":"locality"
},
  "geometry": {"coordinates":[10.09845,5.51785],"type":"Point"}
}