{
  "type": "Feature",
  "properties": {
    "gn:admin1_code":"9.0",
    "gn:asciiname":"Likomba",
    "gn:country_code":"CM",
    "gn:dem":191,
    "gn:feature_class":"P",
    "gn:feature_code":"PPL",
    "gn:name":"Likomba",
    "gn:population":0,
    "gn:timezone":"Africa/Douala",
    "iso:country":"CM",
    "wof:name":"Likomba",
    "wof:placetype":"locality"
},
  "geometry": {"coordinates":[9.3319,4.0935],"type":"Point"}
}