{
  "type": "Feature",
  "properties": {
    "gn:admin1_code":"11.0",
    "gn:asciiname":"Ngoungoumou",
    "gn:country_code":"CM",
    "gn:dem":600,
    "gn:feature_class":"P",
    "gn:feature_code":"PPL",
    "gn:name":"Ngoungoumou",
    "gn:population":0,
    "gn:timezone":"Africa/Douala",
    "iso:country":"CM",
    "wof:name":"Ngoungoumou",
    "wof:placetype":"locality"
},
  "geometry": {"coordinates":[11.63333,4.05],"type":"Point"}
}