{
  "type": "Feature",
  "properties": {
    "gn:admin1_code":"13.0",
    "gn:asciiname":"Toukte",
    "gn:country_code":"CM",
    "gn:dem":608,
    "gn:feature_class":"P",
    "gn:feature_code":"PPL",
    "gn:name":"Toukt\u00e9",
    "gn:population":0,
    "gn:timezone":"Africa/Douala",
    "iso:country":"CM",
    "wof:name":"Toukte",
    "wof:placetype":"locality"
},
  "geometry": {"coordinates":[13.26227,8.42286],"type":"Point"}
}