{
  "type": "Feature",
  "properties": {
    "gn:admin1_code":"13.0",
    "gn:asciiname":"Bossi",
    "gn:country_code":"CM",
    "gn:dem":1052,
    "gn:feature_class":"P",
    "gn:feature_code":"PPL",
    "gn:name":"Bossi",
    "gn:population":0,
    "gn:timezone":"Africa/Douala",
    "iso:country":"CM",
    "name:cat_x_preferred":[
        "Bossi"
    ],
    "name:deu_x_preferred":[
        "Bossi"
    ],
    "name:fin_x_preferred":[
        "Bossi"
    ],
    "name:fra_x_preferred":[
        "Bossi"
    ],
    "name:ita_x_preferred":[
        "Bossi"
    ],
    "name:ltz_x_preferred":[
        "Bossi"
    ],
    "name:rus_x_preferred":[
        "\u0411\u043e\u0441\u0441\u0438"
    ],
    "name:slv_x_preferred":[
        "Bossi"
    ],
    "name:spa_x_preferred":[
        "Bossi"
    ],
    "wof:name":"Bossi",
    "wof:placetype":"locality"
},
  "geometry": {"coordinates":[13.86667,7.65],"type":"Point"}
}