{
  "type": "Feature",
  "properties": {
    "gn:admin1_code":"14.0",
    "gn:asciiname":"Melange I",
    "gn:country_code":"CM",
    "gn:dem":699,
    "gn:feature_class":"P",
    "gn:feature_code":"PPL",
    "gn:name":"M\u00e9lang\u00e9 I",
    "gn:population":0,
    "gn:timezone":"Africa/Douala",
    "iso:country":"CM",
    "wof:name":"Melange I",
    "wof:placetype":"locality"
},
  "geometry": {"coordinates":[11.11667,3.03333],"type":"Point"}
}