{
  "type": "Feature",
  "properties": {
    "gn:admin1_code":"8.0",
    "gn:asciiname":"Fontsa Toula",
    "gn:country_code":"CM",
    "gn:dem":1455,
    "gn:feature_class":"P",
    "gn:feature_code":"PPL",
    "gn:name":"Fontsa Toula",
    "gn:population":0,
    "gn:timezone":"Africa/Douala",
    "iso:country":"CM",
    "name:fra_x_preferred":[
        "Touala"
    ],
    "name:fra_x_variant":[
        "Fontsa Toula"
    ],
    "name:und_x_variant":[
        "Fontsa"
    ],
    "wof:name":"Fontsa Toula",
    "wof:placetype":"locality"
},
  "geometry": {"coordinates":[10.0804,5.32623],"type":"Point"}
}