{
  "type": "Feature",
  "properties": {
    "gn:admin1_code":"9.0",
    "gn:asciiname":"Limbo",
    "gn:country_code":"CM",
    "gn:dem":786,
    "gn:feature_class":"P",
    "gn:feature_code":"PPL",
    "gn:name":"Limbo",
    "gn:population":0,
    "gn:timezone":"Africa/Douala",
    "iso:country":"CM",
    "wof:name":"Limbo",
    "wof:placetype":"locality"
},
  "geometry": {"coordinates":[9.75861,5.23778],"type":"Point"}
}