{
  "type": "Feature",
  "properties": {
    "gn:admin1_code":"12.0",
    "gn:asciiname":"Ridoua",
    "gn:country_code":"CM",
    "gn:dem":793,
    "gn:feature_class":"P",
    "gn:feature_code":"PPL",
    "gn:name":"Ridoua",
    "gn:population":0,
    "gn:timezone":"Africa/Douala",
    "iso:country":"CM",
    "wof:name":"Ridoua",
    "wof:placetype":"locality"
},
  "geometry": {"coordinates":[13.76226,10.97472],"type":"Point"}
}