{
  "type": "Feature",
  "properties": {
    "gn:admin1_code":"12.0",
    "gn:asciiname":"Ngoy Hijilije",
    "gn:country_code":"CM",
    "gn:dem":291,
    "gn:feature_class":"P",
    "gn:feature_code":"PPL",
    "gn:name":"Ngoy Hijilij\u00e9",
    "gn:population":0,
    "gn:timezone":"Africa/Douala",
    "iso:country":"CM",
    "name:und_x_variant":[
        "Ngoy Dj\u00e9lidj\u00e9"
    ],
    "wof:name":"Ngoy Hijilije",
    "wof:placetype":"locality"
},
  "geometry": {"coordinates":[14.7377,12.05707],"type":"Point"}
}