{
  "type": "Feature",
  "properties": {
    "gn:admin1_code":"7.0",
    "gn:asciiname":"Ngwala",
    "gn:country_code":"CM",
    "gn:dem":1186,
    "gn:feature_class":"P",
    "gn:feature_code":"PPL",
    "gn:name":"Ngwala",
    "gn:population":0,
    "gn:timezone":"Africa/Douala",
    "iso:country":"CM",
    "name:fra_x_preferred":[
        "Ngwala"
    ],
    "name:swa_x_preferred":[
        "Ngwala"
    ],
    "wof:name":"Ngwala",
    "wof:placetype":"locality"
},
  "geometry": {"coordinates":[10.49464,5.99476],"type":"Point"}
}