{
  "type": "Feature",
  "properties": {
    "gn:admin1_code":"8.0",
    "gn:asciiname":"Nzensien",
    "gn:country_code":"CM",
    "gn:dem":759,
    "gn:feature_class":"P",
    "gn:feature_code":"PPL",
    "gn:name":"Nzensien",
    "gn:population":0,
    "gn:timezone":"Africa/Douala",
    "iso:country":"CM",
    "wof:name":"Nzensien",
    "wof:placetype":"locality"
},
  "geometry": {"coordinates":[10.98316,5.36793],"type":"Point"}
}