{
  "type": "Feature",
  "properties": {
    "gn:admin1_code":"8.0",
    "gn:asciiname":"Lele",
    "gn:country_code":"CM",
    "gn:dem":746,
    "gn:feature_class":"P",
    "gn:feature_code":"PPL",
    "gn:name":"L\u00e9l\u00e9",
    "gn:population":0,
    "gn:timezone":"Africa/Douala",
    "iso:country":"CM",
    "name:ceb_x_preferred":[
        "Lele"
    ],
    "name:deu_x_preferred":[
        "Lele"
    ],
    "name:fra_x_preferred":[
        "Lele"
    ],
    "name:hye_x_preferred":[
        "\u053c\u0565\u056c\u0565"
    ],
    "name:ind_x_preferred":[
        "Lele"
    ],
    "name:ita_x_preferred":[
        "Lele"
    ],
    "name:nld_x_preferred":[
        "Lele"
    ],
    "name:swe_x_preferred":[
        "Lele"
    ],
    "wof:name":"Lele",
    "wof:placetype":"locality"
},
  "geometry": {"coordinates":[10.08767,5.25935],"type":"Point"}
}