{
  "type": "Feature",
  "properties": {
    "gn:admin1_code":"5.0",
    "gn:asciiname":"Matanda",
    "gn:country_code":"CM",
    "gn:dem":28,
    "gn:feature_class":"P",
    "gn:feature_code":"PPL",
    "gn:name":"Matanda",
    "gn:population":0,
    "gn:timezone":"Africa/Douala",
    "iso:country":"CM",
    "wof:name":"Matanda",
    "wof:placetype":"locality"
},
  "geometry": {"coordinates":[9.67472,3.94083],"type":"Point"}
}