{
  "type": "Feature",
  "properties": {
    "gn:admin1_code":"12.0",
    "gn:asciiname":"Mourla",
    "gn:country_code":"CM",
    "gn:dem":313,
    "gn:feature_class":"P",
    "gn:feature_code":"PPL",
    "gn:name":"Mourla",
    "gn:population":0,
    "gn:timezone":"Africa/Douala",
    "iso:country":"CM",
    "wof:name":"Mourla",
    "wof:placetype":"locality"
},
  "geometry": {"coordinates":[15.07101,10.92001],"type":"Point"}
}