{
  "type": "Feature",
  "properties": {
    "gn:admin1_code":"8.0",
    "gn:asciiname":"Tounisi",
    "gn:country_code":"CM",
    "gn:dem":989,
    "gn:feature_class":"P",
    "gn:feature_code":"PPL",
    "gn:name":"Tounisi",
    "gn:population":0,
    "gn:timezone":"Africa/Douala",
    "iso:country":"CM",
    "name:fra_x_preferred":[
        "Tounisi"
    ],
    "wof:name":"Tounisi",
    "wof:placetype":"locality"
},
  "geometry": {"coordinates":[10.50547,5.37341],"type":"Point"}
}