{
  "type": "Feature",
  "properties": {
    "gn:admin1_code":"9.0",
    "gn:asciiname":"Ame",
    "gn:country_code":"CM",
    "gn:dem":592,
    "gn:feature_class":"P",
    "gn:feature_code":"PPL",
    "gn:name":"Ame",
    "gn:population":0,
    "gn:timezone":"Africa/Douala",
    "iso:country":"CM",
    "name:und_x_variant":[
        "Ama",
        "Ame"
    ],
    "wof:name":"Ame",
    "wof:placetype":"locality"
},
  "geometry": {"coordinates":[9.66941,6.26467],"type":"Point"}
}