{
  "type": "Feature",
  "properties": {
    "gn:admin1_code":"11.0",
    "gn:asciiname":"Nsenglong",
    "gn:country_code":"CM",
    "gn:dem":680,
    "gn:feature_class":"P",
    "gn:feature_code":"PPL",
    "gn:name":"Nsenglong",
    "gn:population":0,
    "gn:timezone":"Africa/Douala",
    "iso:country":"CM",
    "wof:name":"Nsenglong",
    "wof:placetype":"locality"
},
  "geometry": {"coordinates":[11.48333,3.51667],"type":"Point"}
}