{
  "type": "Feature",
  "properties": {
    "gn:admin1_code":"7.0",
    "gn:asciiname":"Bamundum",
    "gn:country_code":"CM",
    "gn:dem":1293,
    "gn:feature_class":"P",
    "gn:feature_code":"PPL",
    "gn:name":"Bamundum",
    "gn:population":0,
    "gn:timezone":"Africa/Douala",
    "iso:country":"CM",
    "wof:name":"Bamundum",
    "wof:placetype":"locality"
},
  "geometry": {"coordinates":[9.94836,6.16181],"type":"Point"}
}