{
  "type": "Feature",
  "properties": {
    "gn:admin1_code":"5.0",
    "gn:asciiname":"Ngoungou",
    "gn:country_code":"CM",
    "gn:dem":10,
    "gn:feature_class":"P",
    "gn:feature_code":"PPL",
    "gn:name":"Ngoungou",
    "gn:population":0,
    "gn:timezone":"Africa/Douala",
    "iso:country":"CM",
    "wof:name":"Ngoungou",
    "wof:placetype":"locality"
},
  "geometry": {"coordinates":[9.48472,3.98028],"type":"Point"}
}