{
  "type": "Feature",
  "properties": {
    "gn:admin1_code":"13.0",
    "gn:asciiname":"Malom Bali",
    "gn:country_code":"CM",
    "gn:dem":705,
    "gn:feature_class":"P",
    "gn:feature_code":"PPL",
    "gn:name":"Malom Bali",
    "gn:population":0,
    "gn:timezone":"Africa/Douala",
    "iso:country":"CM",
    "wof:name":"Malom Bali",
    "wof:placetype":"locality"
},
  "geometry": {"coordinates":[15.05221,7.99275],"type":"Point"}
}