{
  "type": "Feature",
  "properties": {
    "gn:admin1_code":"11.0",
    "gn:asciiname":"Eyangap",
    "gn:country_code":"CM",
    "gn:dem":675,
    "gn:feature_class":"P",
    "gn:feature_code":"PPL",
    "gn:name":"\u00c9yangap",
    "gn:population":0,
    "gn:timezone":"Africa/Douala",
    "iso:country":"CM",
    "wof:name":"Eyangap",
    "wof:placetype":"locality"
},
  "geometry": {"coordinates":[12.35,3.76667],"type":"Point"}
}