{
  "type": "Feature",
  "properties": {
    "gn:admin1_code":"11.0",
    "gn:asciiname":"Nkasomo",
    "gn:country_code":"CM",
    "gn:dem":701,
    "gn:feature_class":"P",
    "gn:feature_code":"PPL",
    "gn:name":"Nkasomo",
    "gn:population":0,
    "gn:timezone":"Africa/Douala",
    "iso:country":"CM",
    "wof:name":"Nkasomo",
    "wof:placetype":"locality"
},
  "geometry": {"coordinates":[11.61667,3.76667],"type":"Point"}
}