{
  "type": "Feature",
  "properties": {
    "gn:admin1_code":"12.0",
    "gn:asciiname":"Midan",
    "gn:country_code":"CM",
    "gn:dem":295,
    "gn:feature_class":"P",
    "gn:feature_code":"PPL",
    "gn:name":"Midan",
    "gn:population":0,
    "gn:timezone":"Africa/Douala",
    "iso:country":"CM",
    "name:und_x_variant":[
        "Midane"
    ],
    "wof:name":"Midan",
    "wof:placetype":"locality"
},
  "geometry": {"coordinates":[14.72586,12.24043],"type":"Point"}
}