{
  "type": "Feature",
  "properties": {
    "gn:admin1_code":"12.0",
    "gn:asciiname":"Tchaloudi",
    "gn:country_code":"CM",
    "gn:dem":360,
    "gn:feature_class":"P",
    "gn:feature_code":"PPL",
    "gn:name":"Tchaloudi",
    "gn:population":0,
    "gn:timezone":"Africa/Douala",
    "iso:country":"CM",
    "wof:name":"Tchaloudi",
    "wof:placetype":"locality"
},
  "geometry": {"coordinates":[14.44745,10.71522],"type":"Point"}
}