{
  "type": "Feature",
  "properties": {
    "gn:admin1_code":"4.0",
    "gn:asciiname":"Mborguene",
    "gn:country_code":"CM",
    "gn:dem":956,
    "gn:feature_class":"P",
    "gn:feature_code":"PPL",
    "gn:name":"Mborgu\u00e9n\u00e9",
    "gn:population":0,
    "gn:timezone":"Africa/Douala",
    "iso:country":"CM",
    "wof:name":"Mborguene",
    "wof:placetype":"locality"
},
  "geometry": {"coordinates":[14.26667,5.73333],"type":"Point"}
}