{
  "type": "Feature",
  "properties": {
    "gn:admin1_code":"4.0",
    "gn:asciiname":"Ebah",
    "gn:country_code":"CM",
    "gn:dem":738,
    "gn:feature_class":"P",
    "gn:feature_code":"PPL",
    "gn:name":"Ebah",
    "gn:population":0,
    "gn:timezone":"Africa/Douala",
    "iso:country":"CM",
    "wof:name":"Ebah",
    "wof:placetype":"locality"
},
  "geometry": {"coordinates":[12.91667,4.48333],"type":"Point"}
}