{
  "type": "Feature",
  "properties": {
    "gn:admin1_code":"8.0",
    "gn:asciiname":"Bondjifeu",
    "gn:country_code":"CM",
    "gn:dem":1236,
    "gn:feature_class":"P",
    "gn:feature_code":"PPL",
    "gn:name":"Bondjifeu",
    "gn:population":0,
    "gn:timezone":"Africa/Douala",
    "iso:country":"CM",
    "wof:name":"Bondjifeu",
    "wof:placetype":"locality"
},
  "geometry": {"coordinates":[10.32043,5.64674],"type":"Point"}
}