{
  "type": "Feature",
  "properties": {
    "gn:admin1_code":"8.0",
    "gn:asciiname":"Bamfelouk",
    "gn:country_code":"CM",
    "gn:dem":1398,
    "gn:feature_class":"P",
    "gn:feature_code":"PPL",
    "gn:name":"Bamfelouk",
    "gn:population":0,
    "gn:timezone":"Africa/Douala",
    "iso:country":"CM",
    "name:fra_x_preferred":[
        "Bamfelouk"
    ],
    "wof:name":"Bamfelouk",
    "wof:placetype":"locality"
},
  "geometry": {"coordinates":[10.1807,5.2041],"type":"Point"}
}