{
  "type": "Feature",
  "properties": {
    "gn:admin1_code":"5.0",
    "gn:asciiname":"Mwakoumel",
    "gn:country_code":"CM",
    "gn:dem":1280,
    "gn:feature_class":"P",
    "gn:feature_code":"PPL",
    "gn:name":"Mwakoumel",
    "gn:population":0,
    "gn:timezone":"Africa/Douala",
    "iso:country":"CM",
    "wof:name":"Mwakoumel",
    "wof:placetype":"locality"
},
  "geometry": {"coordinates":[9.7952,4.9739],"type":"Point"}
}