{
  "type": "Feature",
  "properties": {
    "gn:admin1_code":"12.0",
    "gn:asciiname":"Bame",
    "gn:country_code":"CM",
    "gn:dem":371,
    "gn:feature_class":"P",
    "gn:feature_code":"PPL",
    "gn:name":"Bam\u00e9",
    "gn:population":0,
    "gn:timezone":"Africa/Douala",
    "iso:country":"CM",
    "name:ceb_x_preferred":[
        "Bame"
    ],
    "name:spa_x_preferred":[
        "Bame"
    ],
    "name:swe_x_preferred":[
        "Bame"
    ],
    "name:und_x_variant":[
        "Banam\u00e9",
        "Bam\u00e9",
        "Baham\u00e9"
    ],
    "wof:name":"Bame",
    "wof:placetype":"locality"
},
  "geometry": {"coordinates":[13.98562,11.15567],"type":"Point"}
}