{
  "type": "Feature",
  "properties": {
    "gn:admin1_code":"12.0",
    "gn:asciiname":"Mbola",
    "gn:country_code":"CM",
    "gn:dem":694,
    "gn:feature_class":"P",
    "gn:feature_code":"PPL",
    "gn:name":"Mbola",
    "gn:population":0,
    "gn:timezone":"Africa/Douala",
    "iso:country":"CM",
    "name:ceb_x_preferred":[
        "Mbola"
    ],
    "name:swe_x_preferred":[
        "Mbola"
    ],
    "wof:name":"Mbola",
    "wof:placetype":"locality"
},
  "geometry": {"coordinates":[13.56964,10.21824],"type":"Point"}
}