{
  "type": "Feature",
  "properties": {
    "gn:admin1_code":"12.0",
    "gn:asciiname":"Bellare",
    "gn:country_code":"CM",
    "gn:dem":416,
    "gn:feature_class":"P",
    "gn:feature_code":"PPL",
    "gn:name":"Bellar\u00e9",
    "gn:population":0,
    "gn:timezone":"Africa/Douala",
    "iso:country":"CM",
    "name:kan_x_preferred":[
        "\u0cac\u0cc6\u0cb3\u0ccd\u0cb3\u0cbe\u0cb0\u0cc6"
    ],
    "name:vie_x_preferred":[
        "Bellare"
    ],
    "wof:name":"Bellare",
    "wof:placetype":"locality"
},
  "geometry": {"coordinates":[14.26498,10.56464],"type":"Point"}
}