{
  "type": "Feature",
  "properties": {
    "gn:admin1_code":"8.0",
    "gn:asciiname":"Chouplang",
    "gn:country_code":"CM",
    "gn:dem":1428,
    "gn:feature_class":"P",
    "gn:feature_code":"PPL",
    "gn:name":"Chouplang",
    "gn:population":0,
    "gn:timezone":"Africa/Douala",
    "iso:country":"CM",
    "name:eng_x_preferred":[
        "Chouplang"
    ],
    "wof:name":"Chouplang",
    "wof:placetype":"locality"
},
  "geometry": {"coordinates":[10.40958,5.17186],"type":"Point"}
}