{
  "type": "Feature",
  "properties": {
    "gn:admin1_code":"11.0",
    "gn:asciiname":"Mvane",
    "gn:country_code":"CM",
    "gn:dem":711,
    "gn:feature_class":"P",
    "gn:feature_code":"PPL",
    "gn:name":"Mvan\u00e9",
    "gn:population":0,
    "gn:timezone":"Africa/Douala",
    "iso:country":"CM",
    "wof:name":"Mvane",
    "wof:placetype":"locality"
},
  "geometry": {"coordinates":[12.58333,3.68333],"type":"Point"}
}