{
  "type": "Feature",
  "properties": {
    "gn:admin1_code":"12.0",
    "gn:asciiname":"Doro",
    "gn:country_code":"CM",
    "gn:dem":291,
    "gn:feature_class":"P",
    "gn:feature_code":"PPL",
    "gn:name":"Doro",
    "gn:population":0,
    "gn:timezone":"Africa/Douala",
    "iso:country":"CM",
    "name:ceb_x_preferred":[
        "Doro"
    ],
    "name:dan_x_preferred":[
        "Doro"
    ],
    "name:deu_x_preferred":[
        "Doro"
    ],
    "name:fra_x_preferred":[
        "Doro"
    ],
    "name:ita_x_preferred":[
        "Doro"
    ],
    "name:nld_x_preferred":[
        "Doro"
    ],
    "name:por_x_preferred":[
        "Doro"
    ],
    "name:sco_x_preferred":[
        "Doro"
    ],
    "name:spa_x_preferred":[
        "Doro"
    ],
    "name:swe_x_preferred":[
        "Doro"
    ],
    "name:uzb_x_preferred":[
        "Doro"
    ],
    "wof:name":"Doro",
    "wof:placetype":"locality"
},
  "geometry": {"coordinates":[14.75923,12.65353],"type":"Point"}
}