{
  "type": "Feature",
  "properties": {
    "gn:admin1_code":"9.0",
    "gn:asciiname":"Dikulu",
    "gn:country_code":"CM",
    "gn:dem":31,
    "gn:feature_class":"P",
    "gn:feature_code":"PPL",
    "gn:name":"Dikulu",
    "gn:population":0,
    "gn:timezone":"Africa/Douala",
    "iso:country":"CM",
    "name:und_x_variant":[
        "Dikullu",
        "Dikoulu",
        "Dikulu"
    ],
    "wof:name":"Dikulu",
    "wof:placetype":"locality"
},
  "geometry": {"coordinates":[9.26879,3.96921],"type":"Point"}
}