{
  "type": "Feature",
  "properties": {
    "gn:admin1_code":"12.0",
    "gn:asciiname":"Megueleng",
    "gn:country_code":"CM",
    "gn:dem":765,
    "gn:feature_class":"P",
    "gn:feature_code":"PPL",
    "gn:name":"M\u00e9gu\u00e9leng",
    "gn:population":0,
    "gn:timezone":"Africa/Douala",
    "iso:country":"CM",
    "wof:name":"Megueleng",
    "wof:placetype":"locality"
},
  "geometry": {"coordinates":[13.78217,10.59484],"type":"Point"}
}