{
  "type": "Feature",
  "properties": {
    "gn:admin1_code":"14.0",
    "gn:asciiname":"Bipindi",
    "gn:country_code":"CM",
    "gn:dem":79,
    "gn:feature_class":"P",
    "gn:feature_code":"PPL",
    "gn:name":"Bipindi",
    "gn:population":0,
    "gn:timezone":"Africa/Douala",
    "iso:country":"CM",
    "name:fra_x_preferred":[
        "Bipindi"
    ],
    "name:msa_x_preferred":[
        "Bipindi"
    ],
    "name:spa_x_preferred":[
        "Bipindi"
    ],
    "name:und_x_variant":[
        "Bipinde"
    ],
    "wof:name":"Bipindi",
    "wof:placetype":"locality"
},
  "geometry": {"coordinates":[10.40907,3.07791],"type":"Point"}
}