{
  "type": "Feature",
  "properties": {
    "gn:admin1_code":"11.0",
    "gn:asciiname":"Ekoangombe",
    "gn:country_code":"CM",
    "gn:dem":415,
    "gn:feature_class":"P",
    "gn:feature_code":"PPL",
    "gn:name":"Ekoangomb\u00e9",
    "gn:population":0,
    "gn:timezone":"Africa/Douala",
    "iso:country":"CM",
    "wof:name":"Ekoangombe",
    "wof:placetype":"locality"
},
  "geometry": {"coordinates":[11.03333,3.96667],"type":"Point"}
}