{
  "type": "Feature",
  "properties": {
    "gn:admin1_code":"12.0",
    "gn:asciiname":"Krenek",
    "gn:country_code":"CM",
    "gn:dem":294,
    "gn:feature_class":"P",
    "gn:feature_code":"PPL",
    "gn:name":"Krenek",
    "gn:population":0,
    "gn:timezone":"Africa/Douala",
    "iso:country":"CM",
    "name:ceb_x_preferred":[
        "Krenek"
    ],
    "name:ces_x_preferred":[
        "K\u0159enek"
    ],
    "name:deu_x_preferred":[
        "Krenek"
    ],
    "name:fra_x_preferred":[
        "K\u0159enek"
    ],
    "name:ita_x_preferred":[
        "Krenek"
    ],
    "name:pol_x_preferred":[
        "K\u0159enek"
    ],
    "wof:name":"Krenek",
    "wof:placetype":"locality"
},
  "geometry": {"coordinates":[14.85732,12.28252],"type":"Point"}
}