{
  "type": "Feature",
  "properties": {
    "gn:admin1_code":"12.0",
    "gn:asciiname":"Semi",
    "gn:country_code":"CM",
    "gn:dem":927,
    "gn:feature_class":"P",
    "gn:feature_code":"PPL",
    "gn:name":"Semi",
    "gn:population":0,
    "gn:timezone":"Africa/Douala",
    "iso:country":"CM",
    "name:bar_x_preferred":[
        "Semi"
    ],
    "name:ceb_x_preferred":[
        "Semi"
    ],
    "name:deu_x_preferred":[
        "Semi"
    ],
    "name:ita_x_preferred":[
        "Semi"
    ],
    "name:jpn_x_preferred":[
        "\u30bb\u30df"
    ],
    "name:por_x_preferred":[
        "Semi"
    ],
    "name:swe_x_preferred":[
        "Semi"
    ],
    "wof:name":"Semi",
    "wof:placetype":"locality"
},
  "geometry": {"coordinates":[13.62042,10.6358],"type":"Point"}
}