{
  "type": "Feature",
  "properties": {
    "gn:admin1_code":"14.0",
    "gn:asciiname":"Bikala",
    "gn:country_code":"CM",
    "gn:dem":390,
    "gn:feature_class":"P",
    "gn:feature_code":"PPL",
    "gn:name":"Bikala",
    "gn:population":0,
    "gn:timezone":"Africa/Douala",
    "iso:country":"CM",
    "wof:name":"Bikala",
    "wof:placetype":"locality"
},
  "geometry": {"coordinates":[10.56667,3.18333],"type":"Point"}
}