{
  "type": "Feature",
  "properties": {
    "gn:admin1_code":"13.0",
    "gn:asciiname":"Lainguel",
    "gn:country_code":"CM",
    "gn:dem":193,
    "gn:feature_class":"P",
    "gn:feature_code":"PPL",
    "gn:name":"La\u00efnguel",
    "gn:population":0,
    "gn:timezone":"Africa/Douala",
    "iso:country":"CM",
    "wof:name":"Lainguel",
    "wof:placetype":"locality"
},
  "geometry": {"coordinates":[13.61084,9.26133],"type":"Point"}
}