{
  "type": "Feature",
  "properties": {
    "gn:admin1_code":"12.0",
    "gn:asciiname":"Motchao",
    "gn:country_code":"CM",
    "gn:dem":512,
    "gn:feature_class":"P",
    "gn:feature_code":"PPL",
    "gn:name":"Motchao",
    "gn:population":0,
    "gn:timezone":"Africa/Douala",
    "iso:country":"CM",
    "name:und_x_variant":[
        "Matchoup"
    ],
    "wof:name":"Motchao",
    "wof:placetype":"locality"
},
  "geometry": {"coordinates":[13.99623,10.51971],"type":"Point"}
}