{
  "type": "Feature",
  "properties": {
    "gn:admin1_code":"8.0",
    "gn:asciiname":"Mayaakwe",
    "gn:country_code":"CM",
    "gn:dem":820,
    "gn:feature_class":"P",
    "gn:feature_code":"PPL",
    "gn:name":"Mayaakw\u00e9",
    "gn:population":0,
    "gn:timezone":"Africa/Douala",
    "iso:country":"CM",
    "name:fra_x_preferred":[
        "Mayakou\u00e9"
    ],
    "name:fra_x_variant":[
        "Mayakw\u00e9"
    ],
    "name:und_x_variant":[
        "Mayaakw\u00e9"
    ],
    "wof:name":"Mayaakwe",
    "wof:placetype":"locality"
},
  "geometry": {"coordinates":[10.87422,5.11588],"type":"Point"}
}