{
  "type": "Feature",
  "properties": {
    "gn:admin1_code":"4.0",
    "gn:asciiname":"Ezambe",
    "gn:country_code":"CM",
    "gn:dem":722,
    "gn:feature_class":"P",
    "gn:feature_code":"PPL",
    "gn:name":"Ezamb\u00e9",
    "gn:population":0,
    "gn:timezone":"Africa/Douala",
    "iso:country":"CM",
    "wof:name":"Ezambe",
    "wof:placetype":"locality"
},
  "geometry": {"coordinates":[12.81667,4.31667],"type":"Point"}
}