{
  "type": "Feature",
  "properties": {
    "gn:admin1_code":"7.0",
    "gn:asciiname":"Aje",
    "gn:country_code":"CM",
    "gn:dem":1258,
    "gn:feature_class":"P",
    "gn:feature_code":"PPL",
    "gn:name":"Aje",
    "gn:population":0,
    "gn:timezone":"Africa/Douala",
    "iso:country":"CM",
    "wof:name":"Aje",
    "wof:placetype":"locality"
},
  "geometry": {"coordinates":[9.9312,5.8325],"type":"Point"}
}