{
  "type": "Feature",
  "properties": {
    "gn:admin1_code":"12.0",
    "gn:asciiname":"Dendem",
    "gn:country_code":"CM",
    "gn:dem":420,
    "gn:feature_class":"P",
    "gn:feature_code":"PPL",
    "gn:name":"Dendem",
    "gn:population":0,
    "gn:timezone":"Africa/Douala",
    "iso:country":"CM",
    "wof:name":"Dendem",
    "wof:placetype":"locality"
},
  "geometry": {"coordinates":[14.24654,10.43363],"type":"Point"}
}