{
  "type": "Feature",
  "properties": {
    "gn:admin1_code":"9.0",
    "gn:asciiname":"Mbutu",
    "gn:country_code":"CM",
    "gn:dem":418,
    "gn:feature_class":"P",
    "gn:feature_code":"PPL",
    "gn:name":"Mbutu",
    "gn:population":0,
    "gn:timezone":"Africa/Douala",
    "iso:country":"CM",
    "wof:name":"Mbutu",
    "wof:placetype":"locality"
},
  "geometry": {"coordinates":[9.6019,6.1193],"type":"Point"}
}