{
  "type": "Feature",
  "properties": {
    "gn:admin1_code":"12.0",
    "gn:asciiname":"Pilzimiri",
    "gn:country_code":"CM",
    "gn:dem":349,
    "gn:feature_class":"P",
    "gn:feature_code":"PPL",
    "gn:name":"Pilzimiri",
    "gn:population":0,
    "gn:timezone":"Africa/Douala",
    "iso:country":"CM",
    "wof:name":"Pilzimiri",
    "wof:placetype":"locality"
},
  "geometry": {"coordinates":[14.49181,10.03117],"type":"Point"}
}