{
  "type": "Feature",
  "properties": {
    "gn:admin1_code":"12.0",
    "gn:asciiname":"Sarman",
    "gn:country_code":"CM",
    "gn:dem":370,
    "gn:feature_class":"P",
    "gn:feature_code":"PPL",
    "gn:name":"Sarman",
    "gn:population":0,
    "gn:timezone":"Africa/Douala",
    "iso:country":"CM",
    "name:ara_x_preferred":[
        "\u0627\u0644\u0635\u0631\u0645\u0627\u0646"
    ],
    "name:fas_x_preferred":[
        "\u0627\u0644\u0635\u0631\u0645\u0627\u0646"
    ],
    "name:pol_x_preferred":[
        "As-Surman"
    ],
    "name:vie_x_preferred":[
        "Sarman"
    ],
    "wof:name":"Sarman",
    "wof:placetype":"locality"
},
  "geometry": {"coordinates":[14.69215,10.26572],"type":"Point"}
}