{
  "type": "Feature",
  "properties": {
    "gn:admin1_code":"13.0",
    "gn:asciiname":"Dalehi",
    "gn:country_code":"CM",
    "gn:dem":291,
    "gn:feature_class":"P",
    "gn:feature_code":"PPL",
    "gn:name":"Dal\u00e9hi",
    "gn:population":0,
    "gn:timezone":"Africa/Douala",
    "iso:country":"CM",
    "wof:name":"Dalehi",
    "wof:placetype":"locality"
},
  "geometry": {"coordinates":[14.2017,9.1235],"type":"Point"}
}