{
  "type": "Feature",
  "properties": {
    "gn:admin1_code":"13.0",
    "gn:asciiname":"Kousmadouma",
    "gn:country_code":"CM",
    "gn:dem":466,
    "gn:feature_class":"P",
    "gn:feature_code":"PPL",
    "gn:name":"Kousmadouma",
    "gn:population":0,
    "gn:timezone":"Africa/Douala",
    "iso:country":"CM",
    "name:und_x_variant":[
        "Koussoumadouma"
    ],
    "wof:name":"Kousmadouma",
    "wof:placetype":"locality"
},
  "geometry": {"coordinates":[13.75995,10.07482],"type":"Point"}
}