{
  "type": "Feature",
  "properties": {
    "gn:admin1_code":"7.0",
    "gn:asciiname":"Tezie",
    "gn:country_code":"CM",
    "gn:dem":852,
    "gn:feature_class":"P",
    "gn:feature_code":"PPL",
    "gn:name":"Tezie",
    "gn:population":0,
    "gn:timezone":"Africa/Douala",
    "iso:country":"CM",
    "name:und_x_variant":[
        "Tedji",
        "Tezie"
    ],
    "wof:name":"Tezie",
    "wof:placetype":"locality"
},
  "geometry": {"coordinates":[9.81488,5.94217],"type":"Point"}
}