{
  "type": "Feature",
  "properties": {
    "gn:admin1_code":"8.0",
    "gn:asciiname":"Bangakou",
    "gn:country_code":"CM",
    "gn:dem":1267,
    "gn:feature_class":"P",
    "gn:feature_code":"PPL",
    "gn:name":"Bangakou",
    "gn:population":0,
    "gn:timezone":"Africa/Douala",
    "iso:country":"CM",
    "wof:name":"Bangakou",
    "wof:placetype":"locality"
},
  "geometry": {"coordinates":[10.29296,5.63786],"type":"Point"}
}