{
  "type": "Feature",
  "properties": {
    "gn:admin1_code":"12.0",
    "gn:asciiname":"Grelie",
    "gn:country_code":"CM",
    "gn:dem":290,
    "gn:feature_class":"P",
    "gn:feature_code":"PPL",
    "gn:name":"Gr\u00e9li\u00e9",
    "gn:population":0,
    "gn:timezone":"Africa/Douala",
    "iso:country":"CM",
    "name:und_x_variant":[
        "Gr\u00e9li\u00e9",
        "Gr\u00e9ll\u00e9"
    ],
    "wof:name":"Grelie",
    "wof:placetype":"locality"
},
  "geometry": {"coordinates":[14.49843,12.3858],"type":"Point"}
}