{
  "type": "Feature",
  "properties": {
    "gn:admin1_code":"12.0",
    "gn:asciiname":"Houmzou",
    "gn:country_code":"CM",
    "gn:dem":893,
    "gn:feature_class":"P",
    "gn:feature_code":"PPL",
    "gn:name":"Houmzou",
    "gn:population":0,
    "gn:timezone":"Africa/Douala",
    "iso:country":"CM",
    "wof:name":"Houmzou",
    "wof:placetype":"locality"
},
  "geometry": {"coordinates":[13.63751,10.67106],"type":"Point"}
}