{
  "type": "Feature",
  "properties": {
    "gn:admin1_code":"11.0",
    "gn:asciiname":"Efoulane",
    "gn:country_code":"CM",
    "gn:dem":664,
    "gn:feature_class":"P",
    "gn:feature_code":"PPL",
    "gn:name":"Efoulane",
    "gn:population":0,
    "gn:timezone":"Africa/Douala",
    "iso:country":"CM",
    "name:und_x_variant":[
        "Efoulan II",
        "Efoulana",
        "Efoulane"
    ],
    "wof:name":"Efoulane",
    "wof:placetype":"locality"
},
  "geometry": {"coordinates":[12.75,4.56667],"type":"Point"}
}