{
  "type": "Feature",
  "properties": {
    "gn:admin1_code":"11.0",
    "gn:asciiname":"Oban",
    "gn:country_code":"CM",
    "gn:dem":609,
    "gn:feature_class":"P",
    "gn:feature_code":"PPL",
    "gn:name":"Oban",
    "gn:population":0,
    "gn:timezone":"Africa/Douala",
    "iso:country":"CM",
    "name:azb_x_preferred":[
        "\u0627\u0648\u0628\u0627\u0646"
    ],
    "name:bre_x_preferred":[
        "An t-\u00d2ban"
    ],
    "name:bul_x_preferred":[
        "\u041e\u0443\u0431\u044a\u043d"
    ],
    "name:cat_x_preferred":[
        "Oban"
    ],
    "name:ceb_x_preferred":[
        "Oban"
    ],
    "name:ces_x_preferred":[
        "Oban"
    ],
    "name:cym_x_preferred":[
        "Oban"
    ],
    "name:deu_x_preferred":[
        "Oban"
    ],
    "name:eus_x_preferred":[
        "Oban"
    ],
    "name:fas_x_preferred":[
        "\u0627\u0648\u0628\u0627\u0646"
    ],
    "name:fra_x_preferred":[
        "Oban"
    ],
    "name:gla_x_preferred":[
        "An t-\u00d2ban"
    ],
    "name:gle_x_preferred":[
        "An t-\u00d3ban"
    ],
    "name:heb_x_preferred":[
        "\u05d0\u05d5\u05d1\u05df"
    ],
    "name:ile_x_preferred":[
        "Oban"
    ],
    "name:ita_x_preferred":[
        "Oban"
    ],
    "name:jpn_x_preferred":[
        "\u30aa\u30fc\u30d0\u30f3"
    ],
    "name:kor_x_preferred":[
        "\uc624\ubc18"
    ],
    "name:kor_x_variant":[
        "\uc624\ubc88"
    ],
    "name:nld_x_preferred":[
        "Oban"
    ],
    "name:nno_x_preferred":[
        "Oban"
    ],
    "name:nor_x_preferred":[
        "Oban"
    ],
    "name:pol_x_preferred":[
        "Oban"
    ],
    "name:por_x_preferred":[
        "Oban"
    ],
    "name:rus_x_preferred":[
        "\u041e\u0431\u0430\u043d"
    ],
    "name:sco_x_preferred":[
        "Oban"
    ],
    "name:spa_x_preferred":[
        "Oban"
    ],
    "name:swe_x_preferred":[
        "Oban"
    ],
    "name:tur_x_preferred":[
        "Oban"
    ],
    "name:ukr_x_preferred":[
        "\u041e\u0431\u0430\u043d"
    ],
    "name:urd_x_preferred":[
        "\u0627\u0648\u0628\u0627\u0646"
    ],
    "name:vie_x_preferred":[
        "Oban"
    ],
    "name:zho_cn_x_preferred":[
        "\u5965\u672c"
    ],
    "name:zho_tw_x_preferred":[
        "\u5967\u672c"
    ],
    "wof:name":"Oban",
    "wof:placetype":"locality"
},
  "geometry": {"coordinates":[11.41667,4.05],"type":"Point"}
}