{
  "type": "Feature",
  "properties": {
    "gn:admin1_code":"12.0",
    "gn:asciiname":"Nyemnyemi",
    "gn:country_code":"CM",
    "gn:dem":692,
    "gn:feature_class":"P",
    "gn:feature_code":"PPL",
    "gn:name":"Nyemnyemi",
    "gn:population":0,
    "gn:timezone":"Africa/Douala",
    "iso:country":"CM",
    "name:und_x_variant":[
        "Niam Yami",
        "Nyaminyami",
        "Nyemnyemi"
    ],
    "wof:name":"Nyemnyemi",
    "wof:placetype":"locality"
},
  "geometry": {"coordinates":[13.48606,10.32708],"type":"Point"}
}