{
  "type": "Feature",
  "properties": {
    "gn:admin1_code":"8.0",
    "gn:asciiname":"Tio",
    "gn:country_code":"CM",
    "gn:dem":1379,
    "gn:feature_class":"P",
    "gn:feature_code":"PPL",
    "gn:name":"Tio",
    "gn:population":0,
    "gn:timezone":"Africa/Douala",
    "iso:country":"CM",
    "name:fra_x_preferred":[
        "Tio"
    ],
    "wof:name":"Tio",
    "wof:placetype":"locality"
},
  "geometry": {"coordinates":[10.26494,5.58847],"type":"Point"}
}