{
  "type": "Feature",
  "properties": {
    "gn:admin1_code":"12.0",
    "gn:asciiname":"Bever",
    "gn:country_code":"CM",
    "gn:dem":661,
    "gn:feature_class":"P",
    "gn:feature_code":"PPL",
    "gn:name":"B\u00e9ver",
    "gn:population":0,
    "gn:timezone":"Africa/Douala",
    "iso:country":"CM",
    "name:cat_x_preferred":[
        "Bever"
    ],
    "name:ceb_x_preferred":[
        "Bever"
    ],
    "name:deu_x_preferred":[
        "Bever"
    ],
    "name:epo_x_preferred":[
        "Bever"
    ],
    "name:est_x_preferred":[
        "Bever"
    ],
    "name:eus_x_preferred":[
        "Bever"
    ],
    "name:fra_x_preferred":[
        "Bever"
    ],
    "name:ita_x_preferred":[
        "Bever"
    ],
    "name:nds_x_preferred":[
        "Bever"
    ],
    "name:nld_x_preferred":[
        "Bever"
    ],
    "name:nor_x_preferred":[
        "Bever"
    ],
    "name:rus_x_preferred":[
        "\u0411\u0435\u0432\u0435\u0440"
    ],
    "name:spa_x_preferred":[
        "Bever"
    ],
    "name:swe_x_preferred":[
        "Bever"
    ],
    "name:tur_x_preferred":[
        "Bever"
    ],
    "name:vol_x_preferred":[
        "Bever"
    ],
    "wof:name":"Bever",
    "wof:placetype":"locality"
},
  "geometry": {"coordinates":[13.90803,10.82612],"type":"Point"}
}