{
  "type": "Feature",
  "properties": {
    "gn:admin1_code":"10.0",
    "gn:asciiname":"Djoumbare",
    "gn:country_code":"CM",
    "gn:dem":982,
    "gn:feature_class":"P",
    "gn:feature_code":"PPL",
    "gn:name":"Djoumbar\u00e9",
    "gn:population":0,
    "gn:timezone":"Africa/Douala",
    "iso:country":"CM",
    "wof:name":"Djoumbare",
    "wof:placetype":"locality"
},
  "geometry": {"coordinates":[12.24019,6.95169],"type":"Point"}
}