{
  "type": "Feature",
  "properties": {
    "gn:admin1_code":"13.0",
    "gn:asciiname":"Telbe",
    "gn:country_code":"CM",
    "gn:dem":467,
    "gn:feature_class":"P",
    "gn:feature_code":"PPL",
    "gn:name":"Telb\u00e9",
    "gn:population":0,
    "gn:timezone":"Africa/Douala",
    "iso:country":"CM",
    "wof:name":"Telbe",
    "wof:placetype":"locality"
},
  "geometry": {"coordinates":[14.9303,8.6686],"type":"Point"}
}