{
  "type": "Feature",
  "properties": {
    "gn:admin1_code":"12.0",
    "gn:asciiname":"Mayam",
    "gn:country_code":"CM",
    "gn:dem":475,
    "gn:feature_class":"P",
    "gn:feature_code":"PPL",
    "gn:name":"Mayam",
    "gn:population":0,
    "gn:timezone":"Africa/Douala",
    "iso:country":"CM",
    "wof:name":"Mayam",
    "wof:placetype":"locality"
},
  "geometry": {"coordinates":[13.97974,10.2528],"type":"Point"}
}