{
  "type": "Feature",
  "properties": {
    "gn:admin1_code":"12.0",
    "gn:asciiname":"Fadje",
    "gn:country_code":"CM",
    "gn:dem":293,
    "gn:feature_class":"P",
    "gn:feature_code":"PPL",
    "gn:name":"Fadj\u00e9",
    "gn:population":0,
    "gn:timezone":"Africa/Douala",
    "iso:country":"CM",
    "wof:name":"Fadje",
    "wof:placetype":"locality"
},
  "geometry": {"coordinates":[14.4913,12.49175],"type":"Point"}
}