{
  "type": "Feature",
  "properties": {
    "gn:admin1_code":"13.0",
    "gn:asciiname":"Korma",
    "gn:country_code":"CM",
    "gn:dem":483,
    "gn:feature_class":"P",
    "gn:feature_code":"PPL",
    "gn:name":"Korma",
    "gn:population":0,
    "gn:timezone":"Africa/Douala",
    "iso:country":"CM",
    "wof:name":"Korma",
    "wof:placetype":"locality"
},
  "geometry": {"coordinates":[15.5507,7.7758],"type":"Point"}
}