{
  "type": "Feature",
  "properties": {
    "gn:admin1_code":"4.0",
    "gn:asciiname":"Epi",
    "gn:country_code":"CM",
    "gn:dem":629,
    "gn:feature_class":"P",
    "gn:feature_code":"PPL",
    "gn:name":"Epi",
    "gn:population":0,
    "gn:timezone":"Africa/Douala",
    "iso:country":"CM",
    "wof:name":"Epi",
    "wof:placetype":"locality"
},
  "geometry": {"coordinates":[14.66667,4.23333],"type":"Point"}
}