{
  "type": "Feature",
  "properties": {
    "gn:admin1_code":"12.0",
    "gn:asciiname":"Bouktan",
    "gn:country_code":"CM",
    "gn:dem":321,
    "gn:feature_class":"P",
    "gn:feature_code":"PPL",
    "gn:name":"Bouktan",
    "gn:population":0,
    "gn:timezone":"Africa/Douala",
    "iso:country":"CM",
    "name:und_x_variant":[
        "Bouktani",
        "Bouktan"
    ],
    "wof:name":"Bouktan",
    "wof:placetype":"locality"
},
  "geometry": {"coordinates":[15.03333,10.61667],"type":"Point"}
}