{
  "type": "Feature",
  "properties": {
    "gn:admin1_code":"12.0",
    "gn:asciiname":"Mizao Bling",
    "gn:country_code":"CM",
    "gn:dem":400,
    "gn:feature_class":"P",
    "gn:feature_code":"PPL",
    "gn:name":"Mizao Bling",
    "gn:population":0,
    "gn:timezone":"Africa/Douala",
    "iso:country":"CM",
    "wof:name":"Mizao Bling",
    "wof:placetype":"locality"
},
  "geometry": {"coordinates":[14.27007,10.16301],"type":"Point"}
}