{
  "type": "Feature",
  "properties": {
    "gn:admin1_code":"5.0",
    "gn:asciiname":"Bewang I",
    "gn:country_code":"CM",
    "gn:dem":174,
    "gn:feature_class":"P",
    "gn:feature_code":"PPL",
    "gn:name":"B\u00e9wang I",
    "gn:population":0,
    "gn:timezone":"Africa/Douala",
    "iso:country":"CM",
    "name:und_x_variant":[
        "Bewang",
        "B\u00e9wang I"
    ],
    "wof:name":"Bewang I",
    "wof:placetype":"locality"
},
  "geometry": {"coordinates":[10.08333,4.58333],"type":"Point"}
}