{
  "type": "Feature",
  "properties": {
    "gn:admin1_code":"12.0",
    "gn:asciiname":"Domo",
    "gn:country_code":"CM",
    "gn:dem":330,
    "gn:feature_class":"P",
    "gn:feature_code":"PPL",
    "gn:name":"Domo",
    "gn:population":0,
    "gn:timezone":"Africa/Douala",
    "iso:country":"CM",
    "name:ceb_x_preferred":[
        "Domo"
    ],
    "name:ita_x_preferred":[
        "Domo"
    ],
    "name:nld_x_preferred":[
        "Domo"
    ],
    "name:por_x_preferred":[
        "Domo"
    ],
    "name:spa_x_preferred":[
        "Domo"
    ],
    "name:srp_x_preferred":[
        "Domo"
    ],
    "name:swe_x_preferred":[
        "Domo"
    ],
    "name:und_x_variant":[
        "Doma",
        "Naheina\u2019s",
        "Malda Domo",
        "Domo"
    ],
    "wof:name":"Domo",
    "wof:placetype":"locality"
},
  "geometry": {"coordinates":[15.24153,10.15205],"type":"Point"}
}