{
  "type": "Feature",
  "properties": {
    "gn:admin1_code":"12.0",
    "gn:asciiname":"Petene",
    "gn:country_code":"CM",
    "gn:dem":430,
    "gn:feature_class":"P",
    "gn:feature_code":"PPL",
    "gn:name":"P\u00e9t\u00e9n\u00e9",
    "gn:population":0,
    "gn:timezone":"Africa/Douala",
    "iso:country":"CM",
    "wof:name":"Petene",
    "wof:placetype":"locality"
},
  "geometry": {"coordinates":[14.39186,10.26556],"type":"Point"}
}