{
  "type": "Feature",
  "properties": {
    "gn:admin1_code":"13.0",
    "gn:asciiname":"Djoma",
    "gn:country_code":"CM",
    "gn:dem":296,
    "gn:feature_class":"P",
    "gn:feature_code":"PPL",
    "gn:name":"Djoma",
    "gn:population":0,
    "gn:timezone":"Africa/Douala",
    "iso:country":"CM",
    "wof:name":"Djoma",
    "wof:placetype":"locality"
},
  "geometry": {"coordinates":[13.76899,9.58143],"type":"Point"}
}