{
  "type": "Feature",
  "properties": {
    "gn:admin1_code":"12.0",
    "gn:asciiname":"Agzawaya",
    "gn:country_code":"CM",
    "gn:dem":315,
    "gn:feature_class":"P",
    "gn:feature_code":"PPL",
    "gn:name":"Agzawaya",
    "gn:population":0,
    "gn:timezone":"Africa/Douala",
    "iso:country":"CM",
    "name:und_x_variant":[
        "Agzaoya",
        "Agzawaya"
    ],
    "wof:name":"Agzawaya",
    "wof:placetype":"locality"
},
  "geometry": {"coordinates":[14.32041,11.17264],"type":"Point"}
}