{
  "type": "Feature",
  "properties": {
    "gn:admin1_code":"12.0",
    "gn:asciiname":"Keleo",
    "gn:country_code":"CM",
    "gn:dem":314,
    "gn:feature_class":"P",
    "gn:feature_code":"PPL",
    "gn:name":"K\u00e9l\u00e9o",
    "gn:population":0,
    "gn:timezone":"Africa/Douala",
    "iso:country":"CM",
    "name:und_x_variant":[
        "K\u00e9l\u00e9",
        "K\u00e9l\u00e9o"
    ],
    "wof:name":"Keleo",
    "wof:placetype":"locality"
},
  "geometry": {"coordinates":[14.96647,10.73708],"type":"Point"}
}