{
  "type": "Feature",
  "properties": {
    "gn:admin1_code":"8.0",
    "gn:asciiname":"Boutcheu",
    "gn:country_code":"CM",
    "gn:dem":1421,
    "gn:feature_class":"P",
    "gn:feature_code":"PPL",
    "gn:name":"Boutcheu",
    "gn:population":0,
    "gn:timezone":"Africa/Douala",
    "iso:country":"CM",
    "name:fra_x_preferred":[
        "Baboutcha"
    ],
    "name:fra_x_variant":[
        "Boutcheu"
    ],
    "wof:name":"Boutcheu",
    "wof:placetype":"locality"
},
  "geometry": {"coordinates":[10.16736,5.11391],"type":"Point"}
}