{
  "type": "Feature",
  "properties": {
    "gn:admin1_code":"14.0",
    "gn:asciiname":"Nkan",
    "gn:country_code":"CM",
    "gn:dem":640,
    "gn:feature_class":"P",
    "gn:feature_code":"PPL",
    "gn:name":"Nkan",
    "gn:population":0,
    "gn:timezone":"Africa/Douala",
    "iso:country":"CM",
    "wof:name":"Nkan",
    "wof:placetype":"locality"
},
  "geometry": {"coordinates":[11.21667,2.93333],"type":"Point"}
}