{
  "type": "Feature",
  "properties": {
    "gn:admin1_code":"7.0",
    "gn:asciiname":"Angong",
    "gn:country_code":"CM",
    "gn:dem":999,
    "gn:feature_class":"P",
    "gn:feature_code":"PPL",
    "gn:name":"Angong",
    "gn:population":0,
    "gn:timezone":"Africa/Douala",
    "iso:country":"CM",
    "wof:name":"Angong",
    "wof:placetype":"locality"
},
  "geometry": {"coordinates":[9.834,5.9298],"type":"Point"}
}