{
  "type": "Feature",
  "properties": {
    "gn:admin1_code":"12.0",
    "gn:asciiname":"Gamal",
    "gn:country_code":"CM",
    "gn:dem":300,
    "gn:feature_class":"P",
    "gn:feature_code":"PPL",
    "gn:name":"Gamal",
    "gn:population":0,
    "gn:timezone":"Africa/Douala",
    "iso:country":"CM",
    "name:deu_x_preferred":[
        "Gamal"
    ],
    "name:heb_x_preferred":[
        "\u05d2\u05de\u05dc"
    ],
    "wof:name":"Gamal",
    "wof:placetype":"locality"
},
  "geometry": {"coordinates":[15.09958,11.80111],"type":"Point"}
}