{
  "type": "Feature",
  "properties": {
    "gn:admin1_code":"12.0",
    "gn:asciiname":"Tapadam",
    "gn:country_code":"CM",
    "gn:dem":423,
    "gn:feature_class":"P",
    "gn:feature_code":"PPL",
    "gn:name":"Tapadam",
    "gn:population":0,
    "gn:timezone":"Africa/Douala",
    "iso:country":"CM",
    "wof:name":"Tapadam",
    "wof:placetype":"locality"
},
  "geometry": {"coordinates":[14.24726,10.62381],"type":"Point"}
}