{
  "type": "Feature",
  "properties": {
    "gn:admin1_code":"14.0",
    "gn:asciiname":"Nyangong",
    "gn:country_code":"CM",
    "gn:dem":625,
    "gn:feature_class":"P",
    "gn:feature_code":"PPL",
    "gn:name":"Nyangong",
    "gn:population":0,
    "gn:timezone":"Africa/Douala",
    "iso:country":"CM",
    "wof:name":"Nyangong",
    "wof:placetype":"locality"
},
  "geometry": {"coordinates":[10.75,2.96667],"type":"Point"}
}