{
  "type": "Feature",
  "properties": {
    "gn:admin1_code":"8.0",
    "gn:asciiname":"Banonga",
    "gn:country_code":"CM",
    "gn:dem":842,
    "gn:feature_class":"P",
    "gn:feature_code":"PPL",
    "gn:name":"Banonga",
    "gn:population":0,
    "gn:timezone":"Africa/Douala",
    "iso:country":"CM",
    "wof:name":"Banonga",
    "wof:placetype":"locality"
},
  "geometry": {"coordinates":[10.55,4.98333],"type":"Point"}
}