{
  "type": "Feature",
  "properties": {
    "gn:admin1_code":"4.0",
    "gn:asciiname":"Ouanten",
    "gn:country_code":"CM",
    "gn:dem":879,
    "gn:feature_class":"P",
    "gn:feature_code":"PPL",
    "gn:name":"Ouanten",
    "gn:population":0,
    "gn:timezone":"Africa/Douala",
    "iso:country":"CM",
    "name:und_x_variant":[
        "Ouenden",
        "Ouanden",
        "Ouanten"
    ],
    "wof:name":"Ouanten",
    "wof:placetype":"locality"
},
  "geometry": {"coordinates":[14.25,5.31667],"type":"Point"}
}