{
  "type": "Feature",
  "properties": {
    "gn:admin1_code":"0.0",
    "gn:asciiname":"Ndokbasagog I",
    "gn:country_code":"CM",
    "gn:dem":802,
    "gn:feature_class":"P",
    "gn:feature_code":"PPL",
    "gn:name":"Ndokbasagog I",
    "gn:population":0,
    "gn:timezone":"Africa/Douala",
    "iso:country":"CM",
    "wof:name":"Ndokbasagog I",
    "wof:placetype":"locality"
},
  "geometry": {"coordinates":[10.61667,4.45],"type":"Point"}
}