{
  "type": "Feature",
  "properties": {
    "gn:admin1_code":"11.0",
    "gn:asciiname":"Awout",
    "gn:country_code":"CM",
    "gn:dem":677,
    "gn:feature_class":"P",
    "gn:feature_code":"PPL",
    "gn:name":"Awout",
    "gn:population":0,
    "gn:timezone":"Africa/Douala",
    "iso:country":"CM",
    "wof:name":"Awout",
    "wof:placetype":"locality"
},
  "geometry": {"coordinates":[12.33333,4.11667],"type":"Point"}
}