{
  "type": "Feature",
  "properties": {
    "gn:admin1_code":"12.0",
    "gn:asciiname":"Bangana",
    "gn:country_code":"CM",
    "gn:dem":330,
    "gn:feature_class":"P",
    "gn:feature_code":"PPL",
    "gn:name":"Bangana",
    "gn:population":0,
    "gn:timezone":"Africa/Douala",
    "iso:country":"CM",
    "name:cat_x_preferred":[
        "Bangana"
    ],
    "name:ceb_x_preferred":[
        "Bangana"
    ],
    "name:fra_x_preferred":[
        "Bangana"
    ],
    "name:nld_x_preferred":[
        "Bangana"
    ],
    "name:rus_x_preferred":[
        "Bangana"
    ],
    "name:spa_x_preferred":[
        "Bangana"
    ],
    "name:swe_x_preferred":[
        "Bangana"
    ],
    "name:tha_x_preferred":[
        "\u0e1b\u0e25\u0e32\u0e2b\u0e27\u0e49\u0e32"
    ],
    "name:vie_x_preferred":[
        "Bangana"
    ],
    "name:war_x_preferred":[
        "Bangana"
    ],
    "wof:name":"Bangana",
    "wof:placetype":"locality"
},
  "geometry": {"coordinates":[15.31973,10.20102],"type":"Point"}
}