{
  "type": "Feature",
  "properties": {
    "gn:admin1_code":"8.0",
    "gn:asciiname":"Mendou",
    "gn:country_code":"CM",
    "gn:dem":1670,
    "gn:feature_class":"P",
    "gn:feature_code":"PPL",
    "gn:name":"Mendou",
    "gn:population":0,
    "gn:timezone":"Africa/Douala",
    "iso:country":"CM",
    "wof:name":"Mendou",
    "wof:placetype":"locality"
},
  "geometry": {"coordinates":[10.15885,5.55473],"type":"Point"}
}