{
  "type": "Feature",
  "properties": {
    "gn:admin1_code":"13.0",
    "gn:asciiname":"Tiguere",
    "gn:country_code":"CM",
    "gn:dem":323,
    "gn:feature_class":"P",
    "gn:feature_code":"PPL",
    "gn:name":"Tigu\u00e9r\u00e9",
    "gn:population":0,
    "gn:timezone":"Africa/Douala",
    "iso:country":"CM",
    "wof:name":"Tiguere",
    "wof:placetype":"locality"
},
  "geometry": {"coordinates":[14.0683,9.5258],"type":"Point"}
}