{
  "type": "Feature",
  "properties": {
    "gn:admin1_code":"13.0",
    "gn:asciiname":"Mboukma",
    "gn:country_code":"CM",
    "gn:dem":300,
    "gn:feature_class":"P",
    "gn:feature_code":"PPL",
    "gn:name":"Mboukma",
    "gn:population":0,
    "gn:timezone":"Africa/Douala",
    "iso:country":"CM",
    "name:und_x_variant":[
        "Boukouma",
        "Buguma",
        "Bougouma",
        "Boukma",
        "Mboukma"
    ],
    "wof:name":"Mboukma",
    "wof:placetype":"locality"
},
  "geometry": {"coordinates":[13.97659,8.52172],"type":"Point"}
}