{
  "type": "Feature",
  "properties": {
    "gn:admin1_code":"11.0",
    "gn:asciiname":"Mandjoum",
    "gn:country_code":"CM",
    "gn:dem":911,
    "gn:feature_class":"P",
    "gn:feature_code":"PPL",
    "gn:name":"Mandjoum",
    "gn:population":0,
    "gn:timezone":"Africa/Douala",
    "iso:country":"CM",
    "wof:name":"Mandjoum",
    "wof:placetype":"locality"
},
  "geometry": {"coordinates":[12.00342,6.21796],"type":"Point"}
}