{
  "type": "Feature",
  "properties": {
    "gn:admin1_code":"13.0",
    "gn:asciiname":"Mananya",
    "gn:country_code":"CM",
    "gn:dem":345,
    "gn:feature_class":"P",
    "gn:feature_code":"PPL",
    "gn:name":"Mananya",
    "gn:population":0,
    "gn:timezone":"Africa/Douala",
    "iso:country":"CM",
    "wof:name":"Mananya",
    "wof:placetype":"locality"
},
  "geometry": {"coordinates":[14.4641,8.3639],"type":"Point"}
}