{
  "type": "Feature",
  "properties": {
    "gn:admin1_code":"8.0",
    "gn:asciiname":"Njitande",
    "gn:country_code":"CM",
    "gn:dem":1118,
    "gn:feature_class":"P",
    "gn:feature_code":"PPL",
    "gn:name":"Njitande",
    "gn:population":0,
    "gn:timezone":"Africa/Douala",
    "iso:country":"CM",
    "wof:name":"Njitande",
    "wof:placetype":"locality"
},
  "geometry": {"coordinates":[10.60317,5.53035],"type":"Point"}
}