{
  "type": "Feature",
  "properties": {
    "gn:admin1_code":"8.0",
    "gn:asciiname":"Nkounja",
    "gn:country_code":"CM",
    "gn:dem":1229,
    "gn:feature_class":"P",
    "gn:feature_code":"PPL",
    "gn:name":"Nkounja",
    "gn:population":0,
    "gn:timezone":"Africa/Douala",
    "iso:country":"CM",
    "name:fra_x_preferred":[
        "Koundja"
    ],
    "name:fra_x_variant":[
        "Nkounja",
        "Kounja"
    ],
    "name:und_x_variant":[
        "Kounja"
    ],
    "wof:name":"Nkounja",
    "wof:placetype":"locality"
},
  "geometry": {"coordinates":[10.74364,5.63597],"type":"Point"}
}