{
  "type": "Feature",
  "properties": {
    "gn:admin1_code":"13.0",
    "gn:asciiname":"Seri",
    "gn:country_code":"CM",
    "gn:dem":812,
    "gn:feature_class":"P",
    "gn:feature_code":"PPL",
    "gn:name":"S\u00e9ri",
    "gn:population":0,
    "gn:timezone":"Africa/Douala",
    "iso:country":"CM",
    "name:ceb_x_preferred":[
        "Seri"
    ],
    "name:chv_x_preferred":[
        "\u0421\u0435\u0440\u0438"
    ],
    "name:deu_x_preferred":[
        "Seri"
    ],
    "name:fra_x_preferred":[
        "Seri"
    ],
    "name:heb_x_preferred":[
        "\u05e1\u05e8\u05d9"
    ],
    "name:ita_x_preferred":[
        "Seri"
    ],
    "name:nld_x_preferred":[
        "Seri"
    ],
    "name:pol_x_preferred":[
        "Seri"
    ],
    "name:rus_x_preferred":[
        "\u0421\u0435\u0440\u0438"
    ],
    "name:spa_x_preferred":[
        "Seri"
    ],
    "name:swe_x_preferred":[
        "Seri"
    ],
    "name:und_x_variant":[
        "S\u00e9ri"
    ],
    "wof:name":"Seri",
    "wof:placetype":"locality"
},
  "geometry": {"coordinates":[13.33622,8.44024],"type":"Point"}
}