{
  "type": "Feature",
  "properties": {
    "gn:admin1_code":"13.0",
    "gn:asciiname":"Dalami",
    "gn:country_code":"CM",
    "gn:dem":604,
    "gn:feature_class":"P",
    "gn:feature_code":"PPL",
    "gn:name":"Dalami",
    "gn:population":0,
    "gn:timezone":"Africa/Douala",
    "iso:country":"CM",
    "wof:name":"Dalami",
    "wof:placetype":"locality"
},
  "geometry": {"coordinates":[13.36667,9.93333],"type":"Point"}
}