{
  "type": "Feature",
  "properties": {
    "gn:admin1_code":"13.0",
    "gn:asciiname":"Karewa",
    "gn:country_code":"CM",
    "gn:dem":207,
    "gn:feature_class":"P",
    "gn:feature_code":"PPL",
    "gn:name":"Kar\u00e9wa",
    "gn:population":0,
    "gn:timezone":"Africa/Douala",
    "iso:country":"CM",
    "wof:name":"Karewa",
    "wof:placetype":"locality"
},
  "geometry": {"coordinates":[13.56,9.18185],"type":"Point"}
}