{
  "type": "Feature",
  "properties": {
    "gn:admin1_code":"12.0",
    "gn:asciiname":"Mayo Kewe",
    "gn:country_code":"CM",
    "gn:dem":486,
    "gn:feature_class":"P",
    "gn:feature_code":"PPL",
    "gn:name":"Mayo K\u00e9w\u00e9",
    "gn:population":0,
    "gn:timezone":"Africa/Douala",
    "iso:country":"CM",
    "name:und_x_variant":[
        "Mayo K\u00e9w\u00e9",
        "Ma\u00efk\u00e9v\u00e9"
    ],
    "wof:name":"Mayo Kewe",
    "wof:placetype":"locality"
},
  "geometry": {"coordinates":[13.90687,10.2218],"type":"Point"}
}