{
  "type": "Feature",
  "properties": {
    "gn:admin1_code":"13.0",
    "gn:asciiname":"Boriwala",
    "gn:country_code":"CM",
    "gn:dem":403,
    "gn:feature_class":"P",
    "gn:feature_code":"PPL",
    "gn:name":"Boriwala",
    "gn:population":0,
    "gn:timezone":"Africa/Douala",
    "iso:country":"CM",
    "wof:name":"Boriwala",
    "wof:placetype":"locality"
},
  "geometry": {"coordinates":[13.6173,9.84532],"type":"Point"}
}