{
  "type": "Feature",
  "properties": {
    "gn:admin1_code":"12.0",
    "gn:asciiname":"Goda",
    "gn:country_code":"CM",
    "gn:dem":419,
    "gn:feature_class":"P",
    "gn:feature_code":"PPL",
    "gn:name":"Goda",
    "gn:population":0,
    "gn:timezone":"Africa/Douala",
    "iso:country":"CM",
    "name:ceb_x_preferred":[
        "Goda"
    ],
    "name:deu_x_preferred":[
        "Goda"
    ],
    "name:lit_x_preferred":[
        "Goda"
    ],
    "name:swe_x_preferred":[
        "Goda"
    ],
    "wof:name":"Goda",
    "wof:placetype":"locality"
},
  "geometry": {"coordinates":[14.37158,10.16428],"type":"Point"}
}