{
  "type": "Feature",
  "properties": {
    "gn:admin1_code":"11.0",
    "gn:asciiname":"Mebem",
    "gn:country_code":"CM",
    "gn:dem":703,
    "gn:feature_class":"P",
    "gn:feature_code":"PPL",
    "gn:name":"M\u00e9bem",
    "gn:population":0,
    "gn:timezone":"Africa/Douala",
    "iso:country":"CM",
    "wof:name":"Mebem",
    "wof:placetype":"locality"
},
  "geometry": {"coordinates":[12.18333,3.48333],"type":"Point"}
}