{
  "type": "Feature",
  "properties": {
    "gn:admin1_code":"13.0",
    "gn:asciiname":"Lainde Magogo",
    "gn:country_code":"CM",
    "gn:dem":356,
    "gn:feature_class":"P",
    "gn:feature_code":"PPL",
    "gn:name":"La\u00efnd\u00e9 Magogo",
    "gn:population":0,
    "gn:timezone":"Africa/Douala",
    "iso:country":"CM",
    "wof:name":"Lainde Magogo",
    "wof:placetype":"locality"
},
  "geometry": {"coordinates":[14.2289,9.4079],"type":"Point"}
}