{
  "type": "Feature",
  "properties": {
    "gn:admin1_code":"12.0",
    "gn:asciiname":"Tchabaol",
    "gn:country_code":"CM",
    "gn:dem":430,
    "gn:feature_class":"P",
    "gn:feature_code":"PPL",
    "gn:name":"Tchabaol",
    "gn:population":0,
    "gn:timezone":"Africa/Douala",
    "iso:country":"CM",
    "wof:name":"Tchabaol",
    "wof:placetype":"locality"
},
  "geometry": {"coordinates":[14.23661,10.63332],"type":"Point"}
}