{
  "type": "Feature",
  "properties": {
    "gn:admin1_code":"12.0",
    "gn:asciiname":"Boulare",
    "gn:country_code":"CM",
    "gn:dem":325,
    "gn:feature_class":"P",
    "gn:feature_code":"PPL",
    "gn:name":"Boular\u00e9",
    "gn:population":0,
    "gn:timezone":"Africa/Douala",
    "iso:country":"CM",
    "wof:name":"Boulare",
    "wof:placetype":"locality"
},
  "geometry": {"coordinates":[14.68216,10.84176],"type":"Point"}
}