{
  "type": "Feature",
  "properties": {
    "gn:admin1_code":"8.0",
    "gn:asciiname":"Nkeyie",
    "gn:country_code":"CM",
    "gn:dem":1082,
    "gn:feature_class":"P",
    "gn:feature_code":"PPL",
    "gn:name":"Nk\u00e9yi\u00e9",
    "gn:population":0,
    "gn:timezone":"Africa/Douala",
    "iso:country":"CM",
    "wof:name":"Nkeyie",
    "wof:placetype":"locality"
},
  "geometry": {"coordinates":[10.94911,5.58836],"type":"Point"}
}