{
  "type": "Feature",
  "properties": {
    "gn:admin1_code":"12.0",
    "gn:asciiname":"Amdjagara",
    "gn:country_code":"CM",
    "gn:dem":292,
    "gn:feature_class":"P",
    "gn:feature_code":"PPL",
    "gn:name":"Amdjagara",
    "gn:population":0,
    "gn:timezone":"Africa/Douala",
    "iso:country":"CM",
    "wof:name":"Amdjagara",
    "wof:placetype":"locality"
},
  "geometry": {"coordinates":[14.70945,12.39221],"type":"Point"}
}