{
  "type": "Feature",
  "properties": {
    "gn:admin1_code":"8.0",
    "gn:asciiname":"Mogatchio",
    "gn:country_code":"CM",
    "gn:dem":1252,
    "gn:feature_class":"P",
    "gn:feature_code":"PPL",
    "gn:name":"Mogatchio",
    "gn:population":0,
    "gn:timezone":"Africa/Douala",
    "iso:country":"CM",
    "wof:name":"Mogatchio",
    "wof:placetype":"locality"
},
  "geometry": {"coordinates":[10.31587,5.60809],"type":"Point"}
}