{
  "type": "Feature",
  "properties": {
    "gn:admin1_code":"12.0",
    "gn:asciiname":"Ardebe",
    "gn:country_code":"CM",
    "gn:dem":299,
    "gn:feature_class":"P",
    "gn:feature_code":"PPL",
    "gn:name":"Ard\u00e9b\u00e9",
    "gn:population":0,
    "gn:timezone":"Africa/Douala",
    "iso:country":"CM",
    "wof:name":"Ardebe",
    "wof:placetype":"locality"
},
  "geometry": {"coordinates":[15.05089,12.05086],"type":"Point"}
}