{
  "type": "Feature",
  "properties": {
    "gn:admin1_code":"13.0",
    "gn:asciiname":"Bapouni",
    "gn:country_code":"CM",
    "gn:dem":213,
    "gn:feature_class":"P",
    "gn:feature_code":"PPL",
    "gn:name":"Bapouni",
    "gn:population":0,
    "gn:timezone":"Africa/Douala",
    "iso:country":"CM",
    "name:und_x_variant":[
        "Bapouli",
        "Bapo\u00fani",
        "Bapouni"
    ],
    "wof:name":"Bapouni",
    "wof:placetype":"locality"
},
  "geometry": {"coordinates":[13.87624,8.92605],"type":"Point"}
}