{
  "type": "Feature",
  "properties": {
    "gn:admin1_code":"4.0",
    "gn:asciiname":"Mongobia",
    "gn:country_code":"CM",
    "gn:dem":622,
    "gn:feature_class":"P",
    "gn:feature_code":"PPL",
    "gn:name":"Mongobia",
    "gn:population":0,
    "gn:timezone":"Africa/Douala",
    "iso:country":"CM",
    "wof:name":"Mongobia",
    "wof:placetype":"locality"
},
  "geometry": {"coordinates":[14.48333,4.06667],"type":"Point"}
}