{
  "type": "Feature",
  "properties": {
    "gn:admin1_code":"12.0",
    "gn:asciiname":"Gouringuel",
    "gn:country_code":"CM",
    "gn:dem":567,
    "gn:feature_class":"P",
    "gn:feature_code":"PPL",
    "gn:name":"Gouringuel",
    "gn:population":0,
    "gn:timezone":"Africa/Douala",
    "iso:country":"CM",
    "name:und_x_variant":[
        "Gouringel",
        "Gouringuel",
        "Gouringu\u00e8l"
    ],
    "wof:name":"Gouringuel",
    "wof:placetype":"locality"
},
  "geometry": {"coordinates":[13.87481,10.5889],"type":"Point"}
}