{
  "type": "Feature",
  "properties": {
    "gn:admin1_code":"13.0",
    "gn:asciiname":"Mangzean",
    "gn:country_code":"CM",
    "gn:dem":586,
    "gn:feature_class":"P",
    "gn:feature_code":"PPL",
    "gn:name":"Mangz\u00e9an",
    "gn:population":0,
    "gn:timezone":"Africa/Douala",
    "iso:country":"CM",
    "wof:name":"Mangzean",
    "wof:placetype":"locality"
},
  "geometry": {"coordinates":[13.32969,8.31426],"type":"Point"}
}