{
  "type": "Feature",
  "properties": {
    "gn:admin1_code":"5.0",
    "gn:asciiname":"Bonambassi",
    "gn:country_code":"CM",
    "gn:dem":9,
    "gn:feature_class":"P",
    "gn:feature_code":"PPL",
    "gn:name":"Bonambassi",
    "gn:population":0,
    "gn:timezone":"Africa/Douala",
    "iso:country":"CM",
    "wof:name":"Bonambassi",
    "wof:placetype":"locality"
},
  "geometry": {"coordinates":[9.8392,4.3155],"type":"Point"}
}