{
  "type": "Feature",
  "properties": {
    "gn:admin1_code":"13.0",
    "gn:asciiname":"Djouvoure",
    "gn:country_code":"CM",
    "gn:dem":387,
    "gn:feature_class":"P",
    "gn:feature_code":"PPL",
    "gn:name":"Djouvour\u00e9",
    "gn:population":0,
    "gn:timezone":"Africa/Douala",
    "iso:country":"CM",
    "wof:name":"Djouvoure",
    "wof:placetype":"locality"
},
  "geometry": {"coordinates":[13.90495,10.06194],"type":"Point"}
}