{
  "type": "Feature",
  "properties": {
    "gn:admin1_code":"12.0",
    "gn:asciiname":"Koskele",
    "gn:country_code":"CM",
    "gn:dem":385,
    "gn:feature_class":"P",
    "gn:feature_code":"PPL",
    "gn:name":"Kosk\u00e9l\u00e9",
    "gn:population":0,
    "gn:timezone":"Africa/Douala",
    "iso:country":"CM",
    "wof:name":"Koskele",
    "wof:placetype":"locality"
},
  "geometry": {"coordinates":[14.23847,10.06711],"type":"Point"}
}