{
  "type": "Feature",
  "properties": {
    "gn:admin1_code":"12.0",
    "gn:asciiname":"Hinale",
    "gn:country_code":"CM",
    "gn:dem":301,
    "gn:feature_class":"P",
    "gn:feature_code":"PPL",
    "gn:name":"Hinal\u00e9",
    "gn:population":0,
    "gn:timezone":"Africa/Douala",
    "iso:country":"CM",
    "wof:name":"Hinale",
    "wof:placetype":"locality"
},
  "geometry": {"coordinates":[14.99171,11.58408],"type":"Point"}
}