{
  "type": "Feature",
  "properties": {
    "gn:admin1_code":"9.0",
    "gn:asciiname":"Inua Mba",
    "gn:country_code":"CM",
    "gn:dem":21,
    "gn:feature_class":"P",
    "gn:feature_code":"PPL",
    "gn:name":"Inua Mba",
    "gn:population":0,
    "gn:timezone":"Africa/Douala",
    "iso:country":"CM",
    "wof:name":"Inua Mba",
    "wof:placetype":"locality"
},
  "geometry": {"coordinates":[8.6758,4.5224],"type":"Point"}
}