{
  "type": "Feature",
  "properties": {
    "gn:admin1_code":"12.0",
    "gn:asciiname":"Banissawe",
    "gn:country_code":"CM",
    "gn:dem":290,
    "gn:feature_class":"P",
    "gn:feature_code":"PPL",
    "gn:name":"Banissaw\u00e9",
    "gn:population":0,
    "gn:timezone":"Africa/Douala",
    "iso:country":"CM",
    "name:und_x_variant":[
        "Banissaw\u00e9",
        "Benisaw\u00e9"
    ],
    "wof:name":"Banissawe",
    "wof:placetype":"locality"
},
  "geometry": {"coordinates":[14.35925,12.38678],"type":"Point"}
}