{
  "type": "Feature",
  "properties": {
    "gn:admin1_code":"14.0",
    "gn:asciiname":"Alen",
    "gn:country_code":"CM",
    "gn:dem":617,
    "gn:feature_class":"P",
    "gn:feature_code":"PPL",
    "gn:name":"Alen",
    "gn:population":0,
    "gn:timezone":"Africa/Douala",
    "iso:country":"CM",
    "name:ceb_x_preferred":[
        "Alen"
    ],
    "name:deu_x_preferred":[
        "Alen"
    ],
    "name:eus_x_preferred":[
        "Alen"
    ],
    "name:nld_x_preferred":[
        "Alen"
    ],
    "wof:name":"Alen",
    "wof:placetype":"locality"
},
  "geometry": {"coordinates":[11.03333,2.21667],"type":"Point"}
}