{
  "type": "Feature",
  "properties": {
    "gn:admin1_code":"8.0",
    "gn:asciiname":"Wonla'",
    "gn:country_code":"CM",
    "gn:dem":1387,
    "gn:feature_class":"P",
    "gn:feature_code":"PPL",
    "gn:name":"Wonla\u2019",
    "gn:population":0,
    "gn:timezone":"Africa/Douala",
    "iso:country":"CM",
    "wof:name":"Wonla'",
    "wof:placetype":"locality"
},
  "geometry": {"coordinates":[10.00602,5.42745],"type":"Point"}
}