{
  "type": "Feature",
  "properties": {
    "gn:admin1_code":"12.0",
    "gn:asciiname":"Djelle",
    "gn:country_code":"CM",
    "gn:dem":553,
    "gn:feature_class":"P",
    "gn:feature_code":"PPL",
    "gn:name":"Dj\u00e9ll\u00e9",
    "gn:population":0,
    "gn:timezone":"Africa/Douala",
    "iso:country":"CM",
    "wof:name":"Djelle",
    "wof:placetype":"locality"
},
  "geometry": {"coordinates":[13.84743,10.85156],"type":"Point"}
}