{
  "type": "Feature",
  "properties": {
    "gn:admin1_code":"11.0",
    "gn:asciiname":"Abam",
    "gn:country_code":"CM",
    "gn:dem":632,
    "gn:feature_class":"P",
    "gn:feature_code":"PPL",
    "gn:name":"Abam",
    "gn:population":0,
    "gn:timezone":"Africa/Douala",
    "iso:country":"CM",
    "wof:name":"Abam",
    "wof:placetype":"locality"
},
  "geometry": {"coordinates":[12.68333,4.81667],"type":"Point"}
}