{
  "type": "Feature",
  "properties": {
    "gn:admin1_code":"8.0",
    "gn:asciiname":"Choke",
    "gn:country_code":"CM",
    "gn:dem":1464,
    "gn:feature_class":"P",
    "gn:feature_code":"PPL",
    "gn:name":"Chok\u00e8",
    "gn:population":0,
    "gn:timezone":"Africa/Douala",
    "iso:country":"CM",
    "name:deu_x_preferred":[
        "Choke"
    ],
    "name:fra_x_preferred":[
        "Choke"
    ],
    "name:glg_x_preferred":[
        "Choke"
    ],
    "name:ita_x_preferred":[
        "Choke"
    ],
    "name:por_x_preferred":[
        "Choke"
    ],
    "name:rus_x_preferred":[
        "\u0423\u0434\u0443\u0448\u044c\u0435"
    ],
    "name:ukr_x_preferred":[
        "\u0417\u0430\u0434\u0443\u0445\u0430"
    ],
    "wof:name":"Choke",
    "wof:placetype":"locality"
},
  "geometry": {"coordinates":[10.45066,5.443],"type":"Point"}
}