{
  "type": "Feature",
  "properties": {
    "gn:admin1_code":"11.0",
    "gn:asciiname":"Mbam",
    "gn:country_code":"CM",
    "gn:dem":932,
    "gn:feature_class":"P",
    "gn:feature_code":"PPL",
    "gn:name":"Mbam",
    "gn:population":0,
    "gn:timezone":"Africa/Douala",
    "iso:country":"CM",
    "wof:name":"Mbam",
    "wof:placetype":"locality"
},
  "geometry": {"coordinates":[12.41667,5.98333],"type":"Point"}
}