{
  "type": "Feature",
  "properties": {
    "gn:admin1_code":"11.0",
    "gn:asciiname":"Mbam",
    "gn:country_code":"CM",
    "gn:dem":932,
    "gn:feature_class":"P",
    "gn:feature_code":"PPL",
    "gn:name":"Mbam",
    "gn:population":0,
    "gn:timezone":"Africa/Douala",
    "iso:country":"CM",
    "name:ara_x_preferred":[
        "\u0645\u0628\u0627\u0645"
    ],
    "name:ben_x_preferred":[
        "\u098f\u09ae\u09cd\u09ac\u09be\u09ae"
    ],
    "name:ell_x_preferred":[
        "\u039c\u03bc\u03c0\u03b1\u03bc"
    ],
    "name:fas_x_preferred":[
        "\u0627\u0645\u0628\u0627\u0645"
    ],
    "name:heb_x_preferred":[
        "\u05e8\u05db\u05e1 \u05de\u05d1\u05d0\u05e0\u05d2"
    ],
    "name:hin_x_preferred":[
        "\u090f\u092e\u092c\u0947\u092e"
    ],
    "name:hun_x_preferred":[
        "Mbam"
    ],
    "name:ind_x_preferred":[
        "Mbam"
    ],
    "name:kor_x_preferred":[
        "\uc74c\ubc24"
    ],
    "name:tur_x_preferred":[
        "Mbam"
    ],
    "name:ukr_x_preferred":[
        "\u041c\u0431\u0430\u043c"
    ],
    "name:urd_x_preferred":[
        "\u0627\u06cc\u0645\u0628\u0627\u0645"
    ],
    "name:vie_x_preferred":[
        "S\u00f4ng Mbam"
    ],
    "wof:name":"Mbam",
    "wof:placetype":"locality"
},
  "geometry": {"coordinates":[12.41667,5.98333],"type":"Point"}
}