{
  "type": "Feature",
  "properties": {
    "gn:admin1_code":"12.0",
    "gn:asciiname":"Khouloum-Dma",
    "gn:country_code":"CM",
    "gn:dem":298,
    "gn:feature_class":"P",
    "gn:feature_code":"PPL",
    "gn:name":"Khouloum-Dma",
    "gn:population":0,
    "gn:timezone":"Africa/Douala",
    "iso:country":"CM",
    "name:und_x_variant":[
        "Ndoughoula",
        "Khouloum-Dma"
    ],
    "wof:name":"Khouloum-Dma",
    "wof:placetype":"locality"
},
  "geometry": {"coordinates":[14.59271,11.71028],"type":"Point"}
}