{
  "type": "Feature",
  "properties": {
    "gn:admin1_code":"9.0",
    "gn:asciiname":"Nskumba",
    "gn:country_code":"CM",
    "gn:dem":207,
    "gn:feature_class":"P",
    "gn:feature_code":"PPL",
    "gn:name":"Nskumba",
    "gn:population":0,
    "gn:timezone":"Africa/Douala",
    "iso:country":"CM",
    "wof:name":"Nskumba",
    "wof:placetype":"locality"
},
  "geometry": {"coordinates":[9.5092,6.1665],"type":"Point"}
}