{
  "type": "Feature",
  "properties": {
    "gn:admin1_code":"9.0",
    "gn:asciiname":"Djauru",
    "gn:country_code":"CM",
    "gn:dem":258,
    "gn:feature_class":"P",
    "gn:feature_code":"PPL",
    "gn:name":"Djauru",
    "gn:population":0,
    "gn:timezone":"Africa/Douala",
    "iso:country":"CM",
    "wof:name":"Djauru",
    "wof:placetype":"locality"
},
  "geometry": {"coordinates":[9.7221,6.4471],"type":"Point"}
}