{
  "type": "Feature",
  "properties": {
    "gn:admin1_code":"9.0",
    "gn:asciiname":"Beokoma",
    "gn:country_code":"CM",
    "gn:dem":396,
    "gn:feature_class":"P",
    "gn:feature_code":"PPL",
    "gn:name":"Beokoma",
    "gn:population":0,
    "gn:timezone":"Africa/Douala",
    "iso:country":"CM",
    "wof:name":"Beokoma",
    "wof:placetype":"locality"
},
  "geometry": {"coordinates":[9.0964,4.8739],"type":"Point"}
}