{
  "type": "Feature",
  "properties": {
    "gn:admin1_code":"8.0",
    "gn:asciiname":"Suala'",
    "gn:country_code":"CM",
    "gn:dem":1564,
    "gn:feature_class":"P",
    "gn:feature_code":"PPL",
    "gn:name":"Suala\u2019",
    "gn:population":0,
    "gn:timezone":"Africa/Douala",
    "iso:country":"CM",
    "wof:name":"Suala'",
    "wof:placetype":"locality"
},
  "geometry": {"coordinates":[10.10347,5.44121],"type":"Point"}
}