{
  "type": "Feature",
  "properties": {
    "gn:admin1_code":"10.0",
    "gn:asciiname":"Bayara",
    "gn:country_code":"CM",
    "gn:dem":1061,
    "gn:feature_class":"P",
    "gn:feature_code":"PPL",
    "gn:name":"Bayara",
    "gn:population":0,
    "gn:timezone":"Africa/Douala",
    "iso:country":"CM",
    "name:fra_x_preferred":[
        "Bayara"
    ],
    "wof:name":"Bayara",
    "wof:placetype":"locality"
},
  "geometry": {"coordinates":[14.46667,6.96667],"type":"Point"}
}