{
  "type": "Feature",
  "properties": {
    "gn:admin1_code":"9.0",
    "gn:asciiname":"Boa",
    "gn:country_code":"CM",
    "gn:dem":494,
    "gn:feature_class":"P",
    "gn:feature_code":"PPL",
    "gn:name":"Boa",
    "gn:population":0,
    "gn:timezone":"Africa/Douala",
    "iso:country":"CM",
    "name:ara_x_preferred":[
        "\u0628\u0648\u0627"
    ],
    "name:ceb_x_preferred":[
        "Boa"
    ],
    "name:ces_x_preferred":[
        "Boa"
    ],
    "name:dan_x_preferred":[
        "Boa"
    ],
    "name:deu_x_preferred":[
        "Boa"
    ],
    "name:est_x_preferred":[
        "Boa"
    ],
    "name:fin_x_preferred":[
        "Boa"
    ],
    "name:fra_x_preferred":[
        "Boa"
    ],
    "name:glg_x_preferred":[
        "Boa"
    ],
    "name:heb_x_preferred":[
        "\u05d1\u05d5\u05d0\u05d4"
    ],
    "name:ind_x_preferred":[
        "Boa"
    ],
    "name:lat_x_preferred":[
        "Boa"
    ],
    "name:lit_x_preferred":[
        "Boa"
    ],
    "name:nld_x_preferred":[
        "Boa"
    ],
    "name:pol_x_preferred":[
        "Boa"
    ],
    "name:por_x_preferred":[
        "Boa"
    ],
    "name:ron_x_preferred":[
        "Boa"
    ],
    "name:rus_x_preferred":[
        "\u0411\u043e\u0430"
    ],
    "name:slv_x_preferred":[
        "Boa"
    ],
    "name:spa_x_preferred":[
        "Boa"
    ],
    "name:srp_x_preferred":[
        "\u0411\u043e\u0430"
    ],
    "name:swe_x_preferred":[
        "Boa"
    ],
    "name:tgl_x_preferred":[
        "Boa"
    ],
    "name:ukr_x_preferred":[
        "\u0411\u043e\u0430"
    ],
    "wof:name":"Boa",
    "wof:placetype":"locality"
},
  "geometry": {"coordinates":[8.9979,5.027],"type":"Point"}
}