{
  "type": "Feature",
  "properties": {
    "gn:admin1_code":"9.0",
    "gn:asciiname":"Boa",
    "gn:country_code":"CM",
    "gn:dem":494,
    "gn:feature_class":"P",
    "gn:feature_code":"PPL",
    "gn:name":"Boa",
    "gn:population":0,
    "gn:timezone":"Africa/Douala",
    "iso:country":"CM",
    "wof:name":"Boa",
    "wof:placetype":"locality"
},
  "geometry": {"coordinates":[8.9979,5.027],"type":"Point"}
}