{
  "type": "Feature",
  "properties": {
    "gn:admin1_code":"5.0",
    "gn:asciiname":"Melong II",
    "gn:country_code":"CM",
    "gn:dem":871,
    "gn:feature_class":"P",
    "gn:feature_code":"PPL",
    "gn:name":"Melong II",
    "gn:population":0,
    "gn:timezone":"Africa/Douala",
    "iso:country":"CM",
    "wof:name":"Melong II",
    "wof:placetype":"locality"
},
  "geometry": {"coordinates":[9.9629,5.0571],"type":"Point"}
}