{
  "type": "Feature",
  "properties": {
    "gn:admin1_code":"13.0",
    "gn:asciiname":"Bakona",
    "gn:country_code":"CM",
    "gn:dem":310,
    "gn:feature_class":"P",
    "gn:feature_code":"PPL",
    "gn:name":"Bakona",
    "gn:population":0,
    "gn:timezone":"Africa/Douala",
    "iso:country":"CM",
    "wof:name":"Bakona",
    "wof:placetype":"locality"
},
  "geometry": {"coordinates":[13.59568,8.97794],"type":"Point"}
}