{
  "type": "Feature",
  "properties": {
    "gn:admin1_code":"12.0",
    "gn:asciiname":"Gadamayo",
    "gn:country_code":"CM",
    "gn:dem":420,
    "gn:feature_class":"P",
    "gn:feature_code":"PPL",
    "gn:name":"Gadamayo",
    "gn:population":0,
    "gn:timezone":"Africa/Douala",
    "iso:country":"CM",
    "wof:name":"Gadamayo",
    "wof:placetype":"locality"
},
  "geometry": {"coordinates":[14.23747,10.59224],"type":"Point"}
}