{
  "type": "Feature",
  "properties": {
    "gn:admin1_code":"12.0",
    "gn:asciiname":"Gouedezi",
    "gn:country_code":"CM",
    "gn:dem":300,
    "gn:feature_class":"P",
    "gn:feature_code":"PPL",
    "gn:name":"Gouedezi",
    "gn:population":0,
    "gn:timezone":"Africa/Douala",
    "iso:country":"CM",
    "wof:name":"Gouedezi",
    "wof:placetype":"locality"
},
  "geometry": {"coordinates":[15.03278,11.72138],"type":"Point"}
}