{
  "type": "Feature",
  "properties": {
    "gn:admin1_code":"9.0",
    "gn:asciiname":"Tikoro",
    "gn:country_code":"CM",
    "gn:dem":6,
    "gn:feature_class":"P",
    "gn:feature_code":"PPL",
    "gn:name":"Tikoro",
    "gn:population":0,
    "gn:timezone":"Africa/Douala",
    "iso:country":"CM",
    "wof:name":"Tikoro",
    "wof:placetype":"locality"
},
  "geometry": {"coordinates":[8.7004,4.7027],"type":"Point"}
}