{
  "type": "Feature",
  "properties": {
    "gn:admin1_code":"9.0",
    "gn:asciiname":"Ebinsi",
    "gn:country_code":"CM",
    "gn:dem":71,
    "gn:feature_class":"P",
    "gn:feature_code":"PPL",
    "gn:name":"Ebinsi",
    "gn:population":0,
    "gn:timezone":"Africa/Douala",
    "iso:country":"CM",
    "wof:name":"Ebinsi",
    "wof:placetype":"locality"
},
  "geometry": {"coordinates":[9.21386,5.93938],"type":"Point"}
}