{
  "type": "Feature",
  "properties": {
    "gn:admin1_code":"4.0",
    "gn:asciiname":"Touki",
    "gn:country_code":"CM",
    "gn:dem":650,
    "gn:feature_class":"P",
    "gn:feature_code":"PPL",
    "gn:name":"Touki",
    "gn:population":0,
    "gn:timezone":"Africa/Douala",
    "iso:country":"CM",
    "wof:name":"Touki",
    "wof:placetype":"locality"
},
  "geometry": {"coordinates":[13.95,4.51667],"type":"Point"}
}