{
  "type": "Feature",
  "properties": {
    "gn:admin1_code":"7.0",
    "gn:asciiname":"Denku",
    "gn:country_code":"CM",
    "gn:dem":540,
    "gn:feature_class":"P",
    "gn:feature_code":"PPL",
    "gn:name":"Denku",
    "gn:population":0,
    "gn:timezone":"Africa/Douala",
    "iso:country":"CM",
    "wof:name":"Denku",
    "wof:placetype":"locality"
},
  "geometry": {"coordinates":[9.7279,5.8778],"type":"Point"}
}