{
  "type": "Feature",
  "properties": {
    "gn:admin1_code":"12.0",
    "gn:asciiname":"Magada",
    "gn:country_code":"CM",
    "gn:dem":436,
    "gn:feature_class":"P",
    "gn:feature_code":"PPL",
    "gn:name":"Magada",
    "gn:population":0,
    "gn:timezone":"Africa/Douala",
    "iso:country":"CM",
    "name:ceb_x_preferred":[
        "Magada"
    ],
    "name:swe_x_preferred":[
        "Magada"
    ],
    "wof:name":"Magada",
    "wof:placetype":"locality"
},
  "geometry": {"coordinates":[14.18456,10.10421],"type":"Point"}
}