{
  "type": "Feature",
  "properties": {
    "gn:admin1_code":"12.0",
    "gn:asciiname":"Gadamaya",
    "gn:country_code":"CM",
    "gn:dem":457,
    "gn:feature_class":"P",
    "gn:feature_code":"PPL",
    "gn:name":"Gadamaya",
    "gn:population":0,
    "gn:timezone":"Africa/Douala",
    "iso:country":"CM",
    "wof:name":"Gadamaya",
    "wof:placetype":"locality"
},
  "geometry": {"coordinates":[13.91194,10.93162],"type":"Point"}
}