{
  "type": "Feature",
  "properties": {
    "gn:admin1_code":"5.0",
    "gn:asciiname":"Tounjok",
    "gn:country_code":"CM",
    "gn:dem":29,
    "gn:feature_class":"P",
    "gn:feature_code":"PPL",
    "gn:name":"Tounjok",
    "gn:population":0,
    "gn:timezone":"Africa/Douala",
    "iso:country":"CM",
    "wof:name":"Tounjok",
    "wof:placetype":"locality"
},
  "geometry": {"coordinates":[9.91667,4.21667],"type":"Point"}
}