{
  "type": "Feature",
  "properties": {
    "gn:admin1_code":"13.0",
    "gn:asciiname":"Bola",
    "gn:country_code":"CM",
    "gn:dem":355,
    "gn:feature_class":"P",
    "gn:feature_code":"PPL",
    "gn:name":"Bola",
    "gn:population":0,
    "gn:timezone":"Africa/Douala",
    "iso:country":"CM",
    "name:cat_x_preferred":[
        "Bola"
    ],
    "name:ceb_x_preferred":[
        "Bola"
    ],
    "name:deu_x_preferred":[
        "Bola"
    ],
    "name:eus_x_preferred":[
        "Bola"
    ],
    "name:fra_x_preferred":[
        "Bola"
    ],
    "name:ind_x_preferred":[
        "Bola"
    ],
    "name:ita_x_preferred":[
        "Bola"
    ],
    "name:nld_x_preferred":[
        "Bola"
    ],
    "name:pol_x_preferred":[
        "Bola"
    ],
    "name:por_x_preferred":[
        "Bola"
    ],
    "name:spa_x_preferred":[
        "Bola"
    ],
    "name:sun_x_preferred":[
        "Bola"
    ],
    "name:swe_x_preferred":[
        "Bola"
    ],
    "wof:name":"Bola",
    "wof:placetype":"locality"
},
  "geometry": {"coordinates":[13.69746,9.77582],"type":"Point"}
}