{
  "type": "Feature",
  "properties": {
    "gn:admin1_code":"7.0",
    "gn:asciiname":"Mbato",
    "gn:country_code":"CM",
    "gn:dem":1163,
    "gn:feature_class":"P",
    "gn:feature_code":"PPL",
    "gn:name":"Mbato",
    "gn:population":0,
    "gn:timezone":"Africa/Douala",
    "iso:country":"CM",
    "wof:name":"Mbato",
    "wof:placetype":"locality"
},
  "geometry": {"coordinates":[10.53799,5.88969],"type":"Point"}
}