{
  "type": "Feature",
  "properties": {
    "gn:admin1_code":"7.0",
    "gn:asciiname":"Nen",
    "gn:country_code":"CM",
    "gn:dem":936,
    "gn:feature_class":"P",
    "gn:feature_code":"PPL",
    "gn:name":"Nen",
    "gn:population":0,
    "gn:timezone":"Africa/Douala",
    "iso:country":"CM",
    "name:deu_x_preferred":[
        "Nen"
    ],
    "name:fra_x_preferred":[
        "Nen"
    ],
    "name:nld_x_preferred":[
        "Nen"
    ],
    "wof:name":"Nen",
    "wof:placetype":"locality"
},
  "geometry": {"coordinates":[9.8332,5.827],"type":"Point"}
}