{
  "type": "Feature",
  "properties": {
    "gn:admin1_code":"7.0",
    "gn:asciiname":"Nen",
    "gn:country_code":"CM",
    "gn:dem":936,
    "gn:feature_class":"P",
    "gn:feature_code":"PPL",
    "gn:name":"Nen",
    "gn:population":0,
    "gn:timezone":"Africa/Douala",
    "iso:country":"CM",
    "name:ara_x_preferred":[
        "\u0646\u064a\u0646"
    ],
    "name:ben_x_preferred":[
        "\u09a8\u09c7\u09a8"
    ],
    "name:deu_x_preferred":[
        "Nen"
    ],
    "name:ell_x_preferred":[
        "\u039d\u03b5\u03bd"
    ],
    "name:fas_x_preferred":[
        "\u0646\u0650\u0646"
    ],
    "name:fra_x_preferred":[
        "Nen"
    ],
    "name:heb_x_preferred":[
        "\u05e0\u05b6\u05df"
    ],
    "name:hin_x_preferred":[
        "\u0928\u0947\u0928\u094b"
    ],
    "name:hun_x_preferred":[
        "Nen"
    ],
    "name:ind_x_preferred":[
        "Nen"
    ],
    "name:nld_x_preferred":[
        "Nen"
    ],
    "name:por_x_preferred":[
        "Nen"
    ],
    "name:urd_x_preferred":[
        "\u0646\u06cc\u0646"
    ],
    "wof:name":"Nen",
    "wof:placetype":"locality"
},
  "geometry": {"coordinates":[9.8332,5.827],"type":"Point"}
}