{
  "type": "Feature",
  "properties": {
    "gn:admin1_code":"4.0",
    "gn:asciiname":"Pepo",
    "gn:country_code":"CM",
    "gn:dem":685,
    "gn:feature_class":"P",
    "gn:feature_code":"PPL",
    "gn:name":"P\u00e9po",
    "gn:population":0,
    "gn:timezone":"Africa/Douala",
    "iso:country":"CM",
    "wof:name":"Pepo",
    "wof:placetype":"locality"
},
  "geometry": {"coordinates":[13.91667,3.93333],"type":"Point"}
}