{
  "type": "Feature",
  "properties": {
    "gn:admin1_code":"13.0",
    "gn:asciiname":"Home Garal",
    "gn:country_code":"CM",
    "gn:dem":385,
    "gn:feature_class":"P",
    "gn:feature_code":"PPL",
    "gn:name":"Hom\u00e9 Garal",
    "gn:population":0,
    "gn:timezone":"Africa/Douala",
    "iso:country":"CM",
    "wof:name":"Home Garal",
    "wof:placetype":"locality"
},
  "geometry": {"coordinates":[14.1179,8.3455],"type":"Point"}
}