{
  "type": "Feature",
  "properties": {
    "gn:admin1_code":"9.0",
    "gn:asciiname":"Bakumba",
    "gn:country_code":"CM",
    "gn:dem":157,
    "gn:feature_class":"P",
    "gn:feature_code":"PPL",
    "gn:name":"Bakumba",
    "gn:population":0,
    "gn:timezone":"Africa/Douala",
    "iso:country":"CM",
    "wof:name":"Bakumba",
    "wof:placetype":"locality"
},
  "geometry": {"coordinates":[9.5773,5.8313],"type":"Point"}
}