{
  "type": "Feature",
  "properties": {
    "gn:admin1_code":"12.0",
    "gn:asciiname":"Ngoro",
    "gn:country_code":"CM",
    "gn:dem":352,
    "gn:feature_class":"P",
    "gn:feature_code":"PPL",
    "gn:name":"Ngoro",
    "gn:population":0,
    "gn:timezone":"Africa/Douala",
    "iso:country":"CM",
    "name:deu_x_preferred":[
        "Ngoro"
    ],
    "name:fra_x_preferred":[
        "Ngoro"
    ],
    "name:ita_x_preferred":[
        "Ngoro"
    ],
    "name:msa_x_preferred":[
        "Ngoro"
    ],
    "name:spa_x_preferred":[
        "Ngoro"
    ],
    "wof:name":"Ngoro",
    "wof:placetype":"locality"
},
  "geometry": {"coordinates":[14.83439,10.06695],"type":"Point"}
}