{
  "type": "Feature",
  "properties": {
    "gn:admin1_code":"13.0",
    "gn:asciiname":"Yorni",
    "gn:country_code":"CM",
    "gn:dem":282,
    "gn:feature_class":"P",
    "gn:feature_code":"PPL",
    "gn:name":"Yorni",
    "gn:population":0,
    "gn:timezone":"Africa/Douala",
    "iso:country":"CM",
    "wof:name":"Yorni",
    "wof:placetype":"locality"
},
  "geometry": {"coordinates":[13.05918,8.72531],"type":"Point"}
}