{
  "type": "Feature",
  "properties": {
    "gn:admin1_code":"9.0",
    "gn:asciiname":"Ekumbe Ekundunene",
    "gn:country_code":"CM",
    "gn:dem":68,
    "gn:feature_class":"P",
    "gn:feature_code":"PPL",
    "gn:name":"Ekumbe Ekundunene",
    "gn:population":0,
    "gn:timezone":"Africa/Douala",
    "iso:country":"CM",
    "name:und_x_variant":[
        "Ekume Ekundunene",
        "Ekumbe Ekundunene"
    ],
    "wof:name":"Ekumbe Ekundunene",
    "wof:placetype":"locality"
},
  "geometry": {"coordinates":[9.1557,4.4835],"type":"Point"}
}