{
  "type": "Feature",
  "properties": {
    "gn:admin1_code":"12.0",
    "gn:asciiname":"Goualda",
    "gn:country_code":"CM",
    "gn:dem":788,
    "gn:feature_class":"P",
    "gn:feature_code":"PPL",
    "gn:name":"Goualda",
    "gn:population":0,
    "gn:timezone":"Africa/Douala",
    "iso:country":"CM",
    "wof:name":"Goualda",
    "wof:placetype":"locality"
},
  "geometry": {"coordinates":[14.0082,10.9418],"type":"Point"}
}