{
  "type": "Feature",
  "properties": {
    "gn:admin1_code":"13.0",
    "gn:asciiname":"Bihi",
    "gn:country_code":"CM",
    "gn:dem":649,
    "gn:feature_class":"P",
    "gn:feature_code":"PPL",
    "gn:name":"Bihi",
    "gn:population":0,
    "gn:timezone":"Africa/Douala",
    "iso:country":"CM",
    "name:ceb_x_preferred":[
        "Bihi"
    ],
    "name:deu_x_preferred":[
        "Bihi"
    ],
    "name:fra_x_preferred":[
        "Bihi"
    ],
    "name:mai_x_preferred":[
        "\u092c\u093f\u0939\u093f"
    ],
    "name:msa_x_preferred":[
        "Bihi"
    ],
    "name:nep_x_preferred":[
        "\u092c\u093f\u0939\u0940"
    ],
    "name:new_x_preferred":[
        "\u092c\u093f\u0939\u0940"
    ],
    "name:pol_x_preferred":[
        "Bihi"
    ],
    "wof:name":"Bihi",
    "wof:placetype":"locality"
},
  "geometry": {"coordinates":[13.3381,10.00106],"type":"Point"}
}