{
  "type": "Feature",
  "properties": {
    "gn:admin1_code":"8.0",
    "gn:asciiname":"Tchuefi",
    "gn:country_code":"CM",
    "gn:dem":1454,
    "gn:feature_class":"P",
    "gn:feature_code":"PPL",
    "gn:name":"Tchu\u00e9fi",
    "gn:population":0,
    "gn:timezone":"Africa/Douala",
    "iso:country":"CM",
    "wof:name":"Tchuefi",
    "wof:placetype":"locality"
},
  "geometry": {"coordinates":[10.20476,5.48704],"type":"Point"}
}