{
  "type": "Feature",
  "properties": {
    "gn:admin1_code":"8.0",
    "gn:asciiname":"Fossong Eleleng",
    "gn:country_code":"CM",
    "gn:dem":1462,
    "gn:feature_class":"P",
    "gn:feature_code":"PPL",
    "gn:name":"Fossong Eleleng",
    "gn:population":0,
    "gn:timezone":"Africa/Douala",
    "iso:country":"CM",
    "name:und_x_variant":[
        "Fossong Ellelem",
        "Fossong Eteleng",
        "Fossong Eleleng"
    ],
    "wof:name":"Fossong Eleleng",
    "wof:placetype":"locality"
},
  "geometry": {"coordinates":[9.97214,5.56943],"type":"Point"}
}