{
  "type": "Feature",
  "properties": {
    "gn:admin1_code":"8.0",
    "gn:asciiname":"Tchie",
    "gn:country_code":"CM",
    "gn:dem":1582,
    "gn:feature_class":"P",
    "gn:feature_code":"PPL",
    "gn:name":"Tchie",
    "gn:population":0,
    "gn:timezone":"Africa/Douala",
    "iso:country":"CM",
    "name:fra_x_preferred":[
        "Tchie"
    ],
    "wof:name":"Tchie",
    "wof:placetype":"locality"
},
  "geometry": {"coordinates":[10.36214,5.3425],"type":"Point"}
}