{
  "type": "Feature",
  "properties": {
    "gn:admin1_code":"12.0",
    "gn:asciiname":"Yoldeo",
    "gn:country_code":"CM",
    "gn:dem":354,
    "gn:feature_class":"P",
    "gn:feature_code":"PPL",
    "gn:name":"Yold\u00e9o",
    "gn:population":0,
    "gn:timezone":"Africa/Douala",
    "iso:country":"CM",
    "name:und_x_variant":[
        "Jold\u0113o",
        "Djeld\u00e9",
        "Yold\u00e9o"
    ],
    "wof:name":"Yoldeo",
    "wof:placetype":"locality"
},
  "geometry": {"coordinates":[14.55499,10.58357],"type":"Point"}
}