{
  "type": "Feature",
  "properties": {
    "gn:admin1_code":"12.0",
    "gn:asciiname":"Garle",
    "gn:country_code":"CM",
    "gn:dem":307,
    "gn:feature_class":"P",
    "gn:feature_code":"PPL",
    "gn:name":"Garl\u00e9",
    "gn:population":0,
    "gn:timezone":"Africa/Douala",
    "iso:country":"CM",
    "wof:name":"Garle",
    "wof:placetype":"locality"
},
  "geometry": {"coordinates":[14.97054,11.33113],"type":"Point"}
}