{
  "type": "Feature",
  "properties": {
    "gn:admin1_code":"9.0",
    "gn:asciiname":"Bakut",
    "gn:country_code":"CM",
    "gn:dem":145,
    "gn:feature_class":"P",
    "gn:feature_code":"PPL",
    "gn:name":"Bakut",
    "gn:population":0,
    "gn:timezone":"Africa/Douala",
    "iso:country":"CM",
    "wof:name":"Bakut",
    "wof:placetype":"locality"
},
  "geometry": {"coordinates":[9.12034,5.45785],"type":"Point"}
}