{
  "type": "Feature",
  "properties": {
    "gn:admin1_code":"7.0",
    "gn:asciiname":"Mbashie",
    "gn:country_code":"CM",
    "gn:dem":1173,
    "gn:feature_class":"P",
    "gn:feature_code":"PPL",
    "gn:name":"Mbashie",
    "gn:population":0,
    "gn:timezone":"Africa/Douala",
    "iso:country":"CM",
    "name:fra_x_preferred":[
        "Mbashie"
    ],
    "wof:name":"Mbashie",
    "wof:placetype":"locality"
},
  "geometry": {"coordinates":[10.51672,5.85209],"type":"Point"}
}