{
  "type": "Feature",
  "properties": {
    "gn:admin1_code":"9.0",
    "gn:asciiname":"Inodo",
    "gn:country_code":"CM",
    "gn:dem":9,
    "gn:feature_class":"P",
    "gn:feature_code":"PPL",
    "gn:name":"Inodo",
    "gn:population":0,
    "gn:timezone":"Africa/Douala",
    "iso:country":"CM",
    "wof:name":"Inodo",
    "wof:placetype":"locality"
},
  "geometry": {"coordinates":[8.8867,4.4285],"type":"Point"}
}