{
  "type": "Feature",
  "properties": {
    "gn:admin1_code":"5.0",
    "gn:asciiname":"Mbondjo II",
    "gn:country_code":"CM",
    "gn:dem":21,
    "gn:feature_class":"P",
    "gn:feature_code":"PPL",
    "gn:name":"Mbondjo II",
    "gn:population":0,
    "gn:timezone":"Africa/Douala",
    "iso:country":"CM",
    "wof:name":"Mbondjo II",
    "wof:placetype":"locality"
},
  "geometry": {"coordinates":[9.5263,4.2169],"type":"Point"}
}