{
  "type": "Feature",
  "properties": {
    "gn:admin1_code":"12.0",
    "gn:asciiname":"Mafaoli",
    "gn:country_code":"CM",
    "gn:dem":797,
    "gn:feature_class":"P",
    "gn:feature_code":"PPL",
    "gn:name":"Mafaoli",
    "gn:population":0,
    "gn:timezone":"Africa/Douala",
    "iso:country":"CM",
    "wof:name":"Mafaoli",
    "wof:placetype":"locality"
},
  "geometry": {"coordinates":[13.82106,10.72839],"type":"Point"}
}