{
  "type": "Feature",
  "properties": {
    "gn:admin1_code":"12.0",
    "gn:asciiname":"Gazawa",
    "gn:country_code":"CM",
    "gn:dem":469,
    "gn:feature_class":"P",
    "gn:feature_code":"PPL",
    "gn:name":"Gazawa",
    "gn:population":0,
    "gn:timezone":"Africa/Douala",
    "iso:country":"CM",
    "name:und_x_variant":[
        "Gasaua",
        "Gassoua",
        "Gassaoua",
        "Gazaoua",
        "Gazawa"
    ],
    "wof:name":"Gazawa",
    "wof:placetype":"locality"
},
  "geometry": {"coordinates":[14.14043,10.53084],"type":"Point"}
}