{
  "type": "Feature",
  "properties": {
    "gn:admin1_code":"4.0",
    "gn:asciiname":"Amoure",
    "gn:country_code":"CM",
    "gn:dem":594,
    "gn:feature_class":"P",
    "gn:feature_code":"PPL",
    "gn:name":"Amour\u00e9",
    "gn:population":0,
    "gn:timezone":"Africa/Douala",
    "iso:country":"CM",
    "wof:name":"Amoure",
    "wof:placetype":"locality"
},
  "geometry": {"coordinates":[14.41667,4.23333],"type":"Point"}
}