{
  "type": "Feature",
  "properties": {
    "gn:admin1_code":"8.0",
    "gn:asciiname":"Manganja",
    "gn:country_code":"CM",
    "gn:dem":1222,
    "gn:feature_class":"P",
    "gn:feature_code":"PPL",
    "gn:name":"Manganja",
    "gn:population":0,
    "gn:timezone":"Africa/Douala",
    "iso:country":"CM",
    "wof:name":"Manganja",
    "wof:placetype":"locality"
},
  "geometry": {"coordinates":[10.71118,5.64951],"type":"Point"}
}