{
  "type": "Feature",
  "properties": {
    "gn:admin1_code":"12.0",
    "gn:asciiname":"Mogowa Arde",
    "gn:country_code":"CM",
    "gn:dem":319,
    "gn:feature_class":"P",
    "gn:feature_code":"PPL",
    "gn:name":"Mogowa Ard\u00e9",
    "gn:population":0,
    "gn:timezone":"Africa/Douala",
    "iso:country":"CM",
    "name:und_x_variant":[
        "Ard\u00e9",
        "Mogowa Ard\u00e9"
    ],
    "wof:name":"Mogowa Arde",
    "wof:placetype":"locality"
},
  "geometry": {"coordinates":[14.3811,11.12263],"type":"Point"}
}