{
  "type": "Feature",
  "properties": {
    "gn:admin1_code":"11.0",
    "gn:asciiname":"Mebou",
    "gn:country_code":"CM",
    "gn:dem":701,
    "gn:feature_class":"P",
    "gn:feature_code":"PPL",
    "gn:name":"M\u00e9bou",
    "gn:population":0,
    "gn:timezone":"Africa/Douala",
    "iso:country":"CM",
    "wof:name":"Mebou",
    "wof:placetype":"locality"
},
  "geometry": {"coordinates":[11.73333,3.85],"type":"Point"}
}