{
  "type": "Feature",
  "properties": {
    "gn:admin1_code":"4.0",
    "gn:asciiname":"Nginda",
    "gn:country_code":"CM",
    "gn:dem":665,
    "gn:feature_class":"P",
    "gn:feature_code":"PPL",
    "gn:name":"Nginda",
    "gn:population":0,
    "gn:timezone":"Africa/Douala",
    "iso:country":"CM",
    "wof:name":"Nginda",
    "wof:placetype":"locality"
},
  "geometry": {"coordinates":[13.23333,4.58333],"type":"Point"}
}