{
  "type": "Feature",
  "properties": {
    "gn:admin1_code":"8.0",
    "gn:asciiname":"Njitekwet",
    "gn:country_code":"CM",
    "gn:dem":1178,
    "gn:feature_class":"P",
    "gn:feature_code":"PPL",
    "gn:name":"Njitekwet",
    "gn:population":0,
    "gn:timezone":"Africa/Douala",
    "iso:country":"CM",
    "wof:name":"Njitekwet",
    "wof:placetype":"locality"
},
  "geometry": {"coordinates":[10.7932,5.77919],"type":"Point"}
}