{
  "type": "Feature",
  "properties": {
    "gn:admin1_code":"12.0",
    "gn:asciiname":"Tchebele",
    "gn:country_code":"CM",
    "gn:dem":980,
    "gn:feature_class":"P",
    "gn:feature_code":"PPL",
    "gn:name":"Tch\u00e9b\u00e9l\u00e9",
    "gn:population":0,
    "gn:timezone":"Africa/Douala",
    "iso:country":"CM",
    "wof:name":"Tchebele",
    "wof:placetype":"locality"
},
  "geometry": {"coordinates":[13.70152,10.82459],"type":"Point"}
}