{
  "type": "Feature",
  "properties": {
    "gn:admin1_code":"12.0",
    "gn:asciiname":"Ouro Said",
    "gn:country_code":"CM",
    "gn:dem":379,
    "gn:feature_class":"P",
    "gn:feature_code":"PPL",
    "gn:name":"Ouro Sa\u00efd",
    "gn:population":0,
    "gn:timezone":"Africa/Douala",
    "iso:country":"CM",
    "wof:name":"Ouro Said",
    "wof:placetype":"locality"
},
  "geometry": {"coordinates":[14.41118,10.61334],"type":"Point"}
}