{
  "type": "Feature",
  "properties": {
    "gn:admin1_code":"10.0",
    "gn:asciiname":"Gop",
    "gn:country_code":"CM",
    "gn:dem":698,
    "gn:feature_class":"P",
    "gn:feature_code":"PPL",
    "gn:name":"Gop",
    "gn:population":0,
    "gn:timezone":"Africa/Douala",
    "iso:country":"CM",
    "wof:name":"Gop",
    "wof:placetype":"locality"
},
  "geometry": {"coordinates":[13.55,7.68333],"type":"Point"}
}