{
  "type": "Feature",
  "properties": {
    "gn:admin1_code":"7.0",
    "gn:asciiname":"Bagam",
    "gn:country_code":"CM",
    "gn:dem":1184,
    "gn:feature_class":"P",
    "gn:feature_code":"PPL",
    "gn:name":"Bagam",
    "gn:population":0,
    "gn:timezone":"Africa/Douala",
    "iso:country":"CM",
    "wof:name":"Bagam",
    "wof:placetype":"locality"
},
  "geometry": {"coordinates":[10.42021,5.81155],"type":"Point"}
}