{
  "type": "Feature",
  "properties": {
    "gn:admin1_code":"12.0",
    "gn:asciiname":"Kobro",
    "gn:country_code":"CM",
    "gn:dem":291,
    "gn:feature_class":"P",
    "gn:feature_code":"PPL",
    "gn:name":"Kobro",
    "gn:population":0,
    "gn:timezone":"Africa/Douala",
    "iso:country":"CM",
    "wof:name":"Kobro",
    "wof:placetype":"locality"
},
  "geometry": {"coordinates":[14.70093,12.68097],"type":"Point"}
}