{
  "type": "Feature",
  "properties": {
    "gn:admin1_code":"12.0",
    "gn:asciiname":"Amchilga",
    "gn:country_code":"CM",
    "gn:dem":292,
    "gn:feature_class":"P",
    "gn:feature_code":"PPL",
    "gn:name":"Amchilga",
    "gn:population":0,
    "gn:timezone":"Africa/Douala",
    "iso:country":"CM",
    "wof:name":"Amchilga",
    "wof:placetype":"locality"
},
  "geometry": {"coordinates":[14.38167,12.52634],"type":"Point"}
}