{
  "type": "Feature",
  "properties": {
    "gn:admin1_code":"12.0",
    "gn:asciiname":"Ouro Loppe",
    "gn:country_code":"CM",
    "gn:dem":464,
    "gn:feature_class":"P",
    "gn:feature_code":"PPL",
    "gn:name":"Ouro Loppe",
    "gn:population":0,
    "gn:timezone":"Africa/Douala",
    "iso:country":"CM",
    "wof:name":"Ouro Loppe",
    "wof:placetype":"locality"
},
  "geometry": {"coordinates":[14.23333,10.35],"type":"Point"}
}