{
  "type": "Feature",
  "properties": {
    "gn:admin1_code":"8.0",
    "gn:asciiname":"Mena'",
    "gn:country_code":"CM",
    "gn:dem":1467,
    "gn:feature_class":"P",
    "gn:feature_code":"PPL",
    "gn:name":"Mena\u2019",
    "gn:population":0,
    "gn:timezone":"Africa/Douala",
    "iso:country":"CM",
    "wof:name":"Mena'",
    "wof:placetype":"locality"
},
  "geometry": {"coordinates":[10.14589,5.37552],"type":"Point"}
}