{
  "type": "Feature",
  "properties": {
    "gn:admin1_code":"8.0",
    "gn:asciiname":"Fondjomoko",
    "gn:country_code":"CM",
    "gn:dem":877,
    "gn:feature_class":"P",
    "gn:feature_code":"PPL",
    "gn:name":"Fondjomoko",
    "gn:population":0,
    "gn:timezone":"Africa/Douala",
    "iso:country":"CM",
    "wof:name":"Fondjomoko",
    "wof:placetype":"locality"
},
  "geometry": {"coordinates":[10.0897,5.16685],"type":"Point"}
}