{
  "type": "Feature",
  "properties": {
    "gn:admin1_code":"8.0",
    "gn:asciiname":"Nja'",
    "gn:country_code":"CM",
    "gn:dem":1409,
    "gn:feature_class":"P",
    "gn:feature_code":"PPL",
    "gn:name":"Nja\u2019",
    "gn:population":0,
    "gn:timezone":"Africa/Douala",
    "iso:country":"CM",
    "name:fra_x_preferred":[
        "Bandja"
    ],
    "name:msa_x_preferred":[
        "Bandja"
    ],
    "name:und_x_variant":[
        "Nja\u2019"
    ],
    "wof:name":"Nja'",
    "wof:placetype":"locality"
},
  "geometry": {"coordinates":[10.26218,5.45548],"type":"Point"}
}