{
  "type": "Feature",
  "properties": {
    "gn:admin1_code":"13.0",
    "gn:asciiname":"Gounou",
    "gn:country_code":"CM",
    "gn:dem":1116,
    "gn:feature_class":"P",
    "gn:feature_code":"PPL",
    "gn:name":"Gounou",
    "gn:population":0,
    "gn:timezone":"Africa/Douala",
    "iso:country":"CM",
    "wof:name":"Gounou",
    "wof:placetype":"locality"
},
  "geometry": {"coordinates":[14.85,7.18333],"type":"Point"}
}