{
  "type": "Feature",
  "properties": {
    "gn:admin1_code":"8.0",
    "gn:asciiname":"Tchuedu",
    "gn:country_code":"CM",
    "gn:dem":1507,
    "gn:feature_class":"P",
    "gn:feature_code":"PPL",
    "gn:name":"Tchu\u00e9du",
    "gn:population":0,
    "gn:timezone":"Africa/Douala",
    "iso:country":"CM",
    "wof:name":"Tchuedu",
    "wof:placetype":"locality"
},
  "geometry": {"coordinates":[10.19052,5.43315],"type":"Point"}
}