{
  "type": "Feature",
  "properties": {
    "gn:admin1_code":"8.0",
    "gn:asciiname":"Koum",
    "gn:country_code":"CM",
    "gn:dem":1532,
    "gn:feature_class":"P",
    "gn:feature_code":"PPL",
    "gn:name":"Koum",
    "gn:population":0,
    "gn:timezone":"Africa/Douala",
    "iso:country":"CM",
    "wof:name":"Koum",
    "wof:placetype":"locality"
},
  "geometry": {"coordinates":[10.22501,5.60023],"type":"Point"}
}