{
  "type": "Feature",
  "properties": {
    "gn:admin1_code":"13.0",
    "gn:asciiname":"Ndiambadi",
    "gn:country_code":"CM",
    "gn:dem":253,
    "gn:feature_class":"P",
    "gn:feature_code":"PPL",
    "gn:name":"Ndiambadi",
    "gn:population":0,
    "gn:timezone":"Africa/Douala",
    "iso:country":"CM",
    "name:und_x_variant":[
        "Djambati",
        "Diambati",
        "Ndiam Badi",
        "Ndiambadi"
    ],
    "wof:name":"Ndiambadi",
    "wof:placetype":"locality"
},
  "geometry": {"coordinates":[13.82379,9.12023],"type":"Point"}
}