{
  "type": "Feature",
  "properties": {
    "gn:admin1_code":"12.0",
    "gn:asciiname":"Wayom",
    "gn:country_code":"CM",
    "gn:dem":694,
    "gn:feature_class":"P",
    "gn:feature_code":"PPL",
    "gn:name":"Wayom",
    "gn:population":0,
    "gn:timezone":"Africa/Douala",
    "iso:country":"CM",
    "wof:name":"Wayom",
    "wof:placetype":"locality"
},
  "geometry": {"coordinates":[13.95252,10.73696],"type":"Point"}
}