{
  "type": "Feature",
  "properties": {
    "gn:admin1_code":"13.0",
    "gn:asciiname":"Lak",
    "gn:country_code":"CM",
    "gn:dem":761,
    "gn:feature_class":"P",
    "gn:feature_code":"PPL",
    "gn:name":"Lak",
    "gn:population":0,
    "gn:timezone":"Africa/Douala",
    "iso:country":"CM",
    "wof:name":"Lak",
    "wof:placetype":"locality"
},
  "geometry": {"coordinates":[13.71518,9.97767],"type":"Point"}
}