{
  "type": "Feature",
  "properties": {
    "gn:admin1_code":"4.0",
    "gn:asciiname":"Kongo",
    "gn:country_code":"CM",
    "gn:dem":521,
    "gn:feature_class":"P",
    "gn:feature_code":"PPL",
    "gn:name":"Kongo",
    "gn:population":0,
    "gn:timezone":"Africa/Douala",
    "iso:country":"CM",
    "name:afr_x_preferred":[
        "Kongo"
    ],
    "name:aze_x_preferred":[
        "Konqo"
    ],
    "name:bak_x_preferred":[
        "\u041a\u043e\u043d\u0433\u043e"
    ],
    "name:bel_x_preferred":[
        "\u041a\u043e\u043d\u0433\u0430"
    ],
    "name:bos_x_preferred":[
        "Kongo"
    ],
    "name:bre_x_preferred":[
        "Kongo"
    ],
    "name:bul_x_preferred":[
        "\u041a\u043e\u043d\u0433\u043e"
    ],
    "name:ceb_x_preferred":[
        "Kongo"
    ],
    "name:ces_x_preferred":[
        "Kongo"
    ],
    "name:crh_x_preferred":[
        "Kongo"
    ],
    "name:deu_x_preferred":[
        "Kongo"
    ],
    "name:diq_x_preferred":[
        "Kongo"
    ],
    "name:dsb_x_preferred":[
        "Kongo"
    ],
    "name:epo_x_preferred":[
        "Kongo"
    ],
    "name:est_x_preferred":[
        "Kongo"
    ],
    "name:eus_x_preferred":[
        "Kongo"
    ],
    "name:fin_x_preferred":[
        "Kongo"
    ],
    "name:fra_x_preferred":[
        "Kongo"
    ],
    "name:frr_x_preferred":[
        "Kongo"
    ],
    "name:fry_x_preferred":[
        "Kongo"
    ],
    "name:hat_x_preferred":[
        "Kongo"
    ],
    "name:hrv_x_preferred":[
        "Kongo"
    ],
    "name:hsb_x_preferred":[
        "Kongo"
    ],
    "name:hun_x_preferred":[
        "Kong\u00f3"
    ],
    "name:ido_x_preferred":[
        "Kongo"
    ],
    "name:ind_x_preferred":[
        "Kongo"
    ],
    "name:isl_x_preferred":[
        "Kong\u00f3"
    ],
    "name:ita_x_preferred":[
        "Kongo"
    ],
    "name:kaz_x_preferred":[
        "\u041a\u043e\u043d\u0433\u043e"
    ],
    "name:kon_x_preferred":[
        "Kongo"
    ],
    "name:kur_x_preferred":[
        "Kongo"
    ],
    "name:lav_x_preferred":[
        "Kongo"
    ],
    "name:lim_x_preferred":[
        "Kongo"
    ],
    "name:lin_x_preferred":[
        "Kongo"
    ],
    "name:ltz_x_preferred":[
        "Kongo"
    ],
    "name:mkd_x_preferred":[
        "\u041a\u043e\u043d\u0433\u043e"
    ],
    "name:mon_x_preferred":[
        "\u041a\u043e\u043d\u0433\u043e"
    ],
    "name:nds_x_preferred":[
        "Kongo"
    ],
    "name:nno_x_preferred":[
        "Kongo"
    ],
    "name:nor_x_preferred":[
        "Kongo"
    ],
    "name:oss_x_preferred":[
        "\u041a\u043e\u043d\u0433\u043e"
    ],
    "name:pol_x_preferred":[
        "Kongo"
    ],
    "name:rus_x_preferred":[
        "\u041a\u043e\u043d\u0433\u043e"
    ],
    "name:sah_x_preferred":[
        "\u041a\u043e\u043d\u0433\u043e"
    ],
    "name:slk_x_preferred":[
        "Kongo"
    ],
    "name:slv_x_preferred":[
        "Kongo"
    ],
    "name:srp_x_preferred":[
        "\u041a\u043e\u043d\u0433\u043e"
    ],
    "name:swa_x_preferred":[
        "Kongo"
    ],
    "name:swe_x_preferred":[
        "Kongo"
    ],
    "name:tur_x_preferred":[
        "Kongo"
    ],
    "name:ukr_x_preferred":[
        "\u041a\u043e\u043d\u0433\u043e"
    ],
    "name:und_x_variant":[
        "Ndi\u2019s",
        "Kungo",
        "Koungo",
        "Kongo"
    ],
    "name:uzb_x_preferred":[
        "Kongo"
    ],
    "name:vep_x_preferred":[
        "Kongo"
    ],
    "name:yor_x_preferred":[
        "Kongo"
    ],
    "wof:name":"Kongo",
    "wof:placetype":"locality"
},
  "geometry": {"coordinates":[15.05,3.15],"type":"Point"}
}