{
  "type": "Feature",
  "properties": {
    "gn:admin1_code":"12.0",
    "gn:asciiname":"Mahel",
    "gn:country_code":"CM",
    "gn:dem":356,
    "gn:feature_class":"P",
    "gn:feature_code":"PPL",
    "gn:name":"Mahel",
    "gn:population":0,
    "gn:timezone":"Africa/Douala",
    "iso:country":"CM",
    "wof:name":"Mahel",
    "wof:placetype":"locality"
},
  "geometry": {"coordinates":[14.46327,10.7324],"type":"Point"}
}