{
  "type": "Feature",
  "properties": {
    "gn:admin1_code":"12.0",
    "gn:asciiname":"Vredeke",
    "gn:country_code":"CM",
    "gn:dem":456,
    "gn:feature_class":"P",
    "gn:feature_code":"PPL",
    "gn:name":"Vr\u00e9d\u00e9k\u00e9",
    "gn:population":0,
    "gn:timezone":"Africa/Douala",
    "iso:country":"CM",
    "wof:name":"Vredeke",
    "wof:placetype":"locality"
},
  "geometry": {"coordinates":[13.83781,11.07585],"type":"Point"}
}