{
  "type": "Feature",
  "properties": {
    "gn:admin1_code":"13.0",
    "gn:asciiname":"Djibao",
    "gn:country_code":"CM",
    "gn:dem":381,
    "gn:feature_class":"P",
    "gn:feature_code":"PPL",
    "gn:name":"Djibao",
    "gn:population":0,
    "gn:timezone":"Africa/Douala",
    "iso:country":"CM",
    "name:und_x_variant":[
        "Jebo",
        "Djebo",
        "Djabao",
        "Dj\u00e9boa",
        "Djibao"
    ],
    "wof:name":"Djibao",
    "wof:placetype":"locality"
},
  "geometry": {"coordinates":[14.80937,8.68309],"type":"Point"}
}