{
  "type": "Feature",
  "properties": {
    "gn:admin1_code":"8.0",
    "gn:asciiname":"King-Place",
    "gn:country_code":"CM",
    "gn:dem":1247,
    "gn:feature_class":"P",
    "gn:feature_code":"PPL",
    "gn:name":"King-Place",
    "gn:population":0,
    "gn:timezone":"Africa/Douala",
    "iso:country":"CM",
    "wof:name":"King-Place",
    "wof:placetype":"locality"
},
  "geometry": {"coordinates":[10.30297,5.69434],"type":"Point"}
}