{
  "type": "Feature",
  "properties": {
    "gn:admin1_code":"14.0",
    "gn:asciiname":"Mfouladja",
    "gn:country_code":"CM",
    "gn:dem":682,
    "gn:feature_class":"P",
    "gn:feature_code":"PPL",
    "gn:name":"Mfouladja",
    "gn:population":0,
    "gn:timezone":"Africa/Douala",
    "iso:country":"CM",
    "wof:name":"Mfouladja",
    "wof:placetype":"locality"
},
  "geometry": {"coordinates":[12.03333,3.06667],"type":"Point"}
}