{
  "type": "Feature",
  "properties": {
    "gn:admin1_code":"8.0",
    "gn:asciiname":"Manswen Fowyom",
    "gn:country_code":"CM",
    "gn:dem":754,
    "gn:feature_class":"P",
    "gn:feature_code":"PPL",
    "gn:name":"Manswen Fowyom",
    "gn:population":0,
    "gn:timezone":"Africa/Douala",
    "iso:country":"CM",
    "name:und_x_variant":[
        "Mansouen Foyouom"
    ],
    "wof:name":"Manswen Fowyom",
    "wof:placetype":"locality"
},
  "geometry": {"coordinates":[10.92963,5.46403],"type":"Point"}
}