{
  "type": "Feature",
  "properties": {
    "gn:admin1_code":"12.0",
    "gn:asciiname":"Mokol",
    "gn:country_code":"CM",
    "gn:dem":853,
    "gn:feature_class":"P",
    "gn:feature_code":"PPL",
    "gn:name":"Mokol",
    "gn:population":0,
    "gn:timezone":"Africa/Douala",
    "iso:country":"CM",
    "wof:name":"Mokol",
    "wof:placetype":"locality"
},
  "geometry": {"coordinates":[13.70697,10.37083],"type":"Point"}
}