{
  "type": "Feature",
  "properties": {
    "gn:admin1_code":"8.0",
    "gn:asciiname":"Tche",
    "gn:country_code":"CM",
    "gn:dem":721,
    "gn:feature_class":"P",
    "gn:feature_code":"PPL",
    "gn:name":"Tche",
    "gn:population":0,
    "gn:timezone":"Africa/Douala",
    "iso:country":"CM",
    "wof:name":"Tche",
    "wof:placetype":"locality"
},
  "geometry": {"coordinates":[11.26667,6.03333],"type":"Point"}
}