{
  "type": "Feature",
  "properties": {
    "gn:admin1_code":"8.0",
    "gn:asciiname":"Mbeng",
    "gn:country_code":"CM",
    "gn:dem":1516,
    "gn:feature_class":"P",
    "gn:feature_code":"PPL",
    "gn:name":"Mbeng",
    "gn:population":0,
    "gn:timezone":"Africa/Douala",
    "iso:country":"CM",
    "name:und_x_variant":[
        "Mbeng II"
    ],
    "wof:name":"Mbeng",
    "wof:placetype":"locality"
},
  "geometry": {"coordinates":[10.09932,5.4869],"type":"Point"}
}