{
  "type": "Feature",
  "properties": {
    "gn:admin1_code":"14.0",
    "gn:asciiname":"Ngonde",
    "gn:country_code":"CM",
    "gn:dem":613,
    "gn:feature_class":"P",
    "gn:feature_code":"PPL",
    "gn:name":"Ngond\u00e9",
    "gn:population":0,
    "gn:timezone":"Africa/Douala",
    "iso:country":"CM",
    "wof:name":"Ngonde",
    "wof:placetype":"locality"
},
  "geometry": {"coordinates":[11.41667,2.73333],"type":"Point"}
}