{
  "type": "Feature",
  "properties": {
    "gn:admin1_code":"12.0",
    "gn:asciiname":"Mouna",
    "gn:country_code":"CM",
    "gn:dem":774,
    "gn:feature_class":"P",
    "gn:feature_code":"PPL",
    "gn:name":"Mouna",
    "gn:population":0,
    "gn:timezone":"Africa/Douala",
    "iso:country":"CM",
    "name:ara_x_preferred":[
        "\u0644\u0627\u0645\u0648\u0646\u0627"
    ],
    "name:fra_x_preferred":[
        "Mouna"
    ],
    "name:spa_x_preferred":[
        "Mouna"
    ],
    "wof:name":"Mouna",
    "wof:placetype":"locality"
},
  "geometry": {"coordinates":[13.41608,10.07456],"type":"Point"}
}