{
  "type": "Feature",
  "properties": {
    "gn:admin1_code":"12.0",
    "gn:asciiname":"Mouna",
    "gn:country_code":"CM",
    "gn:dem":774,
    "gn:feature_class":"P",
    "gn:feature_code":"PPL",
    "gn:name":"Mouna",
    "gn:population":0,
    "gn:timezone":"Africa/Douala",
    "iso:country":"CM",
    "wof:name":"Mouna",
    "wof:placetype":"locality"
},
  "geometry": {"coordinates":[13.41608,10.07456],"type":"Point"}
}