{
  "type": "Feature",
  "properties": {
    "gn:admin1_code":"13.0",
    "gn:asciiname":"Mokirve",
    "gn:country_code":"CM",
    "gn:dem":957,
    "gn:feature_class":"P",
    "gn:feature_code":"PPL",
    "gn:name":"Mokirv\u00e9",
    "gn:population":0,
    "gn:timezone":"Africa/Douala",
    "iso:country":"CM",
    "name:und_x_variant":[
        "Hakirvia",
        "Makirv\u00e9",
        "Mokirv\u00e9"
    ],
    "wof:name":"Mokirve",
    "wof:placetype":"locality"
},
  "geometry": {"coordinates":[13.34798,10.09246],"type":"Point"}
}