{
  "type": "Feature",
  "properties": {
    "gn:admin1_code":"9.0",
    "gn:asciiname":"Bwenga",
    "gn:country_code":"CM",
    "gn:dem":21,
    "gn:feature_class":"P",
    "gn:feature_code":"PPL",
    "gn:name":"Bwenga",
    "gn:population":0,
    "gn:timezone":"Africa/Douala",
    "iso:country":"CM",
    "wof:name":"Bwenga",
    "wof:placetype":"locality"
},
  "geometry": {"coordinates":[9.3392,4.0435],"type":"Point"}
}