{
  "type": "Feature",
  "properties": {
    "gn:admin1_code":"10.0",
    "gn:asciiname":"Mbipoy",
    "gn:country_code":"CM",
    "gn:dem":868,
    "gn:feature_class":"P",
    "gn:feature_code":"PPL",
    "gn:name":"Mbipoy",
    "gn:population":0,
    "gn:timezone":"Africa/Douala",
    "iso:country":"CM",
    "wof:name":"Mbipoy",
    "wof:placetype":"locality"
},
  "geometry": {"coordinates":[12.61004,6.43512],"type":"Point"}
}