{
  "type": "Feature",
  "properties": {
    "gn:admin1_code":"14.0",
    "gn:asciiname":"Okpwang",
    "gn:country_code":"CM",
    "gn:dem":719,
    "gn:feature_class":"P",
    "gn:feature_code":"PPL",
    "gn:name":"Okpwang",
    "gn:population":0,
    "gn:timezone":"Africa/Douala",
    "iso:country":"CM",
    "name:und_x_variant":[
        "Okpweng",
        "Okpwang"
    ],
    "wof:name":"Okpwang",
    "wof:placetype":"locality"
},
  "geometry": {"coordinates":[11.56667,2.85],"type":"Point"}
}