{
  "type": "Feature",
  "properties": {
    "gn:admin1_code":"14.0",
    "gn:asciiname":"Mefiep",
    "gn:country_code":"CM",
    "gn:dem":704,
    "gn:feature_class":"P",
    "gn:feature_code":"PPL",
    "gn:name":"M\u00e9fiep",
    "gn:population":0,
    "gn:timezone":"Africa/Douala",
    "iso:country":"CM",
    "wof:name":"Mefiep",
    "wof:placetype":"locality"
},
  "geometry": {"coordinates":[11.61667,2.98333],"type":"Point"}
}