{
  "type": "Feature",
  "properties": {
    "gn:admin1_code":"7.0",
    "gn:asciiname":"Megan",
    "gn:country_code":"CM",
    "gn:dem":1188,
    "gn:feature_class":"P",
    "gn:feature_code":"PPL",
    "gn:name":"Megan",
    "gn:population":0,
    "gn:timezone":"Africa/Douala",
    "iso:country":"CM",
    "wof:name":"Megan",
    "wof:placetype":"locality"
},
  "geometry": {"coordinates":[10.46283,5.89938],"type":"Point"}
}