{
  "type": "Feature",
  "properties": {
    "gn:admin1_code":"7.0",
    "gn:asciiname":"Megan",
    "gn:country_code":"CM",
    "gn:dem":1188,
    "gn:feature_class":"P",
    "gn:feature_code":"PPL",
    "gn:name":"Megan",
    "gn:population":0,
    "gn:timezone":"Africa/Douala",
    "iso:country":"CM",
    "name:cym_x_preferred":[
        "Megan"
    ],
    "name:deu_x_preferred":[
        "Megan"
    ],
    "name:fin_x_preferred":[
        "Megan"
    ],
    "name:fra_x_preferred":[
        "Megan"
    ],
    "name:hun_x_preferred":[
        "Meg\u00e1n"
    ],
    "name:ita_x_preferred":[
        "Megan"
    ],
    "name:jpn_x_preferred":[
        "\u30e1\u30fc\u30ac\u30f3"
    ],
    "name:nor_x_preferred":[
        "Megan"
    ],
    "name:spa_x_preferred":[
        "Megan"
    ],
    "name:swe_x_preferred":[
        "Megan"
    ],
    "name:ukr_x_preferred":[
        "\u041c\u0435\u0433\u0430\u043d"
    ],
    "wof:name":"Megan",
    "wof:placetype":"locality"
},
  "geometry": {"coordinates":[10.46283,5.89938],"type":"Point"}
}