{
  "type": "Feature",
  "properties": {
    "gn:admin1_code":"14.0",
    "gn:asciiname":"Nkane",
    "gn:country_code":"CM",
    "gn:dem":591,
    "gn:feature_class":"P",
    "gn:feature_code":"PPL",
    "gn:name":"Nkane",
    "gn:population":0,
    "gn:timezone":"Africa/Douala",
    "iso:country":"CM",
    "name:und_x_variant":[
        "Nkan",
        "Nkane"
    ],
    "wof:name":"Nkane",
    "wof:placetype":"locality"
},
  "geometry": {"coordinates":[11.06667,2.51667],"type":"Point"}
}