{
  "type": "Feature",
  "properties": {
    "gn:admin1_code":"13.0",
    "gn:asciiname":"Bascheo",
    "gn:country_code":"CM",
    "gn:dem":333,
    "gn:feature_class":"P",
    "gn:feature_code":"PPL",
    "gn:name":"Basch\u00e9o",
    "gn:population":0,
    "gn:timezone":"Africa/Douala",
    "iso:country":"CM",
    "name:fra_x_preferred":[
        "Basch\u00e9o"
    ],
    "name:msa_x_preferred":[
        "Bash\u00e9o"
    ],
    "name:spa_x_preferred":[
        "Bash\u00e9o"
    ],
    "name:und_x_variant":[
        "Basch\u00e9",
        "Bachao",
        "Bach\u00e9",
        "Basheo",
        "Bach\u00e9o",
        "Basch\u00e9o"
    ],
    "wof:name":"Bascheo",
    "wof:placetype":"locality"
},
  "geometry": {"coordinates":[13.37222,9.67222],"type":"Point"}
}