{
  "type": "Feature",
  "properties": {
    "gn:admin1_code":"10.0",
    "gn:asciiname":"Alarba",
    "gn:country_code":"CM",
    "gn:dem":885,
    "gn:feature_class":"P",
    "gn:feature_code":"PPL",
    "gn:name":"Alarba",
    "gn:population":0,
    "gn:timezone":"Africa/Douala",
    "iso:country":"CM",
    "name:ara_x_preferred":[
        "\u0623\u0644\u0627\u0631\u0628\u0627"
    ],
    "name:arg_x_preferred":[
        "Alfarba"
    ],
    "name:cat_x_preferred":[
        "Alarba"
    ],
    "name:ceb_x_preferred":[
        "Alarba"
    ],
    "name:eus_x_preferred":[
        "Alarba"
    ],
    "name:fas_x_preferred":[
        "\u0627\u0644\u0627\u0631\u0628\u0627"
    ],
    "name:fra_x_preferred":[
        "Alarba"
    ],
    "name:hak_x_preferred":[
        "Alarba"
    ],
    "name:hun_x_preferred":[
        "Alarba"
    ],
    "name:ita_x_preferred":[
        "Alarba"
    ],
    "name:kaz_x_preferred":[
        "\u0410\u043b\u0430\u0440\u0431\u0430"
    ],
    "name:msa_x_preferred":[
        "Alarba"
    ],
    "name:nld_x_preferred":[
        "Alarba"
    ],
    "name:oci_x_preferred":[
        "Alarba"
    ],
    "name:pol_x_preferred":[
        "Alarba"
    ],
    "name:por_x_preferred":[
        "Alarba"
    ],
    "name:rus_x_preferred":[
        "\u0410\u043b\u0430\u0440\u0431\u0430"
    ],
    "name:spa_x_preferred":[
        "Alarba"
    ],
    "name:swe_x_preferred":[
        "Alarba"
    ],
    "name:ukr_x_preferred":[
        "\u0410\u043b\u0430\u0440\u0431\u0430"
    ],
    "name:uzb_x_preferred":[
        "Alarba"
    ],
    "name:vie_x_preferred":[
        "Alarba"
    ],
    "name:war_x_preferred":[
        "Alarba"
    ],
    "name:zho_x_preferred":[
        "\u963f\u62c9\u5c14\u74e6"
    ],
    "wof:name":"Alarba",
    "wof:placetype":"locality"
},
  "geometry": {"coordinates":[12.3804,6.74399],"type":"Point"}
}