{
  "type": "Feature",
  "properties": {
    "gn:admin1_code":"10.0",
    "gn:asciiname":"Alarba",
    "gn:country_code":"CM",
    "gn:dem":885,
    "gn:feature_class":"P",
    "gn:feature_code":"PPL",
    "gn:name":"Alarba",
    "gn:population":0,
    "gn:timezone":"Africa/Douala",
    "iso:country":"CM",
    "wof:name":"Alarba",
    "wof:placetype":"locality"
},
  "geometry": {"coordinates":[12.3804,6.74399],"type":"Point"}
}