{
  "type": "Feature",
  "properties": {
    "gn:admin1_code":"12.0",
    "gn:asciiname":"Mougoudi",
    "gn:country_code":"CM",
    "gn:dem":467,
    "gn:feature_class":"P",
    "gn:feature_code":"PPL",
    "gn:name":"Mougoudi",
    "gn:population":0,
    "gn:timezone":"Africa/Douala",
    "iso:country":"CM",
    "wof:name":"Mougoudi",
    "wof:placetype":"locality"
},
  "geometry": {"coordinates":[14.1727,10.61865],"type":"Point"}
}