{
  "type": "Feature",
  "properties": {
    "gn:admin1_code":"12.0",
    "gn:asciiname":"Mitchimi",
    "gn:country_code":"CM",
    "gn:dem":758,
    "gn:feature_class":"P",
    "gn:feature_code":"PPL",
    "gn:name":"Mitchimi",
    "gn:population":0,
    "gn:timezone":"Africa/Douala",
    "iso:country":"CM",
    "wof:name":"Mitchimi",
    "wof:placetype":"locality"
},
  "geometry": {"coordinates":[13.53196,10.22233],"type":"Point"}
}