{
  "type": "Feature",
  "properties": {
    "gn:admin1_code":"4.0",
    "gn:asciiname":"Pampa",
    "gn:country_code":"CM",
    "gn:dem":616,
    "gn:feature_class":"P",
    "gn:feature_code":"PPL",
    "gn:name":"Pampa",
    "gn:population":0,
    "gn:timezone":"Africa/Douala",
    "iso:country":"CM",
    "wof:name":"Pampa",
    "wof:placetype":"locality"
},
  "geometry": {"coordinates":[14.53333,4.08333],"type":"Point"}
}