{
  "type": "Feature",
  "properties": {
    "gn:admin1_code":"14.0",
    "gn:asciiname":"Akom",
    "gn:country_code":"CM",
    "gn:dem":679,
    "gn:feature_class":"P",
    "gn:feature_code":"PPL",
    "gn:name":"Akom",
    "gn:population":0,
    "gn:timezone":"Africa/Douala",
    "iso:country":"CM",
    "wof:name":"Akom",
    "wof:placetype":"locality"
},
  "geometry": {"coordinates":[12.71667,2.66667],"type":"Point"}
}