{
  "type": "Feature",
  "properties": {
    "gn:admin1_code":"8.0",
    "gn:asciiname":"Djo",
    "gn:country_code":"CM",
    "gn:dem":1539,
    "gn:feature_class":"P",
    "gn:feature_code":"PPL",
    "gn:name":"Djo",
    "gn:population":0,
    "gn:timezone":"Africa/Douala",
    "iso:country":"CM",
    "name:fra_x_preferred":[
        "Djo"
    ],
    "wof:name":"Djo",
    "wof:placetype":"locality"
},
  "geometry": {"coordinates":[10.40936,5.34963],"type":"Point"}
}