{
  "type": "Feature",
  "properties": {
    "gn:admin1_code":"13.0",
    "gn:asciiname":"Mokorvong",
    "gn:country_code":"CM",
    "gn:dem":345,
    "gn:feature_class":"P",
    "gn:feature_code":"PPL",
    "gn:name":"Mokorvong",
    "gn:population":0,
    "gn:timezone":"Africa/Douala",
    "iso:country":"CM",
    "name:und_x_variant":[
        "Mokorvon",
        "Mokorvong"
    ],
    "wof:name":"Mokorvong",
    "wof:placetype":"locality"
},
  "geometry": {"coordinates":[14.02931,9.95282],"type":"Point"}
}