{
  "type": "Feature",
  "properties": {
    "gn:admin1_code":"13.0",
    "gn:asciiname":"Zevene",
    "gn:country_code":"CM",
    "gn:dem":435,
    "gn:feature_class":"P",
    "gn:feature_code":"PPL",
    "gn:name":"Z\u00e9v\u00e9n\u00e9",
    "gn:population":0,
    "gn:timezone":"Africa/Douala",
    "iso:country":"CM",
    "name:und_x_variant":[
        "Z\u00e9v\u00e9n\u00e9",
        "Z\u00e9y\u00e9n\u00e9"
    ],
    "wof:name":"Zevene",
    "wof:placetype":"locality"
},
  "geometry": {"coordinates":[13.94792,10.13619],"type":"Point"}
}