{
  "type": "Feature",
  "properties": {
    "gn:admin1_code":"7.0",
    "gn:asciiname":"Ntenkissu",
    "gn:country_code":"CM",
    "gn:dem":1038,
    "gn:feature_class":"P",
    "gn:feature_code":"PPL",
    "gn:name":"Ntenkissu",
    "gn:population":0,
    "gn:timezone":"Africa/Douala",
    "iso:country":"CM",
    "wof:name":"Ntenkissu",
    "wof:placetype":"locality"
},
  "geometry": {"coordinates":[10.16667,6.31667],"type":"Point"}
}