{
  "type": "Feature",
  "properties": {
    "gn:admin1_code":"5.0",
    "gn:asciiname":"Buba I",
    "gn:country_code":"CM",
    "gn:dem":187,
    "gn:feature_class":"P",
    "gn:feature_code":"PPL",
    "gn:name":"Buba I",
    "gn:population":0,
    "gn:timezone":"Africa/Douala",
    "iso:country":"CM",
    "wof:name":"Buba I",
    "wof:placetype":"locality"
},
  "geometry": {"coordinates":[9.6321,4.6332],"type":"Point"}
}