{
  "type": "Feature",
  "properties": {
    "gn:admin1_code":"13.0",
    "gn:asciiname":"Yalam",
    "gn:country_code":"CM",
    "gn:dem":475,
    "gn:feature_class":"P",
    "gn:feature_code":"PPL",
    "gn:name":"Yalam",
    "gn:population":0,
    "gn:timezone":"Africa/Douala",
    "iso:country":"CM",
    "wof:name":"Yalam",
    "wof:placetype":"locality"
},
  "geometry": {"coordinates":[13.29215,9.85647],"type":"Point"}
}