{
  "type": "Feature",
  "properties": {
    "gn:admin1_code":"8.0",
    "gn:asciiname":"Kanjiba",
    "gn:country_code":"CM",
    "gn:dem":1282,
    "gn:feature_class":"P",
    "gn:feature_code":"PPL",
    "gn:name":"Kanjiba",
    "gn:population":0,
    "gn:timezone":"Africa/Douala",
    "iso:country":"CM",
    "name:fra_x_preferred":[
        "Kanjiba"
    ],
    "wof:name":"Kanjiba",
    "wof:placetype":"locality"
},
  "geometry": {"coordinates":[10.25566,5.73643],"type":"Point"}
}