{
  "type": "Feature",
  "properties": {
    "iso:country":"CM",
    "name:bul_x_preferred":[
        "\u0411\u0430\u0437\u043e\u0443"
    ],
    "name:ceb_x_preferred":[
        "Bazou"
    ],
    "name:eng_x_preferred":[
        "Bazou"
    ],
    "name:fra_x_preferred":[
        "Bazou"
    ],
    "name:msa_x_preferred":[
        "Bazou"
    ],
    "name:nan_x_preferred":[
        "Bazou"
    ],
    "name:nld_x_preferred":[
        "Bazou"
    ],
    "name:pol_x_preferred":[
        "Bazou"
    ],
    "name:spa_x_preferred":[
        "Bazou"
    ],
    "name:swe_x_preferred":[
        "Bazou"
    ],
    "qs:gn_country":"CM",
    "qs:gn_fcode":"PPL",
    "qs:gn_pop":13058,
    "qs:name":"Bazou",
    "qs:name_adm0":"Cameroun",
    "qs:name_adm1":"Ouest",
    "qs:photos":0,
    "qs:photos_1k":0,
    "qs:photos_9k":1,
    "qs:photos_9r":1,
    "qs:photos_all":1,
    "qs:photos_sr":0,
    "qs:placetype":"Town",
    "qs:pop_sr":"6",
    "qs:woe_adm0":23424785,
    "wd:wordcount":83,
    "wof:name":"Bazou",
    "wof:placetype":"locality",
    "wof:population":13058
},
  "geometry": {"coordinates":[10.46978,5.05695],"type":"Point"}
}