{
  "type": "Feature",
  "properties": {
    "gn:admin1_code":"12.0",
    "gn:asciiname":"Mazoua",
    "gn:country_code":"CM",
    "gn:dem":554,
    "gn:feature_class":"P",
    "gn:feature_code":"PPL",
    "gn:name":"Mazoua",
    "gn:population":0,
    "gn:timezone":"Africa/Douala",
    "iso:country":"CM",
    "wof:name":"Mazoua",
    "wof:placetype":"locality"
},
  "geometry": {"coordinates":[13.89405,10.84837],"type":"Point"}
}