{
  "type": "Feature",
  "properties": {
    "gn:admin1_code":"7.0",
    "gn:asciiname":"Mbakwa II",
    "gn:country_code":"CM",
    "gn:dem":1184,
    "gn:feature_class":"P",
    "gn:feature_code":"PPL",
    "gn:name":"Mbakwa II",
    "gn:population":0,
    "gn:timezone":"Africa/Douala",
    "iso:country":"CM",
    "wof:name":"Mbakwa II",
    "wof:placetype":"locality"
},
  "geometry": {"coordinates":[10.40953,5.82766],"type":"Point"}
}