{
  "type": "Feature",
  "properties": {
    "gn:admin1_code":"9.0",
    "gn:asciiname":"Makwe",
    "gn:country_code":"CM",
    "gn:dem":172,
    "gn:feature_class":"P",
    "gn:feature_code":"PPL",
    "gn:name":"Makwe",
    "gn:population":0,
    "gn:timezone":"Africa/Douala",
    "iso:country":"CM",
    "wof:name":"Makwe",
    "wof:placetype":"locality"
},
  "geometry": {"coordinates":[9.48232,6.16438],"type":"Point"}
}