{
  "type": "Feature",
  "properties": {
    "gn:admin1_code":"12.0",
    "gn:asciiname":"Dokney",
    "gn:country_code":"CM",
    "gn:dem":317,
    "gn:feature_class":"P",
    "gn:feature_code":"PPL",
    "gn:name":"Dokney",
    "gn:population":0,
    "gn:timezone":"Africa/Douala",
    "iso:country":"CM",
    "wof:name":"Dokney",
    "wof:placetype":"locality"
},
  "geometry": {"coordinates":[14.81198,10.81146],"type":"Point"}
}