{
  "type": "Feature",
  "properties": {
    "gn:admin1_code":"14.0",
    "gn:asciiname":"Oding",
    "gn:country_code":"CM",
    "gn:dem":416,
    "gn:feature_class":"P",
    "gn:feature_code":"PPL",
    "gn:name":"Oding",
    "gn:population":0,
    "gn:timezone":"Africa/Douala",
    "iso:country":"CM",
    "wof:name":"Oding",
    "wof:placetype":"locality"
},
  "geometry": {"coordinates":[10.41667,2.41667],"type":"Point"}
}