{
  "type": "Feature",
  "properties": {
    "gn:admin1_code":"13.0",
    "gn:asciiname":"Daloudje",
    "gn:country_code":"CM",
    "gn:dem":326,
    "gn:feature_class":"P",
    "gn:feature_code":"PPL",
    "gn:name":"Daloudj\u00e9",
    "gn:population":0,
    "gn:timezone":"Africa/Douala",
    "iso:country":"CM",
    "wof:name":"Daloudje",
    "wof:placetype":"locality"
},
  "geometry": {"coordinates":[14.1163,9.3788],"type":"Point"}
}