{
  "type": "Feature",
  "properties": {
    "gn:admin1_code":"12.0",
    "gn:asciiname":"Dza",
    "gn:country_code":"CM",
    "gn:dem":633,
    "gn:feature_class":"P",
    "gn:feature_code":"PPL",
    "gn:name":"Dza",
    "gn:population":0,
    "gn:timezone":"Africa/Douala",
    "iso:country":"CM",
    "wof:name":"Dza",
    "wof:placetype":"locality"
},
  "geometry": {"coordinates":[13.86797,10.85076],"type":"Point"}
}