{
  "type": "Feature",
  "properties": {
    "gn:admin1_code":"11.0",
    "gn:asciiname":"Ndokalende",
    "gn:country_code":"CM",
    "gn:dem":1031,
    "gn:feature_class":"P",
    "gn:feature_code":"PPL",
    "gn:name":"Ndokalend\u00e9",
    "gn:population":0,
    "gn:timezone":"Africa/Douala",
    "iso:country":"CM",
    "wof:name":"Ndokalende",
    "wof:placetype":"locality"
},
  "geometry": {"coordinates":[10.78333,4.71667],"type":"Point"}
}