{
  "type": "Feature",
  "properties": {
    "gn:admin1_code":"8.0",
    "gn:asciiname":"Ntamkouop",
    "gn:country_code":"CM",
    "gn:dem":1135,
    "gn:feature_class":"P",
    "gn:feature_code":"PPL",
    "gn:name":"Ntamkouop",
    "gn:population":0,
    "gn:timezone":"Africa/Douala",
    "iso:country":"CM",
    "wof:name":"Ntamkouop",
    "wof:placetype":"locality"
},
  "geometry": {"coordinates":[10.63997,5.58469],"type":"Point"}
}