{
  "type": "Feature",
  "properties": {
    "gn:admin1_code":"11.0",
    "gn:asciiname":"Mbe",
    "gn:country_code":"CM",
    "gn:dem":573,
    "gn:feature_class":"P",
    "gn:feature_code":"PPL",
    "gn:name":"Mb\u00e9",
    "gn:population":0,
    "gn:timezone":"Africa/Douala",
    "iso:country":"CM",
    "name:ara_x_preferred":[
        "\u0625\u0645\u0628\u064a\u0648"
    ],
    "name:ben_x_preferred":[
        "\u098f\u09ae\u09cd\u09ac\u09c7"
    ],
    "name:ceb_x_preferred":[
        "Mbe"
    ],
    "name:ell_x_preferred":[
        "\u039c\u03c0\u03b5"
    ],
    "name:fas_x_preferred":[
        "\u0627\u0645\u0628\u0647"
    ],
    "name:heb_x_preferred":[
        "\u05de\u05d1\u05d4"
    ],
    "name:hin_x_preferred":[
        "\u092c\u0947"
    ],
    "name:hun_x_preferred":[
        "Mbe"
    ],
    "name:ind_x_preferred":[
        "Mbe"
    ],
    "name:jpn_x_preferred":[
        "\u30f3\u30d9"
    ],
    "name:kor_x_preferred":[
        "\uc74c\ubca0"
    ],
    "name:pol_x_preferred":[
        "Mbe"
    ],
    "name:por_x_preferred":[
        "Mbe"
    ],
    "name:rus_x_preferred":[
        "\u041c\u0431\u0435"
    ],
    "name:swe_x_preferred":[
        "Mbe"
    ],
    "name:tur_x_preferred":[
        "Mbe"
    ],
    "name:ukr_x_preferred":[
        "\u041c\u0431\u0435"
    ],
    "name:urd_x_preferred":[
        "\u0627\u06cc\u0645\u0628\u06cc"
    ],
    "name:vie_x_preferred":[
        "Mbe"
    ],
    "name:zho_cn_x_preferred":[
        "\u59c6\u8d1d"
    ],
    "name:zho_tw_x_preferred":[
        "\u59c6\u8c9d"
    ],
    "wof:name":"Mbe",
    "wof:placetype":"locality"
},
  "geometry": {"coordinates":[11.86667,4.28333],"type":"Point"}
}