{
  "type": "Feature",
  "properties": {
    "gn:admin1_code":"4.0",
    "gn:asciiname":"Massiam",
    "gn:country_code":"CM",
    "gn:dem":597,
    "gn:feature_class":"P",
    "gn:feature_code":"PPL",
    "gn:name":"Massiam",
    "gn:population":0,
    "gn:timezone":"Africa/Douala",
    "iso:country":"CM",
    "name:und_x_variant":[
        "Kalo\u2019s",
        "Massia",
        "Massiang",
        "Massian",
        "Massiam"
    ],
    "wof:name":"Massiam",
    "wof:placetype":"locality"
},
  "geometry": {"coordinates":[14.91667,3.08333],"type":"Point"}
}