{
  "type": "Feature",
  "properties": {
    "gn:admin1_code":"10.0",
    "gn:asciiname":"Garga",
    "gn:country_code":"CM",
    "gn:dem":889,
    "gn:feature_class":"P",
    "gn:feature_code":"PPL",
    "gn:name":"Garga",
    "gn:population":0,
    "gn:timezone":"Africa/Douala",
    "iso:country":"CM",
    "name:ben_x_preferred":[
        "\u0997\u09b0\u09cd\u0997 \u09ae\u09c1\u09a8\u09bf"
    ],
    "name:hin_x_preferred":[
        "\u0917\u0930\u094d\u0917"
    ],
    "name:spa_x_preferred":[
        "Garga Muni"
    ],
    "name:vie_x_preferred":[
        "Garga"
    ],
    "wof:name":"Garga",
    "wof:placetype":"locality"
},
  "geometry": {"coordinates":[12.68333,6.25],"type":"Point"}
}