{
  "type": "Feature",
  "properties": {
    "gn:admin1_code":"14.0",
    "gn:asciiname":"Madoungou",
    "gn:country_code":"CM",
    "gn:dem":91,
    "gn:feature_class":"P",
    "gn:feature_code":"PPL",
    "gn:name":"Madoungou",
    "gn:population":0,
    "gn:timezone":"Africa/Douala",
    "iso:country":"CM",
    "wof:name":"Madoungou",
    "wof:placetype":"locality"
},
  "geometry": {"coordinates":[10.33333,3.06667],"type":"Point"}
}