{
  "type": "Feature",
  "properties": {
    "gn:admin1_code":"14.0",
    "gn:asciiname":"Mimbi",
    "gn:country_code":"CM",
    "gn:dem":643,
    "gn:feature_class":"P",
    "gn:feature_code":"PPL",
    "gn:name":"Mimbi",
    "gn:population":0,
    "gn:timezone":"Africa/Douala",
    "iso:country":"CM",
    "wof:name":"Mimbi",
    "wof:placetype":"locality"
},
  "geometry": {"coordinates":[12.53333,3.21667],"type":"Point"}
}