{
  "type": "Feature",
  "properties": {
    "gn:admin1_code":"12.0",
    "gn:asciiname":"Dorkale",
    "gn:country_code":"CM",
    "gn:dem":469,
    "gn:feature_class":"P",
    "gn:feature_code":"PPL",
    "gn:name":"Dorkal\u00e9",
    "gn:population":0,
    "gn:timezone":"Africa/Douala",
    "iso:country":"CM",
    "wof:name":"Dorkale",
    "wof:placetype":"locality"
},
  "geometry": {"coordinates":[13.88788,10.93051],"type":"Point"}
}