{
  "type": "Feature",
  "properties": {
    "gn:admin1_code":"9.0",
    "gn:asciiname":"Jilap",
    "gn:country_code":"CM",
    "gn:dem":1235,
    "gn:feature_class":"P",
    "gn:feature_code":"PPL",
    "gn:name":"Jilap",
    "gn:population":0,
    "gn:timezone":"Africa/Douala",
    "iso:country":"CM",
    "wof:name":"Jilap",
    "wof:placetype":"locality"
},
  "geometry": {"coordinates":[9.945,5.5606],"type":"Point"}
}