{
  "type": "Feature",
  "properties": {
    "gn:admin1_code":"8.0",
    "gn:asciiname":"Famla'",
    "gn:country_code":"CM",
    "gn:dem":1528,
    "gn:feature_class":"P",
    "gn:feature_code":"PPL",
    "gn:name":"Famla\u2019",
    "gn:population":0,
    "gn:timezone":"Africa/Douala",
    "iso:country":"CM",
    "wof:name":"Famla'",
    "wof:placetype":"locality"
},
  "geometry": {"coordinates":[10.46982,5.25453],"type":"Point"}
}