{
  "type": "Feature",
  "properties": {
    "gn:admin1_code":"8.0",
    "gn:asciiname":"Nyamga'",
    "gn:country_code":"CM",
    "gn:dem":1418,
    "gn:feature_class":"P",
    "gn:feature_code":"PPL",
    "gn:name":"Nyamga\u2019",
    "gn:population":0,
    "gn:timezone":"Africa/Douala",
    "iso:country":"CM",
    "wof:name":"Nyamga'",
    "wof:placetype":"locality"
},
  "geometry": {"coordinates":[10.55153,5.08836],"type":"Point"}
}