{
  "type": "Feature",
  "properties": {
    "gn:admin1_code":"10.0",
    "gn:asciiname":"Deng-Haoussa",
    "gn:country_code":"CM",
    "gn:dem":804,
    "gn:feature_class":"P",
    "gn:feature_code":"PPL",
    "gn:name":"Deng-Haoussa",
    "gn:population":0,
    "gn:timezone":"Africa/Douala",
    "iso:country":"CM",
    "wof:name":"Deng-Haoussa",
    "wof:placetype":"locality"
},
  "geometry": {"coordinates":[13.68333,6.01667],"type":"Point"}
}