{
  "type": "Feature",
  "properties": {
    "gn:admin1_code":"5.0",
    "gn:asciiname":"Dipendi",
    "gn:country_code":"CM",
    "gn:dem":34,
    "gn:feature_class":"P",
    "gn:feature_code":"PPL",
    "gn:name":"Dipendi",
    "gn:population":0,
    "gn:timezone":"Africa/Douala",
    "iso:country":"CM",
    "wof:name":"Dipendi",
    "wof:placetype":"locality"
},
  "geometry": {"coordinates":[9.94806,3.615],"type":"Point"}
}