{
  "type": "Feature",
  "properties": {
    "gn:admin1_code":"13.0",
    "gn:asciiname":"Tapare",
    "gn:country_code":"CM",
    "gn:dem":285,
    "gn:feature_class":"P",
    "gn:feature_code":"PPL",
    "gn:name":"Tapar\u00e9",
    "gn:population":0,
    "gn:timezone":"Africa/Douala",
    "iso:country":"CM",
    "wof:name":"Tapare",
    "wof:placetype":"locality"
},
  "geometry": {"coordinates":[14.18994,8.50967],"type":"Point"}
}