{
  "type": "Feature",
  "properties": {
    "gn:admin1_code":"8.0",
    "gn:asciiname":"Batsela II",
    "gn:country_code":"CM",
    "gn:dem":1375,
    "gn:feature_class":"P",
    "gn:feature_code":"PPL",
    "gn:name":"Batsela II",
    "gn:population":0,
    "gn:timezone":"Africa/Douala",
    "iso:country":"CM",
    "name:fra_x_preferred":[
        "Batsela"
    ],
    "wof:name":"Batsela II",
    "wof:placetype":"locality"
},
  "geometry": {"coordinates":[10.29151,5.57064],"type":"Point"}
}