{
  "type": "Feature",
  "properties": {
    "gn:admin1_code":"9.0",
    "gn:asciiname":"Tembe",
    "gn:country_code":"CM",
    "gn:dem":224,
    "gn:feature_class":"P",
    "gn:feature_code":"PPL",
    "gn:name":"Tembe",
    "gn:population":0,
    "gn:timezone":"Africa/Douala",
    "iso:country":"CM",
    "name:eng_x_preferred":[
        "Tembe"
    ],
    "wof:name":"Tembe",
    "wof:placetype":"locality"
},
  "geometry": {"coordinates":[9.63811,6.5101],"type":"Point"}
}