{
  "type": "Feature",
  "properties": {
    "gn:admin1_code":"13.0",
    "gn:asciiname":"Kafinarou",
    "gn:country_code":"CM",
    "gn:dem":240,
    "gn:feature_class":"P",
    "gn:feature_code":"PPL",
    "gn:name":"Kafinarou",
    "gn:population":0,
    "gn:timezone":"Africa/Douala",
    "iso:country":"CM",
    "name:und_x_variant":[
        "Kanarou"
    ],
    "wof:name":"Kafinarou",
    "wof:placetype":"locality"
},
  "geometry": {"coordinates":[13.96238,9.66859],"type":"Point"}
}