{
  "type": "Feature",
  "properties": {
    "gn:admin1_code":"12.0",
    "gn:asciiname":"Louguerso",
    "gn:country_code":"CM",
    "gn:dem":486,
    "gn:feature_class":"P",
    "gn:feature_code":"PPL",
    "gn:name":"Lougu\u00e8rso",
    "gn:population":0,
    "gn:timezone":"Africa/Douala",
    "iso:country":"CM",
    "wof:name":"Louguerso",
    "wof:placetype":"locality"
},
  "geometry": {"coordinates":[13.89011,10.25466],"type":"Point"}
}