{
  "type": "Feature",
  "properties": {
    "gn:admin1_code":"9.0",
    "gn:asciiname":"Ebeagwa II",
    "gn:country_code":"CM",
    "gn:dem":170,
    "gn:feature_class":"P",
    "gn:feature_code":"PPL",
    "gn:name":"Ebeagwa II",
    "gn:population":0,
    "gn:timezone":"Africa/Douala",
    "iso:country":"CM",
    "wof:name":"Ebeagwa II",
    "wof:placetype":"locality"
},
  "geometry": {"coordinates":[9.7324,5.5732],"type":"Point"}
}