{
  "type": "Feature",
  "properties": {
    "gn:admin1_code":"9.0",
    "gn:asciiname":"Dibonda I",
    "gn:country_code":"CM",
    "gn:dem":727,
    "gn:feature_class":"P",
    "gn:feature_code":"PPL",
    "gn:name":"Dibonda I",
    "gn:population":0,
    "gn:timezone":"Africa/Douala",
    "iso:country":"CM",
    "wof:name":"Dibonda I",
    "wof:placetype":"locality"
},
  "geometry": {"coordinates":[9.1474,5.0816],"type":"Point"}
}