{
  "type": "Feature",
  "properties": {
    "gn:admin1_code":"9.0",
    "gn:asciiname":"Bambele",
    "gn:country_code":"CM",
    "gn:dem":234,
    "gn:feature_class":"P",
    "gn:feature_code":"PPL",
    "gn:name":"Bambele",
    "gn:population":0,
    "gn:timezone":"Africa/Douala",
    "iso:country":"CM",
    "wof:name":"Bambele",
    "wof:placetype":"locality"
},
  "geometry": {"coordinates":[9.5891,4.7968],"type":"Point"}
}