{
  "type": "Feature",
  "properties": {
    "gn:admin1_code":"4.0",
    "gn:asciiname":"Sobolo",
    "gn:country_code":"CM",
    "gn:dem":590,
    "gn:feature_class":"P",
    "gn:feature_code":"PPL",
    "gn:name":"Sobolo",
    "gn:population":0,
    "gn:timezone":"Africa/Douala",
    "iso:country":"CM",
    "name:ara_x_preferred":[
        "\u0633\u0648\u0628\u0648\u0644\u0648"
    ],
    "name:und_x_variant":[
        "Sogolo",
        "Sobolo"
    ],
    "wof:name":"Sobolo",
    "wof:placetype":"locality"
},
  "geometry": {"coordinates":[14.78333,4.18333],"type":"Point"}
}