{
  "type": "Feature",
  "properties": {
    "gn:admin1_code":"13.0",
    "gn:asciiname":"Bogdou",
    "gn:country_code":"CM",
    "gn:dem":312,
    "gn:feature_class":"P",
    "gn:feature_code":"PPL",
    "gn:name":"Bogdou",
    "gn:population":0,
    "gn:timezone":"Africa/Douala",
    "iso:country":"CM",
    "wof:name":"Bogdou",
    "wof:placetype":"locality"
},
  "geometry": {"coordinates":[12.58333,8.51667],"type":"Point"}
}