{
  "type": "Feature",
  "properties": {
    "gn:admin1_code":"9.0",
    "gn:asciiname":"Katjinga I",
    "gn:country_code":"CM",
    "gn:dem":873,
    "gn:feature_class":"P",
    "gn:feature_code":"PPL",
    "gn:name":"Katjinga I",
    "gn:population":0,
    "gn:timezone":"Africa/Douala",
    "iso:country":"CM",
    "wof:name":"Katjinga I",
    "wof:placetype":"locality"
},
  "geometry": {"coordinates":[9.4469,6.3376],"type":"Point"}
}