{
  "type": "Feature",
  "properties": {
    "gn:admin1_code":"13.0",
    "gn:asciiname":"Guirlao",
    "gn:country_code":"CM",
    "gn:dem":540,
    "gn:feature_class":"P",
    "gn:feature_code":"PPL",
    "gn:name":"Guirlao",
    "gn:population":0,
    "gn:timezone":"Africa/Douala",
    "iso:country":"CM",
    "name:und_x_variant":[
        "G\u012dlau",
        "Guilaou",
        "Guirlao"
    ],
    "wof:name":"Guirlao",
    "wof:placetype":"locality"
},
  "geometry": {"coordinates":[13.68485,10.00675],"type":"Point"}
}