{
  "type": "Feature",
  "properties": {
    "gn:admin1_code":"9.0",
    "gn:asciiname":"Boviongo",
    "gn:country_code":"CM",
    "gn:dem":247,
    "gn:feature_class":"P",
    "gn:feature_code":"PPL",
    "gn:name":"Boviongo",
    "gn:population":0,
    "gn:timezone":"Africa/Douala",
    "iso:country":"CM",
    "name:und_x_variant":[
        "Moviongo",
        "Bowiongo",
        "Boviongo"
    ],
    "wof:name":"Boviongo",
    "wof:placetype":"locality"
},
  "geometry": {"coordinates":[9.1817,4.426],"type":"Point"}
}