{
  "type": "Feature",
  "properties": {
    "gn:admin1_code":"13.0",
    "gn:asciiname":"Goudak",
    "gn:country_code":"CM",
    "gn:dem":435,
    "gn:feature_class":"P",
    "gn:feature_code":"PPL",
    "gn:name":"Goudak",
    "gn:population":0,
    "gn:timezone":"Africa/Douala",
    "iso:country":"CM",
    "wof:name":"Goudak",
    "wof:placetype":"locality"
},
  "geometry": {"coordinates":[13.90765,10.10871],"type":"Point"}
}