{
  "type": "Feature",
  "properties": {
    "gn:admin1_code":"11.0",
    "gn:asciiname":"Nkongmeyos",
    "gn:country_code":"CM",
    "gn:dem":690,
    "gn:feature_class":"P",
    "gn:feature_code":"PPL",
    "gn:name":"Nkongmeyos",
    "gn:population":0,
    "gn:timezone":"Africa/Douala",
    "iso:country":"CM",
    "wof:name":"Nkongmeyos",
    "wof:placetype":"locality"
},
  "geometry": {"coordinates":[11.31667,3.61667],"type":"Point"}
}