{
  "type": "Feature",
  "properties": {
    "gn:admin1_code":"12.0",
    "gn:asciiname":"Djarengol",
    "gn:country_code":"CM",
    "gn:dem":412,
    "gn:feature_class":"P",
    "gn:feature_code":"PPL",
    "gn:name":"Djarengol",
    "gn:population":0,
    "gn:timezone":"Africa/Douala",
    "iso:country":"CM",
    "wof:name":"Djarengol",
    "wof:placetype":"locality"
},
  "geometry": {"coordinates":[14.29886,10.57436],"type":"Point"}
}