{
  "type": "Feature",
  "properties": {
    "gn:admin1_code":"13.0",
    "gn:asciiname":"Ouro Bah Barka",
    "gn:country_code":"CM",
    "gn:dem":271,
    "gn:feature_class":"P",
    "gn:feature_code":"PPL",
    "gn:name":"Ouro Bah Barka",
    "gn:population":0,
    "gn:timezone":"Africa/Douala",
    "iso:country":"CM",
    "wof:name":"Ouro Bah Barka",
    "wof:placetype":"locality"
},
  "geometry": {"coordinates":[13.89651,9.08181],"type":"Point"}
}