{
  "type": "Feature",
  "properties": {
    "gn:admin1_code":"12.0",
    "gn:asciiname":"Rourounde",
    "gn:country_code":"CM",
    "gn:dem":288,
    "gn:feature_class":"P",
    "gn:feature_code":"PPL",
    "gn:name":"Rouround\u00e9",
    "gn:population":0,
    "gn:timezone":"Africa/Douala",
    "iso:country":"CM",
    "name:und_x_variant":[
        "Rouround\u00e9",
        "Fadj\u00e9"
    ],
    "wof:name":"Rourounde",
    "wof:placetype":"locality"
},
  "geometry": {"coordinates":[14.22725,12.43174],"type":"Point"}
}