{
  "type": "Feature",
  "properties": {
    "gn:admin1_code":"8.0",
    "gn:asciiname":"Tchinla",
    "gn:country_code":"CM",
    "gn:dem":1432,
    "gn:feature_class":"P",
    "gn:feature_code":"PPL",
    "gn:name":"Tchinla",
    "gn:population":0,
    "gn:timezone":"Africa/Douala",
    "iso:country":"CM",
    "wof:name":"Tchinla",
    "wof:placetype":"locality"
},
  "geometry": {"coordinates":[10.24188,5.68108],"type":"Point"}
}