{
  "type": "Feature",
  "properties": {
    "gn:admin1_code":"12.0",
    "gn:asciiname":"Woromari",
    "gn:country_code":"CM",
    "gn:dem":291,
    "gn:feature_class":"P",
    "gn:feature_code":"PPL",
    "gn:name":"Woromari",
    "gn:population":0,
    "gn:timezone":"Africa/Douala",
    "iso:country":"CM",
    "name:und_x_variant":[
        "Ouaramari"
    ],
    "wof:name":"Woromari",
    "wof:placetype":"locality"
},
  "geometry": {"coordinates":[14.20288,12.42094],"type":"Point"}
}