{
  "type": "Feature",
  "properties": {
    "gn:admin1_code":"12.0",
    "gn:asciiname":"Mada",
    "gn:country_code":"CM",
    "gn:dem":716,
    "gn:feature_class":"P",
    "gn:feature_code":"PPL",
    "gn:name":"Mada",
    "gn:population":0,
    "gn:timezone":"Africa/Douala",
    "iso:country":"CM",
    "name:fra_x_preferred":[
        "Mada"
    ],
    "wof:name":"Mada",
    "wof:placetype":"locality"
},
  "geometry": {"coordinates":[13.94542,10.79978],"type":"Point"}
}