{
  "type": "Feature",
  "properties": {
    "gn:admin1_code":"14.0",
    "gn:asciiname":"Mekaa",
    "gn:country_code":"CM",
    "gn:dem":608,
    "gn:feature_class":"P",
    "gn:feature_code":"PPL",
    "gn:name":"M\u00e9kaa",
    "gn:population":0,
    "gn:timezone":"Africa/Douala",
    "iso:country":"CM",
    "wof:name":"Mekaa",
    "wof:placetype":"locality"
},
  "geometry": {"coordinates":[10.93333,2.88333],"type":"Point"}
}