{
  "type": "Feature",
  "properties": {
    "gn:admin1_code":"12.0",
    "gn:asciiname":"Kazarao",
    "gn:country_code":"CM",
    "gn:dem":413,
    "gn:feature_class":"P",
    "gn:feature_code":"PPL",
    "gn:name":"Kazarao",
    "gn:population":0,
    "gn:timezone":"Africa/Douala",
    "iso:country":"CM",
    "wof:name":"Kazarao",
    "wof:placetype":"locality"
},
  "geometry": {"coordinates":[14.43565,10.24436],"type":"Point"}
}