{
  "type": "Feature",
  "properties": {
    "gn:admin1_code":"7.0",
    "gn:asciiname":"Anyene",
    "gn:country_code":"CM",
    "gn:dem":1604,
    "gn:feature_class":"P",
    "gn:feature_code":"PPL",
    "gn:name":"Anyene",
    "gn:population":0,
    "gn:timezone":"Africa/Douala",
    "iso:country":"CM",
    "wof:name":"Anyene",
    "wof:placetype":"locality"
},
  "geometry": {"coordinates":[10.02094,5.79284],"type":"Point"}
}