{
  "type": "Feature",
  "properties": {
    "gn:admin1_code":"11.0",
    "gn:asciiname":"Emvong",
    "gn:country_code":"CM",
    "gn:dem":693,
    "gn:feature_class":"P",
    "gn:feature_code":"PPL",
    "gn:name":"Emvong",
    "gn:population":0,
    "gn:timezone":"Africa/Douala",
    "iso:country":"CM",
    "wof:name":"Emvong",
    "wof:placetype":"locality"
},
  "geometry": {"coordinates":[12.28333,3.95],"type":"Point"}
}