{
  "type": "Feature",
  "properties": {
    "gn:admin1_code":"13.0",
    "gn:asciiname":"Mouena",
    "gn:country_code":"CM",
    "gn:dem":654,
    "gn:feature_class":"P",
    "gn:feature_code":"PPL",
    "gn:name":"Mou\u00e9na",
    "gn:population":0,
    "gn:timezone":"Africa/Douala",
    "iso:country":"CM",
    "wof:name":"Mouena",
    "wof:placetype":"locality"
},
  "geometry": {"coordinates":[13.39829,10.06895],"type":"Point"}
}