{
  "type": "Feature",
  "properties": {
    "gn:admin1_code":"10.0",
    "gn:asciiname":"Tschamba",
    "gn:country_code":"CM",
    "gn:dem":740,
    "gn:feature_class":"P",
    "gn:feature_code":"PPL",
    "gn:name":"Tschamba",
    "gn:population":0,
    "gn:timezone":"Africa/Douala",
    "iso:country":"CM",
    "wof:name":"Tschamba",
    "wof:placetype":"locality"
},
  "geometry": {"coordinates":[11.46667,6.31667],"type":"Point"}
}