{
  "type": "Feature",
  "properties": {
    "gn:admin1_code":"13.0",
    "gn:asciiname":"Sare",
    "gn:country_code":"CM",
    "gn:dem":641,
    "gn:feature_class":"P",
    "gn:feature_code":"PPL",
    "gn:name":"Sar\u00e9",
    "gn:population":0,
    "gn:timezone":"Africa/Douala",
    "iso:country":"CM",
    "name:ara_x_preferred":[
        "\u0633\u0627\u0631\u064a"
    ],
    "name:arg_x_preferred":[
        "Sara"
    ],
    "name:bre_x_preferred":[
        "Sara"
    ],
    "name:cat_x_preferred":[
        "Sara"
    ],
    "name:ceb_x_preferred":[
        "Sare"
    ],
    "name:deu_x_preferred":[
        "Sare"
    ],
    "name:epo_x_preferred":[
        "Sare"
    ],
    "name:eus_x_preferred":[
        "Sara"
    ],
    "name:fin_x_preferred":[
        "Sare"
    ],
    "name:fra_x_preferred":[
        "Sare"
    ],
    "name:hun_x_preferred":[
        "Sare"
    ],
    "name:hye_x_preferred":[
        "\u054d\u0561\u0580"
    ],
    "name:ind_x_preferred":[
        "Sare"
    ],
    "name:ita_x_preferred":[
        "Sare"
    ],
    "name:kaz_x_preferred":[
        "\u0421\u0430\u0440"
    ],
    "name:lat_x_preferred":[
        "Sare"
    ],
    "name:msa_x_preferred":[
        "Sare"
    ],
    "name:nld_x_preferred":[
        "Sare"
    ],
    "name:oci_x_preferred":[
        "Sara"
    ],
    "name:pms_x_preferred":[
        "Sare"
    ],
    "name:pnb_x_preferred":[
        "\u0633\u0627\u0631\u06d2"
    ],
    "name:pol_x_preferred":[
        "Sare"
    ],
    "name:por_x_preferred":[
        "Sare"
    ],
    "name:ron_x_preferred":[
        "Sare"
    ],
    "name:rus_x_preferred":[
        "\u0421\u0430\u0440"
    ],
    "name:slk_x_preferred":[
        "Sare"
    ],
    "name:spa_x_preferred":[
        "Sare"
    ],
    "name:swa_x_preferred":[
        "Mto Sare"
    ],
    "name:swe_x_preferred":[
        "Sare"
    ],
    "name:ukr_x_preferred":[
        "\u0421\u0430\u0440"
    ],
    "name:uzb_x_preferred":[
        "Sare"
    ],
    "name:vie_x_preferred":[
        "Sare"
    ],
    "name:vol_x_preferred":[
        "Sare"
    ],
    "name:war_x_preferred":[
        "Sare"
    ],
    "name:zho_x_preferred":[
        "\u8428\u5c14"
    ],
    "wof:name":"Sare",
    "wof:placetype":"locality"
},
  "geometry": {"coordinates":[13.26972,8.42547],"type":"Point"}
}