{
  "type": "Feature",
  "properties": {
    "gn:admin1_code":"5.0",
    "gn:asciiname":"Ndokiamen",
    "gn:country_code":"CM",
    "gn:dem":138,
    "gn:feature_class":"P",
    "gn:feature_code":"PPL",
    "gn:name":"Ndokiamen",
    "gn:population":0,
    "gn:timezone":"Africa/Douala",
    "iso:country":"CM",
    "wof:name":"Ndokiamen",
    "wof:placetype":"locality"
},
  "geometry": {"coordinates":[9.9381,4.5283],"type":"Point"}
}