{
  "type": "Feature",
  "properties": {
    "gn:admin1_code":"4.0",
    "gn:asciiname":"Kombo",
    "gn:country_code":"CM",
    "gn:dem":639,
    "gn:feature_class":"P",
    "gn:feature_code":"PPL",
    "gn:name":"Kombo",
    "gn:population":0,
    "gn:timezone":"Africa/Douala",
    "iso:country":"CM",
    "wof:name":"Kombo",
    "wof:placetype":"locality"
},
  "geometry": {"coordinates":[14.83333,4.31667],"type":"Point"}
}