{
  "type": "Feature",
  "properties": {
    "gn:admin1_code":"12.0",
    "gn:asciiname":"Jiri",
    "gn:country_code":"CM",
    "gn:dem":969,
    "gn:feature_class":"P",
    "gn:feature_code":"PPL",
    "gn:name":"Jiri",
    "gn:population":0,
    "gn:timezone":"Africa/Douala",
    "iso:country":"CM",
    "wof:name":"Jiri",
    "wof:placetype":"locality"
},
  "geometry": {"coordinates":[13.57533,10.471],"type":"Point"}
}