{
  "type": "Feature",
  "properties": {
    "gn:admin1_code":"12.0",
    "gn:asciiname":"Jiri",
    "gn:country_code":"CM",
    "gn:dem":969,
    "gn:feature_class":"P",
    "gn:feature_code":"PPL",
    "gn:name":"Jiri",
    "gn:population":0,
    "gn:timezone":"Africa/Douala",
    "iso:country":"CM",
    "name:bih_x_preferred":[
        "\u091c\u093f\u0930\u0940"
    ],
    "name:ceb_x_preferred":[
        "Jiri"
    ],
    "name:deu_x_preferred":[
        "Jiri"
    ],
    "name:dty_x_preferred":[
        "\u091c\u093f\u0930\u0940"
    ],
    "name:fra_x_preferred":[
        "Jiri"
    ],
    "name:lit_x_preferred":[
        "D\u017eiri"
    ],
    "name:mai_x_preferred":[
        "\u091c\u093f\u0930\u0940 \u0928\u0917\u0930\u092a\u093e\u0932\u093f\u0915\u093e"
    ],
    "name:msa_x_preferred":[
        "Jiri"
    ],
    "name:nep_x_preferred":[
        "\u091c\u093f\u0930\u0940 \u0928\u0917\u0930\u092a\u093e\u0932\u093f\u0915\u093e"
    ],
    "name:new_x_preferred":[
        "\u091c\u093f\u0930\u0940"
    ],
    "name:pol_x_preferred":[
        "Jiri"
    ],
    "name:rus_x_preferred":[
        "\u0414\u0436\u0438\u0440\u0438"
    ],
    "wof:name":"Jiri",
    "wof:placetype":"locality"
},
  "geometry": {"coordinates":[13.57533,10.471],"type":"Point"}
}