{
  "type": "Feature",
  "properties": {
    "gn:admin1_code":"5.0",
    "gn:asciiname":"Mbangue I",
    "gn:country_code":"CM",
    "gn:dem":32,
    "gn:feature_class":"P",
    "gn:feature_code":"PPL",
    "gn:name":"Mbangu\u00e9 I",
    "gn:population":0,
    "gn:timezone":"Africa/Douala",
    "iso:country":"CM",
    "wof:name":"Mbangue I",
    "wof:placetype":"locality"
},
  "geometry": {"coordinates":[9.7034,4.1646],"type":"Point"}
}