{
  "type": "Feature",
  "properties": {
    "gn:admin1_code":"12.0",
    "gn:asciiname":"Dororeya",
    "gn:country_code":"CM",
    "gn:dem":297,
    "gn:feature_class":"P",
    "gn:feature_code":"PPL",
    "gn:name":"Doror\u00e9ya",
    "gn:population":0,
    "gn:timezone":"Africa/Douala",
    "iso:country":"CM",
    "wof:name":"Dororeya",
    "wof:placetype":"locality"
},
  "geometry": {"coordinates":[14.85643,12.26698],"type":"Point"}
}