{
  "type": "Feature",
  "properties": {
    "gn:admin1_code":"12.0",
    "gn:asciiname":"Golombere",
    "gn:country_code":"CM",
    "gn:dem":320,
    "gn:feature_class":"P",
    "gn:feature_code":"PPL",
    "gn:name":"Golomb\u00e9r\u00e9",
    "gn:population":0,
    "gn:timezone":"Africa/Douala",
    "iso:country":"CM",
    "wof:name":"Golombere",
    "wof:placetype":"locality"
},
  "geometry": {"coordinates":[14.76941,10.74989],"type":"Point"}
}