{
  "type": "Feature",
  "properties": {
    "gn:admin1_code":"13.0",
    "gn:asciiname":"Ouro Labare",
    "gn:country_code":"CM",
    "gn:dem":211,
    "gn:feature_class":"P",
    "gn:feature_code":"PPL",
    "gn:name":"Ouro Labar\u00e9",
    "gn:population":0,
    "gn:timezone":"Africa/Douala",
    "iso:country":"CM",
    "name:und_x_variant":[
        "Labar\u00e9",
        "Ouro Labar\u00e9"
    ],
    "wof:name":"Ouro Labare",
    "wof:placetype":"locality"
},
  "geometry": {"coordinates":[13.83373,9.40183],"type":"Point"}
}