{
  "type": "Feature",
  "properties": {
    "gn:admin1_code":"5.0",
    "gn:asciiname":"Nsapak",
    "gn:country_code":"CM",
    "gn:dem":496,
    "gn:feature_class":"P",
    "gn:feature_code":"PPL",
    "gn:name":"Nsapak",
    "gn:population":0,
    "gn:timezone":"Africa/Douala",
    "iso:country":"CM",
    "wof:name":"Nsapak",
    "wof:placetype":"locality"
},
  "geometry": {"coordinates":[10.65,4.23333],"type":"Point"}
}