{
  "type": "Feature",
  "properties": {
    "gn:admin1_code":"13.0",
    "gn:asciiname":"Sadouya",
    "gn:country_code":"CM",
    "gn:dem":221,
    "gn:feature_class":"P",
    "gn:feature_code":"PPL",
    "gn:name":"Sadouya",
    "gn:population":0,
    "gn:timezone":"Africa/Douala",
    "iso:country":"CM",
    "wof:name":"Sadouya",
    "wof:placetype":"locality"
},
  "geometry": {"coordinates":[13.97255,8.71827],"type":"Point"}
}