{
  "type": "Feature",
  "properties": {
    "gn:admin1_code":"13.0",
    "gn:asciiname":"Riwango",
    "gn:country_code":"CM",
    "gn:dem":200,
    "gn:feature_class":"P",
    "gn:feature_code":"PPL",
    "gn:name":"Riwango",
    "gn:population":0,
    "gn:timezone":"Africa/Douala",
    "iso:country":"CM",
    "wof:name":"Riwango",
    "wof:placetype":"locality"
},
  "geometry": {"coordinates":[13.74749,9.35567],"type":"Point"}
}