{
  "type": "Feature",
  "properties": {
    "gn:admin1_code":"8.0",
    "gn:asciiname":"Fotsouli",
    "gn:country_code":"CM",
    "gn:dem":1420,
    "gn:feature_class":"P",
    "gn:feature_code":"PPL",
    "gn:name":"Fotsouli",
    "gn:population":0,
    "gn:timezone":"Africa/Douala",
    "iso:country":"CM",
    "name:fra_x_preferred":[
        "Fotsouli"
    ],
    "wof:name":"Fotsouli",
    "wof:placetype":"locality"
},
  "geometry": {"coordinates":[10.00513,5.44699],"type":"Point"}
}