{
  "type": "Feature",
  "properties": {
    "gn:admin1_code":"5.0",
    "gn:asciiname":"Ndoutou",
    "gn:country_code":"CM",
    "gn:dem":346,
    "gn:feature_class":"P",
    "gn:feature_code":"PPL",
    "gn:name":"Ndoutou",
    "gn:population":0,
    "gn:timezone":"Africa/Douala",
    "iso:country":"CM",
    "wof:name":"Ndoutou",
    "wof:placetype":"locality"
},
  "geometry": {"coordinates":[10.36254,5.01119],"type":"Point"}
}