{
  "type": "Feature",
  "properties": {
    "gn:admin1_code":"9.0",
    "gn:asciiname":"Mosie",
    "gn:country_code":"CM",
    "gn:dem":286,
    "gn:feature_class":"P",
    "gn:feature_code":"PPL",
    "gn:name":"Mosie",
    "gn:population":0,
    "gn:timezone":"Africa/Douala",
    "iso:country":"CM",
    "wof:name":"Mosie",
    "wof:placetype":"locality"
},
  "geometry": {"coordinates":[9.74,5.7397],"type":"Point"}
}