{
  "type": "Feature",
  "properties": {
    "gn:admin1_code":"9.0",
    "gn:asciiname":"Konye",
    "gn:country_code":"CM",
    "gn:dem":262,
    "gn:feature_class":"P",
    "gn:feature_code":"PPL",
    "gn:name":"Konye",
    "gn:population":0,
    "gn:timezone":"Africa/Douala",
    "iso:country":"CM",
    "name:cat_x_preferred":[
        "Konia eisentrauti"
    ],
    "name:ceb_x_preferred":[
        "Konia eisentrauti"
    ],
    "name:eus_x_preferred":[
        "Konia eisentrauti"
    ],
    "name:fra_x_preferred":[
        "Konia eisentrauti"
    ],
    "name:nld_x_preferred":[
        "Konia eisentrauti"
    ],
    "name:por_x_preferred":[
        "Konia eisentrauti"
    ],
    "name:spa_x_preferred":[
        "Konia eisentrauti"
    ],
    "name:srp_x_preferred":[
        "Konia eisentrauti"
    ],
    "name:swe_x_preferred":[
        "Konia eisentrauti"
    ],
    "name:und_x_variant":[
        "Konje",
        "Konye"
    ],
    "name:vie_x_preferred":[
        "Konia eisentrauti"
    ],
    "name:war_x_preferred":[
        "Konia eisentrauti"
    ],
    "name:zho_x_preferred":[
        "\u57c3\u6c0f\u5eb7\u5c3c\u9e97\u9b5a"
    ],
    "wof:name":"Konye",
    "wof:placetype":"locality"
},
  "geometry": {"coordinates":[9.4768,4.9371],"type":"Point"}
}