{
  "type": "Feature",
  "properties": {
    "gn:admin1_code":"9.0",
    "gn:asciiname":"Konye",
    "gn:country_code":"CM",
    "gn:dem":262,
    "gn:feature_class":"P",
    "gn:feature_code":"PPL",
    "gn:name":"Konye",
    "gn:population":0,
    "gn:timezone":"Africa/Douala",
    "iso:country":"CM",
    "name:und_x_variant":[
        "Konje",
        "Konye"
    ],
    "wof:name":"Konye",
    "wof:placetype":"locality"
},
  "geometry": {"coordinates":[9.4768,4.9371],"type":"Point"}
}