{
  "type": "Feature",
  "properties": {
    "gn:admin1_code":"11.0",
    "gn:asciiname":"Ndoumba",
    "gn:country_code":"CM",
    "gn:dem":591,
    "gn:feature_class":"P",
    "gn:feature_code":"PPL",
    "gn:name":"Ndoumba",
    "gn:population":0,
    "gn:timezone":"Africa/Douala",
    "iso:country":"CM",
    "wof:name":"Ndoumba",
    "wof:placetype":"locality"
},
  "geometry": {"coordinates":[12.76667,4.98333],"type":"Point"}
}