{
  "type": "Feature",
  "properties": {
    "gn:admin1_code":"8.0",
    "gn:asciiname":"Kopking",
    "gn:country_code":"CM",
    "gn:dem":1426,
    "gn:feature_class":"P",
    "gn:feature_code":"PPL",
    "gn:name":"Kopking",
    "gn:population":0,
    "gn:timezone":"Africa/Douala",
    "iso:country":"CM",
    "wof:name":"Kopking",
    "wof:placetype":"locality"
},
  "geometry": {"coordinates":[10.50243,5.09351],"type":"Point"}
}