{
  "type": "Feature",
  "properties": {
    "gn:admin1_code":"10.0",
    "gn:asciiname":"Doualayel",
    "gn:country_code":"CM",
    "gn:dem":1084,
    "gn:feature_class":"P",
    "gn:feature_code":"PPL",
    "gn:name":"Doualayel",
    "gn:population":0,
    "gn:timezone":"Africa/Douala",
    "iso:country":"CM",
    "name:und_x_variant":[
        "Petit Douala",
        "Douala",
        "Doualayel"
    ],
    "wof:name":"Doualayel",
    "wof:placetype":"locality"
},
  "geometry": {"coordinates":[12.66667,7.01667],"type":"Point"}
}