{
  "type": "Feature",
  "properties": {
    "gn:admin1_code":"12.0",
    "gn:asciiname":"Moudawa",
    "gn:country_code":"CM",
    "gn:dem":478,
    "gn:feature_class":"P",
    "gn:feature_code":"PPL",
    "gn:name":"Moudawa",
    "gn:population":0,
    "gn:timezone":"Africa/Douala",
    "iso:country":"CM",
    "wof:name":"Moudawa",
    "wof:placetype":"locality"
},
  "geometry": {"coordinates":[14.19594,10.3539],"type":"Point"}
}