{
  "type": "Feature",
  "properties": {
    "gn:admin1_code":"5.0",
    "gn:asciiname":"Pendjok",
    "gn:country_code":"CM",
    "gn:dem":377,
    "gn:feature_class":"P",
    "gn:feature_code":"PPL",
    "gn:name":"Pendjok",
    "gn:population":0,
    "gn:timezone":"Africa/Douala",
    "iso:country":"CM",
    "wof:name":"Pendjok",
    "wof:placetype":"locality"
},
  "geometry": {"coordinates":[10.73333,4.11667],"type":"Point"}
}