{
  "type": "Feature",
  "properties": {
    "gn:admin1_code":"11.0",
    "gn:asciiname":"Ezezang",
    "gn:country_code":"CM",
    "gn:dem":751,
    "gn:feature_class":"P",
    "gn:feature_code":"PPL",
    "gn:name":"\u00c9z\u00e9zang",
    "gn:population":0,
    "gn:timezone":"Africa/Douala",
    "iso:country":"CM",
    "wof:name":"Ezezang",
    "wof:placetype":"locality"
},
  "geometry": {"coordinates":[11.48333,4.03333],"type":"Point"}
}