{
  "type": "Feature",
  "properties": {
    "gn:admin1_code":"13.0",
    "gn:asciiname":"Tongo",
    "gn:country_code":"CM",
    "gn:dem":304,
    "gn:feature_class":"P",
    "gn:feature_code":"PPL",
    "gn:name":"Tongo",
    "gn:population":0,
    "gn:timezone":"Africa/Douala",
    "iso:country":"CM",
    "wof:name":"Tongo",
    "wof:placetype":"locality"
},
  "geometry": {"coordinates":[13.51012,8.91837],"type":"Point"}
}