{
  "type": "Feature",
  "properties": {
    "gn:admin1_code":"13.0",
    "gn:asciiname":"Dembare",
    "gn:country_code":"CM",
    "gn:dem":382,
    "gn:feature_class":"P",
    "gn:feature_code":"PPL",
    "gn:name":"Dembar\u00e9",
    "gn:population":0,
    "gn:timezone":"Africa/Douala",
    "iso:country":"CM",
    "wof:name":"Dembare",
    "wof:placetype":"locality"
},
  "geometry": {"coordinates":[13.52339,8.547],"type":"Point"}
}