{
  "type": "Feature",
  "properties": {
    "gn:admin1_code":"8.0",
    "gn:asciiname":"La'tchie",
    "gn:country_code":"CM",
    "gn:dem":1462,
    "gn:feature_class":"P",
    "gn:feature_code":"PPL",
    "gn:name":"La\u2019tchi\u00e9",
    "gn:population":0,
    "gn:timezone":"Africa/Douala",
    "iso:country":"CM",
    "wof:name":"La'tchie",
    "wof:placetype":"locality"
},
  "geometry": {"coordinates":[10.32248,5.48557],"type":"Point"}
}