{
  "type": "Feature",
  "properties": {
    "gn:admin1_code":"9.0",
    "gn:asciiname":"Muanjekan",
    "gn:country_code":"CM",
    "gn:dem":1365,
    "gn:feature_class":"P",
    "gn:feature_code":"PPL",
    "gn:name":"Muanjekan",
    "gn:population":0,
    "gn:timezone":"Africa/Douala",
    "iso:country":"CM",
    "name:und_x_variant":[
        "Mang\u00e9kam",
        "Muanjekan"
    ],
    "wof:name":"Muanjekan",
    "wof:placetype":"locality"
},
  "geometry": {"coordinates":[9.7801,5.15275],"type":"Point"}
}