{
  "type": "Feature",
  "properties": {
    "gn:admin1_code":"13.0",
    "gn:asciiname":"Gor",
    "gn:country_code":"CM",
    "gn:dem":472,
    "gn:feature_class":"P",
    "gn:feature_code":"PPL",
    "gn:name":"Gor",
    "gn:population":0,
    "gn:timezone":"Africa/Douala",
    "iso:country":"CM",
    "name:nld_x_preferred":[
        "Gor"
    ],
    "name:ron_x_preferred":[
        "Gor"
    ],
    "name:rus_x_preferred":[
        "\u0413\u043e\u0440"
    ],
    "name:tur_x_preferred":[
        "Gor"
    ],
    "name:ukr_x_preferred":[
        "\u0413\u043e\u0440"
    ],
    "name:zho_x_preferred":[
        "Gor"
    ],
    "wof:name":"Gor",
    "wof:placetype":"locality"
},
  "geometry": {"coordinates":[14.9972,8.6417],"type":"Point"}
}