{
  "type": "Feature",
  "properties": {
    "gn:admin1_code":"5.0",
    "gn:asciiname":"Ndobeginge",
    "gn:country_code":"CM",
    "gn:dem":107,
    "gn:feature_class":"P",
    "gn:feature_code":"PPL",
    "gn:name":"Ndob\u00e9ging\u00e9",
    "gn:population":0,
    "gn:timezone":"Africa/Douala",
    "iso:country":"CM",
    "name:und_x_variant":[
        "Ndob\u00e9gu\u00e9ngue II",
        "Ndogobangu\u00e9",
        "Ndob\u00e9gu\u00e9ngu\u00e9",
        "Ndob\u00e9ging\u00e9"
    ],
    "wof:name":"Ndobeginge",
    "wof:placetype":"locality"
},
  "geometry": {"coordinates":[10.13333,4.35],"type":"Point"}
}