{
  "type": "Feature",
  "properties": {
    "gn:admin1_code":"12.0",
    "gn:asciiname":"Soukoungo Mandarao",
    "gn:country_code":"CM",
    "gn:dem":369,
    "gn:feature_class":"P",
    "gn:feature_code":"PPL",
    "gn:name":"Soukoungo Mandarao",
    "gn:population":0,
    "gn:timezone":"Africa/Douala",
    "iso:country":"CM",
    "wof:name":"Soukoungo Mandarao",
    "wof:placetype":"locality"
},
  "geometry": {"coordinates":[14.33333,10.86667],"type":"Point"}
}