{
  "type": "Feature",
  "properties": {
    "gn:admin1_code":"12.0",
    "gn:asciiname":"Dagueum",
    "gn:country_code":"CM",
    "gn:dem":308,
    "gn:feature_class":"P",
    "gn:feature_code":"PPL",
    "gn:name":"Dagueum",
    "gn:population":0,
    "gn:timezone":"Africa/Douala",
    "iso:country":"CM",
    "name:und_x_variant":[
        "Daguen",
        "Dagueum"
    ],
    "wof:name":"Dagueum",
    "wof:placetype":"locality"
},
  "geometry": {"coordinates":[14.9529,11.26028],"type":"Point"}
}