{
  "type": "Feature",
  "properties": {
    "gn:admin1_code":"8.0",
    "gn:asciiname":"Balaangwen",
    "gn:country_code":"CM",
    "gn:dem":1294,
    "gn:feature_class":"P",
    "gn:feature_code":"PPL",
    "gn:name":"Balaangw\u00e9n",
    "gn:population":0,
    "gn:timezone":"Africa/Douala",
    "iso:country":"CM",
    "wof:name":"Balaangwen",
    "wof:placetype":"locality"
},
  "geometry": {"coordinates":[10.37721,5.55388],"type":"Point"}
}