{
  "type": "Feature",
  "properties": {
    "gn:admin1_code":"9.0",
    "gn:asciiname":"Mbule",
    "gn:country_code":"CM",
    "gn:dem":773,
    "gn:feature_class":"P",
    "gn:feature_code":"PPL",
    "gn:name":"Mbule",
    "gn:population":0,
    "gn:timezone":"Africa/Douala",
    "iso:country":"CM",
    "name:fra_x_preferred":[
        "Mbule"
    ],
    "wof:name":"Mbule",
    "wof:placetype":"locality"
},
  "geometry": {"coordinates":[9.6687,4.8039],"type":"Point"}
}