{
  "type": "Feature",
  "properties": {
    "gn:admin1_code":"9.0",
    "gn:asciiname":"Bakundu Foe",
    "gn:country_code":"CM",
    "gn:dem":78,
    "gn:feature_class":"P",
    "gn:feature_code":"PPL",
    "gn:name":"Bakundu Foe",
    "gn:population":0,
    "gn:timezone":"Africa/Douala",
    "iso:country":"CM",
    "wof:name":"Bakundu Foe",
    "wof:placetype":"locality"
},
  "geometry": {"coordinates":[9.2235,4.4721],"type":"Point"}
}