{
  "type": "Feature",
  "properties": {
    "gn:admin1_code":"12.0",
    "gn:asciiname":"Mada",
    "gn:country_code":"CM",
    "gn:dem":301,
    "gn:feature_class":"P",
    "gn:feature_code":"PPL",
    "gn:name":"Mada",
    "gn:population":0,
    "gn:timezone":"Africa/Douala",
    "iso:country":"CM",
    "wof:name":"Mada",
    "wof:placetype":"locality"
},
  "geometry": {"coordinates":[14.73861,11.54556],"type":"Point"}
}