{
  "type": "Feature",
  "properties": {
    "gn:admin1_code":"9.0",
    "gn:asciiname":"Baduma",
    "gn:country_code":"CM",
    "gn:dem":252,
    "gn:feature_class":"P",
    "gn:feature_code":"PPL",
    "gn:name":"Baduma",
    "gn:population":0,
    "gn:timezone":"Africa/Douala",
    "iso:country":"CM",
    "wof:name":"Baduma",
    "wof:placetype":"locality"
},
  "geometry": {"coordinates":[9.45873,4.83137],"type":"Point"}
}