{
  "type": "Feature",
  "properties": {
    "gn:admin1_code":"8.0",
    "gn:asciiname":"Kouba",
    "gn:country_code":"CM",
    "gn:dem":1104,
    "gn:feature_class":"P",
    "gn:feature_code":"PPL",
    "gn:name":"Kouba",
    "gn:population":0,
    "gn:timezone":"Africa/Douala",
    "iso:country":"CM",
    "name:ceb_x_preferred":[
        "Kouba"
    ],
    "name:ces_x_preferred":[
        "Kouba"
    ],
    "name:deu_x_preferred":[
        "Kouba"
    ],
    "name:fra_x_preferred":[
        "Kouba"
    ],
    "name:msa_x_preferred":[
        "Kouba"
    ],
    "name:rus_x_preferred":[
        "\u041a\u043e\u0443\u0431\u0430"
    ],
    "name:slk_x_preferred":[
        "Kouba"
    ],
    "name:swe_x_preferred":[
        "Kouba"
    ],
    "wof:name":"Kouba",
    "wof:placetype":"locality"
},
  "geometry": {"coordinates":[10.48596,5.00503],"type":"Point"}
}