{
  "type": "Feature",
  "properties": {
    "gn:admin1_code":"13.0",
    "gn:asciiname":"Mayo Alim",
    "gn:country_code":"CM",
    "gn:dem":454,
    "gn:feature_class":"P",
    "gn:feature_code":"PPL",
    "gn:name":"Mayo Alim",
    "gn:population":0,
    "gn:timezone":"Africa/Douala",
    "iso:country":"CM",
    "wof:name":"Mayo Alim",
    "wof:placetype":"locality"
},
  "geometry": {"coordinates":[13.60858,8.04701],"type":"Point"}
}