{
  "type": "Feature",
  "properties": {
    "gn:admin1_code":"14.0",
    "gn:asciiname":"Nyabibete",
    "gn:country_code":"CM",
    "gn:dem":664,
    "gn:feature_class":"P",
    "gn:feature_code":"PPL",
    "gn:name":"Nyabib\u00e9t\u00e9",
    "gn:population":0,
    "gn:timezone":"Africa/Douala",
    "iso:country":"CM",
    "wof:name":"Nyabibete",
    "wof:placetype":"locality"
},
  "geometry": {"coordinates":[12.56667,2.76667],"type":"Point"}
}