{
  "type": "Feature",
  "properties": {
    "gn:admin1_code":"13.0",
    "gn:asciiname":"Bessoum",
    "gn:country_code":"CM",
    "gn:dem":250,
    "gn:feature_class":"P",
    "gn:feature_code":"PPL",
    "gn:name":"Bessoum",
    "gn:population":0,
    "gn:timezone":"Africa/Douala",
    "iso:country":"CM",
    "wof:name":"Bessoum",
    "wof:placetype":"locality"
},
  "geometry": {"coordinates":[13.88248,9.54582],"type":"Point"}
}