{
  "type": "Feature",
  "properties": {
    "gn:admin1_code":"8.0",
    "gn:asciiname":"Foto",
    "gn:country_code":"CM",
    "gn:dem":1450,
    "gn:feature_class":"P",
    "gn:feature_code":"PPL",
    "gn:name":"Foto",
    "gn:population":0,
    "gn:timezone":"Africa/Douala",
    "iso:country":"CM",
    "name:fra_x_preferred":[
        "Foto"
    ],
    "name:fra_x_variant":[
        "Photo"
    ],
    "name:por_x_preferred":[
        "Foto"
    ],
    "wof:name":"Foto",
    "wof:placetype":"locality"
},
  "geometry": {"coordinates":[10.07251,5.46459],"type":"Point"}
}