{
  "type": "Feature",
  "properties": {
    "gn:admin1_code":"11.0",
    "gn:asciiname":"Koum",
    "gn:country_code":"CM",
    "gn:dem":676,
    "gn:feature_class":"P",
    "gn:feature_code":"PPL",
    "gn:name":"Koum",
    "gn:population":0,
    "gn:timezone":"Africa/Douala",
    "iso:country":"CM",
    "wof:name":"Koum",
    "wof:placetype":"locality"
},
  "geometry": {"coordinates":[12.23333,3.66667],"type":"Point"}
}