{
  "type": "Feature",
  "properties": {
    "gn:admin1_code":"13.0",
    "gn:asciiname":"Bigalere",
    "gn:country_code":"CM",
    "gn:dem":747,
    "gn:feature_class":"P",
    "gn:feature_code":"PPL",
    "gn:name":"Bigal\u00e9re",
    "gn:population":0,
    "gn:timezone":"Africa/Douala",
    "iso:country":"CM",
    "wof:name":"Bigalere",
    "wof:placetype":"locality"
},
  "geometry": {"coordinates":[14.95,8.38333],"type":"Point"}
}