{
  "type": "Feature",
  "properties": {
    "gn:admin1_code":"9.0",
    "gn:asciiname":"Ekok",
    "gn:country_code":"CM",
    "gn:dem":78,
    "gn:feature_class":"P",
    "gn:feature_code":"PPL",
    "gn:name":"Ekok",
    "gn:population":0,
    "gn:timezone":"Africa/Douala",
    "iso:country":"CM",
    "name:und_x_variant":[
        "Ekor",
        "Ekok"
    ],
    "wof:name":"Ekok",
    "wof:placetype":"locality"
},
  "geometry": {"coordinates":[8.85657,5.80696],"type":"Point"}
}