{
  "type": "Feature",
  "properties": {
    "gn:admin1_code":"11.0",
    "gn:asciiname":"Nkong",
    "gn:country_code":"CM",
    "gn:dem":411,
    "gn:feature_class":"P",
    "gn:feature_code":"PPL",
    "gn:name":"Nkong",
    "gn:population":0,
    "gn:timezone":"Africa/Douala",
    "iso:country":"CM",
    "wof:name":"Nkong",
    "wof:placetype":"locality"
},
  "geometry": {"coordinates":[11.06667,4.15],"type":"Point"}
}