{
  "type": "Feature",
  "properties": {
    "gn:admin1_code":"4.0",
    "gn:asciiname":"Ngato",
    "gn:country_code":"CM",
    "gn:dem":526,
    "gn:feature_class":"P",
    "gn:feature_code":"PPL",
    "gn:name":"Ngato",
    "gn:population":0,
    "gn:timezone":"Africa/Douala",
    "iso:country":"CM",
    "wof:name":"Ngato",
    "wof:placetype":"locality"
},
  "geometry": {"coordinates":[14.96667,3.25],"type":"Point"}
}