{
  "type": "Feature",
  "properties": {
    "gn:admin1_code":"8.0",
    "gn:asciiname":"Menouet",
    "gn:country_code":"CM",
    "gn:dem":1336,
    "gn:feature_class":"P",
    "gn:feature_code":"PPL",
    "gn:name":"Menouet",
    "gn:population":0,
    "gn:timezone":"Africa/Douala",
    "iso:country":"CM",
    "wof:name":"Menouet",
    "wof:placetype":"locality"
},
  "geometry": {"coordinates":[10.03932,5.44604],"type":"Point"}
}