{
  "type": "Feature",
  "properties": {
    "gn:admin1_code":"7.0",
    "gn:asciiname":"Batadji",
    "gn:country_code":"CM",
    "gn:dem":707,
    "gn:feature_class":"P",
    "gn:feature_code":"PPL",
    "gn:name":"Batadji",
    "gn:population":0,
    "gn:timezone":"Africa/Douala",
    "iso:country":"CM",
    "wof:name":"Batadji",
    "wof:placetype":"locality"
},
  "geometry": {"coordinates":[9.8628,6.2309],"type":"Point"}
}