{
  "type": "Feature",
  "properties": {
    "gn:admin1_code":"9.0",
    "gn:asciiname":"Mosongosele Ngolo",
    "gn:country_code":"CM",
    "gn:dem":51,
    "gn:feature_class":"P",
    "gn:feature_code":"PPL",
    "gn:name":"Mosongosele Ngolo",
    "gn:population":0,
    "gn:timezone":"Africa/Douala",
    "iso:country":"CM",
    "wof:name":"Mosongosele Ngolo",
    "wof:placetype":"locality"
},
  "geometry": {"coordinates":[8.9712,4.7992],"type":"Point"}
}