{
  "type": "Feature",
  "properties": {
    "gn:admin1_code":"10.0",
    "gn:asciiname":"Makouladje",
    "gn:country_code":"CM",
    "gn:dem":1011,
    "gn:feature_class":"P",
    "gn:feature_code":"PPL",
    "gn:name":"Makouladj\u00e9",
    "gn:population":0,
    "gn:timezone":"Africa/Douala",
    "iso:country":"CM",
    "wof:name":"Makouladje",
    "wof:placetype":"locality"
},
  "geometry": {"coordinates":[12.18168,6.98851],"type":"Point"}
}