{
  "type": "Feature",
  "properties": {
    "gn:admin1_code":"10.0",
    "gn:asciiname":"Mbale",
    "gn:country_code":"CM",
    "gn:dem":964,
    "gn:feature_class":"P",
    "gn:feature_code":"PPL",
    "gn:name":"Mbal\u00e9",
    "gn:population":0,
    "gn:timezone":"Africa/Douala",
    "iso:country":"CM",
    "name:und_x_variant":[
        "Mbali",
        "Mbal\u00e9"
    ],
    "wof:name":"Mbale",
    "wof:placetype":"locality"
},
  "geometry": {"coordinates":[14.38333,6.15],"type":"Point"}
}