{
  "type": "Feature",
  "properties": {
    "gn:admin1_code":"12.0",
    "gn:asciiname":"Djiguilim",
    "gn:country_code":"CM",
    "gn:dem":457,
    "gn:feature_class":"P",
    "gn:feature_code":"PPL",
    "gn:name":"Djiguilim",
    "gn:population":0,
    "gn:timezone":"Africa/Douala",
    "iso:country":"CM",
    "wof:name":"Djiguilim",
    "wof:placetype":"locality"
},
  "geometry": {"coordinates":[14.11789,10.3807],"type":"Point"}
}