{
  "type": "Feature",
  "properties": {
    "gn:admin1_code":"5.0",
    "gn:asciiname":"Okola",
    "gn:country_code":"CM",
    "gn:dem":28,
    "gn:feature_class":"P",
    "gn:feature_code":"PPL",
    "gn:name":"Okola",
    "gn:population":0,
    "gn:timezone":"Africa/Douala",
    "iso:country":"CM",
    "wof:name":"Okola",
    "wof:placetype":"locality"
},
  "geometry": {"coordinates":[9.81639,3.64056],"type":"Point"}
}