{
  "type": "Feature",
  "properties": {
    "gn:admin1_code":"9.0",
    "gn:asciiname":"Bai Kuke",
    "gn:country_code":"CM",
    "gn:dem":58,
    "gn:feature_class":"P",
    "gn:feature_code":"PPL",
    "gn:name":"Bai Kuke",
    "gn:population":0,
    "gn:timezone":"Africa/Douala",
    "iso:country":"CM",
    "wof:name":"Bai Kuke",
    "wof:placetype":"locality"
},
  "geometry": {"coordinates":[9.1449,4.4589],"type":"Point"}
}