{
  "type": "Feature",
  "properties": {
    "gn:admin1_code":"9.0",
    "gn:asciiname":"Mussaka Village",
    "gn:country_code":"CM",
    "gn:dem":506,
    "gn:feature_class":"P",
    "gn:feature_code":"PPL",
    "gn:name":"Mussaka Village",
    "gn:population":0,
    "gn:timezone":"Africa/Douala",
    "iso:country":"CM",
    "wof:name":"Mussaka Village",
    "wof:placetype":"locality"
},
  "geometry": {"coordinates":[9.3317,4.1757],"type":"Point"}
}