{
  "type": "Feature",
  "properties": {
    "gn:admin1_code":"12.0",
    "gn:asciiname":"Djebrili",
    "gn:country_code":"CM",
    "gn:dem":439,
    "gn:feature_class":"P",
    "gn:feature_code":"PPL",
    "gn:name":"Dj\u00e9brili",
    "gn:population":0,
    "gn:timezone":"Africa/Douala",
    "iso:country":"CM",
    "wof:name":"Djebrili",
    "wof:placetype":"locality"
},
  "geometry": {"coordinates":[13.85365,11.08919],"type":"Point"}
}