{
  "type": "Feature",
  "properties": {
    "gn:admin1_code":"13.0",
    "gn:asciiname":"Ndili",
    "gn:country_code":"CM",
    "gn:dem":492,
    "gn:feature_class":"P",
    "gn:feature_code":"PPL",
    "gn:name":"Ndili",
    "gn:population":0,
    "gn:timezone":"Africa/Douala",
    "iso:country":"CM",
    "name:und_x_variant":[
        "Ndoula",
        "Ndili"
    ],
    "wof:name":"Ndili",
    "wof:placetype":"locality"
},
  "geometry": {"coordinates":[13.64567,10.00594],"type":"Point"}
}