{
  "type": "Feature",
  "properties": {
    "gn:admin1_code":"4.0",
    "gn:asciiname":"Nzinbele",
    "gn:country_code":"CM",
    "gn:dem":682,
    "gn:feature_class":"P",
    "gn:feature_code":"PPL",
    "gn:name":"Nzinb\u00e9l\u00e9",
    "gn:population":0,
    "gn:timezone":"Africa/Douala",
    "iso:country":"CM",
    "wof:name":"Nzinbele",
    "wof:placetype":"locality"
},
  "geometry": {"coordinates":[14.18333,4.38333],"type":"Point"}
}