{
  "type": "Feature",
  "properties": {
    "gn:admin1_code":"12.0",
    "gn:asciiname":"Taram",
    "gn:country_code":"CM",
    "gn:dem":325,
    "gn:feature_class":"P",
    "gn:feature_code":"PPL",
    "gn:name":"Taram",
    "gn:population":0,
    "gn:timezone":"Africa/Douala",
    "iso:country":"CM",
    "wof:name":"Taram",
    "wof:placetype":"locality"
},
  "geometry": {"coordinates":[14.77121,10.71403],"type":"Point"}
}