{
  "type": "Feature",
  "properties": {
    "gn:admin1_code":"8.0",
    "gn:asciiname":"Nguie",
    "gn:country_code":"CM",
    "gn:dem":1454,
    "gn:feature_class":"P",
    "gn:feature_code":"PPL",
    "gn:name":"Ngui\u00e9",
    "gn:population":0,
    "gn:timezone":"Africa/Douala",
    "iso:country":"CM",
    "wof:name":"Nguie",
    "wof:placetype":"locality"
},
  "geometry": {"coordinates":[10.21998,5.54469],"type":"Point"}
}