{
  "type": "Feature",
  "properties": {
    "gn:admin1_code":"12.0",
    "gn:asciiname":"Hamadou",
    "gn:country_code":"CM",
    "gn:dem":304,
    "gn:feature_class":"P",
    "gn:feature_code":"PPL",
    "gn:name":"Hamadou",
    "gn:population":0,
    "gn:timezone":"Africa/Douala",
    "iso:country":"CM",
    "name:und_x_variant":[
        "Amadou",
        "Hamadou"
    ],
    "wof:name":"Hamadou",
    "wof:placetype":"locality"
},
  "geometry": {"coordinates":[15.04114,11.43394],"type":"Point"}
}