{
  "type": "Feature",
  "properties": {
    "gn:admin1_code":"12.0",
    "gn:asciiname":"Gartchono",
    "gn:country_code":"CM",
    "gn:dem":294,
    "gn:feature_class":"P",
    "gn:feature_code":"PPL",
    "gn:name":"Gartchono",
    "gn:population":0,
    "gn:timezone":"Africa/Douala",
    "iso:country":"CM",
    "name:und_x_variant":[
        "Gortchonou",
        "Gartchono"
    ],
    "wof:name":"Gartchono",
    "wof:placetype":"locality"
},
  "geometry": {"coordinates":[14.59502,12.29182],"type":"Point"}
}