{
  "type": "Feature",
  "properties": {
    "gn:admin1_code":"12.0",
    "gn:asciiname":"Guech",
    "gn:country_code":"CM",
    "gn:dem":303,
    "gn:feature_class":"P",
    "gn:feature_code":"PPL",
    "gn:name":"Guech",
    "gn:population":0,
    "gn:timezone":"Africa/Douala",
    "iso:country":"CM",
    "name:und_x_variant":[
        "Guesch",
        "Guech"
    ],
    "wof:name":"Guech",
    "wof:placetype":"locality"
},
  "geometry": {"coordinates":[14.95569,11.4864],"type":"Point"}
}