{
  "type": "Feature",
  "properties": {
    "gn:admin1_code":"11.0",
    "gn:asciiname":"Koengboe",
    "gn:country_code":"CM",
    "gn:dem":754,
    "gn:feature_class":"P",
    "gn:feature_code":"PPL",
    "gn:name":"Koengbo\u00e9",
    "gn:population":0,
    "gn:timezone":"Africa/Douala",
    "iso:country":"CM",
    "wof:name":"Koengboe",
    "wof:placetype":"locality"
},
  "geometry": {"coordinates":[11.63333,5.46667],"type":"Point"}
}