{
  "type": "Feature",
  "properties": {
    "gn:admin1_code":"14.0",
    "gn:asciiname":"Ebodie",
    "gn:country_code":"CM",
    "gn:dem":40,
    "gn:feature_class":"P",
    "gn:feature_code":"PPL",
    "gn:name":"Ebodi\u00e9",
    "gn:population":0,
    "gn:timezone":"Africa/Douala",
    "iso:country":"CM",
    "wof:name":"Ebodie",
    "wof:placetype":"locality"
},
  "geometry": {"coordinates":[9.83333,2.56667],"type":"Point"}
}