{
  "type": "Feature",
  "properties": {
    "gn:admin1_code":"13.0",
    "gn:asciiname":"Bouissa",
    "gn:country_code":"CM",
    "gn:dem":726,
    "gn:feature_class":"P",
    "gn:feature_code":"PPL",
    "gn:name":"Bouissa",
    "gn:population":0,
    "gn:timezone":"Africa/Douala",
    "iso:country":"CM",
    "wof:name":"Bouissa",
    "wof:placetype":"locality"
},
  "geometry": {"coordinates":[15.2117,7.3096],"type":"Point"}
}