{
  "type": "Feature",
  "properties": {
    "gn:admin1_code":"8.0",
    "gn:asciiname":"Bakoga",
    "gn:country_code":"CM",
    "gn:dem":1299,
    "gn:feature_class":"P",
    "gn:feature_code":"PPL",
    "gn:name":"Bakoga",
    "gn:population":0,
    "gn:timezone":"Africa/Douala",
    "iso:country":"CM",
    "wof:name":"Bakoga",
    "wof:placetype":"locality"
},
  "geometry": {"coordinates":[10.29958,5.63228],"type":"Point"}
}