{
  "type": "Feature",
  "properties": {
    "iso:country":"CM",
    "name:ceb_x_preferred":[
        "Loum"
    ],
    "name:ces_x_preferred":[
        "Loum"
    ],
    "name:deu_x_preferred":[
        "Loum"
    ],
    "name:eng_x_preferred":[
        "Loum"
    ],
    "name:epo_x_preferred":[
        "Loum"
    ],
    "name:fin_x_preferred":[
        "Loum"
    ],
    "name:fra_x_preferred":[
        "Loum"
    ],
    "name:hun_x_preferred":[
        "Loum"
    ],
    "name:ita_x_preferred":[
        "Loum"
    ],
    "name:msa_x_preferred":[
        "Loum"
    ],
    "name:nan_x_preferred":[
        "Loum"
    ],
    "name:nld_x_preferred":[
        "Loum"
    ],
    "name:pol_x_preferred":[
        "Loum"
    ],
    "name:por_x_preferred":[
        "Loum"
    ],
    "name:ron_x_preferred":[
        "Loum"
    ],
    "name:rus_x_preferred":[
        "\u041b\u0443\u043c"
    ],
    "name:swe_x_preferred":[
        "Loum"
    ],
    "name:unk_x_variant":[
        "Lum"
    ],
    "name:war_x_preferred":[
        "Loum"
    ],
    "name:zho_x_preferred":[
        "\u76e7\u59c6"
    ],
    "qs:gn_country":"CM",
    "qs:gn_fcode":"PPL",
    "qs:gn_pop":177429,
    "qs:name":"Loum",
    "qs:name_adm0":"Cameroun",
    "qs:name_adm1":"Littoral",
    "qs:photos":0,
    "qs:photos_1k":0,
    "qs:photos_9k":1,
    "qs:photos_9r":1,
    "qs:photos_all":3,
    "qs:photos_sr":0,
    "qs:placetype":"Town",
    "qs:pop_sr":"9",
    "qs:woe_adm0":23424785,
    "wd:wordcount":37,
    "wof:name":"Loum",
    "wof:placetype":"locality",
    "wof:population":177429
},
  "geometry": {"coordinates":[9.7351,4.7182],"type":"Point"}
}