{
  "type": "Feature",
  "properties": {
    "gn:admin1_code":"11.0",
    "gn:asciiname":"Abang",
    "gn:country_code":"CM",
    "gn:dem":666,
    "gn:feature_class":"P",
    "gn:feature_code":"PPL",
    "gn:name":"Abang",
    "gn:population":0,
    "gn:timezone":"Africa/Douala",
    "iso:country":"CM",
    "wof:name":"Abang",
    "wof:placetype":"locality"
},
  "geometry": {"coordinates":[11.53333,3.38333],"type":"Point"}
}