{
  "type": "Feature",
  "properties": {
    "gn:admin1_code":"5.0",
    "gn:asciiname":"Masok",
    "gn:country_code":"CM",
    "gn:dem":172,
    "gn:feature_class":"P",
    "gn:feature_code":"PPL",
    "gn:name":"Masok",
    "gn:population":0,
    "gn:timezone":"Africa/Douala",
    "iso:country":"CM",
    "name:und_x_variant":[
        "Massok",
        "Masok"
    ],
    "wof:name":"Masok",
    "wof:placetype":"locality"
},
  "geometry": {"coordinates":[10.46667,4.13333],"type":"Point"}
}