{
  "type": "Feature",
  "properties": {
    "gn:admin1_code":"8.0",
    "gn:asciiname":"Bassamba",
    "gn:country_code":"CM",
    "gn:dem":1030,
    "gn:feature_class":"P",
    "gn:feature_code":"PPL",
    "gn:name":"Bassamba",
    "gn:population":0,
    "gn:timezone":"Africa/Douala",
    "iso:country":"CM",
    "name:fra_x_preferred":[
        "Sa\u2019mba"
    ],
    "wof:name":"Bassamba",
    "wof:placetype":"locality"
},
  "geometry": {"coordinates":[10.57121,5.05436],"type":"Point"}
}