{
  "type": "Feature",
  "properties": {
    "gn:admin1_code":"12.0",
    "gn:asciiname":"Oundoukoum",
    "gn:country_code":"CM",
    "gn:dem":463,
    "gn:feature_class":"P",
    "gn:feature_code":"PPL",
    "gn:name":"Oundoukoum",
    "gn:population":0,
    "gn:timezone":"Africa/Douala",
    "iso:country":"CM",
    "wof:name":"Oundoukoum",
    "wof:placetype":"locality"
},
  "geometry": {"coordinates":[13.98572,10.94492],"type":"Point"}
}