{
  "type": "Feature",
  "properties": {
    "gn:admin1_code":"13.0",
    "gn:asciiname":"Tifel",
    "gn:country_code":"CM",
    "gn:dem":263,
    "gn:feature_class":"P",
    "gn:feature_code":"PPL",
    "gn:name":"Tif\u00e8l",
    "gn:population":0,
    "gn:timezone":"Africa/Douala",
    "iso:country":"CM",
    "name:und_x_variant":[
        "Tif\u00e8l",
        "Tifel"
    ],
    "wof:name":"Tifel",
    "wof:placetype":"locality"
},
  "geometry": {"coordinates":[13.35362,9.47642],"type":"Point"}
}