{
  "type": "Feature",
  "properties": {
    "gn:admin1_code":"9.0",
    "gn:asciiname":"Monkey Kombo",
    "gn:country_code":"CM",
    "gn:dem":10,
    "gn:feature_class":"P",
    "gn:feature_code":"PPL",
    "gn:name":"Monkey Kombo",
    "gn:population":0,
    "gn:timezone":"Africa/Douala",
    "iso:country":"CM",
    "wof:name":"Monkey Kombo",
    "wof:placetype":"locality"
},
  "geometry": {"coordinates":[9.3834,4.0569],"type":"Point"}
}