{
  "type": "Feature",
  "properties": {
    "gn:admin1_code":"7.0",
    "gn:asciiname":"Ewa",
    "gn:country_code":"CM",
    "gn:dem":1333,
    "gn:feature_class":"P",
    "gn:feature_code":"PPL",
    "gn:name":"Ewa",
    "gn:population":0,
    "gn:timezone":"Africa/Douala",
    "iso:country":"CM",
    "name:ceb_x_preferred":[
        "Ewa"
    ],
    "name:deu_x_preferred":[
        "Ewa"
    ],
    "name:fra_x_preferred":[
        "Ewa"
    ],
    "name:heb_x_preferred":[
        "\u05d0\u05d5\u05d5\u05d4"
    ],
    "name:hun_x_preferred":[
        "Ewa"
    ],
    "name:pol_x_preferred":[
        "Ewa"
    ],
    "name:por_x_preferred":[
        "Ewa"
    ],
    "name:swe_x_preferred":[
        "Ewa"
    ],
    "wof:name":"Ewa",
    "wof:placetype":"locality"
},
  "geometry": {"coordinates":[9.9161,5.7555],"type":"Point"}
}