{
  "type": "Feature",
  "properties": {
    "gn:admin1_code":"8.0",
    "gn:asciiname":"Meka",
    "gn:country_code":"CM",
    "gn:dem":1501,
    "gn:feature_class":"P",
    "gn:feature_code":"PPL",
    "gn:name":"Meka",
    "gn:population":0,
    "gn:timezone":"Africa/Douala",
    "iso:country":"CM",
    "wof:name":"Meka",
    "wof:placetype":"locality"
},
  "geometry": {"coordinates":[10.08956,5.38488],"type":"Point"}
}