{
  "type": "Feature",
  "properties": {
    "gn:admin1_code":"0.0",
    "gn:asciiname":"Yoa",
    "gn:country_code":"CM",
    "gn:dem":641,
    "gn:feature_class":"P",
    "gn:feature_code":"PPL",
    "gn:name":"Yoa",
    "gn:population":0,
    "gn:timezone":"Africa/Douala",
    "iso:country":"CM",
    "wof:name":"Yoa",
    "wof:placetype":"locality"
},
  "geometry": {"coordinates":[13.23333,4.83333],"type":"Point"}
}