{
  "type": "Feature",
  "properties": {
    "gn:admin1_code":"9.0",
    "gn:asciiname":"Baka",
    "gn:country_code":"CM",
    "gn:dem":868,
    "gn:feature_class":"P",
    "gn:feature_code":"PPL",
    "gn:name":"Baka",
    "gn:population":0,
    "gn:timezone":"Africa/Douala",
    "iso:country":"CM",
    "name:bel_x_preferred":[
        "\u0411\u0430\u043a\u0430"
    ],
    "name:cat_x_preferred":[
        "Baka"
    ],
    "name:ceb_x_preferred":[
        "Baka"
    ],
    "name:deu_x_preferred":[
        "Baka"
    ],
    "name:fra_x_preferred":[
        "Baka"
    ],
    "name:hun_x_preferred":[
        "Baka"
    ],
    "name:ita_x_preferred":[
        "Baka"
    ],
    "name:lav_x_preferred":[
        "Baka"
    ],
    "name:nld_x_preferred":[
        "Baka"
    ],
    "name:pol_x_preferred":[
        "Baka"
    ],
    "name:rus_x_preferred":[
        "\u0411\u0430\u043a\u0430"
    ],
    "name:spa_x_preferred":[
        "Baka"
    ],
    "name:srp_x_preferred":[
        "\u0411\u0430\u043a\u0430"
    ],
    "name:swe_x_preferred":[
        "Baka"
    ],
    "name:tgl_x_preferred":[
        "Baka"
    ],
    "name:ukr_x_preferred":[
        "\u0411\u0430\u043a\u0430"
    ],
    "wof:name":"Baka",
    "wof:placetype":"locality"
},
  "geometry": {"coordinates":[9.6861,6.1302],"type":"Point"}
}