{
  "type": "Feature",
  "properties": {
    "gn:admin1_code":"12.0",
    "gn:asciiname":"Gadaka",
    "gn:country_code":"CM",
    "gn:dem":700,
    "gn:feature_class":"P",
    "gn:feature_code":"PPL",
    "gn:name":"Gadaka",
    "gn:population":0,
    "gn:timezone":"Africa/Douala",
    "iso:country":"CM",
    "name:azb_x_preferred":[
        "\u0642\u0627\u062f\u0627\u06a9\u0627"
    ],
    "name:deu_x_preferred":[
        "Gadaka"
    ],
    "name:fas_x_preferred":[
        "\u06af\u0627\u062f\u0627\u06a9\u0627"
    ],
    "name:zho_x_preferred":[
        "\u7518\u8fbe\u5361"
    ],
    "wof:name":"Gadaka",
    "wof:placetype":"locality"
},
  "geometry": {"coordinates":[13.94129,10.62981],"type":"Point"}
}