{
  "type": "Feature",
  "properties": {
    "gn:admin1_code":"12.0",
    "gn:asciiname":"Abkous Hamaldie",
    "gn:country_code":"CM",
    "gn:dem":292,
    "gn:feature_class":"P",
    "gn:feature_code":"PPL",
    "gn:name":"Abkous Hamaldi\u00e9",
    "gn:population":0,
    "gn:timezone":"Africa/Douala",
    "iso:country":"CM",
    "name:und_x_variant":[
        "Abou Kous I",
        "Abkous Hamaldi\u00e9",
        "Aboukous I"
    ],
    "wof:name":"Abkous Hamaldie",
    "wof:placetype":"locality"
},
  "geometry": {"coordinates":[14.59651,12.43738],"type":"Point"}
}