{
  "type": "Feature",
  "properties": {
    "gn:admin1_code":"11.0",
    "gn:asciiname":"Nkolbison",
    "gn:country_code":"CM",
    "gn:dem":688,
    "gn:feature_class":"P",
    "gn:feature_code":"PPL",
    "gn:name":"Nkolbison",
    "gn:population":0,
    "gn:timezone":"Africa/Douala",
    "iso:country":"CM",
    "wof:name":"Nkolbison",
    "wof:placetype":"locality"
},
  "geometry": {"coordinates":[11.61667,3.85],"type":"Point"}
}