{
  "type": "Feature",
  "properties": {
    "gn:admin1_code":"9.0",
    "gn:asciiname":"Ndjia",
    "gn:country_code":"CM",
    "gn:dem":413,
    "gn:feature_class":"P",
    "gn:feature_code":"PPL",
    "gn:name":"Ndjia",
    "gn:population":0,
    "gn:timezone":"Africa/Douala",
    "iso:country":"CM",
    "wof:name":"Ndjia",
    "wof:placetype":"locality"
},
  "geometry": {"coordinates":[8.98333,4.88333],"type":"Point"}
}