{
  "type": "Feature",
  "properties": {
    "gn:admin1_code":"8.0",
    "gn:asciiname":"Mbwe I",
    "gn:country_code":"CM",
    "gn:dem":1495,
    "gn:feature_class":"P",
    "gn:feature_code":"PPL",
    "gn:name":"Mbw\u00e9 I",
    "gn:population":0,
    "gn:timezone":"Africa/Douala",
    "iso:country":"CM",
    "wof:name":"Mbwe I",
    "wof:placetype":"locality"
},
  "geometry": {"coordinates":[10.2352,5.55798],"type":"Point"}
}