{
  "type": "Feature",
  "properties": {
    "gn:admin1_code":"12.0",
    "gn:asciiname":"Dom Aidi",
    "gn:country_code":"CM",
    "gn:dem":332,
    "gn:feature_class":"P",
    "gn:feature_code":"PPL",
    "gn:name":"Dom A\u00efdi",
    "gn:population":0,
    "gn:timezone":"Africa/Douala",
    "iso:country":"CM",
    "wof:name":"Dom Aidi",
    "wof:placetype":"locality"
},
  "geometry": {"coordinates":[15.45269,9.98313],"type":"Point"}
}