{
  "type": "Feature",
  "properties": {
    "gn:admin1_code":"12.0",
    "gn:asciiname":"Mayel Modibo",
    "gn:country_code":"CM",
    "gn:dem":401,
    "gn:feature_class":"P",
    "gn:feature_code":"PPL",
    "gn:name":"Mayel Modibo",
    "gn:population":0,
    "gn:timezone":"Africa/Douala",
    "iso:country":"CM",
    "wof:name":"Mayel Modibo",
    "wof:placetype":"locality"
},
  "geometry": {"coordinates":[14.43191,10.3709],"type":"Point"}
}