{
  "type": "Feature",
  "properties": {
    "gn:admin1_code":"12.0",
    "gn:asciiname":"Mabas",
    "gn:country_code":"CM",
    "gn:dem":963,
    "gn:feature_class":"P",
    "gn:feature_code":"PPL",
    "gn:name":"Mabas",
    "gn:population":0,
    "gn:timezone":"Africa/Douala",
    "iso:country":"CM",
    "wof:name":"Mabas",
    "wof:placetype":"locality"
},
  "geometry": {"coordinates":[13.65418,10.81014],"type":"Point"}
}