{
  "type": "Feature",
  "properties": {
    "gn:admin1_code":"9.0",
    "gn:asciiname":"Batika",
    "gn:country_code":"CM",
    "gn:dem":25,
    "gn:feature_class":"P",
    "gn:feature_code":"PPL",
    "gn:name":"Batika",
    "gn:population":0,
    "gn:timezone":"Africa/Douala",
    "iso:country":"CM",
    "name:hif_x_preferred":[
        "Batika"
    ],
    "name:und_x_variant":[
        "Bateka",
        "Batika"
    ],
    "wof:name":"Batika",
    "wof:placetype":"locality"
},
  "geometry": {"coordinates":[8.6811,4.7782],"type":"Point"}
}