{
  "type": "Feature",
  "properties": {
    "gn:admin1_code":"14.0",
    "gn:asciiname":"Nkolenyang",
    "gn:country_code":"CM",
    "gn:dem":644,
    "gn:feature_class":"P",
    "gn:feature_code":"PPL",
    "gn:name":"Nkol\u00e9nyang",
    "gn:population":0,
    "gn:timezone":"Africa/Douala",
    "iso:country":"CM",
    "wof:name":"Nkolenyang",
    "wof:placetype":"locality"
},
  "geometry": {"coordinates":[12.58333,2.43333],"type":"Point"}
}