{
  "type": "Feature",
  "properties": {
    "gn:admin1_code":"11.0",
    "gn:asciiname":"Bilik",
    "gn:country_code":"CM",
    "gn:dem":657,
    "gn:feature_class":"P",
    "gn:feature_code":"PPL",
    "gn:name":"Bilik",
    "gn:population":0,
    "gn:timezone":"Africa/Douala",
    "iso:country":"CM",
    "name:und_x_variant":[
        "Bilik I",
        "Bilik"
    ],
    "wof:name":"Bilik",
    "wof:placetype":"locality"
},
  "geometry": {"coordinates":[11.28333,3.51667],"type":"Point"}
}