{
  "type": "Feature",
  "properties": {
    "gn:admin1_code":"4.0",
    "gn:asciiname":"Wama",
    "gn:country_code":"CM",
    "gn:dem":680,
    "gn:feature_class":"P",
    "gn:feature_code":"PPL",
    "gn:name":"Wama",
    "gn:population":0,
    "gn:timezone":"Africa/Douala",
    "iso:country":"CM",
    "name:ceb_x_preferred":[
        "Wama"
    ],
    "name:deu_x_preferred":[
        "Wama"
    ],
    "name:swe_x_preferred":[
        "Wama"
    ],
    "name:und_x_variant":[
        "Ouama",
        "Wama"
    ],
    "wof:name":"Wama",
    "wof:placetype":"locality"
},
  "geometry": {"coordinates":[13.15,4.05],"type":"Point"}
}