{
  "type": "Feature",
  "properties": {
    "gn:admin1_code":"4.0",
    "gn:asciiname":"Gbadjanga",
    "gn:country_code":"CM",
    "gn:dem":615,
    "gn:feature_class":"P",
    "gn:feature_code":"PPL",
    "gn:name":"Gbadjanga",
    "gn:population":0,
    "gn:timezone":"Africa/Douala",
    "iso:country":"CM",
    "wof:name":"Gbadjanga",
    "wof:placetype":"locality"
},
  "geometry": {"coordinates":[14.93333,4.26667],"type":"Point"}
}