{
  "type": "Feature",
  "properties": {
    "gn:admin1_code":"12.0",
    "gn:asciiname":"Krenoya",
    "gn:country_code":"CM",
    "gn:dem":294,
    "gn:feature_class":"P",
    "gn:feature_code":"PPL",
    "gn:name":"Krenoya",
    "gn:population":0,
    "gn:timezone":"Africa/Douala",
    "iso:country":"CM",
    "name:und_x_variant":[
        "Amkoundro"
    ],
    "wof:name":"Krenoya",
    "wof:placetype":"locality"
},
  "geometry": {"coordinates":[14.55921,12.42862],"type":"Point"}
}