{
  "type": "Feature",
  "properties": {
    "gn:admin1_code":"12.0",
    "gn:asciiname":"Drame",
    "gn:country_code":"CM",
    "gn:dem":386,
    "gn:feature_class":"P",
    "gn:feature_code":"PPL",
    "gn:name":"Dram\u00e9",
    "gn:population":0,
    "gn:timezone":"Africa/Douala",
    "iso:country":"CM",
    "wof:name":"Drame",
    "wof:placetype":"locality"
},
  "geometry": {"coordinates":[14.42516,10.07237],"type":"Point"}
}