{
  "type": "Feature",
  "properties": {
    "gn:admin1_code":"13.0",
    "gn:asciiname":"Koumkeoudji",
    "gn:country_code":"CM",
    "gn:dem":418,
    "gn:feature_class":"P",
    "gn:feature_code":"PPL",
    "gn:name":"Koumk\u00e9oudji",
    "gn:population":0,
    "gn:timezone":"Africa/Douala",
    "iso:country":"CM",
    "name:und_x_variant":[
        "Koumk\u00e9oudji",
        "Koum Kaoudji"
    ],
    "wof:name":"Koumkeoudji",
    "wof:placetype":"locality"
},
  "geometry": {"coordinates":[13.79397,9.87246],"type":"Point"}
}