{
  "type": "Feature",
  "properties": {
    "gn:admin1_code":"13.0",
    "gn:asciiname":"Doudzougou",
    "gn:country_code":"CM",
    "gn:dem":379,
    "gn:feature_class":"P",
    "gn:feature_code":"PPL",
    "gn:name":"Doudzougou",
    "gn:population":0,
    "gn:timezone":"Africa/Douala",
    "iso:country":"CM",
    "wof:name":"Doudzougou",
    "wof:placetype":"locality"
},
  "geometry": {"coordinates":[13.69196,9.79351],"type":"Point"}
}