{
  "type": "Feature",
  "properties": {
    "gn:admin1_code":"12.0",
    "gn:asciiname":"Ouredin",
    "gn:country_code":"CM",
    "gn:dem":290,
    "gn:feature_class":"P",
    "gn:feature_code":"PPL",
    "gn:name":"Our\u00e9din",
    "gn:population":0,
    "gn:timezone":"Africa/Douala",
    "iso:country":"CM",
    "wof:name":"Ouredin",
    "wof:placetype":"locality"
},
  "geometry": {"coordinates":[14.58519,12.34748],"type":"Point"}
}