{
  "type": "Feature",
  "properties": {
    "gn:admin1_code":"11.0",
    "gn:asciiname":"Medalmbom",
    "gn:country_code":"CM",
    "gn:dem":646,
    "gn:feature_class":"P",
    "gn:feature_code":"PPL",
    "gn:name":"M\u00e9dalmbom",
    "gn:population":0,
    "gn:timezone":"Africa/Douala",
    "iso:country":"CM",
    "wof:name":"Medalmbom",
    "wof:placetype":"locality"
},
  "geometry": {"coordinates":[12.83333,4.76667],"type":"Point"}
}