{
  "type": "Feature",
  "properties": {
    "gn:admin1_code":"8.0",
    "gn:asciiname":"Meket",
    "gn:country_code":"CM",
    "gn:dem":1573,
    "gn:feature_class":"P",
    "gn:feature_code":"PPL",
    "gn:name":"Meket",
    "gn:population":0,
    "gn:timezone":"Africa/Douala",
    "iso:country":"CM",
    "name:amh_x_preferred":[
        "\u1218\u1244\u1275"
    ],
    "name:ceb_x_preferred":[
        "Meket"
    ],
    "name:fra_x_preferred":[
        "Meket"
    ],
    "name:swe_x_preferred":[
        "Meket"
    ],
    "wof:name":"Meket",
    "wof:placetype":"locality"
},
  "geometry": {"coordinates":[9.95,5.36667],"type":"Point"}
}