{
  "type": "Feature",
  "properties": {
    "gn:admin1_code":"5.0",
    "gn:asciiname":"Timbo",
    "gn:country_code":"CM",
    "gn:dem":-9999,
    "gn:feature_class":"P",
    "gn:feature_code":"PPL",
    "gn:name":"Timbo",
    "gn:population":0,
    "gn:timezone":"Africa/Douala",
    "iso:country":"CM",
    "name:ara_x_preferred":[
        "\u062a\u064a\u0645\u0628\u0648"
    ],
    "name:cat_x_preferred":[
        "Timbo"
    ],
    "name:fra_x_preferred":[
        "Timbo"
    ],
    "name:ita_x_preferred":[
        "Timbo"
    ],
    "name:msa_x_preferred":[
        "Timbo"
    ],
    "name:spa_x_preferred":[
        "Timbo"
    ],
    "wof:name":"Timbo",
    "wof:placetype":"locality"
},
  "geometry": {"coordinates":[9.74917,3.46306],"type":"Point"}
}