{
  "type": "Feature",
  "properties": {
    "gn:admin1_code":"9.0",
    "gn:asciiname":"Akpassang",
    "gn:country_code":"CM",
    "gn:dem":31,
    "gn:feature_class":"P",
    "gn:feature_code":"PPL",
    "gn:name":"Akpassang",
    "gn:population":0,
    "gn:timezone":"Africa/Douala",
    "iso:country":"CM",
    "name:und_x_variant":[
        "Ekundukundu II",
        "Akpassang"
    ],
    "wof:name":"Akpassang",
    "wof:placetype":"locality"
},
  "geometry": {"coordinates":[8.7063,4.9819],"type":"Point"}
}