{
  "type": "Feature",
  "properties": {
    "gn:admin1_code":"9.0",
    "gn:asciiname":"Idabato I",
    "gn:country_code":"CM",
    "gn:dem":7,
    "gn:feature_class":"P",
    "gn:feature_code":"PPL",
    "gn:name":"Idabato I",
    "gn:population":0,
    "gn:timezone":"Africa/Douala",
    "iso:country":"CM",
    "wof:name":"Idabato I",
    "wof:placetype":"locality"
},
  "geometry": {"coordinates":[8.5028,4.5351],"type":"Point"}
}