{
  "type": "Feature",
  "properties": {
    "gn:admin1_code":"5.0",
    "gn:asciiname":"Bonamouang",
    "gn:country_code":"CM",
    "gn:dem":6,
    "gn:feature_class":"P",
    "gn:feature_code":"PPL",
    "gn:name":"Bonamouang",
    "gn:population":0,
    "gn:timezone":"Africa/Douala",
    "iso:country":"CM",
    "wof:name":"Bonamouang",
    "wof:placetype":"locality"
},
  "geometry": {"coordinates":[9.7251,4.0874],"type":"Point"}
}