{
  "type": "Feature",
  "properties": {
    "gn:admin1_code":"8.0",
    "gn:asciiname":"Njila'",
    "gn:country_code":"CM",
    "gn:dem":1505,
    "gn:feature_class":"P",
    "gn:feature_code":"PPL",
    "gn:name":"Njila\u2019",
    "gn:population":0,
    "gn:timezone":"Africa/Douala",
    "iso:country":"CM",
    "wof:name":"Njila'",
    "wof:placetype":"locality"
},
  "geometry": {"coordinates":[10.32692,5.41955],"type":"Point"}
}