{
  "type": "Feature",
  "properties": {
    "gn:admin1_code":"8.0",
    "gn:asciiname":"Djoua",
    "gn:country_code":"CM",
    "gn:dem":1479,
    "gn:feature_class":"P",
    "gn:feature_code":"PPL",
    "gn:name":"Djoua",
    "gn:population":0,
    "gn:timezone":"Africa/Douala",
    "iso:country":"CM",
    "name:und_x_variant":[
        "Djoua II"
    ],
    "wof:name":"Djoua",
    "wof:placetype":"locality"
},
  "geometry": {"coordinates":[10.17033,5.44792],"type":"Point"}
}