{
  "type": "Feature",
  "properties": {
    "gn:admin1_code":"4.0",
    "gn:asciiname":"Pezam",
    "gn:country_code":"CM",
    "gn:dem":377,
    "gn:feature_class":"P",
    "gn:feature_code":"PPL",
    "gn:name":"P\u00e9zam",
    "gn:population":0,
    "gn:timezone":"Africa/Douala",
    "iso:country":"CM",
    "wof:name":"Pezam",
    "wof:placetype":"locality"
},
  "geometry": {"coordinates":[15.21667,2.05],"type":"Point"}
}