{
  "type": "Feature",
  "properties": {
    "gn:admin1_code":"8.0",
    "gn:asciiname":"Leghon",
    "gn:country_code":"CM",
    "gn:dem":1505,
    "gn:feature_class":"P",
    "gn:feature_code":"PPL",
    "gn:name":"Leghon",
    "gn:population":0,
    "gn:timezone":"Africa/Douala",
    "iso:country":"CM",
    "name:fra_x_preferred":[
        "Leghong"
    ],
    "wof:name":"Leghon",
    "wof:placetype":"locality"
},
  "geometry": {"coordinates":[10.19852,5.44429],"type":"Point"}
}