{
  "type": "Feature",
  "properties": {
    "gn:admin1_code":"8.0",
    "gn:asciiname":"Mfessang",
    "gn:country_code":"CM",
    "gn:dem":1016,
    "gn:feature_class":"P",
    "gn:feature_code":"PPL",
    "gn:name":"Mfessang",
    "gn:population":0,
    "gn:timezone":"Africa/Douala",
    "iso:country":"CM",
    "name:fra_x_preferred":[
        "Mfessang"
    ],
    "wof:name":"Mfessang",
    "wof:placetype":"locality"
},
  "geometry": {"coordinates":[10.64921,5.43921],"type":"Point"}
}