{
  "type": "Feature",
  "properties": {
    "gn:admin1_code":"4.0",
    "gn:asciiname":"Mayos",
    "gn:country_code":"CM",
    "gn:dem":695,
    "gn:feature_class":"P",
    "gn:feature_code":"PPL",
    "gn:name":"Mayos",
    "gn:population":0,
    "gn:timezone":"Africa/Douala",
    "iso:country":"CM",
    "wof:name":"Mayos",
    "wof:placetype":"locality"
},
  "geometry": {"coordinates":[13.88333,3.91667],"type":"Point"}
}