{
  "type": "Feature",
  "properties": {
    "gn:admin1_code":"12.0",
    "gn:asciiname":"Njogbore",
    "gn:country_code":"CM",
    "gn:dem":413,
    "gn:feature_class":"P",
    "gn:feature_code":"PPL",
    "gn:name":"Njogbor\u00e9",
    "gn:population":0,
    "gn:timezone":"Africa/Douala",
    "iso:country":"CM",
    "wof:name":"Njogbore",
    "wof:placetype":"locality"
},
  "geometry": {"coordinates":[14.28947,10.48178],"type":"Point"}
}