{
  "type": "Feature",
  "properties": {
    "gn:admin1_code":"13.0",
    "gn:asciiname":"Bousui",
    "gn:country_code":"CM",
    "gn:dem":477,
    "gn:feature_class":"P",
    "gn:feature_code":"PPL",
    "gn:name":"Bousui",
    "gn:population":0,
    "gn:timezone":"Africa/Douala",
    "iso:country":"CM",
    "wof:name":"Bousui",
    "wof:placetype":"locality"
},
  "geometry": {"coordinates":[15.5101,7.7823],"type":"Point"}
}