{
  "type": "Feature",
  "properties": {
    "gn:admin1_code":"13.0",
    "gn:asciiname":"Baksa",
    "gn:country_code":"CM",
    "gn:dem":389,
    "gn:feature_class":"P",
    "gn:feature_code":"PPL",
    "gn:name":"Baksa",
    "gn:population":0,
    "gn:timezone":"Africa/Douala",
    "iso:country":"CM",
    "name:ceb_x_preferred":[
        "Baksa"
    ],
    "name:fra_x_preferred":[
        "Baksa"
    ],
    "name:hun_x_preferred":[
        "Baksa"
    ],
    "name:swe_x_preferred":[
        "Baksa"
    ],
    "name:und_x_variant":[
        "Baka"
    ],
    "wof:name":"Baksa",
    "wof:placetype":"locality"
},
  "geometry": {"coordinates":[14.2223,9.374],"type":"Point"}
}