{
  "type": "Feature",
  "properties": {
    "gn:admin1_code":"12.0",
    "gn:asciiname":"Damrou",
    "gn:country_code":"CM",
    "gn:dem":301,
    "gn:feature_class":"P",
    "gn:feature_code":"PPL",
    "gn:name":"Damrou",
    "gn:population":0,
    "gn:timezone":"Africa/Douala",
    "iso:country":"CM",
    "wof:name":"Damrou",
    "wof:placetype":"locality"
},
  "geometry": {"coordinates":[15.05836,11.71219],"type":"Point"}
}