{
  "type": "Feature",
  "properties": {
    "gn:admin1_code":"13.0",
    "gn:asciiname":"Baidiga",
    "gn:country_code":"CM",
    "gn:dem":574,
    "gn:feature_class":"P",
    "gn:feature_code":"PPL",
    "gn:name":"Baidiga",
    "gn:population":0,
    "gn:timezone":"Africa/Douala",
    "iso:country":"CM",
    "wof:name":"Baidiga",
    "wof:placetype":"locality"
},
  "geometry": {"coordinates":[15.4252,7.45778],"type":"Point"}
}