{
  "type": "Feature",
  "properties": {
    "gn:admin1_code":"9.0",
    "gn:asciiname":"Numba",
    "gn:country_code":"CM",
    "gn:dem":558,
    "gn:feature_class":"P",
    "gn:feature_code":"PPL",
    "gn:name":"Numba",
    "gn:population":0,
    "gn:timezone":"Africa/Douala",
    "iso:country":"CM",
    "name:jpn_x_preferred":[
        "Numba"
    ],
    "name:mal_x_preferred":[
        "\u0d28\u0d41\u0d02\u0d2c"
    ],
    "wof:name":"Numba",
    "wof:placetype":"locality"
},
  "geometry": {"coordinates":[9.7143,5.8389],"type":"Point"}
}