{
  "type": "Feature",
  "properties": {
    "gn:admin1_code":"7.0",
    "gn:asciiname":"Awun",
    "gn:country_code":"CM",
    "gn:dem":1180,
    "gn:feature_class":"P",
    "gn:feature_code":"PPL",
    "gn:name":"Awun",
    "gn:population":0,
    "gn:timezone":"Africa/Douala",
    "iso:country":"CM",
    "wof:name":"Awun",
    "wof:placetype":"locality"
},
  "geometry": {"coordinates":[9.9082,5.8238],"type":"Point"}
}