{
  "type": "Feature",
  "properties": {
    "gn:admin1_code":"4.0",
    "gn:asciiname":"Ekom",
    "gn:country_code":"CM",
    "gn:dem":699,
    "gn:feature_class":"P",
    "gn:feature_code":"PPL",
    "gn:name":"\u00c9kom",
    "gn:population":0,
    "gn:timezone":"Africa/Douala",
    "iso:country":"CM",
    "wof:name":"Ekom",
    "wof:placetype":"locality"
},
  "geometry": {"coordinates":[13.03333,3.35],"type":"Point"}
}