{
  "type": "Feature",
  "properties": {
    "gn:admin1_code":"12.0",
    "gn:asciiname":"Douval",
    "gn:country_code":"CM",
    "gn:dem":1092,
    "gn:feature_class":"P",
    "gn:feature_code":"PPL",
    "gn:name":"Douval",
    "gn:population":0,
    "gn:timezone":"Africa/Douala",
    "iso:country":"CM",
    "wof:name":"Douval",
    "wof:placetype":"locality"
},
  "geometry": {"coordinates":[13.78352,10.90338],"type":"Point"}
}