{
  "type": "Feature",
  "properties": {
    "gn:admin1_code":"13.0",
    "gn:asciiname":"Kamboro",
    "gn:country_code":"CM",
    "gn:dem":255,
    "gn:feature_class":"P",
    "gn:feature_code":"PPL",
    "gn:name":"Kamboro",
    "gn:population":0,
    "gn:timezone":"Africa/Douala",
    "iso:country":"CM",
    "wof:name":"Kamboro",
    "wof:placetype":"locality"
},
  "geometry": {"coordinates":[12.81667,8.71667],"type":"Point"}
}