{
  "type": "Feature",
  "properties": {
    "gn:admin1_code":"12.0",
    "gn:asciiname":"Kilda",
    "gn:country_code":"CM",
    "gn:dem":531,
    "gn:feature_class":"P",
    "gn:feature_code":"PPL",
    "gn:name":"Kilda",
    "gn:population":0,
    "gn:timezone":"Africa/Douala",
    "iso:country":"CM",
    "wof:name":"Kilda",
    "wof:placetype":"locality"
},
  "geometry": {"coordinates":[13.89912,10.83225],"type":"Point"}
}