{
  "type": "Feature",
  "properties": {
    "gn:admin1_code":"8.0",
    "gn:asciiname":"Bankadjou",
    "gn:country_code":"CM",
    "gn:dem":1170,
    "gn:feature_class":"P",
    "gn:feature_code":"PPL",
    "gn:name":"Bankadjou",
    "gn:population":0,
    "gn:timezone":"Africa/Douala",
    "iso:country":"CM",
    "name:fra_x_preferred":[
        "Nkajou"
    ],
    "wof:name":"Bankadjou",
    "wof:placetype":"locality"
},
  "geometry": {"coordinates":[10.38854,5.58546],"type":"Point"}
}