{
  "type": "Feature",
  "properties": {
    "gn:admin1_code":"8.0",
    "gn:asciiname":"Doumse",
    "gn:country_code":"CM",
    "gn:dem":1388,
    "gn:feature_class":"P",
    "gn:feature_code":"PPL",
    "gn:name":"Doums\u00e9",
    "gn:population":0,
    "gn:timezone":"Africa/Douala",
    "iso:country":"CM",
    "wof:name":"Doumse",
    "wof:placetype":"locality"
},
  "geometry": {"coordinates":[10.30038,5.50712],"type":"Point"}
}