{
  "type": "Feature",
  "properties": {
    "gn:admin1_code":"10.0",
    "gn:asciiname":"Beza",
    "gn:country_code":"CM",
    "gn:dem":850,
    "gn:feature_class":"P",
    "gn:feature_code":"PPL",
    "gn:name":"B\u00e9za",
    "gn:population":0,
    "gn:timezone":"Africa/Douala",
    "iso:country":"CM",
    "wof:name":"Beza",
    "wof:placetype":"locality"
},
  "geometry": {"coordinates":[12.79271,6.3368],"type":"Point"}
}