{
  "type": "Feature",
  "properties": {
    "gn:admin1_code":"9.0",
    "gn:asciiname":"Owe",
    "gn:country_code":"CM",
    "gn:dem":71,
    "gn:feature_class":"P",
    "gn:feature_code":"PPL",
    "gn:name":"Owe",
    "gn:population":0,
    "gn:timezone":"Africa/Douala",
    "iso:country":"CM",
    "name:und_x_variant":[
        "Owe Yoke",
        "Owe"
    ],
    "wof:name":"Owe",
    "wof:placetype":"locality"
},
  "geometry": {"coordinates":[9.3806,4.2986],"type":"Point"}
}