{
  "type": "Feature",
  "properties": {
    "gn:admin1_code":"5.0",
    "gn:asciiname":"Ndog Mbiango",
    "gn:country_code":"CM",
    "gn:dem":27,
    "gn:feature_class":"P",
    "gn:feature_code":"PPL",
    "gn:name":"Ndog Mbiango",
    "gn:population":0,
    "gn:timezone":"Africa/Douala",
    "iso:country":"CM",
    "wof:name":"Ndog Mbiango",
    "wof:placetype":"locality"
},
  "geometry": {"coordinates":[10.03333,3.46667],"type":"Point"}
}