{
  "type": "Feature",
  "properties": {
    "gn:admin1_code":"11.0",
    "gn:asciiname":"Efandi",
    "gn:country_code":"CM",
    "gn:dem":714,
    "gn:feature_class":"P",
    "gn:feature_code":"PPL",
    "gn:name":"Efandi",
    "gn:population":0,
    "gn:timezone":"Africa/Douala",
    "iso:country":"CM",
    "wof:name":"Efandi",
    "wof:placetype":"locality"
},
  "geometry": {"coordinates":[11.76667,3.83333],"type":"Point"}
}