{
  "type": "Feature",
  "properties": {
    "gn:admin1_code":"5.0",
    "gn:asciiname":"Song Woang",
    "gn:country_code":"CM",
    "gn:dem":271,
    "gn:feature_class":"P",
    "gn:feature_code":"PPL",
    "gn:name":"Song Woang",
    "gn:population":0,
    "gn:timezone":"Africa/Douala",
    "iso:country":"CM",
    "wof:name":"Song Woang",
    "wof:placetype":"locality"
},
  "geometry": {"coordinates":[10.55,3.81667],"type":"Point"}
}