{
  "type": "Feature",
  "properties": {
    "gn:admin1_code":"12.0",
    "gn:asciiname":"Malame",
    "gn:country_code":"CM",
    "gn:dem":310,
    "gn:feature_class":"P",
    "gn:feature_code":"PPL",
    "gn:name":"Malam\u00e9",
    "gn:population":0,
    "gn:timezone":"Africa/Douala",
    "iso:country":"CM",
    "wof:name":"Malame",
    "wof:placetype":"locality"
},
  "geometry": {"coordinates":[14.84901,11.01264],"type":"Point"}
}