{
  "type": "Feature",
  "properties": {
    "gn:admin1_code":"12.0",
    "gn:asciiname":"Mogodjere",
    "gn:country_code":"CM",
    "gn:dem":774,
    "gn:feature_class":"P",
    "gn:feature_code":"PPL",
    "gn:name":"Mogodj\u00e9r\u00e9",
    "gn:population":0,
    "gn:timezone":"Africa/Douala",
    "iso:country":"CM",
    "wof:name":"Mogodjere",
    "wof:placetype":"locality"
},
  "geometry": {"coordinates":[13.94673,10.65642],"type":"Point"}
}