{
  "type": "Feature",
  "properties": {
    "gn:admin1_code":"8.0",
    "gn:asciiname":"Zennela",
    "gn:country_code":"CM",
    "gn:dem":1492,
    "gn:feature_class":"P",
    "gn:feature_code":"PPL",
    "gn:name":"Zennela",
    "gn:population":0,
    "gn:timezone":"Africa/Douala",
    "iso:country":"CM",
    "wof:name":"Zennela",
    "wof:placetype":"locality"
},
  "geometry": {"coordinates":[9.95,5.38333],"type":"Point"}
}