{
  "type": "Feature",
  "properties": {
    "gn:admin1_code":"12.0",
    "gn:asciiname":"Pomla",
    "gn:country_code":"CM",
    "gn:dem":591,
    "gn:feature_class":"P",
    "gn:feature_code":"PPL",
    "gn:name":"Pomla",
    "gn:population":0,
    "gn:timezone":"Africa/Douala",
    "iso:country":"CM",
    "wof:name":"Pomla",
    "wof:placetype":"locality"
},
  "geometry": {"coordinates":[13.89659,10.6108],"type":"Point"}
}