{
  "type": "Feature",
  "properties": {
    "gn:admin1_code":"12.0",
    "gn:asciiname":"Houtfire",
    "gn:country_code":"CM",
    "gn:dem":335,
    "gn:feature_class":"P",
    "gn:feature_code":"PPL",
    "gn:name":"Houtfir\u00e9",
    "gn:population":0,
    "gn:timezone":"Africa/Douala",
    "iso:country":"CM",
    "wof:name":"Houtfire",
    "wof:placetype":"locality"
},
  "geometry": {"coordinates":[14.76322,10.53163],"type":"Point"}
}