{
  "type": "Feature",
  "properties": {
    "gn:admin1_code":"8.0",
    "gn:asciiname":"Njout",
    "gn:country_code":"CM",
    "gn:dem":1521,
    "gn:feature_class":"P",
    "gn:feature_code":"PPL",
    "gn:name":"Njout",
    "gn:population":0,
    "gn:timezone":"Africa/Douala",
    "iso:country":"CM",
    "wof:name":"Njout",
    "wof:placetype":"locality"
},
  "geometry": {"coordinates":[10.35238,5.4167],"type":"Point"}
}