{
  "type": "Feature",
  "properties": {
    "gn:admin1_code":"13.0",
    "gn:asciiname":"Soumore",
    "gn:country_code":"CM",
    "gn:dem":220,
    "gn:feature_class":"P",
    "gn:feature_code":"PPL",
    "gn:name":"Soumor\u00e9",
    "gn:population":0,
    "gn:timezone":"Africa/Douala",
    "iso:country":"CM",
    "wof:name":"Soumore",
    "wof:placetype":"locality"
},
  "geometry": {"coordinates":[12.98333,9.11667],"type":"Point"}
}