{
  "type": "Feature",
  "properties": {
    "gn:admin1_code":"14.0",
    "gn:asciiname":"Tekmo II",
    "gn:country_code":"CM",
    "gn:dem":676,
    "gn:feature_class":"P",
    "gn:feature_code":"PPL",
    "gn:name":"Tekmo II",
    "gn:population":0,
    "gn:timezone":"Africa/Douala",
    "iso:country":"CM",
    "name:und_x_variant":[
        "T\u00e9komo",
        "Tekmo II"
    ],
    "wof:name":"Tekmo II",
    "wof:placetype":"locality"
},
  "geometry": {"coordinates":[12.13333,3.18333],"type":"Point"}
}