{
  "type": "Feature",
  "properties": {
    "gn:admin1_code":"12.0",
    "gn:asciiname":"Yam Djidji",
    "gn:country_code":"CM",
    "gn:dem":444,
    "gn:feature_class":"P",
    "gn:feature_code":"PPL",
    "gn:name":"Yam Djidji",
    "gn:population":0,
    "gn:timezone":"Africa/Douala",
    "iso:country":"CM",
    "wof:name":"Yam Djidji",
    "wof:placetype":"locality"
},
  "geometry": {"coordinates":[14.17346,10.56998],"type":"Point"}
}