{
  "type": "Feature",
  "properties": {
    "gn:admin1_code":"12.0",
    "gn:asciiname":"Touksou",
    "gn:country_code":"CM",
    "gn:dem":338,
    "gn:feature_class":"P",
    "gn:feature_code":"PPL",
    "gn:name":"Touksou",
    "gn:population":0,
    "gn:timezone":"Africa/Douala",
    "iso:country":"CM",
    "wof:name":"Touksou",
    "wof:placetype":"locality"
},
  "geometry": {"coordinates":[15.05,10.05],"type":"Point"}
}