{
  "type": "Feature",
  "properties": {
    "gn:admin1_code":"7.0",
    "gn:asciiname":"Laikom",
    "gn:country_code":"CM",
    "gn:dem":1416,
    "gn:feature_class":"P",
    "gn:feature_code":"PPL",
    "gn:name":"Laikom",
    "gn:population":0,
    "gn:timezone":"Africa/Douala",
    "iso:country":"CM",
    "name:und_x_variant":[
        "Laakom",
        "Laikom"
    ],
    "wof:name":"Laikom",
    "wof:placetype":"locality"
},
  "geometry": {"coordinates":[10.33333,6.25],"type":"Point"}
}