{
  "type": "Feature",
  "properties": {
    "gn:admin1_code":"7.0",
    "gn:asciiname":"Momo",
    "gn:country_code":"CM",
    "gn:dem":1173,
    "gn:feature_class":"P",
    "gn:feature_code":"PPL",
    "gn:name":"Momo",
    "gn:population":0,
    "gn:timezone":"Africa/Douala",
    "iso:country":"CM",
    "name:ceb_x_preferred":[
        "Momo"
    ],
    "name:dan_x_preferred":[
        "Momo"
    ],
    "name:deu_x_preferred":[
        "Momo"
    ],
    "name:est_x_preferred":[
        "Momo"
    ],
    "name:fin_x_preferred":[
        "Momo"
    ],
    "name:fra_x_preferred":[
        "Momo"
    ],
    "name:hun_x_preferred":[
        "Momo"
    ],
    "name:hye_x_preferred":[
        "\u0544\u0578\u0574\u0578"
    ],
    "name:ita_x_preferred":[
        "Momo"
    ],
    "name:jpn_x_preferred":[
        "\u30e2\u30e2"
    ],
    "name:lit_x_preferred":[
        "Momo"
    ],
    "name:nld_x_preferred":[
        "Momo"
    ],
    "name:pol_x_preferred":[
        "Momo"
    ],
    "name:por_x_preferred":[
        "Momo"
    ],
    "name:rus_x_preferred":[
        "\u041c\u043e\u043c\u043e"
    ],
    "name:slk_x_preferred":[
        "Momo"
    ],
    "name:spa_x_preferred":[
        "Momo"
    ],
    "name:swe_x_preferred":[
        "Momo"
    ],
    "name:tgl_x_preferred":[
        "Momo"
    ],
    "name:tha_x_preferred":[
        "\u0e42\u0e21\u0e42\u0e21"
    ],
    "name:tur_x_preferred":[
        "Momo"
    ],
    "name:ukr_x_preferred":[
        "\u041c\u043e\u043c\u043e"
    ],
    "name:zho_x_preferred":[
        "Momo"
    ],
    "wof:name":"Momo",
    "wof:placetype":"locality"
},
  "geometry": {"coordinates":[10.43987,5.97916],"type":"Point"}
}