{
  "type": "Feature",
  "properties": {
    "gn:admin1_code":"7.0",
    "gn:asciiname":"Momo",
    "gn:country_code":"CM",
    "gn:dem":1173,
    "gn:feature_class":"P",
    "gn:feature_code":"PPL",
    "gn:name":"Momo",
    "gn:population":0,
    "gn:timezone":"Africa/Douala",
    "iso:country":"CM",
    "wof:name":"Momo",
    "wof:placetype":"locality"
},
  "geometry": {"coordinates":[10.43987,5.97916],"type":"Point"}
}