{
  "type": "Feature",
  "properties": {
    "gn:admin1_code":"13.0",
    "gn:asciiname":"Lainde",
    "gn:country_code":"CM",
    "gn:dem":192,
    "gn:feature_class":"P",
    "gn:feature_code":"PPL",
    "gn:name":"La\u00efnd\u00e9",
    "gn:population":0,
    "gn:timezone":"Africa/Douala",
    "iso:country":"CM",
    "wof:name":"Lainde",
    "wof:placetype":"locality"
},
  "geometry": {"coordinates":[13.41916,9.34327],"type":"Point"}
}