{
  "type": "Feature",
  "properties": {
    "gn:admin1_code":"13.0",
    "gn:asciiname":"Mbadji",
    "gn:country_code":"CM",
    "gn:dem":614,
    "gn:feature_class":"P",
    "gn:feature_code":"PPL",
    "gn:name":"Mbadji",
    "gn:population":0,
    "gn:timezone":"Africa/Douala",
    "iso:country":"CM",
    "wof:name":"Mbadji",
    "wof:placetype":"locality"
},
  "geometry": {"coordinates":[13.55,8.21667],"type":"Point"}
}