{
  "type": "Feature",
  "properties": {
    "gn:admin1_code":"14.0",
    "gn:asciiname":"Mengong",
    "gn:cc2":"CM",
    "gn:country_code":"CM",
    "gn:dem":723,
    "gn:feature_class":"P",
    "gn:feature_code":"PPL",
    "gn:name":"Mengong",
    "gn:population":0,
    "gn:timezone":"Africa/Douala",
    "iso:country":"CM",
    "name:fra_x_preferred":[
        "Mengong"
    ],
    "name:msa_x_preferred":[
        "Mengong"
    ],
    "name:spa_x_preferred":[
        "Mengong"
    ],
    "name:und_x_variant":[
        "Mang\u00f3ng",
        "Mengang",
        "Mengong"
    ],
    "wof:name":"Mengong",
    "wof:placetype":"locality"
},
  "geometry": {"coordinates":[11.41667,2.93333],"type":"Point"}
}