{
  "type": "Feature",
  "properties": {
    "gn:admin1_code":"14.0",
    "gn:asciiname":"Mekak",
    "gn:country_code":"CM",
    "gn:dem":607,
    "gn:feature_class":"P",
    "gn:feature_code":"PPL",
    "gn:name":"M\u00e9kak",
    "gn:population":0,
    "gn:timezone":"Africa/Douala",
    "iso:country":"CM",
    "wof:name":"Mekak",
    "wof:placetype":"locality"
},
  "geometry": {"coordinates":[10.93333,2.21667],"type":"Point"}
}