{
  "type": "Feature",
  "properties": {
    "gn:admin1_code":"12.0",
    "gn:asciiname":"Magadi II",
    "gn:country_code":"CM",
    "gn:dem":290,
    "gn:feature_class":"P",
    "gn:feature_code":"PPL",
    "gn:name":"Magadi II",
    "gn:population":0,
    "gn:timezone":"Africa/Douala",
    "iso:country":"CM",
    "name:und_x_variant":[
        "Magadi"
    ],
    "wof:name":"Magadi II",
    "wof:placetype":"locality"
},
  "geometry": {"coordinates":[14.30638,12.52956],"type":"Point"}
}