{
  "type": "Feature",
  "properties": {
    "gn:admin1_code":"8.0",
    "gn:asciiname":"Madoum II",
    "gn:country_code":"CM",
    "gn:dem":1284,
    "gn:feature_class":"P",
    "gn:feature_code":"PPL",
    "gn:name":"Madoum II",
    "gn:population":0,
    "gn:timezone":"Africa/Douala",
    "iso:country":"CM",
    "wof:name":"Madoum II",
    "wof:placetype":"locality"
},
  "geometry": {"coordinates":[10.53795,5.11551],"type":"Point"}
}