{
  "type": "Feature",
  "properties": {
    "gn:admin1_code":"12.0",
    "gn:asciiname":"Kourgui",
    "gn:country_code":"CM",
    "gn:dem":413,
    "gn:feature_class":"P",
    "gn:feature_code":"PPL",
    "gn:name":"Kourgui",
    "gn:population":0,
    "gn:timezone":"Africa/Douala",
    "iso:country":"CM",
    "name:und_x_variant":[
        "Kourgi",
        "Kourgul",
        "Kourgui"
    ],
    "wof:name":"Kourgui",
    "wof:placetype":"locality"
},
  "geometry": {"coordinates":[14.11111,11.08806],"type":"Point"}
}