{
  "type": "Feature",
  "properties": {
    "gn:admin1_code":"13.0",
    "gn:asciiname":"Tongo",
    "gn:country_code":"CM",
    "gn:dem":186,
    "gn:feature_class":"P",
    "gn:feature_code":"PPL",
    "gn:name":"Tongo",
    "gn:population":0,
    "gn:timezone":"Africa/Douala",
    "iso:country":"CM",
    "name:ceb_x_preferred":[
        "Tongo"
    ],
    "name:fra_x_preferred":[
        "Tongo"
    ],
    "name:ind_x_preferred":[
        "Tongo"
    ],
    "name:pol_x_preferred":[
        "Tongo"
    ],
    "name:swe_x_preferred":[
        "Tongo"
    ],
    "wof:name":"Tongo",
    "wof:placetype":"locality"
},
  "geometry": {"coordinates":[13.43949,9.35019],"type":"Point"}
}