{
  "type": "Feature",
  "properties": {
    "gn:admin1_code":"10.0",
    "gn:asciiname":"Mayo Dankali",
    "gn:country_code":"CM",
    "gn:dem":1004,
    "gn:feature_class":"P",
    "gn:feature_code":"PPL",
    "gn:name":"Mayo Dankali",
    "gn:population":0,
    "gn:timezone":"Africa/Douala",
    "iso:country":"CM",
    "name:und_x_variant":[
        "Dankali"
    ],
    "wof:name":"Mayo Dankali",
    "wof:placetype":"locality"
},
  "geometry": {"coordinates":[12.36185,6.98867],"type":"Point"}
}