{
  "type": "Feature",
  "properties": {
    "gn:admin1_code":"10.0",
    "gn:asciiname":"Amadou Nabata",
    "gn:country_code":"CM",
    "gn:dem":1265,
    "gn:feature_class":"P",
    "gn:feature_code":"PPL",
    "gn:name":"Amadou Nabata",
    "gn:population":0,
    "gn:timezone":"Africa/Douala",
    "iso:country":"CM",
    "wof:name":"Amadou Nabata",
    "wof:placetype":"locality"
},
  "geometry": {"coordinates":[14.65,6.81667],"type":"Point"}
}