{
  "type": "Feature",
  "properties": {
    "gn:admin1_code":"11.0",
    "gn:asciiname":"Emamemvam",
    "gn:country_code":"CM",
    "gn:dem":673,
    "gn:feature_class":"P",
    "gn:feature_code":"PPL",
    "gn:name":"Emamemvam",
    "gn:population":0,
    "gn:timezone":"Africa/Douala",
    "iso:country":"CM",
    "wof:name":"Emamemvam",
    "wof:placetype":"locality"
},
  "geometry": {"coordinates":[11.88333,3.53333],"type":"Point"}
}