{
  "type": "Feature",
  "properties": {
    "gn:admin1_code":"8.0",
    "gn:asciiname":"Chienke",
    "gn:country_code":"CM",
    "gn:dem":1821,
    "gn:feature_class":"P",
    "gn:feature_code":"PPL",
    "gn:name":"Chienke",
    "gn:population":0,
    "gn:timezone":"Africa/Douala",
    "iso:country":"CM",
    "wof:name":"Chienke",
    "wof:placetype":"locality"
},
  "geometry": {"coordinates":[10.40049,5.25714],"type":"Point"}
}