{
  "type": "Feature",
  "properties": {
    "gn:admin1_code":"8.0",
    "gn:asciiname":"Lepipi I",
    "gn:country_code":"CM",
    "gn:dem":1454,
    "gn:feature_class":"P",
    "gn:feature_code":"PPL",
    "gn:name":"Lepipi I",
    "gn:population":0,
    "gn:timezone":"Africa/Douala",
    "iso:country":"CM",
    "wof:name":"Lepipi I",
    "wof:placetype":"locality"
},
  "geometry": {"coordinates":[10.22903,5.50943],"type":"Point"}
}