{
  "type": "Feature",
  "properties": {
    "gn:admin1_code":"13.0",
    "gn:asciiname":"Boudang Touilbere",
    "gn:country_code":"CM",
    "gn:dem":201,
    "gn:feature_class":"P",
    "gn:feature_code":"PPL",
    "gn:name":"Boudang Touilb\u00e9r\u00e9",
    "gn:population":0,
    "gn:timezone":"Africa/Douala",
    "iso:country":"CM",
    "wof:name":"Boudang Touilbere",
    "wof:placetype":"locality"
},
  "geometry": {"coordinates":[12.93333,9.16667],"type":"Point"}
}