{
  "type": "Feature",
  "properties": {
    "gn:admin1_code":"14.0",
    "gn:asciiname":"Sonkote",
    "gn:country_code":"CM",
    "gn:dem":592,
    "gn:feature_class":"P",
    "gn:feature_code":"PPL",
    "gn:name":"Sonkote",
    "gn:population":0,
    "gn:timezone":"Africa/Douala",
    "iso:country":"CM",
    "wof:name":"Sonkote",
    "wof:placetype":"locality"
},
  "geometry": {"coordinates":[11.01667,2.86667],"type":"Point"}
}