{
  "type": "Feature",
  "properties": {
    "gn:admin1_code":"11.0",
    "gn:asciiname":"Yalongo",
    "gn:country_code":"CM",
    "gn:dem":598,
    "gn:feature_class":"P",
    "gn:feature_code":"PPL",
    "gn:name":"Yalongo",
    "gn:population":0,
    "gn:timezone":"Africa/Douala",
    "iso:country":"CM",
    "wof:name":"Yalongo",
    "wof:placetype":"locality"
},
  "geometry": {"coordinates":[11.68333,4.65],"type":"Point"}
}