{
  "type": "Feature",
  "properties": {
    "gn:admin1_code":"12.0",
    "gn:asciiname":"Lougouma",
    "gn:country_code":"CM",
    "gn:dem":306,
    "gn:feature_class":"P",
    "gn:feature_code":"PPL",
    "gn:name":"Lougouma",
    "gn:population":0,
    "gn:timezone":"Africa/Douala",
    "iso:country":"CM",
    "wof:name":"Lougouma",
    "wof:placetype":"locality"
},
  "geometry": {"coordinates":[14.89015,11.29764],"type":"Point"}
}