{
  "type": "Feature",
  "properties": {
    "gn:admin1_code":"13.0",
    "gn:asciiname":"Boumi",
    "gn:country_code":"CM",
    "gn:dem":421,
    "gn:feature_class":"P",
    "gn:feature_code":"PPL",
    "gn:name":"Boumi",
    "gn:population":0,
    "gn:timezone":"Africa/Douala",
    "iso:country":"CM",
    "wof:name":"Boumi",
    "wof:placetype":"locality"
},
  "geometry": {"coordinates":[13.38736,8.42776],"type":"Point"}
}