{
  "type": "Feature",
  "properties": {
    "gn:admin1_code":"12.0",
    "gn:asciiname":"Mogoday",
    "gn:country_code":"CM",
    "gn:dem":526,
    "gn:feature_class":"P",
    "gn:feature_code":"PPL",
    "gn:name":"Mogoday",
    "gn:population":0,
    "gn:timezone":"Africa/Douala",
    "iso:country":"CM",
    "wof:name":"Mogoday",
    "wof:placetype":"locality"
},
  "geometry": {"coordinates":[13.98406,10.52886],"type":"Point"}
}