{
  "type": "Feature",
  "properties": {
    "gn:admin1_code":"14.0",
    "gn:asciiname":"Mvila",
    "gn:country_code":"CM",
    "gn:dem":572,
    "gn:feature_class":"P",
    "gn:feature_code":"PPL",
    "gn:name":"Mvila",
    "gn:population":0,
    "gn:timezone":"Africa/Douala",
    "iso:country":"CM",
    "name:deu_x_preferred":[
        "Mvila"
    ],
    "name:fra_x_preferred":[
        "Mvila"
    ],
    "name:nld_x_preferred":[
        "Mvila"
    ],
    "name:nor_x_preferred":[
        "Mvila"
    ],
    "name:pol_x_preferred":[
        "Mvila"
    ],
    "name:rus_x_preferred":[
        "\u041c\u0432\u0438\u043b\u0430"
    ],
    "name:spa_x_preferred":[
        "Mvila"
    ],
    "name:urd_x_preferred":[
        "\u0645\u0648\u06cc\u0644\u0627"
    ],
    "name:zho_x_preferred":[
        "\u59c6\u7dad\u62c9\u5dde"
    ],
    "wof:name":"Mvila",
    "wof:placetype":"locality"
},
  "geometry": {"coordinates":[11.08333,2.85],"type":"Point"}
}