{
  "type": "Feature",
  "properties": {
    "gn:admin1_code":"12.0",
    "gn:asciiname":"Goundey",
    "gn:country_code":"CM",
    "gn:dem":383,
    "gn:feature_class":"P",
    "gn:feature_code":"PPL",
    "gn:name":"Goundey",
    "gn:population":0,
    "gn:timezone":"Africa/Douala",
    "iso:country":"CM",
    "name:und_x_variant":[
        "Goundey Mango",
        "Goundey"
    ],
    "wof:name":"Goundey",
    "wof:placetype":"locality"
},
  "geometry": {"coordinates":[14.69969,10.02735],"type":"Point"}
}