{
  "type": "Feature",
  "properties": {
    "gn:admin1_code":"7.0",
    "gn:asciiname":"Koping",
    "gn:country_code":"CM",
    "gn:dem":1367,
    "gn:feature_class":"P",
    "gn:feature_code":"PPL",
    "gn:name":"Koping",
    "gn:population":0,
    "gn:timezone":"Africa/Douala",
    "iso:country":"CM",
    "name:fra_x_preferred":[
        "Koping"
    ],
    "wof:name":"Koping",
    "wof:placetype":"locality"
},
  "geometry": {"coordinates":[10.04871,5.86028],"type":"Point"}
}