{
  "type": "Feature",
  "properties": {
    "gn:admin1_code":"13.0",
    "gn:asciiname":"Lakbin",
    "gn:country_code":"CM",
    "gn:dem":607,
    "gn:feature_class":"P",
    "gn:feature_code":"PPL",
    "gn:name":"Lakbin",
    "gn:population":0,
    "gn:timezone":"Africa/Douala",
    "iso:country":"CM",
    "wof:name":"Lakbin",
    "wof:placetype":"locality"
},
  "geometry": {"coordinates":[15.27955,7.32581],"type":"Point"}
}