{
  "type": "Feature",
  "properties": {
    "gn:admin1_code":"12.0",
    "gn:asciiname":"Mayo Kaba",
    "gn:country_code":"CM",
    "gn:dem":522,
    "gn:feature_class":"P",
    "gn:feature_code":"PPL",
    "gn:name":"Mayo Kaba",
    "gn:population":0,
    "gn:timezone":"Africa/Douala",
    "iso:country":"CM",
    "wof:name":"Mayo Kaba",
    "wof:placetype":"locality"
},
  "geometry": {"coordinates":[13.8693,10.28261],"type":"Point"}
}