{
  "type": "Feature",
  "properties": {
    "gn:admin1_code":"14.0",
    "gn:asciiname":"Mouge",
    "gn:country_code":"CM",
    "gn:dem":453,
    "gn:feature_class":"P",
    "gn:feature_code":"PPL",
    "gn:name":"Moug\u00e9",
    "gn:population":0,
    "gn:timezone":"Africa/Douala",
    "iso:country":"CM",
    "name:und_x_variant":[
        "Mougu\u00e9",
        "Moug\u00e9"
    ],
    "wof:name":"Mouge",
    "wof:placetype":"locality"
},
  "geometry": {"coordinates":[10.63333,3.23333],"type":"Point"}
}