{
  "type": "Feature",
  "properties": {
    "gn:admin1_code":"13.0",
    "gn:asciiname":"Arnadola",
    "gn:country_code":"CM",
    "gn:dem":1140,
    "gn:feature_class":"P",
    "gn:feature_code":"PPL",
    "gn:name":"Arnadola",
    "gn:population":0,
    "gn:timezone":"Africa/Douala",
    "iso:country":"CM",
    "wof:name":"Arnadola",
    "wof:placetype":"locality"
},
  "geometry": {"coordinates":[13.85,7.65],"type":"Point"}
}