{
  "type": "Feature",
  "properties": {
    "gn:admin1_code":"9.0",
    "gn:asciiname":"Nchang",
    "gn:country_code":"CM",
    "gn:dem":176,
    "gn:feature_class":"P",
    "gn:feature_code":"PPL",
    "gn:name":"Nchang",
    "gn:population":0,
    "gn:timezone":"Africa/Douala",
    "iso:country":"CM",
    "wof:name":"Nchang",
    "wof:placetype":"locality"
},
  "geometry": {"coordinates":[9.2165,5.6433],"type":"Point"}
}