{
  "type": "Feature",
  "properties": {
    "gn:admin1_code":"4.0",
    "gn:asciiname":"Lala II",
    "gn:country_code":"CM",
    "gn:dem":661,
    "gn:feature_class":"P",
    "gn:feature_code":"PPL",
    "gn:name":"Lala II",
    "gn:population":0,
    "gn:timezone":"Africa/Douala",
    "iso:country":"CM",
    "name:und_x_variant":[
        "Lala",
        "Lala II"
    ],
    "wof:name":"Lala II",
    "wof:placetype":"locality"
},
  "geometry": {"coordinates":[14.31667,4.85],"type":"Point"}
}