{
  "type": "Feature",
  "properties": {
    "gn:admin1_code":"12.0",
    "gn:asciiname":"Mounkeu",
    "gn:country_code":"CM",
    "gn:dem":298,
    "gn:feature_class":"P",
    "gn:feature_code":"PPL",
    "gn:name":"Mounkeu",
    "gn:population":0,
    "gn:timezone":"Africa/Douala",
    "iso:country":"CM",
    "name:und_x_variant":[
        "M\u00fanke",
        "Mounk\u00e9",
        "Mounkeu"
    ],
    "wof:name":"Mounkeu",
    "wof:placetype":"locality"
},
  "geometry": {"coordinates":[14.99652,11.88971],"type":"Point"}
}