{
  "type": "Feature",
  "properties": {
    "gn:admin1_code":"12.0",
    "gn:asciiname":"Bouche",
    "gn:country_code":"CM",
    "gn:dem":706,
    "gn:feature_class":"P",
    "gn:feature_code":"PPL",
    "gn:name":"Bouch\u00e9",
    "gn:population":0,
    "gn:timezone":"Africa/Douala",
    "iso:country":"CM",
    "wof:name":"Bouche",
    "wof:placetype":"locality"
},
  "geometry": {"coordinates":[14.017,10.91286],"type":"Point"}
}