{
  "type": "Feature",
  "properties": {
    "gn:admin1_code":"13.0",
    "gn:asciiname":"Madjadou",
    "gn:country_code":"CM",
    "gn:dem":549,
    "gn:feature_class":"P",
    "gn:feature_code":"PPL",
    "gn:name":"Madjadou",
    "gn:population":0,
    "gn:timezone":"Africa/Douala",
    "iso:country":"CM",
    "wof:name":"Madjadou",
    "wof:placetype":"locality"
},
  "geometry": {"coordinates":[13.39828,8.14808],"type":"Point"}
}