{
  "type": "Feature",
  "properties": {
    "gn:admin1_code":"7.0",
    "gn:asciiname":"Niko",
    "gn:country_code":"CM",
    "gn:dem":1521,
    "gn:feature_class":"P",
    "gn:feature_code":"PPL",
    "gn:name":"Niko",
    "gn:population":0,
    "gn:timezone":"Africa/Douala",
    "iso:country":"CM",
    "wof:name":"Niko",
    "wof:placetype":"locality"
},
  "geometry": {"coordinates":[9.8868,6.1383],"type":"Point"}
}