{
  "type": "Feature",
  "properties": {
    "gn:admin1_code":"9.0",
    "gn:asciiname":"Pungo",
    "gn:country_code":"CM",
    "gn:dem":23,
    "gn:feature_class":"P",
    "gn:feature_code":"PPL",
    "gn:name":"Pungo",
    "gn:population":0,
    "gn:timezone":"Africa/Douala",
    "iso:country":"CM",
    "wof:name":"Pungo",
    "wof:placetype":"locality"
},
  "geometry": {"coordinates":[9.3993,4.1154],"type":"Point"}
}