{
  "type": "Feature",
  "properties": {
    "gn:admin1_code":"13.0",
    "gn:asciiname":"Koyanga",
    "gn:country_code":"CM",
    "gn:dem":202,
    "gn:feature_class":"P",
    "gn:feature_code":"PPL",
    "gn:name":"Koyanga",
    "gn:population":0,
    "gn:timezone":"Africa/Douala",
    "iso:country":"CM",
    "wof:name":"Koyanga",
    "wof:placetype":"locality"
},
  "geometry": {"coordinates":[13.54632,9.2668],"type":"Point"}
}