{
  "type": "Feature",
  "properties": {
    "gn:admin1_code":"12.0",
    "gn:asciiname":"Yam Kouvel",
    "gn:country_code":"CM",
    "gn:dem":457,
    "gn:feature_class":"P",
    "gn:feature_code":"PPL",
    "gn:name":"Yam Kouv\u00e8l",
    "gn:population":0,
    "gn:timezone":"Africa/Douala",
    "iso:country":"CM",
    "wof:name":"Yam Kouvel",
    "wof:placetype":"locality"
},
  "geometry": {"coordinates":[13.97872,10.95507],"type":"Point"}
}