{
  "type": "Feature",
  "properties": {
    "gn:admin1_code":"4.0",
    "gn:asciiname":"Melen V",
    "gn:country_code":"CM",
    "gn:dem":669,
    "gn:feature_class":"P",
    "gn:feature_code":"PPL",
    "gn:name":"M\u00e9len V",
    "gn:population":0,
    "gn:timezone":"Africa/Douala",
    "iso:country":"CM",
    "wof:name":"Melen V",
    "wof:placetype":"locality"
},
  "geometry": {"coordinates":[13.06667,3.48333],"type":"Point"}
}