{
  "type": "Feature",
  "properties": {
    "gn:admin1_code":"9.0",
    "gn:asciiname":"Baro",
    "gn:country_code":"CM",
    "gn:dem":112,
    "gn:feature_class":"P",
    "gn:feature_code":"PPL",
    "gn:name":"Baro",
    "gn:population":0,
    "gn:timezone":"Africa/Douala",
    "iso:country":"CM",
    "wof:name":"Baro",
    "wof:placetype":"locality"
},
  "geometry": {"coordinates":[9.2091,5.6679],"type":"Point"}
}