{
  "type": "Feature",
  "properties": {
    "gn:admin1_code":"8.0",
    "gn:asciiname":"Topou",
    "gn:country_code":"CM",
    "gn:dem":1481,
    "gn:feature_class":"P",
    "gn:feature_code":"PPL",
    "gn:name":"Topou",
    "gn:population":0,
    "gn:timezone":"Africa/Douala",
    "iso:country":"CM",
    "wof:name":"Topou",
    "wof:placetype":"locality"
},
  "geometry": {"coordinates":[10.36293,5.44048],"type":"Point"}
}