{
  "type": "Feature",
  "properties": {
    "gn:admin1_code":"12.0",
    "gn:asciiname":"Ngozoko",
    "gn:country_code":"CM",
    "gn:dem":603,
    "gn:feature_class":"P",
    "gn:feature_code":"PPL",
    "gn:name":"Ngozoko",
    "gn:population":0,
    "gn:timezone":"Africa/Douala",
    "iso:country":"CM",
    "wof:name":"Ngozoko",
    "wof:placetype":"locality"
},
  "geometry": {"coordinates":[13.99718,10.68022],"type":"Point"}
}