{
  "type": "Feature",
  "properties": {
    "gn:admin1_code":"12.0",
    "gn:asciiname":"Bazouda",
    "gn:country_code":"CM",
    "gn:dem":843,
    "gn:feature_class":"P",
    "gn:feature_code":"PPL",
    "gn:name":"Bazouda",
    "gn:population":0,
    "gn:timezone":"Africa/Douala",
    "iso:country":"CM",
    "wof:name":"Bazouda",
    "wof:placetype":"locality"
},
  "geometry": {"coordinates":[13.83515,10.81577],"type":"Point"}
}