{
  "type": "Feature",
  "properties": {
    "gn:admin1_code":"13.0",
    "gn:asciiname":"Hore Nyiwa",
    "gn:country_code":"CM",
    "gn:dem":327,
    "gn:feature_class":"P",
    "gn:feature_code":"PPL",
    "gn:name":"H\u00f4r\u00e9 Ny\u00eewa",
    "gn:population":0,
    "gn:timezone":"Africa/Douala",
    "iso:country":"CM",
    "name:und_x_variant":[
        "H\u00f4r\u00e9 Ny\u00eewa",
        "Dima"
    ],
    "wof:name":"Hore Nyiwa",
    "wof:placetype":"locality"
},
  "geometry": {"coordinates":[13.54736,8.78114],"type":"Point"}
}