{
  "type": "Feature",
  "properties": {
    "gn:admin1_code":"7.0",
    "gn:asciiname":"Sowe",
    "gn:country_code":"CM",
    "gn:dem":1199,
    "gn:feature_class":"P",
    "gn:feature_code":"PPL",
    "gn:name":"Sowe",
    "gn:population":0,
    "gn:timezone":"Africa/Douala",
    "iso:country":"CM",
    "name:deu_x_preferred":[
        "Sowe"
    ],
    "name:und_x_variant":[
        "Sawe",
        "Kaw",
        "Sa",
        "Sowe"
    ],
    "wof:name":"Sowe",
    "wof:placetype":"locality"
},
  "geometry": {"coordinates":[10.36667,6.45],"type":"Point"}
}