{
  "type": "Feature",
  "properties": {
    "gn:admin1_code":"12.0",
    "gn:asciiname":"Kalgoulou",
    "gn:country_code":"CM",
    "gn:dem":302,
    "gn:feature_class":"P",
    "gn:feature_code":"PPL",
    "gn:name":"Kalgoulou",
    "gn:population":0,
    "gn:timezone":"Africa/Douala",
    "iso:country":"CM",
    "wof:name":"Kalgoulou",
    "wof:placetype":"locality"
},
  "geometry": {"coordinates":[14.99273,11.54765],"type":"Point"}
}