{
  "type": "Feature",
  "properties": {
    "gn:admin1_code":"10.0",
    "gn:asciiname":"Batoakoum",
    "gn:country_code":"CM",
    "gn:dem":728,
    "gn:feature_class":"P",
    "gn:feature_code":"PPL",
    "gn:name":"Batoakoum",
    "gn:population":0,
    "gn:timezone":"Africa/Douala",
    "iso:country":"CM",
    "name:und_x_variant":[
        "Mbotakoum",
        "Batoakoum"
    ],
    "wof:name":"Batoakoum",
    "wof:placetype":"locality"
},
  "geometry": {"coordinates":[11.28333,6.13333],"type":"Point"}
}