{
  "type": "Feature",
  "properties": {
    "gn:admin1_code":"12.0",
    "gn:asciiname":"Djafada",
    "gn:country_code":"CM",
    "gn:dem":407,
    "gn:feature_class":"P",
    "gn:feature_code":"PPL",
    "gn:name":"Djafada",
    "gn:population":0,
    "gn:timezone":"Africa/Douala",
    "iso:country":"CM",
    "wof:name":"Djafada",
    "wof:placetype":"locality"
},
  "geometry": {"coordinates":[14.4485,10.17395],"type":"Point"}
}