{
  "type": "Feature",
  "properties": {
    "gn:admin1_code":"8.0",
    "gn:asciiname":"Tchie",
    "gn:country_code":"CM",
    "gn:dem":1497,
    "gn:feature_class":"P",
    "gn:feature_code":"PPL",
    "gn:name":"Tchi\u00e8",
    "gn:population":0,
    "gn:timezone":"Africa/Douala",
    "iso:country":"CM",
    "wof:name":"Tchie",
    "wof:placetype":"locality"
},
  "geometry": {"coordinates":[10.32025,5.47453],"type":"Point"}
}