{
  "type": "Feature",
  "properties": {
    "gn:admin1_code":"12.0",
    "gn:asciiname":"Mouskate",
    "gn:country_code":"CM",
    "gn:dem":300,
    "gn:feature_class":"P",
    "gn:feature_code":"PPL",
    "gn:name":"Mouskat\u00e9",
    "gn:population":0,
    "gn:timezone":"Africa/Douala",
    "iso:country":"CM",
    "name:und_x_variant":[
        "Mask\u00e9t\u00e9",
        "Mouskat\u00e9"
    ],
    "wof:name":"Mouskate",
    "wof:placetype":"locality"
},
  "geometry": {"coordinates":[14.98097,11.83666],"type":"Point"}
}