{
  "type": "Feature",
  "properties": {
    "gn:admin1_code":"12.0",
    "gn:asciiname":"Mingouas",
    "gn:country_code":"CM",
    "gn:dem":566,
    "gn:feature_class":"P",
    "gn:feature_code":"PPL",
    "gn:name":"Mingouas",
    "gn:population":0,
    "gn:timezone":"Africa/Douala",
    "iso:country":"CM",
    "wof:name":"Mingouas",
    "wof:placetype":"locality"
},
  "geometry": {"coordinates":[14.01801,10.57439],"type":"Point"}
}