{
  "type": "Feature",
  "properties": {
    "gn:admin1_code":"10.0",
    "gn:asciiname":"Djaoro Abo",
    "gn:country_code":"CM",
    "gn:dem":955,
    "gn:feature_class":"P",
    "gn:feature_code":"PPL",
    "gn:name":"Djaoro Abo",
    "gn:population":0,
    "gn:timezone":"Africa/Douala",
    "iso:country":"CM",
    "wof:name":"Djaoro Abo",
    "wof:placetype":"locality"
},
  "geometry": {"coordinates":[13.13333,7.26667],"type":"Point"}
}