{
  "type": "Feature",
  "properties": {
    "gn:admin1_code":"12.0",
    "gn:asciiname":"Moudoukoua",
    "gn:country_code":"CM",
    "gn:dem":590,
    "gn:feature_class":"P",
    "gn:feature_code":"PPL",
    "gn:name":"Moudoukoua",
    "gn:population":0,
    "gn:timezone":"Africa/Douala",
    "iso:country":"CM",
    "name:und_x_variant":[
        "Moudougoua"
    ],
    "wof:name":"Moudoukoua",
    "wof:placetype":"locality"
},
  "geometry": {"coordinates":[13.7865,10.9432],"type":"Point"}
}