{
  "type": "Feature",
  "properties": {
    "gn:admin1_code":"12.0",
    "gn:asciiname":"Zanga",
    "gn:country_code":"CM",
    "gn:dem":418,
    "gn:feature_class":"P",
    "gn:feature_code":"PPL",
    "gn:name":"Zanga",
    "gn:population":0,
    "gn:timezone":"Africa/Douala",
    "iso:country":"CM",
    "wof:name":"Zanga",
    "wof:placetype":"locality"
},
  "geometry": {"coordinates":[13.8742,11.11984],"type":"Point"}
}