{
  "type": "Feature",
  "properties": {
    "gn:admin1_code":"4.0",
    "gn:asciiname":"Koso",
    "gn:country_code":"CM",
    "gn:dem":655,
    "gn:feature_class":"P",
    "gn:feature_code":"PPL",
    "gn:name":"Koso",
    "gn:population":0,
    "gn:timezone":"Africa/Douala",
    "iso:country":"CM",
    "name:ceb_x_preferred":[
        "Koso"
    ],
    "name:swe_x_preferred":[
        "Koso"
    ],
    "name:und_x_variant":[
        "Kosso",
        "Kossa",
        "Koso"
    ],
    "wof:name":"Koso",
    "wof:placetype":"locality"
},
  "geometry": {"coordinates":[14.16667,3.93333],"type":"Point"}
}