{
  "type": "Feature",
  "properties": {
    "gn:admin1_code":"10.0",
    "gn:asciiname":"Longtre",
    "gn:country_code":"CM",
    "gn:dem":1185,
    "gn:feature_class":"P",
    "gn:feature_code":"PPL",
    "gn:name":"Longtr\u00e9",
    "gn:population":0,
    "gn:timezone":"Africa/Douala",
    "iso:country":"CM",
    "wof:name":"Longtre",
    "wof:placetype":"locality"
},
  "geometry": {"coordinates":[13.55,7.25],"type":"Point"}
}