{
  "type": "Feature",
  "properties": {
    "gn:admin1_code":"4.0",
    "gn:admin2_code":"2229251.0",
    "gn:asciiname":"Sarambi",
    "gn:country_code":"CM",
    "gn:dem":712,
    "gn:feature_class":"P",
    "gn:feature_code":"PPL",
    "gn:name":"Sarambi",
    "gn:population":0,
    "gn:timezone":"Africa/Douala",
    "iso:country":"CM",
    "wof:name":"Sarambi",
    "wof:placetype":"locality"
},
  "geometry": {"coordinates":[13.91667,5.56667],"type":"Point"}
}