{
  "type": "Feature",
  "properties": {
    "gn:admin1_code":"7.0",
    "gn:asciiname":"Bajem",
    "gn:country_code":"CM",
    "gn:dem":823,
    "gn:feature_class":"P",
    "gn:feature_code":"PPL",
    "gn:name":"Bajem",
    "gn:population":0,
    "gn:timezone":"Africa/Douala",
    "iso:country":"CM",
    "wof:name":"Bajem",
    "wof:placetype":"locality"
},
  "geometry": {"coordinates":[9.775,5.8933],"type":"Point"}
}