{
  "type": "Feature",
  "properties": {
    "gn:admin1_code":"8.0",
    "gn:asciiname":"Panket",
    "gn:country_code":"CM",
    "gn:dem":1169,
    "gn:feature_class":"P",
    "gn:feature_code":"PPL",
    "gn:name":"Pank\u00e8t",
    "gn:population":0,
    "gn:timezone":"Africa/Douala",
    "iso:country":"CM",
    "wof:name":"Panket",
    "wof:placetype":"locality"
},
  "geometry": {"coordinates":[10.52163,5.63015],"type":"Point"}
}