{
  "type": "Feature",
  "properties": {
    "gn:admin1_code":"8.0",
    "gn:asciiname":"Djemgang",
    "gn:country_code":"CM",
    "gn:dem":1488,
    "gn:feature_class":"P",
    "gn:feature_code":"PPL",
    "gn:name":"Djemgang",
    "gn:population":0,
    "gn:timezone":"Africa/Douala",
    "iso:country":"CM",
    "wof:name":"Djemgang",
    "wof:placetype":"locality"
},
  "geometry": {"coordinates":[10.49655,5.26341],"type":"Point"}
}