{
  "type": "Feature",
  "properties": {
    "gn:admin1_code":"8.0",
    "gn:asciiname":"Mboutong",
    "gn:country_code":"CM",
    "gn:dem":1246,
    "gn:feature_class":"P",
    "gn:feature_code":"PPL",
    "gn:name":"Mboutong",
    "gn:population":0,
    "gn:timezone":"Africa/Douala",
    "iso:country":"CM",
    "wof:name":"Mboutong",
    "wof:placetype":"locality"
},
  "geometry": {"coordinates":[10.42292,5.03859],"type":"Point"}
}