{
  "type": "Feature",
  "properties": {
    "gn:admin1_code":"9.0",
    "gn:asciiname":"Mongossi",
    "gn:country_code":"CM",
    "gn:dem":12,
    "gn:feature_class":"P",
    "gn:feature_code":"PPL",
    "gn:name":"Mongossi",
    "gn:population":0,
    "gn:timezone":"Africa/Douala",
    "iso:country":"CM",
    "wof:name":"Mongossi",
    "wof:placetype":"locality"
},
  "geometry": {"coordinates":[9.0117,4.5757],"type":"Point"}
}