{
  "type": "Feature",
  "properties": {
    "gn:admin1_code":"8.0",
    "gn:asciiname":"Tsela'",
    "gn:country_code":"CM",
    "gn:dem":1811,
    "gn:feature_class":"P",
    "gn:feature_code":"PPL",
    "gn:name":"Tsela\u2019",
    "gn:population":0,
    "gn:timezone":"Africa/Douala",
    "iso:country":"CM",
    "name:fra_x_preferred":[
        "Batsela"
    ],
    "name:und_x_variant":[
        "Tsela\u2019",
        "Tsela\u2019 I"
    ],
    "wof:name":"Tsela'",
    "wof:placetype":"locality"
},
  "geometry": {"coordinates":[10.36803,5.26129],"type":"Point"}
}