{
  "type": "Feature",
  "properties": {
    "gn:admin1_code":"12.0",
    "gn:asciiname":"Gaviang",
    "gn:country_code":"CM",
    "gn:dem":446,
    "gn:feature_class":"P",
    "gn:feature_code":"PPL",
    "gn:name":"Gaviang",
    "gn:population":0,
    "gn:timezone":"Africa/Douala",
    "iso:country":"CM",
    "wof:name":"Gaviang",
    "wof:placetype":"locality"
},
  "geometry": {"coordinates":[14.28862,10.37549],"type":"Point"}
}