{
  "type": "Feature",
  "properties": {
    "gn:admin1_code":"8.0",
    "gn:asciiname":"Mvetchwet",
    "gn:country_code":"CM",
    "gn:dem":1468,
    "gn:feature_class":"P",
    "gn:feature_code":"PPL",
    "gn:name":"Mvetchwet",
    "gn:population":0,
    "gn:timezone":"Africa/Douala",
    "iso:country":"CM",
    "name:fra_x_preferred":[
        "Mvetchwet"
    ],
    "wof:name":"Mvetchwet",
    "wof:placetype":"locality"
},
  "geometry": {"coordinates":[10.48781,5.12748],"type":"Point"}
}