{
  "type": "Feature",
  "properties": {
    "gn:admin1_code":"4.0",
    "gn:asciiname":"Ngoto",
    "gn:country_code":"CM",
    "gn:dem":614,
    "gn:feature_class":"P",
    "gn:feature_code":"PPL",
    "gn:name":"Ngoto",
    "gn:population":0,
    "gn:timezone":"Africa/Douala",
    "iso:country":"CM",
    "name:und_x_variant":[
        "Godo",
        "Ngoto"
    ],
    "wof:name":"Ngoto",
    "wof:placetype":"locality"
},
  "geometry": {"coordinates":[14.76667,4.18333],"type":"Point"}
}