{
  "type": "Feature",
  "properties": {
    "gn:admin1_code":"4.0",
    "gn:asciiname":"Sangale",
    "gn:country_code":"CM",
    "gn:dem":603,
    "gn:feature_class":"P",
    "gn:feature_code":"PPL",
    "gn:name":"Sangal\u00e9",
    "gn:population":0,
    "gn:timezone":"Africa/Douala",
    "iso:country":"CM",
    "name:und_x_variant":[
        "Sanguali",
        "Sangal\u00e9"
    ],
    "wof:name":"Sangale",
    "wof:placetype":"locality"
},
  "geometry": {"coordinates":[14.81667,4.16667],"type":"Point"}
}