{
  "type": "Feature",
  "properties": {
    "gn:admin1_code":"12.0",
    "gn:asciiname":"Sague Chia",
    "gn:country_code":"CM",
    "gn:dem":291,
    "gn:feature_class":"P",
    "gn:feature_code":"PPL",
    "gn:name":"Sagu\u00e9 Chia",
    "gn:population":0,
    "gn:timezone":"Africa/Douala",
    "iso:country":"CM",
    "name:und_x_variant":[
        "Sagu\u00e9 Chia",
        "Sagu\u00e9"
    ],
    "wof:name":"Sague Chia",
    "wof:placetype":"locality"
},
  "geometry": {"coordinates":[14.52726,12.60595],"type":"Point"}
}