{
  "type": "Feature",
  "properties": {
    "gn:admin1_code":"5.0",
    "gn:asciiname":"Ekomdjong",
    "gn:country_code":"CM",
    "gn:dem":473,
    "gn:feature_class":"P",
    "gn:feature_code":"PPL",
    "gn:name":"Ekomdjong",
    "gn:population":0,
    "gn:timezone":"Africa/Douala",
    "iso:country":"CM",
    "wof:name":"Ekomdjong",
    "wof:placetype":"locality"
},
  "geometry": {"coordinates":[9.8978,4.8042],"type":"Point"}
}