{
  "type": "Feature",
  "properties": {
    "gn:admin1_code":"12.0",
    "gn:asciiname":"Diguir",
    "gn:country_code":"CM",
    "gn:dem":355,
    "gn:feature_class":"P",
    "gn:feature_code":"PPL",
    "gn:name":"Diguir",
    "gn:population":0,
    "gn:timezone":"Africa/Douala",
    "iso:country":"CM",
    "wof:name":"Diguir",
    "wof:placetype":"locality"
},
  "geometry": {"coordinates":[14.50347,10.71834],"type":"Point"}
}