{
  "type": "Feature",
  "properties": {
    "gn:admin1_code":"11.0",
    "gn:asciiname":"Odza I",
    "gn:country_code":"CM",
    "gn:dem":693,
    "gn:feature_class":"P",
    "gn:feature_code":"PPL",
    "gn:name":"Odza I",
    "gn:population":0,
    "gn:timezone":"Africa/Douala",
    "iso:country":"CM",
    "name:und_x_variant":[
        "Ozoa",
        "Odza",
        "Odza I"
    ],
    "wof:name":"Odza I",
    "wof:placetype":"locality"
},
  "geometry": {"coordinates":[11.53333,3.78333],"type":"Point"}
}