{
  "type": "Feature",
  "properties": {
    "gn:admin1_code":"4.0",
    "gn:asciiname":"Biwala",
    "gn:country_code":"CM",
    "gn:dem":583,
    "gn:feature_class":"P",
    "gn:feature_code":"PPL",
    "gn:name":"Biwala",
    "gn:population":0,
    "gn:timezone":"Africa/Douala",
    "iso:country":"CM",
    "name:und_x_variant":[
        "Mata\u2019s",
        "Bivola",
        "Biw\u014flo",
        "Biwala"
    ],
    "wof:name":"Biwala",
    "wof:placetype":"locality"
},
  "geometry": {"coordinates":[14.95,3.15],"type":"Point"}
}