{
  "type": "Feature",
  "properties": {
    "gn:admin1_code":"12.0",
    "gn:asciiname":"Bla Matoko",
    "gn:country_code":"CM",
    "gn:dem":311,
    "gn:feature_class":"P",
    "gn:feature_code":"PPL",
    "gn:name":"Bla Matoko",
    "gn:population":0,
    "gn:timezone":"Africa/Douala",
    "iso:country":"CM",
    "name:und_x_variant":[
        "Bila Matoko",
        "Bla Matoko"
    ],
    "wof:name":"Bla Matoko",
    "wof:placetype":"locality"
},
  "geometry": {"coordinates":[14.81109,10.91901],"type":"Point"}
}