{
  "type": "Feature",
  "properties": {
    "gn:admin1_code":"12.0",
    "gn:asciiname":"Soulfa",
    "gn:country_code":"CM",
    "gn:dem":292,
    "gn:feature_class":"P",
    "gn:feature_code":"PPL",
    "gn:name":"Soulfa",
    "gn:population":0,
    "gn:timezone":"Africa/Douala",
    "iso:country":"CM",
    "name:und_x_variant":[
        "Sulfa",
        "Soulfa"
    ],
    "wof:name":"Soulfa",
    "wof:placetype":"locality"
},
  "geometry": {"coordinates":[14.46623,12.39686],"type":"Point"}
}