{
  "type": "Feature",
  "properties": {
    "gn:admin1_code":"12.0",
    "gn:asciiname":"Abassouni I",
    "gn:country_code":"CM",
    "gn:dem":290,
    "gn:feature_class":"P",
    "gn:feature_code":"PPL",
    "gn:name":"Abassouni I",
    "gn:population":0,
    "gn:timezone":"Africa/Douala",
    "iso:country":"CM",
    "name:und_x_variant":[
        "Abasouni",
        "Abassouni I"
    ],
    "wof:name":"Abassouni I",
    "wof:placetype":"locality"
},
  "geometry": {"coordinates":[14.27851,12.67275],"type":"Point"}
}