{
  "type": "Feature",
  "properties": {
    "gn:admin1_code":"13.0",
    "gn:asciiname":"Niambaran",
    "gn:country_code":"CM",
    "gn:dem":809,
    "gn:feature_class":"P",
    "gn:feature_code":"PPL",
    "gn:name":"Niambaran",
    "gn:population":0,
    "gn:timezone":"Africa/Douala",
    "iso:country":"CM",
    "wof:name":"Niambaran",
    "wof:placetype":"locality"
},
  "geometry": {"coordinates":[13.16667,7.63333],"type":"Point"}
}