{
  "type": "Feature",
  "properties": {
    "gn:admin1_code":"12.0",
    "gn:asciiname":"Ndodehe Arabe",
    "gn:country_code":"CM",
    "gn:dem":291,
    "gn:feature_class":"P",
    "gn:feature_code":"PPL",
    "gn:name":"Ndod\u00e9h\u00e9 Arabe",
    "gn:population":0,
    "gn:timezone":"Africa/Douala",
    "iso:country":"CM",
    "name:und_x_variant":[
        "Ndod\u00e9h\u00e9 Arabe",
        "Ndod\u00e9h\u00e9"
    ],
    "wof:name":"Ndodehe Arabe",
    "wof:placetype":"locality"
},
  "geometry": {"coordinates":[14.43757,12.46289],"type":"Point"}
}