{
  "type": "Feature",
  "properties": {
    "gn:admin1_code":"13.0",
    "gn:asciiname":"Ganmba",
    "gn:country_code":"CM",
    "gn:dem":586,
    "gn:feature_class":"P",
    "gn:feature_code":"PPL",
    "gn:name":"Ganmba",
    "gn:population":0,
    "gn:timezone":"Africa/Douala",
    "iso:country":"CM",
    "name:und_x_variant":[
        "Gamba",
        "Ganmba"
    ],
    "wof:name":"Ganmba",
    "wof:placetype":"locality"
},
  "geometry": {"coordinates":[13.57485,8.11998],"type":"Point"}
}