{
  "type": "Feature",
  "properties": {
    "gn:admin1_code":"13.0",
    "gn:asciiname":"Bokire-Balda",
    "gn:country_code":"CM",
    "gn:dem":230,
    "gn:feature_class":"P",
    "gn:feature_code":"PPL",
    "gn:name":"Bokir\u00e9-Balda",
    "gn:population":0,
    "gn:timezone":"Africa/Douala",
    "iso:country":"CM",
    "name:und_x_variant":[
        "Bokir\u00e9-Balda",
        "Balda"
    ],
    "wof:name":"Bokire-Balda",
    "wof:placetype":"locality"
},
  "geometry": {"coordinates":[13.89615,9.62612],"type":"Point"}
}