{
  "type": "Feature",
  "properties": {
    "gn:country":"CM",
    "gn:fcode":"PPL",
    "gn:population":5390,
    "iso:country":"CM",
    "name:bul_x_preferred":[
        "\u041e\u043a\u043e\u043b\u0430"
    ],
    "name:ceb_x_preferred":[
        "Okola"
    ],
    "name:deu_x_preferred":[
        "Okola"
    ],
    "name:eng_x_preferred":[
        "Okola"
    ],
    "name:fra_x_preferred":[
        "Okola"
    ],
    "name:hun_x_preferred":[
        "Okola"
    ],
    "name:ita_x_preferred":[
        "Okola"
    ],
    "name:msa_x_preferred":[
        "Okola"
    ],
    "name:nan_x_preferred":[
        "Okola"
    ],
    "name:nld_x_preferred":[
        "Okola"
    ],
    "name:spa_x_preferred":[
        "Okola"
    ],
    "name:swe_x_preferred":[
        "Okola"
    ],
    "name:szl_x_preferred":[
        "Okola"
    ],
    "qs_pg:aaroncc":"CM",
    "qs_pg:gn_country":"CM",
    "qs_pg:gn_fcode":"PPL",
    "qs_pg:gn_pop":5390,
    "qs_pg:name":"Okola",
    "qs_pg:photos_9r":0,
    "qs_pg:photos_sr":0,
    "qs_pg:pop_sr":5,
    "qs_pg:qs_pg_placetype":"locality",
    "wof:name":"Okola",
    "wof:placetype":"locality",
    "wof:population":5390
},
  "geometry": {"coordinates":[11.38333,4.01667],"type":"Point"}
}