{
  "type": "Feature",
  "properties": {
    "gn:admin1_code":"10.0",
    "gn:asciiname":"Maboum",
    "gn:country_code":"CM",
    "gn:dem":1173,
    "gn:feature_class":"P",
    "gn:feature_code":"PPL",
    "gn:name":"Maboum",
    "gn:population":0,
    "gn:timezone":"Africa/Douala",
    "iso:country":"CM",
    "wof:name":"Maboum",
    "wof:placetype":"locality"
},
  "geometry": {"coordinates":[13.78333,7.58333],"type":"Point"}
}