{
  "type": "Feature",
  "properties": {
    "gn:admin1_code":"4.0",
    "gn:asciiname":"Dem",
    "gn:country_code":"CM",
    "gn:dem":653,
    "gn:feature_class":"P",
    "gn:feature_code":"PPL",
    "gn:name":"Dem",
    "gn:population":0,
    "gn:timezone":"Africa/Douala",
    "iso:country":"CM",
    "wof:name":"Dem",
    "wof:placetype":"locality"
},
  "geometry": {"coordinates":[14.44359,4.46622],"type":"Point"}
}