{
  "type": "Feature",
  "properties": {
    "gn:admin1_code":"12.0",
    "gn:asciiname":"Porkouata",
    "gn:country_code":"CM",
    "gn:dem":658,
    "gn:feature_class":"P",
    "gn:feature_code":"PPL",
    "gn:name":"Porkouata",
    "gn:population":0,
    "gn:timezone":"Africa/Douala",
    "iso:country":"CM",
    "wof:name":"Porkouata",
    "wof:placetype":"locality"
},
  "geometry": {"coordinates":[13.98688,10.78022],"type":"Point"}
}