{
  "type": "Feature",
  "properties": {
    "gn:admin1_code":"4.0",
    "gn:asciiname":"Mang",
    "gn:country_code":"CM",
    "gn:dem":613,
    "gn:feature_class":"P",
    "gn:feature_code":"PPL",
    "gn:name":"Mang",
    "gn:population":0,
    "gn:timezone":"Africa/Douala",
    "iso:country":"CM",
    "name:ceb_x_preferred":[
        "Mang"
    ],
    "name:deu_x_preferred":[
        "Mang"
    ],
    "name:fra_x_preferred":[
        "Mang"
    ],
    "name:swe_x_preferred":[
        "Mang"
    ],
    "wof:name":"Mang",
    "wof:placetype":"locality"
},
  "geometry": {"coordinates":[14.03333,3.33333],"type":"Point"}
}