{
  "type": "Feature",
  "properties": {
    "gn:admin1_code":"13.0",
    "gn:asciiname":"Sokbe Toukoulou",
    "gn:country_code":"CM",
    "gn:dem":572,
    "gn:feature_class":"P",
    "gn:feature_code":"PPL",
    "gn:name":"Sokb\u00e9 Toukoulou",
    "gn:population":0,
    "gn:timezone":"Africa/Douala",
    "iso:country":"CM",
    "wof:name":"Sokbe Toukoulou",
    "wof:placetype":"locality"
},
  "geometry": {"coordinates":[15.4469,7.5286],"type":"Point"}
}