{
  "type": "Feature",
  "properties": {
    "gn:admin1_code":"8.0",
    "gn:asciiname":"Tchitchi",
    "gn:country_code":"CM",
    "gn:dem":1440,
    "gn:feature_class":"P",
    "gn:feature_code":"PPL",
    "gn:name":"Tchitchi",
    "gn:population":0,
    "gn:timezone":"Africa/Douala",
    "iso:country":"CM",
    "wof:name":"Tchitchi",
    "wof:placetype":"locality"
},
  "geometry": {"coordinates":[10.42187,5.19943],"type":"Point"}
}