{
  "type": "Feature",
  "properties": {
    "gn:admin1_code":"9.0",
    "gn:asciiname":"Ekong",
    "gn:country_code":"CM",
    "gn:dem":153,
    "gn:feature_class":"P",
    "gn:feature_code":"PPL",
    "gn:name":"Ekong",
    "gn:population":0,
    "gn:timezone":"Africa/Douala",
    "iso:country":"CM",
    "name:und_x_variant":[
        "Ekon",
        "Ekong"
    ],
    "wof:name":"Ekong",
    "wof:placetype":"locality"
},
  "geometry": {"coordinates":[8.8449,5.2229],"type":"Point"}
}