{
  "type": "Feature",
  "properties": {
    "gn:admin1_code":"11.0",
    "gn:asciiname":"Nsamba",
    "gn:country_code":"CM",
    "gn:dem":686,
    "gn:feature_class":"P",
    "gn:feature_code":"PPL",
    "gn:name":"Nsamba",
    "gn:population":0,
    "gn:timezone":"Africa/Douala",
    "iso:country":"CM",
    "wof:name":"Nsamba",
    "wof:placetype":"locality"
},
  "geometry": {"coordinates":[12.23333,4.18333],"type":"Point"}
}