{
  "type": "Feature",
  "properties": {
    "gn:admin1_code":"12.0",
    "gn:asciiname":"Bissoue",
    "gn:country_code":"CM",
    "gn:dem":355,
    "gn:feature_class":"P",
    "gn:feature_code":"PPL",
    "gn:name":"Bissou\u00e9",
    "gn:population":0,
    "gn:timezone":"Africa/Douala",
    "iso:country":"CM",
    "name:und_x_variant":[
        "Bilissou\u00e9",
        "Bissou\u00e9"
    ],
    "wof:name":"Bissoue",
    "wof:placetype":"locality"
},
  "geometry": {"coordinates":[14.7909,9.9901],"type":"Point"}
}