{
  "type": "Feature",
  "properties": {
    "gn:admin1_code":"4.0",
    "gn:asciiname":"Mboua",
    "gn:country_code":"CM",
    "gn:dem":610,
    "gn:feature_class":"P",
    "gn:feature_code":"PPL",
    "gn:name":"Mboua",
    "gn:population":0,
    "gn:timezone":"Africa/Douala",
    "iso:country":"CM",
    "name:und_x_variant":[
        "Mboa",
        "Mboua"
    ],
    "wof:name":"Mboua",
    "wof:placetype":"locality"
},
  "geometry": {"coordinates":[14.26667,4.41667],"type":"Point"}
}