{
  "type": "Feature",
  "properties": {
    "gn:admin1_code":"11.0",
    "gn:asciiname":"Ekondong",
    "gn:country_code":"CM",
    "gn:dem":621,
    "gn:feature_class":"P",
    "gn:feature_code":"PPL",
    "gn:name":"Ekondong",
    "gn:population":0,
    "gn:timezone":"Africa/Douala",
    "iso:country":"CM",
    "wof:name":"Ekondong",
    "wof:placetype":"locality"
},
  "geometry": {"coordinates":[12.66667,4.85],"type":"Point"}
}