{
  "type": "Feature",
  "properties": {
    "gn:admin1_code":"9.0",
    "gn:asciiname":"Ngamoki",
    "gn:country_code":"CM",
    "gn:dem":905,
    "gn:feature_class":"P",
    "gn:feature_code":"PPL",
    "gn:name":"Ngamoki",
    "gn:population":0,
    "gn:timezone":"Africa/Douala",
    "iso:country":"CM",
    "wof:name":"Ngamoki",
    "wof:placetype":"locality"
},
  "geometry": {"coordinates":[9.2072,5.0199],"type":"Point"}
}