{
  "type": "Feature",
  "properties": {
    "gn:admin1_code":"8.0",
    "gn:asciiname":"Kwo'nkeng",
    "gn:country_code":"CM",
    "gn:dem":1529,
    "gn:feature_class":"P",
    "gn:feature_code":"PPL",
    "gn:name":"Kwo\u2019nkeng",
    "gn:population":0,
    "gn:timezone":"Africa/Douala",
    "iso:country":"CM",
    "wof:name":"Kwo'nkeng",
    "wof:placetype":"locality"
},
  "geometry": {"coordinates":[10.23977,5.35738],"type":"Point"}
}