{
  "type": "Feature",
  "properties": {
    "gn:admin1_code":"12.0",
    "gn:asciiname":"Vouzouk",
    "gn:country_code":"CM",
    "gn:dem":1045,
    "gn:feature_class":"P",
    "gn:feature_code":"PPL",
    "gn:name":"Vouzouk",
    "gn:population":0,
    "gn:timezone":"Africa/Douala",
    "iso:country":"CM",
    "wof:name":"Vouzouk",
    "wof:placetype":"locality"
},
  "geometry": {"coordinates":[13.72163,10.8513],"type":"Point"}
}