{
  "type": "Feature",
  "properties": {
    "gn:admin1_code":"12.0",
    "gn:asciiname":"Palaoudi",
    "gn:country_code":"CM",
    "gn:dem":430,
    "gn:feature_class":"P",
    "gn:feature_code":"PPL",
    "gn:name":"Palaoudi",
    "gn:population":0,
    "gn:timezone":"Africa/Douala",
    "iso:country":"CM",
    "wof:name":"Palaoudi",
    "wof:placetype":"locality"
},
  "geometry": {"coordinates":[14.22136,10.4524],"type":"Point"}
}