{
  "type": "Feature",
  "properties": {
    "gn:admin1_code":"4.0",
    "gn:asciiname":"Alouma",
    "gn:country_code":"CM",
    "gn:dem":653,
    "gn:feature_class":"P",
    "gn:feature_code":"PPL",
    "gn:name":"Alouma",
    "gn:population":0,
    "gn:timezone":"Africa/Douala",
    "iso:country":"CM",
    "name:und_x_variant":[
        "Al\u016bma",
        "Alouma"
    ],
    "wof:name":"Alouma",
    "wof:placetype":"locality"
},
  "geometry": {"coordinates":[12.58333,3.46667],"type":"Point"}
}