{
  "type": "Feature",
  "properties": {
    "gn:admin1_code":"12.0",
    "gn:asciiname":"Kouyape",
    "gn:country_code":"CM",
    "gn:dem":418,
    "gn:feature_class":"P",
    "gn:feature_code":"PPL",
    "gn:name":"Kouyap\u00e9",
    "gn:population":0,
    "gn:timezone":"Africa/Douala",
    "iso:country":"CM",
    "name:und_x_variant":[
        "Kwiap\u00e9",
        "Kouyap\u00e9"
    ],
    "wof:name":"Kouyape",
    "wof:placetype":"locality"
},
  "geometry": {"coordinates":[13.96664,11.02101],"type":"Point"}
}