{
  "type": "Feature",
  "properties": {
    "gn:admin1_code":"13.0",
    "gn:asciiname":"Casier",
    "gn:country_code":"CM",
    "gn:dem":425,
    "gn:feature_class":"P",
    "gn:feature_code":"PPL",
    "gn:name":"Casier",
    "gn:population":0,
    "gn:timezone":"Africa/Douala",
    "iso:country":"CM",
    "name:azb_x_preferred":[
        "\u06a9\u0627\u0632\u06cc\u0631"
    ],
    "name:bul_x_preferred":[
        "\u041a\u0430\u0437\u0438\u0435\u0440"
    ],
    "name:ceb_x_preferred":[
        "Casier"
    ],
    "name:deu_x_preferred":[
        "Casier"
    ],
    "name:epo_x_preferred":[
        "Casier"
    ],
    "name:eus_x_preferred":[
        "Casier"
    ],
    "name:fas_x_preferred":[
        "\u06a9\u0627\u0632\u06cc\u0631"
    ],
    "name:fra_x_preferred":[
        "Casier"
    ],
    "name:hun_x_preferred":[
        "Casier"
    ],
    "name:hye_x_preferred":[
        "\u053f\u0561\u0566\u056b\u0565\u0580"
    ],
    "name:ita_x_preferred":[
        "Casier"
    ],
    "name:jpn_x_preferred":[
        "\u30ab\u30b8\u30a8\u30fc\u30eb"
    ],
    "name:kaz_x_preferred":[
        "\u041a\u0430\u0437\u044c\u0435\u0440"
    ],
    "name:lat_x_preferred":[
        "Casierum"
    ],
    "name:lmo_x_preferred":[
        "Casier"
    ],
    "name:msa_x_preferred":[
        "Casier"
    ],
    "name:nap_x_preferred":[
        "Casier"
    ],
    "name:nld_x_preferred":[
        "Casier"
    ],
    "name:pms_x_preferred":[
        "Casier"
    ],
    "name:pol_x_preferred":[
        "Casier"
    ],
    "name:por_x_preferred":[
        "Casier"
    ],
    "name:ron_x_preferred":[
        "Casier"
    ],
    "name:rus_x_preferred":[
        "\u041a\u0430\u0437\u044c\u0435\u0440"
    ],
    "name:scn_x_preferred":[
        "Casier"
    ],
    "name:spa_x_preferred":[
        "Casier"
    ],
    "name:srp_x_preferred":[
        "\u041a\u0430\u0437\u0438\u0458\u0435\u0440"
    ],
    "name:tgl_x_preferred":[
        "Casier"
    ],
    "name:ukr_x_preferred":[
        "\u041a\u0430\u0437\u0456\u0454\u0440"
    ],
    "name:uzb_x_preferred":[
        "Casier"
    ],
    "name:vec_x_preferred":[
        "Casier"
    ],
    "name:vie_x_preferred":[
        "Casier"
    ],
    "name:vol_x_preferred":[
        "Casier"
    ],
    "name:war_x_preferred":[
        "Casier"
    ],
    "name:zho_x_preferred":[
        "\u5361\u8c22\u5c14"
    ],
    "wof:name":"Casier",
    "wof:placetype":"locality"
},
  "geometry": {"coordinates":[13.926,10.09535],"type":"Point"}
}