{
  "type": "Feature",
  "properties": {
    "gn:admin1_code":"13.0",
    "gn:asciiname":"Casier",
    "gn:country_code":"CM",
    "gn:dem":425,
    "gn:feature_class":"P",
    "gn:feature_code":"PPL",
    "gn:name":"Casier",
    "gn:population":0,
    "gn:timezone":"Africa/Douala",
    "iso:country":"CM",
    "wof:name":"Casier",
    "wof:placetype":"locality"
},
  "geometry": {"coordinates":[13.926,10.09535],"type":"Point"}
}