{
  "type": "Feature",
  "properties": {
    "gn:admin1_code":"13.0",
    "gn:asciiname":"Babanguel",
    "gn:country_code":"CM",
    "gn:dem":325,
    "gn:feature_class":"P",
    "gn:feature_code":"PPL",
    "gn:name":"Babanguel",
    "gn:population":0,
    "gn:timezone":"Africa/Douala",
    "iso:country":"CM",
    "wof:name":"Babanguel",
    "wof:placetype":"locality"
},
  "geometry": {"coordinates":[13.71349,9.60428],"type":"Point"}
}