{
  "type": "Feature",
  "properties": {
    "gn:admin1_code":"7.0",
    "gn:asciiname":"Lamessang",
    "gn:country_code":"CM",
    "gn:dem":1199,
    "gn:feature_class":"P",
    "gn:feature_code":"PPL",
    "gn:name":"Lamessang",
    "gn:population":0,
    "gn:timezone":"Africa/Douala",
    "iso:country":"CM",
    "wof:name":"Lamessang",
    "wof:placetype":"locality"
},
  "geometry": {"coordinates":[10.35004,5.919],"type":"Point"}
}