{
  "type": "Feature",
  "properties": {
    "gn:admin1_code":"12.0",
    "gn:asciiname":"Assana",
    "gn:country_code":"CM",
    "gn:dem":388,
    "gn:feature_class":"P",
    "gn:feature_code":"PPL",
    "gn:name":"Assana",
    "gn:population":0,
    "gn:timezone":"Africa/Douala",
    "iso:country":"CM",
    "wof:name":"Assana",
    "wof:placetype":"locality"
},
  "geometry": {"coordinates":[14.01667,11.08333],"type":"Point"}
}