{
  "type": "Feature",
  "properties": {
    "gn:admin1_code":"11.0",
    "gn:asciiname":"Dikonop",
    "gn:country_code":"CM",
    "gn:dem":361,
    "gn:feature_class":"P",
    "gn:feature_code":"PPL",
    "gn:name":"Dikonop",
    "gn:population":0,
    "gn:timezone":"Africa/Douala",
    "iso:country":"CM",
    "name:und_x_variant":[
        "Dikongob",
        "Dikonop"
    ],
    "wof:name":"Dikonop",
    "wof:placetype":"locality"
},
  "geometry": {"coordinates":[10.75,3.96667],"type":"Point"}
}