{
  "type": "Feature",
  "properties": {
    "gn:admin1_code":"12.0",
    "gn:asciiname":"Mangafe Djarengol",
    "gn:country_code":"CM",
    "gn:dem":373,
    "gn:feature_class":"P",
    "gn:feature_code":"PPL",
    "gn:name":"Mangaf\u00e9 Djarengol",
    "gn:population":0,
    "gn:timezone":"Africa/Douala",
    "iso:country":"CM",
    "wof:name":"Mangafe Djarengol",
    "wof:placetype":"locality"
},
  "geometry": {"coordinates":[14.29588,10.93051],"type":"Point"}
}