{
  "type": "Feature",
  "properties": {
    "gn:admin1_code":"5.0",
    "gn:asciiname":"Mbarembeng",
    "gn:country_code":"CM",
    "gn:dem":603,
    "gn:feature_class":"P",
    "gn:feature_code":"PPL",
    "gn:name":"Mbarembeng",
    "gn:population":0,
    "gn:timezone":"Africa/Douala",
    "iso:country":"CM",
    "name:fra_x_preferred":[
        "Mbarembeng"
    ],
    "wof:name":"Mbarembeng",
    "wof:placetype":"locality"
},
  "geometry": {"coordinates":[10.02633,5.008],"type":"Point"}
}