{
  "type": "Feature",
  "properties": {
    "gn:admin1_code":"4.0",
    "gn:asciiname":"Mekoum",
    "gn:country_code":"CM",
    "gn:dem":597,
    "gn:feature_class":"P",
    "gn:feature_code":"PPL",
    "gn:name":"M\u00e9koum",
    "gn:population":0,
    "gn:timezone":"Africa/Douala",
    "iso:country":"CM",
    "name:und_x_variant":[
        "Akum",
        "Akoum",
        "M\u00e9koum"
    ],
    "wof:name":"Mekoum",
    "wof:placetype":"locality"
},
  "geometry": {"coordinates":[13.53333,2.93333],"type":"Point"}
}