{
  "type": "Feature",
  "properties": {
    "gn:admin1_code":"12.0",
    "gn:asciiname":"Tcheme",
    "gn:country_code":"CM",
    "gn:dem":623,
    "gn:feature_class":"P",
    "gn:feature_code":"PPL",
    "gn:name":"Tch\u00e9m\u00e9",
    "gn:population":0,
    "gn:timezone":"Africa/Douala",
    "iso:country":"CM",
    "wof:name":"Tcheme",
    "wof:placetype":"locality"
},
  "geometry": {"coordinates":[13.84934,10.83787],"type":"Point"}
}