{
  "type": "Feature",
  "properties": {
    "gn:admin1_code":"11.0",
    "gn:asciiname":"Nkolmebang",
    "gn:country_code":"CM",
    "gn:dem":533,
    "gn:feature_class":"P",
    "gn:feature_code":"PPL",
    "gn:name":"Nkolm\u00e9bang",
    "gn:population":0,
    "gn:timezone":"Africa/Douala",
    "iso:country":"CM",
    "wof:name":"Nkolmebang",
    "wof:placetype":"locality"
},
  "geometry": {"coordinates":[11.41667,4.38333],"type":"Point"}
}