{
  "type": "Feature",
  "properties": {
    "gn:admin1_code":"10.0",
    "gn:asciiname":"Soule",
    "gn:country_code":"CM",
    "gn:dem":1188,
    "gn:feature_class":"P",
    "gn:feature_code":"PPL",
    "gn:name":"Soul\u00e9",
    "gn:population":0,
    "gn:timezone":"Africa/Douala",
    "iso:country":"CM",
    "name:afr_x_preferred":[
        "Soule"
    ],
    "name:arg_x_preferred":[
        "Sola"
    ],
    "name:bre_x_preferred":[
        "Zuberoa"
    ],
    "name:cat_x_preferred":[
        "Zuberoa"
    ],
    "name:cym_x_preferred":[
        "Zuberoa"
    ],
    "name:deu_x_preferred":[
        "Soule"
    ],
    "name:epo_x_preferred":[
        "Zubero"
    ],
    "name:eus_x_preferred":[
        "Zuberoa"
    ],
    "name:fas_x_preferred":[
        "\u0633\u0648\u0644"
    ],
    "name:fra_x_preferred":[
        "Soule"
    ],
    "name:frp_x_preferred":[
        "Sola"
    ],
    "name:glg_x_preferred":[
        "Zuberoa"
    ],
    "name:hrv_x_preferred":[
        "Zuberoa"
    ],
    "name:ita_x_preferred":[
        "Soule"
    ],
    "name:jpn_x_preferred":[
        "\u30b9\u30fc\u30eb"
    ],
    "name:lat_x_preferred":[
        "Sula"
    ],
    "name:nld_x_preferred":[
        "Soule"
    ],
    "name:nor_x_preferred":[
        "Zuberoa"
    ],
    "name:oci_x_preferred":[
        "Sola"
    ],
    "name:pol_x_preferred":[
        "Soule"
    ],
    "name:spa_x_preferred":[
        "Sola"
    ],
    "name:swe_x_preferred":[
        "Zuberoa"
    ],
    "name:ukr_x_preferred":[
        "\u0421\u0443\u0431\u0435\u0440\u043e\u0430"
    ],
    "name:vec_x_preferred":[
        "Zuberoa"
    ],
    "wof:name":"Soule",
    "wof:placetype":"locality"
},
  "geometry": {"coordinates":[12.98333,6.88333],"type":"Point"}
}