{
  "type": "Feature",
  "properties": {
    "gn:admin1_code":"10.0",
    "gn:asciiname":"Soule",
    "gn:country_code":"CM",
    "gn:dem":1188,
    "gn:feature_class":"P",
    "gn:feature_code":"PPL",
    "gn:name":"Soul\u00e9",
    "gn:population":0,
    "gn:timezone":"Africa/Douala",
    "iso:country":"CM",
    "wof:name":"Soule",
    "wof:placetype":"locality"
},
  "geometry": {"coordinates":[12.98333,6.88333],"type":"Point"}
}