{
  "type": "Feature",
  "properties": {
    "gn:admin1_code":"9.0",
    "gn:asciiname":"Bekoko",
    "gn:country_code":"CM",
    "gn:dem":67,
    "gn:feature_class":"P",
    "gn:feature_code":"PPL",
    "gn:name":"Bekoko",
    "gn:population":0,
    "gn:timezone":"Africa/Douala",
    "iso:country":"CM",
    "name:und_x_variant":[
        "Bekoki",
        "Bekoko"
    ],
    "wof:name":"Bekoko",
    "wof:placetype":"locality"
},
  "geometry": {"coordinates":[8.85182,4.92333],"type":"Point"}
}