{
  "type": "Feature",
  "properties": {
    "gn:admin1_code":"8.0",
    "gn:asciiname":"Ngwengwa",
    "gn:country_code":"CM",
    "gn:dem":1849,
    "gn:feature_class":"P",
    "gn:feature_code":"PPL",
    "gn:name":"Ngwengwa",
    "gn:population":0,
    "gn:timezone":"Africa/Douala",
    "iso:country":"CM",
    "name:fra_x_preferred":[
        "Ngwengwa"
    ],
    "wof:name":"Ngwengwa",
    "wof:placetype":"locality"
},
  "geometry": {"coordinates":[10.38287,5.29052],"type":"Point"}
}