{
  "type": "Feature",
  "properties": {
    "gn:admin1_code":"12.0",
    "gn:asciiname":"Mayo Sanganare",
    "gn:country_code":"CM",
    "gn:dem":851,
    "gn:feature_class":"P",
    "gn:feature_code":"PPL",
    "gn:name":"Mayo Sanganar\u00e9",
    "gn:population":0,
    "gn:timezone":"Africa/Douala",
    "iso:country":"CM",
    "wof:name":"Mayo Sanganare",
    "wof:placetype":"locality"
},
  "geometry": {"coordinates":[13.73193,10.73616],"type":"Point"}
}