{
  "type": "Feature",
  "properties": {
    "gn:admin1_code":"10.0",
    "gn:asciiname":"Danyo",
    "gn:country_code":"CM",
    "gn:dem":873,
    "gn:feature_class":"P",
    "gn:feature_code":"PPL",
    "gn:name":"Danyo",
    "gn:population":0,
    "gn:timezone":"Africa/Douala",
    "iso:country":"CM",
    "wof:name":"Danyo",
    "wof:placetype":"locality"
},
  "geometry": {"coordinates":[12.66435,6.52307],"type":"Point"}
}