{
  "type": "Feature",
  "properties": {
    "gn:admin1_code":"14.0",
    "gn:asciiname":"Momebili",
    "gn:country_code":"CM",
    "gn:dem":604,
    "gn:feature_class":"P",
    "gn:feature_code":"PPL",
    "gn:name":"Mom\u00e9bili",
    "gn:population":0,
    "gn:timezone":"Africa/Douala",
    "iso:country":"CM",
    "wof:name":"Momebili",
    "wof:placetype":"locality"
},
  "geometry": {"coordinates":[11.73333,2.73333],"type":"Point"}
}