{
  "type": "Feature",
  "properties": {
    "gn:admin1_code":"5.0",
    "gn:asciiname":"Mounko",
    "gn:country_code":"CM",
    "gn:dem":670,
    "gn:feature_class":"P",
    "gn:feature_code":"PPL",
    "gn:name":"Mounko",
    "gn:population":0,
    "gn:timezone":"Africa/Douala",
    "iso:country":"CM",
    "name:fra_x_preferred":[
        "Mounko"
    ],
    "wof:name":"Mounko",
    "wof:placetype":"locality"
},
  "geometry": {"coordinates":[10.03476,5.04126],"type":"Point"}
}