{
  "type": "Feature",
  "properties": {
    "gn:admin1_code":"7.0",
    "gn:asciiname":"Tinachong",
    "gn:country_code":"CM",
    "gn:dem":1674,
    "gn:feature_class":"P",
    "gn:feature_code":"PPL",
    "gn:name":"Tinachong",
    "gn:population":0,
    "gn:timezone":"Africa/Douala",
    "iso:country":"CM",
    "name:und_x_variant":[
        "Etinachong",
        "Tinachong"
    ],
    "wof:name":"Tinachong",
    "wof:placetype":"locality"
},
  "geometry": {"coordinates":[9.87612,6.03636],"type":"Point"}
}