{
  "type": "Feature",
  "properties": {
    "gn:admin1_code":"10.0",
    "gn:asciiname":"Ganboukou",
    "gn:country_code":"CM",
    "gn:dem":1121,
    "gn:feature_class":"P",
    "gn:feature_code":"PPL",
    "gn:name":"Ganboukou",
    "gn:population":0,
    "gn:timezone":"Africa/Douala",
    "iso:country":"CM",
    "name:und_x_variant":[
        "Gamboukou",
        "Ganboukou"
    ],
    "wof:name":"Ganboukou",
    "wof:placetype":"locality"
},
  "geometry": {"coordinates":[13.68333,7.56667],"type":"Point"}
}