{
  "type": "Feature",
  "properties": {
    "gn:admin1_code":"8.0",
    "gn:asciiname":"Mekagok",
    "gn:country_code":"CM",
    "gn:dem":1246,
    "gn:feature_class":"P",
    "gn:feature_code":"PPL",
    "gn:name":"M\u00e9kagok",
    "gn:population":0,
    "gn:timezone":"Africa/Douala",
    "iso:country":"CM",
    "wof:name":"Mekagok",
    "wof:placetype":"locality"
},
  "geometry": {"coordinates":[10.32316,5.69154],"type":"Point"}
}