{
  "type": "Feature",
  "properties": {
    "gn:admin1_code":"13.0",
    "gn:asciiname":"Yola Boda",
    "gn:country_code":"CM",
    "gn:dem":363,
    "gn:feature_class":"P",
    "gn:feature_code":"PPL",
    "gn:name":"Yola Boda",
    "gn:population":0,
    "gn:timezone":"Africa/Douala",
    "iso:country":"CM",
    "wof:name":"Yola Boda",
    "wof:placetype":"locality"
},
  "geometry": {"coordinates":[14.3675,9.1246],"type":"Point"}
}