{
  "type": "Feature",
  "properties": {
    "gn:admin1_code":"10.0",
    "gn:asciiname":"Bera",
    "gn:country_code":"CM",
    "gn:dem":1468,
    "gn:feature_class":"P",
    "gn:feature_code":"PPL",
    "gn:name":"B\u00e9ra",
    "gn:population":0,
    "gn:timezone":"Africa/Douala",
    "iso:country":"CM",
    "name:cat_x_preferred":[
        "Bera"
    ],
    "name:ceb_x_preferred":[
        "Bera"
    ],
    "name:deu_x_preferred":[
        "Bera"
    ],
    "name:fra_x_preferred":[
        "Bera"
    ],
    "name:isl_x_preferred":[
        "Bera"
    ],
    "name:ita_x_preferred":[
        "Bera"
    ],
    "name:nld_x_preferred":[
        "Bera"
    ],
    "name:por_x_preferred":[
        "Bera"
    ],
    "name:rus_x_preferred":[
        "\u0411\u0435\u0440\u0430"
    ],
    "name:srp_x_preferred":[
        "\u0411\u0435\u0440\u0430"
    ],
    "name:swe_x_preferred":[
        "Bera"
    ],
    "wof:name":"Bera",
    "wof:placetype":"locality"
},
  "geometry": {"coordinates":[14.08333,7.35],"type":"Point"}
}