{
  "type": "Feature",
  "properties": {
    "gn:admin1_code":"10.0",
    "gn:asciiname":"Bera",
    "gn:country_code":"CM",
    "gn:dem":1468,
    "gn:feature_class":"P",
    "gn:feature_code":"PPL",
    "gn:name":"B\u00e9ra",
    "gn:population":0,
    "gn:timezone":"Africa/Douala",
    "iso:country":"CM",
    "wof:name":"Bera",
    "wof:placetype":"locality"
},
  "geometry": {"coordinates":[14.08333,7.35],"type":"Point"}
}