{
  "type": "Feature",
  "properties": {
    "gn:admin1_code":"13.0",
    "gn:asciiname":"Amedou",
    "gn:country_code":"CM",
    "gn:dem":320,
    "gn:feature_class":"P",
    "gn:feature_code":"PPL",
    "gn:name":"Amedou",
    "gn:population":0,
    "gn:timezone":"Africa/Douala",
    "iso:country":"CM",
    "wof:name":"Amedou",
    "wof:placetype":"locality"
},
  "geometry": {"coordinates":[14.43333,8.93333],"type":"Point"}
}