{
  "type": "Feature",
  "properties": {
    "gn:admin1_code":"12.0",
    "gn:asciiname":"Kolossale",
    "gn:country_code":"CM",
    "gn:dem":309,
    "gn:feature_class":"P",
    "gn:feature_code":"PPL",
    "gn:name":"Kolossal\u00e9",
    "gn:population":0,
    "gn:timezone":"Africa/Douala",
    "iso:country":"CM",
    "wof:name":"Kolossale",
    "wof:placetype":"locality"
},
  "geometry": {"coordinates":[14.38583,11.33583],"type":"Point"}
}