{
  "type": "Feature",
  "properties": {
    "gn:admin1_code":"12.0",
    "gn:asciiname":"Tala Malabrahim",
    "gn:country_code":"CM",
    "gn:dem":393,
    "gn:feature_class":"P",
    "gn:feature_code":"PPL",
    "gn:name":"Tala Malabrahim",
    "gn:population":0,
    "gn:timezone":"Africa/Douala",
    "iso:country":"CM",
    "wof:name":"Tala Malabrahim",
    "wof:placetype":"locality"
},
  "geometry": {"coordinates":[13.99187,11.07688],"type":"Point"}
}