{
  "type": "Feature",
  "properties": {
    "gn:admin1_code":"13.0",
    "gn:asciiname":"Hoy",
    "gn:country_code":"CM",
    "gn:dem":582,
    "gn:feature_class":"P",
    "gn:feature_code":"PPL",
    "gn:name":"Hoy",
    "gn:population":0,
    "gn:timezone":"Africa/Douala",
    "iso:country":"CM",
    "wof:name":"Hoy",
    "wof:placetype":"locality"
},
  "geometry": {"coordinates":[13.32713,8.47872],"type":"Point"}
}