{
  "type": "Feature",
  "properties": {
    "gn:admin1_code":"13.0",
    "gn:asciiname":"Hoy",
    "gn:country_code":"CM",
    "gn:dem":582,
    "gn:feature_class":"P",
    "gn:feature_code":"PPL",
    "gn:name":"Hoy",
    "gn:population":0,
    "gn:timezone":"Africa/Douala",
    "iso:country":"CM",
    "name:ara_x_preferred":[
        "\u062c\u0632\u064a\u0631\u0629 \u0647\u0648\u064a"
    ],
    "name:bre_x_preferred":[
        "Enez Hoy"
    ],
    "name:ceb_x_preferred":[
        "Hoy"
    ],
    "name:cym_x_preferred":[
        "Hoy"
    ],
    "name:deu_x_preferred":[
        "Hoy"
    ],
    "name:ell_x_preferred":[
        "\u03a7\u03cc\u03b9"
    ],
    "name:eus_x_preferred":[
        "Hoy uhartea"
    ],
    "name:fao_x_preferred":[
        "Hoy"
    ],
    "name:fin_x_preferred":[
        "Hoy"
    ],
    "name:fra_x_preferred":[
        "Hoy"
    ],
    "name:gla_x_preferred":[
        "H\u00f2igh"
    ],
    "name:heb_x_preferred":[
        "\u05d4\u05d5\u05d9"
    ],
    "name:ita_x_preferred":[
        "Hoy"
    ],
    "name:jpn_x_preferred":[
        "\u30db\u30a4\u5cf6"
    ],
    "name:lat_x_preferred":[
        "Ho\u00efa insula"
    ],
    "name:nld_x_preferred":[
        "Hoy"
    ],
    "name:nno_x_preferred":[
        "Hoy"
    ],
    "name:nor_x_preferred":[
        "Hoy"
    ],
    "name:pnb_x_preferred":[
        "\u06c1\u0648\u06d3"
    ],
    "name:pol_x_preferred":[
        "Hoy"
    ],
    "name:rus_x_preferred":[
        "\u0425\u043e\u0439"
    ],
    "name:spa_x_preferred":[
        "Hoy"
    ],
    "name:srp_x_preferred":[
        "\u0425\u043e\u0458"
    ],
    "name:swe_x_preferred":[
        "Hoy"
    ],
    "name:zho_x_preferred":[
        "\u970d\u4f0a\u5cf6"
    ],
    "wof:name":"Hoy",
    "wof:placetype":"locality"
},
  "geometry": {"coordinates":[13.32713,8.47872],"type":"Point"}
}