{
  "type": "Feature",
  "properties": {
    "gn:admin1_code":"12.0",
    "gn:asciiname":"Mboura",
    "gn:country_code":"CM",
    "gn:dem":880,
    "gn:feature_class":"P",
    "gn:feature_code":"PPL",
    "gn:name":"Mboura",
    "gn:population":0,
    "gn:timezone":"Africa/Douala",
    "iso:country":"CM",
    "wof:name":"Mboura",
    "wof:placetype":"locality"
},
  "geometry": {"coordinates":[13.58852,10.13657],"type":"Point"}
}