{
  "type": "Feature",
  "properties": {
    "gn:admin1_code":"11.0",
    "gn:asciiname":"Abondo",
    "gn:country_code":"CM",
    "gn:dem":628,
    "gn:feature_class":"P",
    "gn:feature_code":"PPL",
    "gn:name":"Abondo",
    "gn:population":0,
    "gn:timezone":"Africa/Douala",
    "iso:country":"CM",
    "wof:name":"Abondo",
    "wof:placetype":"locality"
},
  "geometry": {"coordinates":[11.61667,4.06667],"type":"Point"}
}