{
  "type": "Feature",
  "properties": {
    "gn:admin1_code":"13.0",
    "gn:asciiname":"Lougguere",
    "gn:country_code":"CM",
    "gn:dem":412,
    "gn:feature_class":"P",
    "gn:feature_code":"PPL",
    "gn:name":"Louggu\u00e9r\u00e9",
    "gn:population":0,
    "gn:timezone":"Africa/Douala",
    "iso:country":"CM",
    "name:und_x_variant":[
        "Lougu\u00e9n\u00e9",
        "Lugere",
        "Loug\u00e9r\u00e9",
        "Louggu\u00e9r\u00e9"
    ],
    "wof:name":"Lougguere",
    "wof:placetype":"locality"
},
  "geometry": {"coordinates":[13.81667,9.93333],"type":"Point"}
}