{
  "type": "Feature",
  "properties": {
    "gn:admin1_code":"13.0",
    "gn:asciiname":"Ouro Boboy",
    "gn:country_code":"CM",
    "gn:dem":257,
    "gn:feature_class":"P",
    "gn:feature_code":"PPL",
    "gn:name":"Ouro Boboy",
    "gn:population":0,
    "gn:timezone":"Africa/Douala",
    "iso:country":"CM",
    "wof:name":"Ouro Boboy",
    "wof:placetype":"locality"
},
  "geometry": {"coordinates":[13.36973,9.47424],"type":"Point"}
}