{
  "type": "Feature",
  "properties": {
    "gn:admin1_code":"12.0",
    "gn:asciiname":"Manawatchi",
    "gn:country_code":"CM",
    "gn:dem":303,
    "gn:feature_class":"P",
    "gn:feature_code":"PPL",
    "gn:name":"Manawatchi",
    "gn:population":0,
    "gn:timezone":"Africa/Douala",
    "iso:country":"CM",
    "wof:name":"Manawatchi",
    "wof:placetype":"locality"
},
  "geometry": {"coordinates":[15.10851,11.53874],"type":"Point"}
}