{
  "type": "Feature",
  "properties": {
    "gn:admin1_code":"9.0",
    "gn:asciiname":"Njongo",
    "gn:country_code":"CM",
    "gn:dem":225,
    "gn:feature_class":"P",
    "gn:feature_code":"PPL",
    "gn:name":"Njongo",
    "gn:population":0,
    "gn:timezone":"Africa/Douala",
    "iso:country":"CM",
    "wof:name":"Njongo",
    "wof:placetype":"locality"
},
  "geometry": {"coordinates":[9.3856,5.4218],"type":"Point"}
}