{
  "type": "Feature",
  "properties": {
    "gn:admin1_code":"9.0",
    "gn:asciiname":"Kilikile",
    "gn:country_code":"CM",
    "gn:dem":912,
    "gn:feature_class":"P",
    "gn:feature_code":"PPL",
    "gn:name":"Kilikile",
    "gn:population":0,
    "gn:timezone":"Africa/Douala",
    "iso:country":"CM",
    "wof:name":"Kilikile",
    "wof:placetype":"locality"
},
  "geometry": {"coordinates":[9.1517,5.0513],"type":"Point"}
}