{
  "type": "Feature",
  "properties": {
    "gn:admin1_code":"4.0",
    "gn:asciiname":"Kissi",
    "gn:country_code":"CM",
    "gn:dem":695,
    "gn:feature_class":"P",
    "gn:feature_code":"PPL",
    "gn:name":"Kissi",
    "gn:population":0,
    "gn:timezone":"Africa/Douala",
    "iso:country":"CM",
    "wof:name":"Kissi",
    "wof:placetype":"locality"
},
  "geometry": {"coordinates":[14.11667,5.75],"type":"Point"}
}