{
  "type": "Feature",
  "properties": {
    "gn:admin1_code":"9.0",
    "gn:asciiname":"Mokundange",
    "gn:country_code":"CM",
    "gn:dem":40,
    "gn:feature_class":"P",
    "gn:feature_code":"PPL",
    "gn:name":"Mokundange",
    "gn:population":0,
    "gn:timezone":"Africa/Douala",
    "iso:country":"CM",
    "name:und_x_variant":[
        "Mukondange",
        "Mokundange"
    ],
    "wof:name":"Mokundange",
    "wof:placetype":"locality"
},
  "geometry": {"coordinates":[9.139,4.0183],"type":"Point"}
}