{
  "type": "Feature",
  "properties": {
    "gn:admin1_code":"4.0",
    "gn:asciiname":"Oudou",
    "gn:country_code":"CM",
    "gn:dem":757,
    "gn:feature_class":"P",
    "gn:feature_code":"PPL",
    "gn:name":"Oudou",
    "gn:population":0,
    "gn:timezone":"Africa/Douala",
    "iso:country":"CM",
    "wof:name":"Oudou",
    "wof:placetype":"locality"
},
  "geometry": {"coordinates":[14.25,4.95],"type":"Point"}
}