{
  "type": "Feature",
  "properties": {
    "gn:admin1_code":"12.0",
    "gn:asciiname":"Kineboya",
    "gn:country_code":"CM",
    "gn:dem":291,
    "gn:feature_class":"P",
    "gn:feature_code":"PPL",
    "gn:name":"Kineboya",
    "gn:population":0,
    "gn:timezone":"Africa/Douala",
    "iso:country":"CM",
    "name:und_x_variant":[
        "Kinboya",
        "Kineboya"
    ],
    "wof:name":"Kineboya",
    "wof:placetype":"locality"
},
  "geometry": {"coordinates":[14.77113,12.4546],"type":"Point"}
}