{
  "type": "Feature",
  "properties": {
    "gn:admin1_code":"4.0",
    "gn:asciiname":"Mese",
    "gn:country_code":"CM",
    "gn:dem":668,
    "gn:feature_class":"P",
    "gn:feature_code":"PPL",
    "gn:name":"M\u00e9s\u00e9",
    "gn:population":0,
    "gn:timezone":"Africa/Douala",
    "iso:country":"CM",
    "name:ceb_x_preferred":[
        "Mese"
    ],
    "name:deu_x_preferred":[
        "Mese"
    ],
    "name:fin_x_preferred":[
        "Mese"
    ],
    "name:hun_x_preferred":[
        "Mese"
    ],
    "name:ind_x_preferred":[
        "Mese"
    ],
    "name:ita_x_preferred":[
        "Mese"
    ],
    "name:msa_x_preferred":[
        "Mese"
    ],
    "name:spa_x_preferred":[
        "Mese"
    ],
    "name:swe_x_preferred":[
        "Mese"
    ],
    "name:ukr_x_preferred":[
        "\u041c\u0435\u0437\u0435"
    ],
    "wof:name":"Mese",
    "wof:placetype":"locality"
},
  "geometry": {"coordinates":[15.08333,3.95],"type":"Point"}
}