{
  "type": "Feature",
  "properties": {
    "gn:admin1_code":"12.0",
    "gn:asciiname":"Gouro Mougza",
    "gn:country_code":"CM",
    "gn:dem":315,
    "gn:feature_class":"P",
    "gn:feature_code":"PPL",
    "gn:name":"Gouro Mougza",
    "gn:population":0,
    "gn:timezone":"Africa/Douala",
    "iso:country":"CM",
    "wof:name":"Gouro Mougza",
    "wof:placetype":"locality"
},
  "geometry": {"coordinates":[14.28167,11.29556],"type":"Point"}
}