{
  "type": "Feature",
  "properties": {
    "gn:admin1_code":"12.0",
    "gn:asciiname":"Hodango",
    "gn:country_code":"CM",
    "gn:dem":570,
    "gn:feature_class":"P",
    "gn:feature_code":"PPL",
    "gn:name":"Hodango",
    "gn:population":0,
    "gn:timezone":"Africa/Douala",
    "iso:country":"CM",
    "wof:name":"Hodango",
    "wof:placetype":"locality"
},
  "geometry": {"coordinates":[13.88021,10.57594],"type":"Point"}
}