{
  "type": "Feature",
  "properties": {
    "gn:admin1_code":"12.0",
    "gn:asciiname":"Golondakri",
    "gn:country_code":"CM",
    "gn:dem":345,
    "gn:feature_class":"P",
    "gn:feature_code":"PPL",
    "gn:name":"Golondakri",
    "gn:population":0,
    "gn:timezone":"Africa/Douala",
    "iso:country":"CM",
    "name:und_x_variant":[
        "Golong Dakri",
        "Golondakri"
    ],
    "wof:name":"Golondakri",
    "wof:placetype":"locality"
},
  "geometry": {"coordinates":[14.88189,10.12485],"type":"Point"}
}