{
  "type": "Feature",
  "properties": {
    "gn:admin1_code":"12.0",
    "gn:asciiname":"Pitchotonguel",
    "gn:country_code":"CM",
    "gn:dem":381,
    "gn:feature_class":"P",
    "gn:feature_code":"PPL",
    "gn:name":"Pitchotonguel",
    "gn:population":0,
    "gn:timezone":"Africa/Douala",
    "iso:country":"CM",
    "wof:name":"Pitchotonguel",
    "wof:placetype":"locality"
},
  "geometry": {"coordinates":[14.71179,10.1014],"type":"Point"}
}