{
  "type": "Feature",
  "properties": {
    "gn:admin1_code":"11.0",
    "gn:asciiname":"Somo",
    "gn:country_code":"CM",
    "gn:dem":811,
    "gn:feature_class":"P",
    "gn:feature_code":"PPL",
    "gn:name":"Somo",
    "gn:population":0,
    "gn:timezone":"Africa/Douala",
    "iso:country":"CM",
    "name:ceb_x_preferred":[
        "Somo"
    ],
    "name:fra_x_preferred":[
        "Somo"
    ],
    "name:ita_x_preferred":[
        "Somo"
    ],
    "name:nld_x_preferred":[
        "Somo"
    ],
    "name:spa_x_preferred":[
        "Somo"
    ],
    "name:swe_x_preferred":[
        "Somo"
    ],
    "wof:name":"Somo",
    "wof:placetype":"locality"
},
  "geometry": {"coordinates":[10.85,4.76667],"type":"Point"}
}