{
  "type": "Feature",
  "properties": {
    "gn:admin1_code":"14.0",
    "gn:asciiname":"Meyo",
    "gn:country_code":"CM",
    "gn:dem":671,
    "gn:feature_class":"P",
    "gn:feature_code":"PPL",
    "gn:name":"Meyo",
    "gn:population":0,
    "gn:timezone":"Africa/Douala",
    "iso:country":"CM",
    "wof:name":"Meyo",
    "wof:placetype":"locality"
},
  "geometry": {"coordinates":[11.95,2.96667],"type":"Point"}
}