{
  "type": "Feature",
  "properties": {
    "gn:admin1_code":"12.0",
    "gn:asciiname":"Oudouloum",
    "gn:country_code":"CM",
    "gn:dem":649,
    "gn:feature_class":"P",
    "gn:feature_code":"PPL",
    "gn:name":"Oudouloum",
    "gn:population":0,
    "gn:timezone":"Africa/Douala",
    "iso:country":"CM",
    "wof:name":"Oudouloum",
    "wof:placetype":"locality"
},
  "geometry": {"coordinates":[13.85805,10.84576],"type":"Point"}
}