{
  "type": "Feature",
  "properties": {
    "gn:admin1_code":"12.0",
    "gn:asciiname":"Mezilem",
    "gn:country_code":"CM",
    "gn:dem":571,
    "gn:feature_class":"P",
    "gn:feature_code":"PPL",
    "gn:name":"M\u00e9zil\u00e8m",
    "gn:population":0,
    "gn:timezone":"Africa/Douala",
    "iso:country":"CM",
    "wof:name":"Mezilem",
    "wof:placetype":"locality"
},
  "geometry": {"coordinates":[13.99479,10.62943],"type":"Point"}
}