{
  "type": "Feature",
  "properties": {
    "gn:admin1_code":"12.0",
    "gn:asciiname":"Milam",
    "gn:country_code":"CM",
    "gn:dem":308,
    "gn:feature_class":"P",
    "gn:feature_code":"PPL",
    "gn:name":"Milam",
    "gn:population":0,
    "gn:timezone":"Africa/Douala",
    "iso:country":"CM",
    "wof:name":"Milam",
    "wof:placetype":"locality"
},
  "geometry": {"coordinates":[14.96916,11.31639],"type":"Point"}
}