{
  "type": "Feature",
  "properties": {
    "gn:admin1_code":"11.0",
    "gn:asciiname":"Bikomam",
    "gn:country_code":"CM",
    "gn:dem":663,
    "gn:feature_class":"P",
    "gn:feature_code":"PPL",
    "gn:name":"Bikomam",
    "gn:population":0,
    "gn:timezone":"Africa/Douala",
    "iso:country":"CM",
    "wof:name":"Bikomam",
    "wof:placetype":"locality"
},
  "geometry": {"coordinates":[11.85,3.55],"type":"Point"}
}