{
  "type": "Feature",
  "properties": {
    "gn:admin1_code":"5.0",
    "gn:asciiname":"Mongombe",
    "gn:country_code":"CM",
    "gn:dem":15,
    "gn:feature_class":"P",
    "gn:feature_code":"PPL",
    "gn:name":"Mongomb\u00e9",
    "gn:population":0,
    "gn:timezone":"Africa/Douala",
    "iso:country":"CM",
    "wof:name":"Mongombe",
    "wof:placetype":"locality"
},
  "geometry": {"coordinates":[10.11667,3.81667],"type":"Point"}
}