{
  "type": "Feature",
  "properties": {
    "gn:admin1_code":"12.0",
    "gn:asciiname":"Dza Mboukou",
    "gn:country_code":"CM",
    "gn:dem":696,
    "gn:feature_class":"P",
    "gn:feature_code":"PPL",
    "gn:name":"Dza Mboukou",
    "gn:population":0,
    "gn:timezone":"Africa/Douala",
    "iso:country":"CM",
    "wof:name":"Dza Mboukou",
    "wof:placetype":"locality"
},
  "geometry": {"coordinates":[14.15456,10.80985],"type":"Point"}
}