{
  "type": "Feature",
  "properties": {
    "gn:admin1_code":"13.0",
    "gn:asciiname":"Gouandaba",
    "gn:country_code":"CM",
    "gn:dem":656,
    "gn:feature_class":"P",
    "gn:feature_code":"PPL",
    "gn:name":"Gouandaba",
    "gn:population":0,
    "gn:timezone":"Africa/Douala",
    "iso:country":"CM",
    "wof:name":"Gouandaba",
    "wof:placetype":"locality"
},
  "geometry": {"coordinates":[13.38398,10.00621],"type":"Point"}
}