{
  "type": "Feature",
  "properties": {
    "gn:admin1_code":"7.0",
    "gn:asciiname":"Ndop",
    "gn:country_code":"CM",
    "gn:dem":1183,
    "gn:feature_class":"P",
    "gn:feature_code":"PPL",
    "gn:name":"Ndop",
    "gn:population":0,
    "gn:timezone":"Africa/Douala",
    "iso:country":"CM",
    "name:ceb_x_preferred":[
        "Ndop"
    ],
    "name:deu_x_preferred":[
        "Ndop"
    ],
    "name:fra_x_preferred":[
        "Ndop"
    ],
    "name:fra_x_variant":[
        "Ramunka",
        "Bamunka"
    ],
    "name:heb_x_preferred":[
        "\u05e0\u05d3\u05d5\u05e4"
    ],
    "name:ita_x_preferred":[
        "Ndop"
    ],
    "name:msa_x_preferred":[
        "Ndop"
    ],
    "name:pol_x_preferred":[
        "Ndop"
    ],
    "name:por_x_preferred":[
        "Ndop"
    ],
    "name:swe_x_preferred":[
        "Ndop"
    ],
    "wof:name":"Ndop",
    "wof:placetype":"locality"
},
  "geometry": {"coordinates":[10.43859,5.98843],"type":"Point"}
}