{
  "type": "Feature",
  "properties": {
    "gn:admin1_code":"13.0",
    "gn:asciiname":"Nakere Abdo",
    "gn:country_code":"CM",
    "gn:dem":312,
    "gn:feature_class":"P",
    "gn:feature_code":"PPL",
    "gn:name":"Nak\u00e9r\u00e9 Abdo",
    "gn:population":0,
    "gn:timezone":"Africa/Douala",
    "iso:country":"CM",
    "wof:name":"Nakere Abdo",
    "wof:placetype":"locality"
},
  "geometry": {"coordinates":[13.91667,9.11667],"type":"Point"}
}