{
  "type": "Feature",
  "properties": {
    "gn:admin1_code":"13.0",
    "gn:asciiname":"Saa Doungaye",
    "gn:country_code":"CM",
    "gn:dem":373,
    "gn:feature_class":"P",
    "gn:feature_code":"PPL",
    "gn:name":"Saa Doungay\u00e9",
    "gn:population":0,
    "gn:timezone":"Africa/Douala",
    "iso:country":"CM",
    "wof:name":"Saa Doungaye",
    "wof:placetype":"locality"
},
  "geometry": {"coordinates":[14.3969,9.1065],"type":"Point"}
}