{
  "type": "Feature",
  "properties": {
    "gn:admin1_code":"11.0",
    "gn:asciiname":"Awa",
    "gn:country_code":"CM",
    "gn:dem":695,
    "gn:feature_class":"P",
    "gn:feature_code":"PPL",
    "gn:name":"Awa",
    "gn:population":0,
    "gn:timezone":"Africa/Douala",
    "iso:country":"CM",
    "wof:name":"Awa",
    "wof:placetype":"locality"
},
  "geometry": {"coordinates":[12.36667,4.03333],"type":"Point"}
}