{
  "type": "Feature",
  "properties": {
    "gn:admin1_code":"10.0",
    "gn:asciiname":"Ardo Balel",
    "gn:country_code":"CM",
    "gn:dem":1137,
    "gn:feature_class":"P",
    "gn:feature_code":"PPL",
    "gn:name":"Ardo Balel",
    "gn:population":0,
    "gn:timezone":"Africa/Douala",
    "iso:country":"CM",
    "wof:name":"Ardo Balel",
    "wof:placetype":"locality"
},
  "geometry": {"coordinates":[14.48333,6.71667],"type":"Point"}
}