{
  "type": "Feature",
  "properties": {
    "gn:admin1_code":"12.0",
    "gn:asciiname":"Guelao",
    "gn:country_code":"CM",
    "gn:dem":294,
    "gn:feature_class":"P",
    "gn:feature_code":"PPL",
    "gn:name":"Gu\u00e9lao",
    "gn:population":0,
    "gn:timezone":"Africa/Douala",
    "iso:country":"CM",
    "name:und_x_variant":[
        "Gu\u00e9lao",
        "Gelao",
        "Guelao"
    ],
    "wof:name":"Guelao",
    "wof:placetype":"locality"
},
  "geometry": {"coordinates":[14.6178,12.30682],"type":"Point"}
}