{
  "type": "Feature",
  "properties": {
    "gn:admin1_code":"7.0",
    "gn:asciiname":"Menja",
    "gn:country_code":"CM",
    "gn:dem":1549,
    "gn:feature_class":"P",
    "gn:feature_code":"PPL",
    "gn:name":"Menja",
    "gn:population":0,
    "gn:timezone":"Africa/Douala",
    "iso:country":"CM",
    "wof:name":"Menja",
    "wof:placetype":"locality"
},
  "geometry": {"coordinates":[10.07592,5.85711],"type":"Point"}
}