{
  "type": "Feature",
  "properties": {
    "gn:admin1_code":"9.0",
    "gn:asciiname":"Tava",
    "gn:country_code":"CM",
    "gn:dem":153,
    "gn:feature_class":"P",
    "gn:feature_code":"PPL",
    "gn:name":"Tava",
    "gn:population":0,
    "gn:timezone":"Africa/Douala",
    "iso:country":"CM",
    "wof:name":"Tava",
    "wof:placetype":"locality"
},
  "geometry": {"coordinates":[9.5161,6.1009],"type":"Point"}
}