{
  "type": "Feature",
  "properties": {
    "gn:admin1_code":"9.0",
    "gn:asciiname":"Tava",
    "gn:country_code":"CM",
    "gn:dem":153,
    "gn:feature_class":"P",
    "gn:feature_code":"PPL",
    "gn:name":"Tava",
    "gn:population":0,
    "gn:timezone":"Africa/Douala",
    "iso:country":"CM",
    "name:aze_x_preferred":[
        "Sac"
    ],
    "name:cat_x_preferred":[
        "Tava"
    ],
    "name:deu_x_preferred":[
        "Sac"
    ],
    "name:fra_x_preferred":[
        "Tava"
    ],
    "name:heb_x_preferred":[
        "\u05e1\u05d0\u05d2'"
    ],
    "name:hin_x_preferred":[
        "\u0924\u0935\u093e"
    ],
    "name:ita_x_preferred":[
        "Saj"
    ],
    "name:mar_x_preferred":[
        "\u0924\u0935\u093e"
    ],
    "name:spa_x_preferred":[
        "Tava"
    ],
    "name:tam_x_preferred":[
        "\u0ba4\u0bcb\u0b9a\u0bc8\u0b95\u0bcd \u0b95\u0bb2\u0bcd"
    ],
    "name:tcy_x_preferred":[
        "\u0c95\u0cbe\u0cb5\u0cb2\u0cbf"
    ],
    "wof:name":"Tava",
    "wof:placetype":"locality"
},
  "geometry": {"coordinates":[9.5161,6.1009],"type":"Point"}
}