{
  "type": "Feature",
  "properties": {
    "gn:admin1_code":"12.0",
    "gn:asciiname":"Zoumbas",
    "gn:country_code":"CM",
    "gn:dem":683,
    "gn:feature_class":"P",
    "gn:feature_code":"PPL",
    "gn:name":"Zoumbas",
    "gn:population":0,
    "gn:timezone":"Africa/Douala",
    "iso:country":"CM",
    "wof:name":"Zoumbas",
    "wof:placetype":"locality"
},
  "geometry": {"coordinates":[13.9786,10.79011],"type":"Point"}
}