{
  "type": "Feature",
  "properties": {
    "gn:admin1_code":"8.0",
    "gn:asciiname":"Sa'nya",
    "gn:country_code":"CM",
    "gn:dem":1331,
    "gn:feature_class":"P",
    "gn:feature_code":"PPL",
    "gn:name":"Sa\u2019nya",
    "gn:population":0,
    "gn:timezone":"Africa/Douala",
    "iso:country":"CM",
    "name:und_x_variant":[
        "Sa\u2019nya",
        "Sagna"
    ],
    "wof:name":"Sa'nya",
    "wof:placetype":"locality"
},
  "geometry": {"coordinates":[10.49029,5.088],"type":"Point"}
}