{
  "type": "Feature",
  "properties": {
    "gn:admin1_code":"11.0",
    "gn:asciiname":"Bibe",
    "gn:country_code":"CM",
    "gn:dem":651,
    "gn:feature_class":"P",
    "gn:feature_code":"PPL",
    "gn:name":"Bib\u00e9",
    "gn:population":0,
    "gn:timezone":"Africa/Douala",
    "iso:country":"CM",
    "name:fra_x_preferred":[
        "Bibey"
    ],
    "name:ita_x_preferred":[
        "Bibey"
    ],
    "name:msa_x_preferred":[
        "Bibey"
    ],
    "name:spa_x_preferred":[
        "Bibey"
    ],
    "name:und_x_variant":[
        "Bibey",
        "Bib\u00e9"
    ],
    "wof:name":"Bibe",
    "wof:placetype":"locality"
},
  "geometry": {"coordinates":[12.81667,4.86667],"type":"Point"}
}