{
  "type": "Feature",
  "properties": {
    "gn:admin1_code":"14.0",
    "gn:asciiname":"Nyangbasa",
    "gn:country_code":"CM",
    "gn:dem":664,
    "gn:feature_class":"P",
    "gn:feature_code":"PPL",
    "gn:name":"Nyangbasa",
    "gn:population":0,
    "gn:timezone":"Africa/Douala",
    "iso:country":"CM",
    "wof:name":"Nyangbasa",
    "wof:placetype":"locality"
},
  "geometry": {"coordinates":[12.36667,3.45],"type":"Point"}
}