{
  "type": "Feature",
  "properties": {
    "gn:admin1_code":"11.0",
    "gn:asciiname":"Emvan",
    "gn:country_code":"CM",
    "gn:dem":756,
    "gn:feature_class":"P",
    "gn:feature_code":"PPL",
    "gn:name":"Emvan",
    "gn:population":0,
    "gn:timezone":"Africa/Douala",
    "iso:country":"CM",
    "name:und_x_variant":[
        "Mvanessi",
        "Emvan"
    ],
    "wof:name":"Emvan",
    "wof:placetype":"locality"
},
  "geometry": {"coordinates":[12.11667,4.03333],"type":"Point"}
}