{
  "type": "Feature",
  "properties": {
    "gn:admin1_code":"5.0",
    "gn:asciiname":"Yankuzok",
    "gn:cc2":"CM",
    "gn:country_code":"CM",
    "gn:dem":35,
    "gn:feature_class":"P",
    "gn:feature_code":"PPL",
    "gn:name":"Yankuzok",
    "gn:population":0,
    "gn:timezone":"Africa/Douala",
    "iso:country":"CM",
    "name:und_x_variant":[
        "Yankouzok",
        "Yangkonsog",
        "Yankuzok"
    ],
    "wof:name":"Yankuzok",
    "wof:placetype":"locality"
},
  "geometry": {"coordinates":[9.82,3.59333],"type":"Point"}
}