{
  "type": "Feature",
  "properties": {
    "gn:admin1_code":"8.0",
    "gn:asciiname":"Mengoue",
    "gn:country_code":"CM",
    "gn:dem":1042,
    "gn:feature_class":"P",
    "gn:feature_code":"PPL",
    "gn:name":"Mengoue",
    "gn:population":0,
    "gn:timezone":"Africa/Douala",
    "iso:country":"CM",
    "wof:name":"Mengoue",
    "wof:placetype":"locality"
},
  "geometry": {"coordinates":[10.99045,5.56776],"type":"Point"}
}