{
  "type": "Feature",
  "properties": {
    "gn:admin1_code":"9.0",
    "gn:asciiname":"Sone",
    "gn:country_code":"CM",
    "gn:dem":26,
    "gn:feature_class":"P",
    "gn:feature_code":"PPL",
    "gn:name":"Sone",
    "gn:population":0,
    "gn:timezone":"Africa/Douala",
    "iso:country":"CM",
    "name:bul_x_preferred":[
        "\u0421\u043e\u043d"
    ],
    "name:cat_x_preferred":[
        "Son"
    ],
    "name:ces_x_preferred":[
        "Son"
    ],
    "name:deu_x_preferred":[
        "Sone"
    ],
    "name:fin_x_preferred":[
        "Sooni"
    ],
    "name:fra_x_preferred":[
        "Sone"
    ],
    "name:hrv_x_preferred":[
        "Son"
    ],
    "name:ita_x_preferred":[
        "Sone"
    ],
    "name:kaz_x_preferred":[
        "\u0421\u043e\u043d"
    ],
    "name:nld_x_preferred":[
        "Sone"
    ],
    "name:nno_x_preferred":[
        "Eininga sone"
    ],
    "name:pol_x_preferred":[
        "Son"
    ],
    "name:rus_x_preferred":[
        "\u0421\u043e\u043d"
    ],
    "name:spa_x_preferred":[
        "Sonio"
    ],
    "wof:name":"Sone",
    "wof:placetype":"locality"
},
  "geometry": {"coordinates":[9.39,4.104],"type":"Point"}
}