{
  "type": "Feature",
  "properties": {
    "gn:admin1_code":"14.0",
    "gn:asciiname":"Mvoula",
    "gn:country_code":"CM",
    "gn:dem":588,
    "gn:feature_class":"P",
    "gn:feature_code":"PPL",
    "gn:name":"Mvoula",
    "gn:population":0,
    "gn:timezone":"Africa/Douala",
    "iso:country":"CM",
    "wof:name":"Mvoula",
    "wof:placetype":"locality"
},
  "geometry": {"coordinates":[11.18333,2.85],"type":"Point"}
}