{
  "type": "Feature",
  "properties": {
    "gn:admin1_code":"10.0",
    "gn:asciiname":"Mayo Meke",
    "gn:country_code":"CM",
    "gn:dem":908,
    "gn:feature_class":"P",
    "gn:feature_code":"PPL",
    "gn:name":"Mayo M\u00e9k\u00e9",
    "gn:population":0,
    "gn:timezone":"Africa/Douala",
    "iso:country":"CM",
    "wof:name":"Mayo Meke",
    "wof:placetype":"locality"
},
  "geometry": {"coordinates":[12.75,6.76667],"type":"Point"}
}