{
  "type": "Feature",
  "properties": {
    "gn:admin1_code":"13.0",
    "gn:asciiname":"Koti Manga",
    "gn:country_code":"CM",
    "gn:dem":591,
    "gn:feature_class":"P",
    "gn:feature_code":"PPL",
    "gn:name":"Koti Manga",
    "gn:population":0,
    "gn:timezone":"Africa/Douala",
    "iso:country":"CM",
    "wof:name":"Koti Manga",
    "wof:placetype":"locality"
},
  "geometry": {"coordinates":[13.50954,8.16289],"type":"Point"}
}