{
  "type": "Feature",
  "properties": {
    "gn:admin1_code":"7.0",
    "gn:asciiname":"Nugu",
    "gn:country_code":"CM",
    "gn:dem":1190,
    "gn:feature_class":"P",
    "gn:feature_code":"PPL",
    "gn:name":"Nugu",
    "gn:population":0,
    "gn:timezone":"Africa/Douala",
    "iso:country":"CM",
    "wof:name":"Nugu",
    "wof:placetype":"locality"
},
  "geometry": {"coordinates":[10.36995,5.92014],"type":"Point"}
}