{
  "type": "Feature",
  "properties": {
    "gn:admin1_code":"11.0",
    "gn:asciiname":"Akondo",
    "gn:country_code":"CM",
    "gn:dem":723,
    "gn:feature_class":"P",
    "gn:feature_code":"PPL",
    "gn:name":"Akondo",
    "gn:population":0,
    "gn:timezone":"Africa/Douala",
    "iso:country":"CM",
    "wof:name":"Akondo",
    "wof:placetype":"locality"
},
  "geometry": {"coordinates":[11.93333,3.98333],"type":"Point"}
}