{
  "type": "Feature",
  "properties": {
    "gn:admin1_code":"8.0",
    "gn:asciiname":"Penhi",
    "gn:country_code":"CM",
    "gn:dem":1591,
    "gn:feature_class":"P",
    "gn:feature_code":"PPL",
    "gn:name":"Penhi",
    "gn:population":0,
    "gn:timezone":"Africa/Douala",
    "iso:country":"CM",
    "wof:name":"Penhi",
    "wof:placetype":"locality"
},
  "geometry": {"coordinates":[10.20302,5.43945],"type":"Point"}
}