{
  "type": "Feature",
  "properties": {
    "gn:admin1_code":"12.0",
    "gn:asciiname":"Goudjougoudjou",
    "gn:country_code":"CM",
    "gn:dem":749,
    "gn:feature_class":"P",
    "gn:feature_code":"PPL",
    "gn:name":"Goudjougoudjou",
    "gn:population":0,
    "gn:timezone":"Africa/Douala",
    "iso:country":"CM",
    "wof:name":"Goudjougoudjou",
    "wof:placetype":"locality"
},
  "geometry": {"coordinates":[13.6068,10.09788],"type":"Point"}
}