{
  "type": "Feature",
  "properties": {
    "gn:admin1_code":"9.0",
    "gn:asciiname":"Mbakem",
    "gn:country_code":"CM",
    "gn:dem":120,
    "gn:feature_class":"P",
    "gn:feature_code":"PPL",
    "gn:name":"Mbakem",
    "gn:population":0,
    "gn:timezone":"Africa/Douala",
    "iso:country":"CM",
    "wof:name":"Mbakem",
    "wof:placetype":"locality"
},
  "geometry": {"coordinates":[9.24032,5.94692],"type":"Point"}
}