{
  "type": "Feature",
  "properties": {
    "gn:admin1_code":"13.0",
    "gn:asciiname":"Djarengol",
    "gn:country_code":"CM",
    "gn:dem":488,
    "gn:feature_class":"P",
    "gn:feature_code":"PPL",
    "gn:name":"Djarengol",
    "gn:population":0,
    "gn:timezone":"Africa/Douala",
    "iso:country":"CM",
    "wof:name":"Djarengol",
    "wof:placetype":"locality"
},
  "geometry": {"coordinates":[13.38394,9.81695],"type":"Point"}
}