{
  "type": "Feature",
  "properties": {
    "gn:admin1_code":"13.0",
    "gn:asciiname":"Djaboule",
    "gn:country_code":"CM",
    "gn:dem":1256,
    "gn:feature_class":"P",
    "gn:feature_code":"PPL",
    "gn:name":"Djaboul\u00e9",
    "gn:population":0,
    "gn:timezone":"Africa/Douala",
    "iso:country":"CM",
    "wof:name":"Djaboule",
    "wof:placetype":"locality"
},
  "geometry": {"coordinates":[14.66667,7.18333],"type":"Point"}
}