{
  "type": "Feature",
  "properties": {
    "gn:admin1_code":"8.0",
    "gn:asciiname":"Kassa",
    "gn:country_code":"CM",
    "gn:dem":1423,
    "gn:feature_class":"P",
    "gn:feature_code":"PPL",
    "gn:name":"Kassa",
    "gn:population":0,
    "gn:timezone":"Africa/Douala",
    "iso:country":"CM",
    "name:ceb_x_preferred":[
        "Kassa"
    ],
    "name:deu_x_preferred":[
        "Kassa"
    ],
    "name:fin_x_preferred":[
        "Kassa"
    ],
    "name:fra_x_preferred":[
        "Kassa"
    ],
    "name:ita_x_preferred":[
        "Kassa"
    ],
    "name:nld_x_preferred":[
        "Kassa"
    ],
    "name:swe_x_preferred":[
        "Kassa"
    ],
    "wof:name":"Kassa",
    "wof:placetype":"locality"
},
  "geometry": {"coordinates":[10.3211,5.49501],"type":"Point"}
}