{
  "type": "Feature",
  "properties": {
    "gn:admin1_code":"13.0",
    "gn:asciiname":"Tchinte",
    "gn:country_code":"CM",
    "gn:dem":544,
    "gn:feature_class":"P",
    "gn:feature_code":"PPL",
    "gn:name":"Tchint\u00e9",
    "gn:population":0,
    "gn:timezone":"Africa/Douala",
    "iso:country":"CM",
    "wof:name":"Tchinte",
    "wof:placetype":"locality"
},
  "geometry": {"coordinates":[13.29937,8.44663],"type":"Point"}
}