{
  "type": "Feature",
  "properties": {
    "gn:admin1_code":"14.0",
    "gn:asciiname":"Melen",
    "gn:country_code":"CM",
    "gn:dem":668,
    "gn:feature_class":"P",
    "gn:feature_code":"PPL",
    "gn:name":"M\u00e9len",
    "gn:population":0,
    "gn:timezone":"Africa/Douala",
    "iso:country":"CM",
    "wof:name":"Melen",
    "wof:placetype":"locality"
},
  "geometry": {"coordinates":[13.03333,2.71667],"type":"Point"}
}