{
  "type": "Feature",
  "properties": {
    "gn:admin1_code":"13.0",
    "gn:asciiname":"Koum",
    "gn:country_code":"CM",
    "gn:dem":366,
    "gn:feature_class":"P",
    "gn:feature_code":"PPL",
    "gn:name":"Koum",
    "gn:population":0,
    "gn:timezone":"Africa/Douala",
    "iso:country":"CM",
    "name:und_x_variant":[
        "Kum",
        "Koum"
    ],
    "wof:name":"Koum",
    "wof:placetype":"locality"
},
  "geometry": {"coordinates":[14.5164,8.38254],"type":"Point"}
}