{
  "type": "Feature",
  "properties": {
    "gn:admin1_code":"5.0",
    "gn:asciiname":"Bonendale",
    "gn:country_code":"CM",
    "gn:dem":11,
    "gn:feature_class":"P",
    "gn:feature_code":"PPL",
    "gn:name":"Bonendal\u00e9",
    "gn:population":0,
    "gn:timezone":"Africa/Douala",
    "iso:country":"CM",
    "wof:name":"Bonendale",
    "wof:placetype":"locality"
},
  "geometry": {"coordinates":[9.6542,4.1175],"type":"Point"}
}