{
  "type": "Feature",
  "properties": {
    "gn:admin1_code":"11.0",
    "gn:asciiname":"Mbering",
    "gn:country_code":"CM",
    "gn:dem":665,
    "gn:feature_class":"P",
    "gn:feature_code":"PPL",
    "gn:name":"Mbering",
    "gn:population":0,
    "gn:timezone":"Africa/Douala",
    "iso:country":"CM",
    "wof:name":"Mbering",
    "wof:placetype":"locality"
},
  "geometry": {"coordinates":[12.31667,5.43333],"type":"Point"}
}