{
  "type": "Feature",
  "properties": {
    "gn:admin1_code":"13.0",
    "gn:asciiname":"Sigari",
    "gn:country_code":"CM",
    "gn:dem":593,
    "gn:feature_class":"P",
    "gn:feature_code":"PPL",
    "gn:name":"Sigari",
    "gn:population":0,
    "gn:timezone":"Africa/Douala",
    "iso:country":"CM",
    "name:fas_x_preferred":[
        "\u0633\u06cc\u06af\u0631\u06cc"
    ],
    "wof:name":"Sigari",
    "wof:placetype":"locality"
},
  "geometry": {"coordinates":[13.18426,8.33944],"type":"Point"}
}