{
  "type": "Feature",
  "properties": {
    "gn:admin1_code":"14.0",
    "gn:asciiname":"Akon",
    "gn:country_code":"CM",
    "gn:dem":422,
    "gn:feature_class":"P",
    "gn:feature_code":"PPL",
    "gn:name":"Akon",
    "gn:population":0,
    "gn:timezone":"Africa/Douala",
    "iso:country":"CM",
    "wof:name":"Akon",
    "wof:placetype":"locality"
},
  "geometry": {"coordinates":[10.48333,2.43333],"type":"Point"}
}