{
  "type": "Feature",
  "properties": {
    "gn:admin1_code":"10.0",
    "gn:asciiname":"Dabere",
    "gn:country_code":"CM",
    "gn:dem":966,
    "gn:feature_class":"P",
    "gn:feature_code":"PPL",
    "gn:name":"Dab\u00e9r\u00e9",
    "gn:population":0,
    "gn:timezone":"Africa/Douala",
    "iso:country":"CM",
    "wof:name":"Dabere",
    "wof:placetype":"locality"
},
  "geometry": {"coordinates":[12.09943,6.61366],"type":"Point"}
}