{
  "type": "Feature",
  "properties": {
    "gn:admin1_code":"12.0",
    "gn:asciiname":"Kore",
    "gn:country_code":"CM",
    "gn:dem":339,
    "gn:feature_class":"P",
    "gn:feature_code":"PPL",
    "gn:name":"Kor\u00e9",
    "gn:population":0,
    "gn:timezone":"Africa/Douala",
    "iso:country":"CM",
    "name:und_x_variant":[
        "Korr\u00e9",
        "Kor\u00e9"
    ],
    "wof:name":"Kore",
    "wof:placetype":"locality"
},
  "geometry": {"coordinates":[14.71253,10.45919],"type":"Point"}
}