{
  "type": "Feature",
  "properties": {
    "gn:admin1_code":"9.0",
    "gn:asciiname":"Ikata",
    "gn:country_code":"CM",
    "gn:dem":104,
    "gn:feature_class":"P",
    "gn:feature_code":"PPL",
    "gn:name":"Ikata",
    "gn:population":0,
    "gn:timezone":"Africa/Douala",
    "iso:country":"CM",
    "name:ceb_x_preferred":[
        "Ikata-ch\u014d"
    ],
    "name:fas_x_preferred":[
        "\u0627\u06cc\u06a9\u0627\u062a\u0627"
    ],
    "name:fra_x_preferred":[
        "Ikata"
    ],
    "name:ita_x_preferred":[
        "Ikata"
    ],
    "name:jpn_x_preferred":[
        "\u4f0a\u65b9\u753a"
    ],
    "name:kat_x_preferred":[
        "\u10d8\u10d9\u10d0\u10e2\u10d0"
    ],
    "name:kor_x_preferred":[
        "\uc774\uce74\ud0c0\uc815"
    ],
    "name:msa_x_preferred":[
        "Ikata"
    ],
    "name:mya_x_preferred":[
        "\u1021\u102d\u1001\u1010\u1019\u103c\u102d\u102f\u1037"
    ],
    "name:rus_x_preferred":[
        "\u0418\u043a\u0430\u0442\u0430"
    ],
    "name:spa_x_preferred":[
        "Ikata"
    ],
    "name:tgl_x_preferred":[
        "Ikata"
    ],
    "name:ukr_x_preferred":[
        "\u0406\u043a\u0430\u0442\u0430"
    ],
    "name:urd_x_preferred":[
        "\u0627\u06a9\u0627\u062a\u0627"
    ],
    "name:zho_x_preferred":[
        "\u4f0a\u65b9\u753a"
    ],
    "wof:name":"Ikata",
    "wof:placetype":"locality"
},
  "geometry": {"coordinates":[9.3594,4.3307],"type":"Point"}
}