{
  "type": "Feature",
  "properties": {
    "gn:admin1_code":"9.0",
    "gn:asciiname":"Ikata",
    "gn:country_code":"CM",
    "gn:dem":104,
    "gn:feature_class":"P",
    "gn:feature_code":"PPL",
    "gn:name":"Ikata",
    "gn:population":0,
    "gn:timezone":"Africa/Douala",
    "iso:country":"CM",
    "wof:name":"Ikata",
    "wof:placetype":"locality"
},
  "geometry": {"coordinates":[9.3594,4.3307],"type":"Point"}
}