{
  "type": "Feature",
  "properties": {
    "gn:admin1_code":"12.0",
    "gn:asciiname":"Bere",
    "gn:country_code":"CM",
    "gn:dem":671,
    "gn:feature_class":"P",
    "gn:feature_code":"PPL",
    "gn:name":"B\u00e9r\u00e9",
    "gn:population":0,
    "gn:timezone":"Africa/Douala",
    "iso:country":"CM",
    "name:ceb_x_preferred":[
        "Bere"
    ],
    "name:deu_x_preferred":[
        "Bere"
    ],
    "name:fra_x_preferred":[
        "Bere"
    ],
    "name:hun_x_preferred":[
        "Bere"
    ],
    "name:swe_x_preferred":[
        "Bere"
    ],
    "wof:name":"Bere",
    "wof:placetype":"locality"
},
  "geometry": {"coordinates":[13.97687,10.80012],"type":"Point"}
}