{
  "type": "Feature",
  "properties": {
    "gn:admin1_code":"13.0",
    "gn:asciiname":"Malwadou",
    "gn:country_code":"CM",
    "gn:dem":372,
    "gn:feature_class":"P",
    "gn:feature_code":"PPL",
    "gn:name":"Malwadou",
    "gn:population":0,
    "gn:timezone":"Africa/Douala",
    "iso:country":"CM",
    "wof:name":"Malwadou",
    "wof:placetype":"locality"
},
  "geometry": {"coordinates":[13.02593,8.52992],"type":"Point"}
}