{
  "type": "Feature",
  "properties": {
    "gn:admin1_code":"12.0",
    "gn:asciiname":"Mofouele",
    "gn:country_code":"CM",
    "gn:dem":776,
    "gn:feature_class":"P",
    "gn:feature_code":"PPL",
    "gn:name":"Mofou\u00e9l\u00e9",
    "gn:population":0,
    "gn:timezone":"Africa/Douala",
    "iso:country":"CM",
    "name:und_x_variant":[
        "Gorail",
        "Moufw\u00e9l\u00e9",
        "Mofou\u00e9l\u00e9"
    ],
    "wof:name":"Mofouele",
    "wof:placetype":"locality"
},
  "geometry": {"coordinates":[13.81124,10.71373],"type":"Point"}
}