{
  "type": "Feature",
  "properties": {
    "gn:admin1_code":"13.0",
    "gn:asciiname":"Garna",
    "gn:country_code":"CM",
    "gn:dem":253,
    "gn:feature_class":"P",
    "gn:feature_code":"PPL",
    "gn:name":"Garna",
    "gn:population":0,
    "gn:timezone":"Africa/Douala",
    "iso:country":"CM",
    "name:ara_x_preferred":[
        "\u063a\u0631\u0646\u0627"
    ],
    "name:fas_x_preferred":[
        "\u06af\u0631\u0646\u0627"
    ],
    "name:mzn_x_preferred":[
        "\u06af\u0631\u0646\u0627"
    ],
    "name:ukr_x_preferred":[
        "\u0490\u0430\u0440\u043d\u0430"
    ],
    "wof:name":"Garna",
    "wof:placetype":"locality"
},
  "geometry": {"coordinates":[13.88013,9.54206],"type":"Point"}
}