{
  "type": "Feature",
  "properties": {
    "gn:admin1_code":"13.0",
    "gn:asciiname":"Garna",
    "gn:country_code":"CM",
    "gn:dem":253,
    "gn:feature_class":"P",
    "gn:feature_code":"PPL",
    "gn:name":"Garna",
    "gn:population":0,
    "gn:timezone":"Africa/Douala",
    "iso:country":"CM",
    "wof:name":"Garna",
    "wof:placetype":"locality"
},
  "geometry": {"coordinates":[13.88013,9.54206],"type":"Point"}
}