{
  "type": "Feature",
  "properties": {
    "gn:admin1_code":"11.0",
    "gn:asciiname":"Nkilzok II",
    "gn:country_code":"CM",
    "gn:dem":685,
    "gn:feature_class":"P",
    "gn:feature_code":"PPL",
    "gn:name":"Nkilzok II",
    "gn:population":0,
    "gn:timezone":"Africa/Douala",
    "iso:country":"CM",
    "name:und_x_variant":[
        "Nkilzok",
        "Nkilzok II"
    ],
    "wof:name":"Nkilzok II",
    "wof:placetype":"locality"
},
  "geometry": {"coordinates":[11.66667,3.66667],"type":"Point"}
}