{
  "type": "Feature",
  "properties": {
    "gn:admin1_code":"11.0",
    "gn:asciiname":"Nkoelon",
    "gn:country_code":"CM",
    "gn:dem":683,
    "gn:feature_class":"P",
    "gn:feature_code":"PPL",
    "gn:name":"Nko\u00e9lon",
    "gn:population":0,
    "gn:timezone":"Africa/Douala",
    "iso:country":"CM",
    "wof:name":"Nkoelon",
    "wof:placetype":"locality"
},
  "geometry": {"coordinates":[11.31667,3.53333],"type":"Point"}
}