{
  "type": "Feature",
  "properties": {
    "gn:admin1_code":"12.0",
    "gn:asciiname":"Gayakere",
    "gn:country_code":"CM",
    "gn:dem":394,
    "gn:feature_class":"P",
    "gn:feature_code":"PPL",
    "gn:name":"Gayak\u00e9r\u00e9",
    "gn:population":0,
    "gn:timezone":"Africa/Douala",
    "iso:country":"CM",
    "wof:name":"Gayakere",
    "wof:placetype":"locality"
},
  "geometry": {"coordinates":[14.31268,10.8042],"type":"Point"}
}