{
  "type": "Feature",
  "properties": {
    "gn:admin1_code":"13.0",
    "gn:asciiname":"Ourogarga",
    "gn:country_code":"CM",
    "gn:dem":173,
    "gn:feature_class":"P",
    "gn:feature_code":"PPL",
    "gn:name":"Ourogarga",
    "gn:population":0,
    "gn:timezone":"Africa/Douala",
    "iso:country":"CM",
    "wof:name":"Ourogarga",
    "wof:placetype":"locality"
},
  "geometry": {"coordinates":[12.88333,9.38333],"type":"Point"}
}