{
  "type": "Feature",
  "properties": {
    "gn:admin1_code":"12.0",
    "gn:asciiname":"Djemeni",
    "gn:country_code":"CM",
    "gn:dem":293,
    "gn:feature_class":"P",
    "gn:feature_code":"PPL",
    "gn:name":"Dj\u00e9m\u00e9ni",
    "gn:population":0,
    "gn:timezone":"Africa/Douala",
    "iso:country":"CM",
    "name:und_x_variant":[
        "Dj\u00e9m\u00e9ni",
        "Amkindine"
    ],
    "wof:name":"Djemeni",
    "wof:placetype":"locality"
},
  "geometry": {"coordinates":[14.70669,12.27582],"type":"Point"}
}