{
  "type": "Feature",
  "properties": {
    "gn:admin1_code":"13.0",
    "gn:asciiname":"Bandi",
    "gn:country_code":"CM",
    "gn:dem":580,
    "gn:feature_class":"P",
    "gn:feature_code":"PPL",
    "gn:name":"Bandi",
    "gn:population":0,
    "gn:timezone":"Africa/Douala",
    "iso:country":"CM",
    "name:ceb_x_preferred":[
        "Bandi"
    ],
    "name:deu_x_preferred":[
        "Bandi"
    ],
    "name:fra_x_preferred":[
        "Bandi"
    ],
    "name:ita_x_preferred":[
        "Bandi"
    ],
    "name:slv_x_preferred":[
        "Bandi"
    ],
    "name:swe_x_preferred":[
        "Bandi"
    ],
    "name:vie_x_preferred":[
        "Bandi"
    ],
    "wof:name":"Bandi",
    "wof:placetype":"locality"
},
  "geometry": {"coordinates":[13.712,10.00778],"type":"Point"}
}