{
  "type": "Feature",
  "properties": {
    "gn:admin1_code":"11.0",
    "gn:asciiname":"Ndelle",
    "gn:country_code":"CM",
    "gn:dem":702,
    "gn:feature_class":"P",
    "gn:feature_code":"PPL",
    "gn:name":"Nd\u00e9ll\u00e9",
    "gn:population":0,
    "gn:timezone":"Africa/Douala",
    "iso:country":"CM",
    "name:und_x_variant":[
        "Ndel\u00e9",
        "Nd\u00e9ll\u00e9"
    ],
    "wof:name":"Ndelle",
    "wof:placetype":"locality"
},
  "geometry": {"coordinates":[12.55,4.01667],"type":"Point"}
}