{
  "type": "Feature",
  "properties": {
    "gn:admin1_code":"11.0",
    "gn:asciiname":"Nkoleman",
    "gn:country_code":"CM",
    "gn:dem":681,
    "gn:feature_class":"P",
    "gn:feature_code":"PPL",
    "gn:name":"Nkol\u00e9man",
    "gn:population":0,
    "gn:timezone":"Africa/Douala",
    "iso:country":"CM",
    "wof:name":"Nkoleman",
    "wof:placetype":"locality"
},
  "geometry": {"coordinates":[11.25,3.55],"type":"Point"}
}