{
  "type": "Feature",
  "properties": {
    "gn:admin1_code":"9.0",
    "gn:asciiname":"Akwaya",
    "gn:country_code":"CM",
    "gn:dem":507,
    "gn:feature_class":"P",
    "gn:feature_code":"PPL",
    "gn:name":"Akwaya",
    "gn:population":0,
    "gn:timezone":"Africa/Douala",
    "iso:country":"CM",
    "name:azb_x_preferred":[
        "\u0627\u06a9\u0648\u0627\u06cc\u0627"
    ],
    "name:deu_x_preferred":[
        "Akwaya"
    ],
    "name:fas_x_preferred":[
        "\u0627\u06a9\u0648\u0627\u06cc\u0627"
    ],
    "name:fra_x_preferred":[
        "Akwaya"
    ],
    "name:ita_x_preferred":[
        "Akwaya"
    ],
    "name:msa_x_preferred":[
        "Akwaya"
    ],
    "name:spa_x_preferred":[
        "Akwaya"
    ],
    "wof:name":"Akwaya",
    "wof:placetype":"locality"
},
  "geometry": {"coordinates":[9.5355,6.3713],"type":"Point"}
}