{
  "type": "Feature",
  "properties": {
    "gn:admin1_code":"7.0",
    "gn:asciiname":"Komine",
    "gn:country_code":"CM",
    "gn:dem":948,
    "gn:feature_class":"P",
    "gn:feature_code":"PPL",
    "gn:name":"Komine",
    "gn:population":0,
    "gn:timezone":"Africa/Douala",
    "iso:country":"CM",
    "name:und_x_variant":[
        "Kamine",
        "Komine"
    ],
    "wof:name":"Komine",
    "wof:placetype":"locality"
},
  "geometry": {"coordinates":[10.56667,6.58333],"type":"Point"}
}