{
  "type": "Feature",
  "properties": {
    "gn:admin1_code":"13.0",
    "gn:asciiname":"Laonina",
    "gn:country_code":"CM",
    "gn:dem":576,
    "gn:feature_class":"P",
    "gn:feature_code":"PPL",
    "gn:name":"Laonina",
    "gn:population":0,
    "gn:timezone":"Africa/Douala",
    "iso:country":"CM",
    "wof:name":"Laonina",
    "wof:placetype":"locality"
},
  "geometry": {"coordinates":[14.91667,7.85],"type":"Point"}
}