{
  "type": "Feature",
  "properties": {
    "gn:admin1_code":"12.0",
    "gn:asciiname":"Goura",
    "gn:country_code":"CM",
    "gn:dem":291,
    "gn:feature_class":"P",
    "gn:feature_code":"PPL",
    "gn:name":"Goura",
    "gn:population":0,
    "gn:timezone":"Africa/Douala",
    "iso:country":"CM",
    "name:ceb_x_preferred":[
        "Goura"
    ],
    "name:deu_x_preferred":[
        "Goura"
    ],
    "name:swe_x_preferred":[
        "Goura"
    ],
    "wof:name":"Goura",
    "wof:placetype":"locality"
},
  "geometry": {"coordinates":[14.51381,12.33651],"type":"Point"}
}