{
  "type": "Feature",
  "properties": {
    "gn:admin1_code":"4.0",
    "gn:asciiname":"Zoulabot",
    "gn:country_code":"CM",
    "gn:dem":647,
    "gn:feature_class":"P",
    "gn:feature_code":"PPL",
    "gn:name":"Zoulabot",
    "gn:population":0,
    "gn:timezone":"Africa/Douala",
    "iso:country":"CM",
    "name:und_x_variant":[
        "Mapea\u2019s",
        "Soulabod",
        "Zoulabod",
        "Ss\u00falabod",
        "Zoulabot"
    ],
    "wof:name":"Zoulabot",
    "wof:placetype":"locality"
},
  "geometry": {"coordinates":[14.03333,3.28333],"type":"Point"}
}