{
  "type": "Feature",
  "properties": {
    "gn:admin1_code":"5.0",
    "gn:asciiname":"Grand Souza",
    "gn:country_code":"CM",
    "gn:dem":73,
    "gn:feature_class":"P",
    "gn:feature_code":"PPL",
    "gn:name":"Grand Souza",
    "gn:population":0,
    "gn:timezone":"Africa/Douala",
    "iso:country":"CM",
    "wof:name":"Grand Souza",
    "wof:placetype":"locality"
},
  "geometry": {"coordinates":[9.6408,4.2348],"type":"Point"}
}