{
  "type": "Feature",
  "properties": {
    "gn:admin1_code":"11.0",
    "gn:asciiname":"Ombamo",
    "gn:country_code":"CM",
    "gn:dem":602,
    "gn:feature_class":"P",
    "gn:feature_code":"PPL",
    "gn:name":"Ombamo",
    "gn:population":0,
    "gn:timezone":"Africa/Douala",
    "iso:country":"CM",
    "wof:name":"Ombamo",
    "wof:placetype":"locality"
},
  "geometry": {"coordinates":[10.98333,4.43333],"type":"Point"}
}