{
  "type": "Feature",
  "properties": {
    "gn:admin1_code":"8.0",
    "gn:asciiname":"Didango",
    "gn:country_code":"CM",
    "gn:dem":1232,
    "gn:feature_class":"P",
    "gn:feature_code":"PPL",
    "gn:name":"Didango",
    "gn:population":0,
    "gn:timezone":"Africa/Douala",
    "iso:country":"CM",
    "name:fra_x_preferred":[
        "Didango"
    ],
    "wof:name":"Didango",
    "wof:placetype":"locality"
},
  "geometry": {"coordinates":[10.71964,5.66452],"type":"Point"}
}