{
  "type": "Feature",
  "properties": {
    "gn:admin1_code":"5.0",
    "gn:asciiname":"Moutimbelembe",
    "gn:country_code":"CM",
    "gn:dem":9,
    "gn:feature_class":"P",
    "gn:feature_code":"PPL",
    "gn:name":"Moutimbelemb\u00e9",
    "gn:population":0,
    "gn:timezone":"Africa/Douala",
    "iso:country":"CM",
    "wof:name":"Moutimbelembe",
    "wof:placetype":"locality"
},
  "geometry": {"coordinates":[9.8191,4.2578],"type":"Point"}
}