{
  "type": "Feature",
  "properties": {
    "gn:admin1_code":"9.0",
    "gn:asciiname":"Kombone",
    "gn:country_code":"CM",
    "gn:dem":138,
    "gn:feature_class":"P",
    "gn:feature_code":"PPL",
    "gn:name":"Kombone",
    "gn:population":0,
    "gn:timezone":"Africa/Douala",
    "iso:country":"CM",
    "wof:name":"Kombone",
    "wof:placetype":"locality"
},
  "geometry": {"coordinates":[9.3061,4.5832],"type":"Point"}
}