{
  "type": "Feature",
  "properties": {
    "gn:admin1_code":"13.0",
    "gn:asciiname":"Ponila",
    "gn:country_code":"CM",
    "gn:dem":303,
    "gn:feature_class":"P",
    "gn:feature_code":"PPL",
    "gn:name":"Ponila",
    "gn:population":0,
    "gn:timezone":"Africa/Douala",
    "iso:country":"CM",
    "wof:name":"Ponila",
    "wof:placetype":"locality"
},
  "geometry": {"coordinates":[13.96667,9.78333],"type":"Point"}
}