{
  "type": "Feature",
  "properties": {
    "gn:admin1_code":"8.0",
    "gn:asciiname":"Letet",
    "gn:country_code":"CM",
    "gn:dem":1547,
    "gn:feature_class":"P",
    "gn:feature_code":"PPL",
    "gn:name":"Letet",
    "gn:population":0,
    "gn:timezone":"Africa/Douala",
    "iso:country":"CM",
    "wof:name":"Letet",
    "wof:placetype":"locality"
},
  "geometry": {"coordinates":[10.11456,5.41068],"type":"Point"}
}