{
  "type": "Feature",
  "properties": {
    "gn:admin1_code":"12.0",
    "gn:asciiname":"Gori",
    "gn:country_code":"CM",
    "gn:dem":289,
    "gn:feature_class":"P",
    "gn:feature_code":"PPL",
    "gn:name":"Gori",
    "gn:population":0,
    "gn:timezone":"Africa/Douala",
    "iso:country":"CM",
    "name:bul_x_preferred":[
        "\u0413\u043e\u0440\u0438"
    ],
    "name:cat_x_preferred":[
        "Gori"
    ],
    "name:ceb_x_preferred":[
        "Gori"
    ],
    "name:deu_x_preferred":[
        "Gori"
    ],
    "name:epo_x_preferred":[
        "Gori"
    ],
    "name:eus_x_preferred":[
        "Gori"
    ],
    "name:fas_x_preferred":[
        "\u06af\u0648\u0631\u06cc"
    ],
    "name:fra_x_preferred":[
        "Gori"
    ],
    "name:ita_x_preferred":[
        "Gori"
    ],
    "name:jpn_x_preferred":[
        "\u30b4\u30ea"
    ],
    "name:kat_x_preferred":[
        "\u10d2\u10dd\u10e0\u10d8"
    ],
    "name:oci_x_preferred":[
        "G\u00f2ri"
    ],
    "name:pms_x_preferred":[
        "Gori"
    ],
    "name:ron_x_preferred":[
        "Gori"
    ],
    "name:rus_x_preferred":[
        "\u0413\u043e\u0440\u0438"
    ],
    "name:sco_x_preferred":[
        "Gori"
    ],
    "name:swe_x_preferred":[
        "Gori"
    ],
    "wof:name":"Gori",
    "wof:placetype":"locality"
},
  "geometry": {"coordinates":[14.6092,12.51477],"type":"Point"}
}