{
  "type": "Feature",
  "properties": {
    "gn:admin1_code":"13.0",
    "gn:asciiname":"Mayo Galke",
    "gn:country_code":"CM",
    "gn:dem":299,
    "gn:feature_class":"P",
    "gn:feature_code":"PPL",
    "gn:name":"Mayo Galk\u00e9",
    "gn:population":0,
    "gn:timezone":"Africa/Douala",
    "iso:country":"CM",
    "wof:name":"Mayo Galke",
    "wof:placetype":"locality"
},
  "geometry": {"coordinates":[14.2341,8.3976],"type":"Point"}
}