{
  "type": "Feature",
  "properties": {
    "gn:admin1_code":"13.0",
    "gn:asciiname":"Douroy",
    "gn:country_code":"CM",
    "gn:dem":347,
    "gn:feature_class":"P",
    "gn:feature_code":"PPL",
    "gn:name":"Douroy",
    "gn:population":0,
    "gn:timezone":"Africa/Douala",
    "iso:country":"CM",
    "wof:name":"Douroy",
    "wof:placetype":"locality"
},
  "geometry": {"coordinates":[14.4015,9.0511],"type":"Point"}
}