{
  "type": "Feature",
  "properties": {
    "gn:admin1_code":"13.0",
    "gn:asciiname":"Tebou",
    "gn:country_code":"CM",
    "gn:dem":501,
    "gn:feature_class":"P",
    "gn:feature_code":"PPL",
    "gn:name":"Tebou",
    "gn:population":0,
    "gn:timezone":"Africa/Lagos",
    "iso:country":"CM",
    "wof:name":"Tebou",
    "wof:placetype":"locality"
},
  "geometry": {"coordinates":[12.48264,8.62879],"type":"Point"}
}