{
  "type": "Feature",
  "properties": {
    "gn:admin1_code":"12.0",
    "gn:asciiname":"Gouarang",
    "gn:country_code":"CM",
    "gn:dem":330,
    "gn:feature_class":"P",
    "gn:feature_code":"PPL",
    "gn:name":"Gouarang",
    "gn:population":0,
    "gn:timezone":"Africa/Douala",
    "iso:country":"CM",
    "wof:name":"Gouarang",
    "wof:placetype":"locality"
},
  "geometry": {"coordinates":[14.98481,10.40302],"type":"Point"}
}