{
  "type": "Feature",
  "properties": {
    "gn:admin1_code":"13.0",
    "gn:asciiname":"Boguel",
    "gn:country_code":"CM",
    "gn:dem":183,
    "gn:feature_class":"P",
    "gn:feature_code":"PPL",
    "gn:name":"Boguel",
    "gn:population":0,
    "gn:timezone":"Africa/Douala",
    "iso:country":"CM",
    "wof:name":"Boguel",
    "wof:placetype":"locality"
},
  "geometry": {"coordinates":[12.95,9.08333],"type":"Point"}
}