{
  "type": "Feature",
  "properties": {
    "gn:admin1_code":"12.0",
    "gn:asciiname":"Djireib II",
    "gn:country_code":"CM",
    "gn:dem":292,
    "gn:feature_class":"P",
    "gn:feature_code":"PPL",
    "gn:name":"Djireib II",
    "gn:population":0,
    "gn:timezone":"Africa/Douala",
    "iso:country":"CM",
    "wof:name":"Djireib II",
    "wof:placetype":"locality"
},
  "geometry": {"coordinates":[14.4298,12.62124],"type":"Point"}
}