{
  "type": "Feature",
  "properties": {
    "gn:admin1_code":"11.0",
    "gn:asciiname":"Ngong",
    "gn:country_code":"CM",
    "gn:dem":570,
    "gn:feature_class":"P",
    "gn:feature_code":"PPL",
    "gn:name":"Ngong",
    "gn:population":0,
    "gn:timezone":"Africa/Douala",
    "iso:country":"CM",
    "name:ceb_x_preferred":[
        "Ngong"
    ],
    "name:deu_x_preferred":[
        "Ngong"
    ],
    "name:swe_x_preferred":[
        "Ngong"
    ],
    "wof:name":"Ngong",
    "wof:placetype":"locality"
},
  "geometry": {"coordinates":[11.38333,4.08333],"type":"Point"}
}