{
  "type": "Feature",
  "properties": {
    "gn:admin1_code":"7.0",
    "gn:asciiname":"Gundom",
    "gn:country_code":"CM",
    "gn:dem":1369,
    "gn:feature_class":"P",
    "gn:feature_code":"PPL",
    "gn:name":"Gundom",
    "gn:population":0,
    "gn:timezone":"Africa/Douala",
    "iso:country":"CM",
    "wof:name":"Gundom",
    "wof:placetype":"locality"
},
  "geometry": {"coordinates":[9.9654,5.9969],"type":"Point"}
}