{
  "type": "Feature",
  "properties": {
    "gn:admin1_code":"5.0",
    "gn:asciiname":"Bwadibo",
    "gn:country_code":"CM",
    "gn:dem":10,
    "gn:feature_class":"P",
    "gn:feature_code":"PPL",
    "gn:name":"Bwadibo",
    "gn:population":0,
    "gn:timezone":"Africa/Douala",
    "iso:country":"CM",
    "name:und_x_variant":[
        "Boadibo",
        "Bwadibo"
    ],
    "wof:name":"Bwadibo",
    "wof:placetype":"locality"
},
  "geometry": {"coordinates":[9.5853,4.0907],"type":"Point"}
}