{
  "type": "Feature",
  "properties": {
    "gn:admin1_code":"8.0",
    "gn:asciiname":"Ndennkem",
    "gn:country_code":"CM",
    "gn:dem":1745,
    "gn:feature_class":"P",
    "gn:feature_code":"PPL",
    "gn:name":"Ndennkem",
    "gn:population":0,
    "gn:timezone":"Africa/Douala",
    "iso:country":"CM",
    "wof:name":"Ndennkem",
    "wof:placetype":"locality"
},
  "geometry": {"coordinates":[10.3217,5.24335],"type":"Point"}
}