{
  "type": "Feature",
  "properties": {
    "gn:admin1_code":"5.0",
    "gn:asciiname":"Nyakele",
    "gn:country_code":"CM",
    "gn:dem":480,
    "gn:feature_class":"P",
    "gn:feature_code":"PPL",
    "gn:name":"Nyak\u00e9l\u00e9",
    "gn:population":0,
    "gn:timezone":"Africa/Douala",
    "iso:country":"CM",
    "name:und_x_variant":[
        "Ngak\u00e9l\u00e9",
        "Nyak\u00e9l\u00e9"
    ],
    "wof:name":"Nyakele",
    "wof:placetype":"locality"
},
  "geometry": {"coordinates":[10.95,4.23333],"type":"Point"}
}