{
  "type": "Feature",
  "properties": {
    "gn:admin1_code":"12.0",
    "gn:asciiname":"Mendeze",
    "gn:country_code":"CM",
    "gn:dem":796,
    "gn:feature_class":"P",
    "gn:feature_code":"PPL",
    "gn:name":"Mend\u00e9z\u00e9",
    "gn:population":0,
    "gn:timezone":"Africa/Douala",
    "iso:country":"CM",
    "name:und_x_variant":[
        "Mend\u00e9s\u00e9",
        "Mend\u00e9z\u00e9",
        "Mend\u00e9ss\u00e9"
    ],
    "wof:name":"Mendeze",
    "wof:placetype":"locality"
},
  "geometry": {"coordinates":[13.81472,10.75295],"type":"Point"}
}