{
  "type": "Feature",
  "properties": {
    "gn:admin1_code":"14.0",
    "gn:asciiname":"Mvasse",
    "gn:country_code":"CM",
    "gn:dem":57,
    "gn:feature_class":"P",
    "gn:feature_code":"PPL",
    "gn:name":"Mvass\u00e9",
    "gn:population":0,
    "gn:timezone":"Africa/Douala",
    "iso:country":"CM",
    "wof:name":"Mvasse",
    "wof:placetype":"locality"
},
  "geometry": {"coordinates":[9.86667,2.33333],"type":"Point"}
}