{
  "type": "Feature",
  "properties": {
    "gn:admin1_code":"11.0",
    "gn:asciiname":"Nkolnget",
    "gn:country_code":"CM",
    "gn:dem":704,
    "gn:feature_class":"P",
    "gn:feature_code":"PPL",
    "gn:name":"Nkolnget",
    "gn:population":0,
    "gn:timezone":"Africa/Douala",
    "iso:country":"CM",
    "wof:name":"Nkolnget",
    "wof:placetype":"locality"
},
  "geometry": {"coordinates":[11.63333,3.75],"type":"Point"}
}