{
  "type": "Feature",
  "properties": {
    "gn:admin1_code":"9.0",
    "gn:asciiname":"Dikome Bafaw",
    "gn:country_code":"CM",
    "gn:dem":296,
    "gn:feature_class":"P",
    "gn:feature_code":"PPL",
    "gn:name":"Dikome Bafaw",
    "gn:population":0,
    "gn:timezone":"Africa/Douala",
    "iso:country":"CM",
    "wof:name":"Dikome Bafaw",
    "wof:placetype":"locality"
},
  "geometry": {"coordinates":[9.46879,4.95443],"type":"Point"}
}