{
  "type": "Feature",
  "properties": {
    "gn:admin1_code":"11.0",
    "gn:asciiname":"Elale",
    "gn:country_code":"CM",
    "gn:dem":482,
    "gn:feature_class":"P",
    "gn:feature_code":"PPL",
    "gn:name":"\u00c9lal\u00e9",
    "gn:population":0,
    "gn:timezone":"Africa/Douala",
    "iso:country":"CM",
    "wof:name":"Elale",
    "wof:placetype":"locality"
},
  "geometry": {"coordinates":[11.13333,4.06667],"type":"Point"}
}