{
  "type": "Feature",
  "properties": {
    "gn:admin1_code":"13.0",
    "gn:asciiname":"Doumboulko",
    "gn:country_code":"CM",
    "gn:dem":730,
    "gn:feature_class":"P",
    "gn:feature_code":"PPL",
    "gn:name":"Doumboulko",
    "gn:population":0,
    "gn:timezone":"Africa/Douala",
    "iso:country":"CM",
    "wof:name":"Doumboulko",
    "wof:placetype":"locality"
},
  "geometry": {"coordinates":[13.27037,8.41478],"type":"Point"}
}