{
  "type": "Feature",
  "properties": {
    "gn:admin1_code":"0.0",
    "gn:asciiname":"Mayo",
    "gn:country_code":"CM",
    "gn:dem":944,
    "gn:feature_class":"P",
    "gn:feature_code":"PPL",
    "gn:name":"Mayo",
    "gn:population":0,
    "gn:timezone":"Africa/Douala",
    "iso:country":"CM",
    "wof:name":"Mayo",
    "wof:placetype":"locality"
},
  "geometry": {"coordinates":[10.26938,5.09024],"type":"Point"}
}