{
  "type": "Feature",
  "properties": {
    "gn:admin1_code":"9.0",
    "gn:asciiname":"Bolifamba",
    "gn:country_code":"CM",
    "gn:dem":495,
    "gn:feature_class":"P",
    "gn:feature_code":"PPL",
    "gn:name":"Bolifamba",
    "gn:population":0,
    "gn:timezone":"Africa/Douala",
    "iso:country":"CM",
    "name:und_x_variant":[
        "Bolifambi",
        "Bolyfamba",
        "Bolifamba"
    ],
    "wof:name":"Bolifamba",
    "wof:placetype":"locality"
},
  "geometry": {"coordinates":[9.3061,4.142],"type":"Point"}
}