{
  "type": "Feature",
  "properties": {
    "gn:admin1_code":"10.0",
    "gn:asciiname":"Sola",
    "gn:country_code":"CM",
    "gn:dem":878,
    "gn:feature_class":"P",
    "gn:feature_code":"PPL",
    "gn:name":"Sola",
    "gn:population":0,
    "gn:timezone":"Africa/Douala",
    "iso:country":"CM",
    "wof:name":"Sola",
    "wof:placetype":"locality"
},
  "geometry": {"coordinates":[12.55176,6.30965],"type":"Point"}
}