{
  "type": "Feature",
  "properties": {
    "gn:admin1_code":"5.0",
    "gn:asciiname":"Mbalie",
    "gn:country_code":"CM",
    "gn:dem":1,
    "gn:feature_class":"P",
    "gn:feature_code":"PPL",
    "gn:name":"Mbali\u00e9",
    "gn:population":0,
    "gn:timezone":"Africa/Douala",
    "iso:country":"CM",
    "wof:name":"Mbalie",
    "wof:placetype":"locality"
},
  "geometry": {"coordinates":[9.77083,3.44306],"type":"Point"}
}