{
  "type": "Feature",
  "properties": {
    "gn:admin1_code":"13.0",
    "gn:asciiname":"Guerete",
    "gn:country_code":"CM",
    "gn:dem":190,
    "gn:feature_class":"P",
    "gn:feature_code":"PPL",
    "gn:name":"Gu\u00e9r\u00e9t\u00e9",
    "gn:population":0,
    "gn:timezone":"Africa/Douala",
    "iso:country":"CM",
    "name:und_x_variant":[
        "Gu\u00e9r\u00e9t\u00e9",
        "G\u00e9r\u00e9t\u00e9",
        "G\u00e9r\u00e9l\u00e9"
    ],
    "wof:name":"Guerete",
    "wof:placetype":"locality"
},
  "geometry": {"coordinates":[12.99639,9.43781],"type":"Point"}
}