{
  "type": "Feature",
  "properties": {
    "gn:admin1_code":"12.0",
    "gn:asciiname":"Borey",
    "gn:country_code":"CM",
    "gn:dem":342,
    "gn:feature_class":"P",
    "gn:feature_code":"PPL",
    "gn:name":"Borey",
    "gn:population":0,
    "gn:timezone":"Africa/Douala",
    "iso:country":"CM",
    "name:bug_x_preferred":[
        "Borey"
    ],
    "name:cat_x_preferred":[
        "Borey"
    ],
    "name:ceb_x_preferred":[
        "Borey"
    ],
    "name:deu_x_preferred":[
        "Borey"
    ],
    "name:eus_x_preferred":[
        "Borey"
    ],
    "name:fra_x_preferred":[
        "Borey"
    ],
    "name:hun_x_preferred":[
        "Borey"
    ],
    "name:ita_x_preferred":[
        "Borey"
    ],
    "name:lat_x_preferred":[
        "Borey"
    ],
    "name:msa_x_preferred":[
        "Borey"
    ],
    "name:nld_x_preferred":[
        "Borey"
    ],
    "name:oci_x_preferred":[
        "Borey"
    ],
    "name:pms_x_preferred":[
        "Borey"
    ],
    "name:pol_x_preferred":[
        "Borey"
    ],
    "name:por_x_preferred":[
        "Borey"
    ],
    "name:rus_x_preferred":[
        "\u0411\u043e\u0440\u0435"
    ],
    "name:slk_x_preferred":[
        "Borey"
    ],
    "name:spa_x_preferred":[
        "Borey"
    ],
    "name:srp_x_preferred":[
        "\u0411\u043e\u0440\u0435"
    ],
    "name:swe_x_preferred":[
        "Borey"
    ],
    "name:ukr_x_preferred":[
        "\u0411\u043e\u0440\u0435"
    ],
    "name:uzb_x_preferred":[
        "Borey"
    ],
    "name:vie_x_preferred":[
        "Borey"
    ],
    "name:vol_x_preferred":[
        "Borey"
    ],
    "name:war_x_preferred":[
        "Borey"
    ],
    "wof:name":"Borey",
    "wof:placetype":"locality"
},
  "geometry": {"coordinates":[14.63869,10.66126],"type":"Point"}
}