{
  "type": "Feature",
  "properties": {
    "gn:admin1_code":"12.0",
    "gn:asciiname":"Borey",
    "gn:country_code":"CM",
    "gn:dem":342,
    "gn:feature_class":"P",
    "gn:feature_code":"PPL",
    "gn:name":"Borey",
    "gn:population":0,
    "gn:timezone":"Africa/Douala",
    "iso:country":"CM",
    "wof:name":"Borey",
    "wof:placetype":"locality"
},
  "geometry": {"coordinates":[14.63869,10.66126],"type":"Point"}
}