{
  "type": "Feature",
  "properties": {
    "gn:admin1_code":"9.0",
    "gn:asciiname":"Ntak",
    "gn:country_code":"CM",
    "gn:dem":1538,
    "gn:feature_class":"P",
    "gn:feature_code":"PPL",
    "gn:name":"Ntak",
    "gn:population":0,
    "gn:timezone":"Africa/Douala",
    "iso:country":"CM",
    "wof:name":"Ntak",
    "wof:placetype":"locality"
},
  "geometry": {"coordinates":[9.7832,5.0361],"type":"Point"}
}