{
  "type": "Feature",
  "properties": {
    "gn:admin1_code":"12.0",
    "gn:asciiname":"Lepros",
    "gn:country_code":"CM",
    "gn:dem":382,
    "gn:feature_class":"P",
    "gn:feature_code":"PPL",
    "gn:name":"L\u00e9pros",
    "gn:population":0,
    "gn:timezone":"Africa/Douala",
    "iso:country":"CM",
    "wof:name":"Lepros",
    "wof:placetype":"locality"
},
  "geometry": {"coordinates":[14.48539,10.14863],"type":"Point"}
}