{
  "type": "Feature",
  "properties": {
    "gn:admin1_code":"7.0",
    "gn:asciiname":"Nyali",
    "gn:country_code":"CM",
    "gn:dem":1742,
    "gn:feature_class":"P",
    "gn:feature_code":"PPL",
    "gn:name":"Nyali",
    "gn:population":0,
    "gn:timezone":"Africa/Douala",
    "iso:country":"CM",
    "name:fra_x_preferred":[
        "Nyali"
    ],
    "name:und_x_variant":[
        "Ngali"
    ],
    "wof:name":"Nyali",
    "wof:placetype":"locality"
},
  "geometry": {"coordinates":[10.04658,5.78317],"type":"Point"}
}