{
  "type": "Feature",
  "properties": {
    "gn:admin1_code":"5.0",
    "gn:asciiname":"Lote",
    "gn:country_code":"CM",
    "gn:dem":1,
    "gn:feature_class":"P",
    "gn:feature_code":"PPL",
    "gn:name":"Lot\u00e9",
    "gn:population":0,
    "gn:timezone":"Africa/Douala",
    "iso:country":"CM",
    "name:ceb_x_preferred":[
        "Lote"
    ],
    "name:deu_x_preferred":[
        "Lote"
    ],
    "name:fra_x_preferred":[
        "Lote"
    ],
    "name:por_x_preferred":[
        "Lote"
    ],
    "name:swe_x_preferred":[
        "Lote"
    ],
    "wof:name":"Lote",
    "wof:placetype":"locality"
},
  "geometry": {"coordinates":[9.78556,3.42722],"type":"Point"}
}