{
  "type": "Feature",
  "properties": {
    "gn:admin1_code":"9.0",
    "gn:asciiname":"Iyowe",
    "gn:country_code":"CM",
    "gn:dem":820,
    "gn:feature_class":"P",
    "gn:feature_code":"PPL",
    "gn:name":"Iyowe",
    "gn:population":0,
    "gn:timezone":"Africa/Douala",
    "iso:country":"CM",
    "wof:name":"Iyowe",
    "wof:placetype":"locality"
},
  "geometry": {"coordinates":[9.1996,5.0434],"type":"Point"}
}