{
  "type": "Feature",
  "properties": {
    "gn:admin1_code":"8.0",
    "gn:asciiname":"La'atchuet",
    "gn:country_code":"CM",
    "gn:dem":1528,
    "gn:feature_class":"P",
    "gn:feature_code":"PPL",
    "gn:name":"La\u2019atchu\u00e8t",
    "gn:population":0,
    "gn:timezone":"Africa/Douala",
    "iso:country":"CM",
    "wof:name":"La'atchuet",
    "wof:placetype":"locality"
},
  "geometry": {"coordinates":[10.03561,5.5179],"type":"Point"}
}