{
  "type": "Feature",
  "properties": {
    "gn:admin1_code":"13.0",
    "gn:asciiname":"Tsora",
    "gn:country_code":"CM",
    "gn:dem":482,
    "gn:feature_class":"P",
    "gn:feature_code":"PPL",
    "gn:name":"Tsora",
    "gn:population":0,
    "gn:timezone":"Africa/Douala",
    "iso:country":"CM",
    "wof:name":"Tsora",
    "wof:placetype":"locality"
},
  "geometry": {"coordinates":[13.62818,9.96353],"type":"Point"}
}