{
  "type": "Feature",
  "properties": {
    "gn:admin1_code":"8.0",
    "gn:asciiname":"Tchang",
    "gn:country_code":"CM",
    "gn:dem":1506,
    "gn:feature_class":"P",
    "gn:feature_code":"PPL",
    "gn:name":"Tchang",
    "gn:population":0,
    "gn:timezone":"Africa/Douala",
    "iso:country":"CM",
    "wof:name":"Tchang",
    "wof:placetype":"locality"
},
  "geometry": {"coordinates":[10.31347,5.40272],"type":"Point"}
}