{
  "type": "Feature",
  "properties": {
    "gn:admin1_code":"8.0",
    "gn:asciiname":"Youte",
    "gn:country_code":"CM",
    "gn:dem":1350,
    "gn:feature_class":"P",
    "gn:feature_code":"PPL",
    "gn:name":"Yout\u00e9",
    "gn:population":0,
    "gn:timezone":"Africa/Douala",
    "iso:country":"CM",
    "name:fra_x_preferred":[
        "Yout\u00e9"
    ],
    "name:und_x_variant":[
        "Youteu"
    ],
    "wof:name":"Youte",
    "wof:placetype":"locality"
},
  "geometry": {"coordinates":[10.21521,5.18958],"type":"Point"}
}