{
  "type": "Feature",
  "properties": {
    "gn:admin1_code":"8.0",
    "gn:asciiname":"Penka Michel",
    "gn:country_code":"CM",
    "gn:dem":1438,
    "gn:feature_class":"P",
    "gn:feature_code":"PPL",
    "gn:name":"Penka Michel",
    "gn:population":0,
    "gn:timezone":"Africa/Douala",
    "iso:country":"CM",
    "name:fra_x_preferred":[
        "Penka Michel"
    ],
    "wof:name":"Penka Michel",
    "wof:placetype":"locality"
},
  "geometry": {"coordinates":[10.24296,5.46976],"type":"Point"}
}