{
  "type": "Feature",
  "properties": {
    "gn:admin1_code":"5.0",
    "gn:asciiname":"Ndokpenda",
    "gn:country_code":"CM",
    "gn:dem":153,
    "gn:feature_class":"P",
    "gn:feature_code":"PPL",
    "gn:name":"Ndokpenda",
    "gn:population":0,
    "gn:timezone":"Africa/Douala",
    "iso:country":"CM",
    "wof:name":"Ndokpenda",
    "wof:placetype":"locality"
},
  "geometry": {"coordinates":[9.9093,4.5444],"type":"Point"}
}