{
  "type": "Feature",
  "properties": {
    "gn:admin1_code":"5.0",
    "gn:asciiname":"Bonanyamalimbe",
    "gn:country_code":"CM",
    "gn:dem":14,
    "gn:feature_class":"P",
    "gn:feature_code":"PPL",
    "gn:name":"Bonanyamalimb\u00e9",
    "gn:population":0,
    "gn:timezone":"Africa/Douala",
    "iso:country":"CM",
    "name:und_x_variant":[
        "Bonayamalimb\u00e9",
        "Bonanyamalimb\u00e9"
    ],
    "wof:name":"Bonanyamalimbe",
    "wof:placetype":"locality"
},
  "geometry": {"coordinates":[9.9182,4.4181],"type":"Point"}
}