{
  "type": "Feature",
  "properties": {
    "gn:admin1_code":"12.0",
    "gn:asciiname":"Wayamayo",
    "gn:country_code":"CM",
    "gn:dem":337,
    "gn:feature_class":"P",
    "gn:feature_code":"PPL",
    "gn:name":"Wayamayo",
    "gn:population":0,
    "gn:timezone":"Africa/Douala",
    "iso:country":"CM",
    "wof:name":"Wayamayo",
    "wof:placetype":"locality"
},
  "geometry": {"coordinates":[14.69416,10.65407],"type":"Point"}
}