{
  "type": "Feature",
  "properties": {
    "gn:admin1_code":"12.0",
    "gn:asciiname":"Charif-Moussari",
    "gn:country_code":"CM",
    "gn:dem":399,
    "gn:feature_class":"P",
    "gn:feature_code":"PPL",
    "gn:name":"Charif-Moussari",
    "gn:population":0,
    "gn:timezone":"Africa/Douala",
    "iso:country":"CM",
    "name:und_x_variant":[
        "Chirmoussari",
        "Charif-Moussari"
    ],
    "wof:name":"Charif-Moussari",
    "wof:placetype":"locality"
},
  "geometry": {"coordinates":[13.92978,11.10527],"type":"Point"}
}