{
  "type": "Feature",
  "properties": {
    "gn:admin1_code":"11.0",
    "gn:asciiname":"Dibang",
    "gn:country_code":"CM",
    "gn:dem":353,
    "gn:feature_class":"P",
    "gn:feature_code":"PPL",
    "gn:name":"Dibang",
    "gn:population":0,
    "gn:timezone":"Africa/Douala",
    "iso:country":"CM",
    "wof:name":"Dibang",
    "wof:placetype":"locality"
},
  "geometry": {"coordinates":[10.71667,3.98333],"type":"Point"}
}