{
  "type": "Feature",
  "properties": {
    "gn:admin1_code":"13.0",
    "gn:asciiname":"Falatikou",
    "gn:country_code":"CM",
    "gn:dem":210,
    "gn:feature_class":"P",
    "gn:feature_code":"PPL",
    "gn:name":"Falatikou",
    "gn:population":0,
    "gn:timezone":"Africa/Douala",
    "iso:country":"CM",
    "wof:name":"Falatikou",
    "wof:placetype":"locality"
},
  "geometry": {"coordinates":[13.74194,9.3669],"type":"Point"}
}