{
  "type": "Feature",
  "properties": {
    "gn:admin1_code":"11.0",
    "gn:asciiname":"Mvono",
    "gn:country_code":"CM",
    "gn:dem":623,
    "gn:feature_class":"P",
    "gn:feature_code":"PPL",
    "gn:name":"Mvono",
    "gn:population":0,
    "gn:timezone":"Africa/Douala",
    "iso:country":"CM",
    "wof:name":"Mvono",
    "wof:placetype":"locality"
},
  "geometry": {"coordinates":[12.36667,4.51667],"type":"Point"}
}