{
  "type": "Feature",
  "properties": {
    "gn:admin1_code":"13.0",
    "gn:asciiname":"Ganda Mango",
    "gn:country_code":"CM",
    "gn:dem":342,
    "gn:feature_class":"P",
    "gn:feature_code":"PPL",
    "gn:name":"Ganda Mango",
    "gn:population":0,
    "gn:timezone":"Africa/Douala",
    "iso:country":"CM",
    "wof:name":"Ganda Mango",
    "wof:placetype":"locality"
},
  "geometry": {"coordinates":[13.82409,9.78499],"type":"Point"}
}