{
  "type": "Feature",
  "properties": {
    "gn:admin1_code":"8.0",
    "gn:asciiname":"Malanden",
    "gn:country_code":"CM",
    "gn:dem":937,
    "gn:feature_class":"P",
    "gn:feature_code":"PPL",
    "gn:name":"Mal\u00e2nden",
    "gn:population":0,
    "gn:timezone":"Africa/Douala",
    "iso:country":"CM",
    "name:fra_x_preferred":[
        "Mal\u00e2nden"
    ],
    "wof:name":"Malanden",
    "wof:placetype":"locality"
},
  "geometry": {"coordinates":[10.82673,5.42983],"type":"Point"}
}