{
  "type": "Feature",
  "properties": {
    "gn:admin1_code":"4.0",
    "gn:asciiname":"Masea",
    "gn:country_code":"CM",
    "gn:dem":559,
    "gn:feature_class":"P",
    "gn:feature_code":"PPL",
    "gn:name":"Mas\u00e9a",
    "gn:population":0,
    "gn:timezone":"Africa/Douala",
    "iso:country":"CM",
    "wof:name":"Masea",
    "wof:placetype":"locality"
},
  "geometry": {"coordinates":[14.86667,3.15],"type":"Point"}
}