{
  "type": "Feature",
  "properties": {
    "gn:admin1_code":"12.0",
    "gn:asciiname":"Kalangay",
    "gn:country_code":"CM",
    "gn:dem":652,
    "gn:feature_class":"P",
    "gn:feature_code":"PPL",
    "gn:name":"Kalangay",
    "gn:population":0,
    "gn:timezone":"Africa/Douala",
    "iso:country":"CM",
    "wof:name":"Kalangay",
    "wof:placetype":"locality"
},
  "geometry": {"coordinates":[13.88713,10.84981],"type":"Point"}
}