{
  "type": "Feature",
  "properties": {
    "gn:admin1_code":"4.0",
    "gn:asciiname":"Bakombele",
    "gn:country_code":"CM",
    "gn:dem":623,
    "gn:feature_class":"P",
    "gn:feature_code":"PPL",
    "gn:name":"Bakomb\u00e9l\u00e9",
    "gn:population":0,
    "gn:timezone":"Africa/Douala",
    "iso:country":"CM",
    "name:und_x_variant":[
        "Bakomb\u00e9b\u00e9",
        "Bakomb\u00e9l\u00e9"
    ],
    "wof:name":"Bakombele",
    "wof:placetype":"locality"
},
  "geometry": {"coordinates":[14.41667,4.31667],"type":"Point"}
}