{
  "type": "Feature",
  "properties": {
    "gn:admin1_code":"12.0",
    "gn:asciiname":"Kolara",
    "gn:country_code":"CM",
    "gn:dem":386,
    "gn:feature_class":"P",
    "gn:feature_code":"PPL",
    "gn:name":"Kolara",
    "gn:population":0,
    "gn:timezone":"Africa/Douala",
    "iso:country":"CM",
    "wof:name":"Kolara",
    "wof:placetype":"locality"
},
  "geometry": {"coordinates":[14.64702,10.26724],"type":"Point"}
}