{
  "type": "Feature",
  "properties": {
    "gn:admin1_code":"8.0",
    "gn:asciiname":"Tchuefeng",
    "gn:country_code":"CM",
    "gn:dem":1481,
    "gn:feature_class":"P",
    "gn:feature_code":"PPL",
    "gn:name":"Tchu\u00e9feng",
    "gn:population":0,
    "gn:timezone":"Africa/Douala",
    "iso:country":"CM",
    "wof:name":"Tchuefeng",
    "wof:placetype":"locality"
},
  "geometry": {"coordinates":[10.17721,5.48931],"type":"Point"}
}