{
  "type": "Feature",
  "properties": {
    "gn:admin1_code":"14.0",
    "gn:asciiname":"Ngoungoumou II",
    "gn:country_code":"CM",
    "gn:dem":673,
    "gn:feature_class":"P",
    "gn:feature_code":"PPL",
    "gn:name":"Ngoungoumou II",
    "gn:population":0,
    "gn:timezone":"Africa/Douala",
    "iso:country":"CM",
    "wof:name":"Ngoungoumou II",
    "wof:placetype":"locality"
},
  "geometry": {"coordinates":[11.76667,3.15],"type":"Point"}
}