{
  "type": "Feature",
  "properties": {
    "gn:admin1_code":"5.0",
    "gn:asciiname":"Ngombi",
    "gn:country_code":"CM",
    "gn:dem":21,
    "gn:feature_class":"P",
    "gn:feature_code":"PPL",
    "gn:name":"Ngombi",
    "gn:population":0,
    "gn:timezone":"Africa/Douala",
    "iso:country":"CM",
    "wof:name":"Ngombi",
    "wof:placetype":"locality"
},
  "geometry": {"coordinates":[9.99,3.61694],"type":"Point"}
}