{
  "type": "Feature",
  "properties": {
    "gn:admin1_code":"12.0",
    "gn:asciiname":"Kay-Kay II",
    "gn:country_code":"CM",
    "gn:dem":315,
    "gn:feature_class":"P",
    "gn:feature_code":"PPL",
    "gn:name":"Kay-Kay II",
    "gn:population":0,
    "gn:timezone":"Africa/Douala",
    "iso:country":"CM",
    "name:und_x_variant":[
        "Kaye Kaye I",
        "Ke\u00efke\u00ef",
        "Kay-Kay",
        "Kay-Kay II"
    ],
    "wof:name":"Kay-Kay II",
    "wof:placetype":"locality"
},
  "geometry": {"coordinates":[15.03506,10.66768],"type":"Point"}
}