{
  "type": "Feature",
  "properties": {
    "gn:admin1_code":"4.0",
    "gn:asciiname":"Nkolekoul",
    "gn:country_code":"CM",
    "gn:dem":675,
    "gn:feature_class":"P",
    "gn:feature_code":"PPL",
    "gn:name":"Nkol\u00e9koul",
    "gn:population":0,
    "gn:timezone":"Africa/Douala",
    "iso:country":"CM",
    "wof:name":"Nkolekoul",
    "wof:placetype":"locality"
},
  "geometry": {"coordinates":[12.88333,3.33333],"type":"Point"}
}