{
  "type": "Feature",
  "properties": {
    "gn:admin1_code":"13.0",
    "gn:asciiname":"Souda",
    "gn:country_code":"CM",
    "gn:dem":563,
    "gn:feature_class":"P",
    "gn:feature_code":"PPL",
    "gn:name":"Souda",
    "gn:population":0,
    "gn:timezone":"Africa/Douala",
    "iso:country":"CM",
    "name:ara_x_preferred":[
        "\u0633\u0648\u062f\u0627"
    ],
    "name:bre_x_preferred":[
        "Souda"
    ],
    "name:cat_x_preferred":[
        "Suda"
    ],
    "name:ceb_x_preferred":[
        "So\u00fada"
    ],
    "name:deu_x_preferred":[
        "Souda"
    ],
    "name:ell_x_preferred":[
        "\u03a3\u03bf\u03cd\u03b4\u03b1 \u03a7\u03b1\u03bd\u03af\u03c9\u03bd"
    ],
    "name:epo_x_preferred":[
        "Suda"
    ],
    "name:fin_x_preferred":[
        "So\u00fada"
    ],
    "name:fra_x_preferred":[
        "Souda"
    ],
    "name:ita_x_preferred":[
        "Suda"
    ],
    "name:lat_x_preferred":[
        "Suda"
    ],
    "name:pol_x_preferred":[
        "Suda"
    ],
    "name:por_x_preferred":[
        "Suda"
    ],
    "name:ron_x_preferred":[
        "Souda"
    ],
    "name:spa_x_preferred":[
        "Suda"
    ],
    "name:swe_x_preferred":[
        "Souda"
    ],
    "name:urd_x_preferred":[
        "\u0633\u0648\u062f\u0627"
    ],
    "wof:name":"Souda",
    "wof:placetype":"locality"
},
  "geometry": {"coordinates":[13.01667,7.78333],"type":"Point"}
}