{
  "type": "Feature",
  "properties": {
    "gn:admin1_code":"7.0",
    "gn:asciiname":"Mbanka",
    "gn:country_code":"CM",
    "gn:dem":1222,
    "gn:feature_class":"P",
    "gn:feature_code":"PPL",
    "gn:name":"Mbanka",
    "gn:population":0,
    "gn:timezone":"Africa/Douala",
    "iso:country":"CM",
    "wof:name":"Mbanka",
    "wof:placetype":"locality"
},
  "geometry": {"coordinates":[10.33525,5.85274],"type":"Point"}
}