{
  "type": "Feature",
  "properties": {
    "gn:admin1_code":"5.0",
    "gn:asciiname":"Ndombeng",
    "gn:country_code":"CM",
    "gn:dem":926,
    "gn:feature_class":"P",
    "gn:feature_code":"PPL",
    "gn:name":"Ndombeng",
    "gn:population":0,
    "gn:timezone":"Africa/Douala",
    "iso:country":"CM",
    "wof:name":"Ndombeng",
    "wof:placetype":"locality"
},
  "geometry": {"coordinates":[9.872,4.9328],"type":"Point"}
}