{
  "type": "Feature",
  "properties": {
    "gn:admin1_code":"8.0",
    "gn:asciiname":"Tomkheu",
    "gn:country_code":"CM",
    "gn:dem":1677,
    "gn:feature_class":"P",
    "gn:feature_code":"PPL",
    "gn:name":"Tomkheu",
    "gn:population":0,
    "gn:timezone":"Africa/Douala",
    "iso:country":"CM",
    "wof:name":"Tomkheu",
    "wof:placetype":"locality"
},
  "geometry": {"coordinates":[10.41412,5.28323],"type":"Point"}
}