{
  "type": "Feature",
  "properties": {
    "gn:admin1_code":"4.0",
    "gn:asciiname":"Momboue",
    "gn:country_code":"CM",
    "gn:dem":483,
    "gn:feature_class":"P",
    "gn:feature_code":"PPL",
    "gn:name":"Mombou\u00e9",
    "gn:population":0,
    "gn:timezone":"Africa/Douala",
    "iso:country":"CM",
    "wof:name":"Momboue",
    "wof:placetype":"locality"
},
  "geometry": {"coordinates":[15.35,2.66667],"type":"Point"}
}