{
  "type": "Feature",
  "properties": {
    "gn:admin1_code":"10.0",
    "gn:asciiname":"Makam",
    "gn:country_code":"CM",
    "gn:dem":989,
    "gn:feature_class":"P",
    "gn:feature_code":"PPL",
    "gn:name":"Makam",
    "gn:population":0,
    "gn:timezone":"Africa/Douala",
    "iso:country":"CM",
    "wof:name":"Makam",
    "wof:placetype":"locality"
},
  "geometry": {"coordinates":[12.10152,6.83085],"type":"Point"}
}