{
  "type": "Feature",
  "properties": {
    "gn:admin1_code":"12.0",
    "gn:asciiname":"Kobong",
    "gn:country_code":"CM",
    "gn:dem":502,
    "gn:feature_class":"P",
    "gn:feature_code":"PPL",
    "gn:name":"Kobong",
    "gn:population":0,
    "gn:timezone":"Africa/Douala",
    "iso:country":"CM",
    "wof:name":"Kobong",
    "wof:placetype":"locality"
},
  "geometry": {"coordinates":[13.88977,10.21805],"type":"Point"}
}