{
  "type": "Feature",
  "properties": {
    "gn:admin1_code":"4.0",
    "gn:asciiname":"Belebili",
    "gn:country_code":"CM",
    "gn:dem":629,
    "gn:feature_class":"P",
    "gn:feature_code":"PPL",
    "gn:name":"Belebili",
    "gn:population":0,
    "gn:timezone":"Africa/Douala",
    "iso:country":"CM",
    "wof:name":"Belebili",
    "wof:placetype":"locality"
},
  "geometry": {"coordinates":[14.78333,4.36667],"type":"Point"}
}