{
  "type": "Feature",
  "properties": {
    "gn:admin1_code":"4.0",
    "gn:asciiname":"Abumandjale",
    "gn:country_code":"CM",
    "gn:dem":710,
    "gn:feature_class":"P",
    "gn:feature_code":"PPL",
    "gn:name":"Abumandjal\u00e9",
    "gn:population":0,
    "gn:timezone":"Africa/Douala",
    "iso:country":"CM",
    "name:und_x_variant":[
        "Aboumadzal\u00e9",
        "Abumandjal\u00e9"
    ],
    "wof:name":"Abumandjale",
    "wof:placetype":"locality"
},
  "geometry": {"coordinates":[13.31667,4.66667],"type":"Point"}
}