{
  "type": "Feature",
  "properties": {
    "gn:admin1_code":"12.0",
    "gn:asciiname":"Dom Tchantches",
    "gn:country_code":"CM",
    "gn:dem":337,
    "gn:feature_class":"P",
    "gn:feature_code":"PPL",
    "gn:name":"Dom Tchantch\u00e8s",
    "gn:population":0,
    "gn:timezone":"Africa/Douala",
    "iso:country":"CM",
    "wof:name":"Dom Tchantches",
    "wof:placetype":"locality"
},
  "geometry": {"coordinates":[15.47045,9.98275],"type":"Point"}
}