{
  "type": "Feature",
  "properties": {
    "gn:admin1_code":"8.0",
    "gn:asciiname":"Laa",
    "gn:country_code":"CM",
    "gn:dem":1465,
    "gn:feature_class":"P",
    "gn:feature_code":"PPL",
    "gn:name":"Laa",
    "gn:population":0,
    "gn:timezone":"Africa/Douala",
    "iso:country":"CM",
    "name:ceb_x_preferred":[
        "Laa"
    ],
    "name:deu_x_preferred":[
        "Laa"
    ],
    "name:fra_x_preferred":[
        "Laa"
    ],
    "name:pol_x_preferred":[
        "Laa"
    ],
    "name:swe_x_preferred":[
        "Laa"
    ],
    "wof:name":"Laa",
    "wof:placetype":"locality"
},
  "geometry": {"coordinates":[10.07939,5.31891],"type":"Point"}
}