{
  "type": "Feature",
  "properties": {
    "gn:admin1_code":"12.0",
    "gn:asciiname":"Kaday",
    "gn:country_code":"CM",
    "gn:dem":334,
    "gn:feature_class":"P",
    "gn:feature_code":"PPL",
    "gn:name":"Kaday",
    "gn:population":0,
    "gn:timezone":"Africa/Douala",
    "iso:country":"CM",
    "name:und_x_variant":[
        "Kade\u00ef",
        "Kaday"
    ],
    "wof:name":"Kaday",
    "wof:placetype":"locality"
},
  "geometry": {"coordinates":[14.75319,10.56274],"type":"Point"}
}