{
  "type": "Feature",
  "properties": {
    "gn:admin1_code":"13.0",
    "gn:asciiname":"Doza",
    "gn:country_code":"CM",
    "gn:dem":563,
    "gn:feature_class":"P",
    "gn:feature_code":"PPL",
    "gn:name":"Doza",
    "gn:population":0,
    "gn:timezone":"Africa/Douala",
    "iso:country":"CM",
    "wof:name":"Doza",
    "wof:placetype":"locality"
},
  "geometry": {"coordinates":[13.88333,7.98333],"type":"Point"}
}