{
  "type": "Feature",
  "properties": {
    "gn:admin1_code":"7.0",
    "gn:asciiname":"Awing Bambuluwe",
    "gn:country_code":"CM",
    "gn:dem":1555,
    "gn:feature_class":"P",
    "gn:feature_code":"PPL",
    "gn:name":"Awing Bambuluwe",
    "gn:population":0,
    "gn:timezone":"Africa/Douala",
    "iso:country":"CM",
    "name:fra_x_preferred":[
        "Bambuluw\u00e9"
    ],
    "name:fra_x_variant":[
        "Awing Bambuluwe"
    ],
    "name:und_x_variant":[
        "Awing"
    ],
    "wof:name":"Awing Bambuluwe",
    "wof:placetype":"locality"
},
  "geometry": {"coordinates":[10.25933,5.84423],"type":"Point"}
}