{
  "type": "Feature",
  "properties": {
    "gn:admin1_code":"12.0",
    "gn:asciiname":"Mandama",
    "gn:country_code":"CM",
    "gn:dem":623,
    "gn:feature_class":"P",
    "gn:feature_code":"PPL",
    "gn:name":"Mandama",
    "gn:population":0,
    "gn:timezone":"Africa/Douala",
    "iso:country":"CM",
    "name:und_x_variant":[
        "Mandananao",
        "Mandama"
    ],
    "wof:name":"Mandama",
    "wof:placetype":"locality"
},
  "geometry": {"coordinates":[13.63087,10.23695],"type":"Point"}
}