{
  "type": "Feature",
  "properties": {
    "gn:admin1_code":"12.0",
    "gn:asciiname":"Manzala",
    "gn:country_code":"CM",
    "gn:dem":458,
    "gn:feature_class":"P",
    "gn:feature_code":"PPL",
    "gn:name":"Manzala",
    "gn:population":0,
    "gn:timezone":"Africa/Douala",
    "iso:country":"CM",
    "wof:name":"Manzala",
    "wof:placetype":"locality"
},
  "geometry": {"coordinates":[14.17166,10.82929],"type":"Point"}
}