{
  "type": "Feature",
  "properties": {
    "gn:admin1_code":"13.0",
    "gn:asciiname":"Labare",
    "gn:country_code":"CM",
    "gn:dem":206,
    "gn:feature_class":"P",
    "gn:feature_code":"PPL",
    "gn:name":"Labar\u00e9",
    "gn:population":0,
    "gn:timezone":"Africa/Douala",
    "iso:country":"CM",
    "wof:name":"Labare",
    "wof:placetype":"locality"
},
  "geometry": {"coordinates":[13.71839,9.09016],"type":"Point"}
}