{
  "type": "Feature",
  "properties": {
    "gn:admin1_code":"7.0",
    "gn:asciiname":"Ntenka",
    "gn:country_code":"CM",
    "gn:dem":1192,
    "gn:feature_class":"P",
    "gn:feature_code":"PPL",
    "gn:name":"Ntenka",
    "gn:population":0,
    "gn:timezone":"Africa/Douala",
    "iso:country":"CM",
    "wof:name":"Ntenka",
    "wof:placetype":"locality"
},
  "geometry": {"coordinates":[10.42583,5.98315],"type":"Point"}
}