{
  "type": "Feature",
  "properties": {
    "gn:admin1_code":"13.0",
    "gn:asciiname":"Bisse",
    "gn:country_code":"CM",
    "gn:dem":286,
    "gn:feature_class":"P",
    "gn:feature_code":"PPL",
    "gn:name":"Biss\u00e9",
    "gn:population":0,
    "gn:timezone":"Africa/Douala",
    "iso:country":"CM",
    "name:bar_x_preferred":[
        "Bisse"
    ],
    "name:deu_x_preferred":[
        "Bisse"
    ],
    "name:epo_x_preferred":[
        "Bisse"
    ],
    "name:fas_x_preferred":[
        "\u0628\u06cc\u0634\u0647"
    ],
    "name:fra_x_preferred":[
        "Bisse"
    ],
    "name:hrv_x_preferred":[
        "Bi\u0161ira"
    ],
    "name:hun_x_preferred":[
        "Bisse"
    ],
    "name:ita_x_preferred":[
        "Bisse"
    ],
    "name:msa_x_preferred":[
        "Bisse"
    ],
    "name:pol_x_preferred":[
        "Bisse"
    ],
    "name:ron_x_preferred":[
        "Bisse"
    ],
    "name:slk_x_preferred":[
        "Bisse"
    ],
    "name:slv_x_preferred":[
        "Bisse"
    ],
    "name:und_x_variant":[
        "Bis\u00e9",
        "Biss\u00e9"
    ],
    "name:vie_x_preferred":[
        "Bisse"
    ],
    "name:zho_x_preferred":[
        "\u6bd4\u4ec0\u8c22"
    ],
    "wof:name":"Bisse",
    "wof:placetype":"locality"
},
  "geometry": {"coordinates":[14.2561,9.142],"type":"Point"}
}