{
  "type": "Feature",
  "properties": {
    "gn:admin1_code":"13.0",
    "gn:asciiname":"Bisse",
    "gn:country_code":"CM",
    "gn:dem":286,
    "gn:feature_class":"P",
    "gn:feature_code":"PPL",
    "gn:name":"Biss\u00e9",
    "gn:population":0,
    "gn:timezone":"Africa/Douala",
    "iso:country":"CM",
    "name:und_x_variant":[
        "Bis\u00e9",
        "Biss\u00e9"
    ],
    "wof:name":"Bisse",
    "wof:placetype":"locality"
},
  "geometry": {"coordinates":[14.2561,9.142],"type":"Point"}
}