{
  "type": "Feature",
  "properties": {
    "gn:admin1_code":"12.0",
    "gn:asciiname":"Gobo",
    "gn:country_code":"CM",
    "gn:dem":333,
    "gn:feature_class":"P",
    "gn:feature_code":"PPL",
    "gn:name":"Gobo",
    "gn:population":0,
    "gn:timezone":"Africa/Douala",
    "iso:country":"CM",
    "name:ceb_x_preferred":[
        "Gobo"
    ],
    "name:fra_x_preferred":[
        "Gobo"
    ],
    "name:ita_x_preferred":[
        "Gobo"
    ],
    "name:nld_x_preferred":[
        "Gobo"
    ],
    "name:por_x_preferred":[
        "Gobo"
    ],
    "name:srp_x_preferred":[
        "Gobo"
    ],
    "name:swe_x_preferred":[
        "Gobo"
    ],
    "name:ukr_x_preferred":[
        "\u0413\u043e\u0431\u043e"
    ],
    "wof:name":"Gobo",
    "wof:placetype":"locality"
},
  "geometry": {"coordinates":[15.43512,10.00986],"type":"Point"}
}