{
  "type": "Feature",
  "properties": {
    "gn:admin1_code":"12.0",
    "gn:asciiname":"Wakaltou",
    "gn:country_code":"CM",
    "gn:dem":296,
    "gn:feature_class":"P",
    "gn:feature_code":"PPL",
    "gn:name":"Wakaltou",
    "gn:population":0,
    "gn:timezone":"Africa/Douala",
    "iso:country":"CM",
    "wof:name":"Wakaltou",
    "wof:placetype":"locality"
},
  "geometry": {"coordinates":[14.8611,12.23824],"type":"Point"}
}