{
  "type": "Feature",
  "properties": {
    "gn:admin1_code":"4.0",
    "gn:asciiname":"Mefade",
    "gn:country_code":"CM",
    "gn:dem":712,
    "gn:feature_class":"P",
    "gn:feature_code":"PPL",
    "gn:name":"M\u00e9fad\u00e9",
    "gn:population":0,
    "gn:timezone":"Africa/Douala",
    "iso:country":"CM",
    "wof:name":"Mefade",
    "wof:placetype":"locality"
},
  "geometry": {"coordinates":[12.61667,3.76667],"type":"Point"}
}