{
  "type": "Feature",
  "properties": {
    "gn:admin1_code":"11.0",
    "gn:asciiname":"Mvamba",
    "gn:country_code":"CM",
    "gn:dem":651,
    "gn:feature_class":"P",
    "gn:feature_code":"PPL",
    "gn:name":"Mvamba",
    "gn:population":0,
    "gn:timezone":"Africa/Douala",
    "iso:country":"CM",
    "wof:name":"Mvamba",
    "wof:placetype":"locality"
},
  "geometry": {"coordinates":[12.31667,4.45],"type":"Point"}
}