{
  "type": "Feature",
  "properties": {
    "gn:admin1_code":"10.0",
    "gn:asciiname":"Bori",
    "gn:country_code":"CM",
    "gn:dem":930,
    "gn:feature_class":"P",
    "gn:feature_code":"PPL",
    "gn:name":"Bori",
    "gn:population":0,
    "gn:timezone":"Africa/Douala",
    "iso:country":"CM",
    "name:ceb_x_preferred":[
        "Bori"
    ],
    "name:deu_x_preferred":[
        "Bori"
    ],
    "name:fra_x_preferred":[
        "Bori"
    ],
    "name:hun_x_preferred":[
        "Bori"
    ],
    "name:ita_x_preferred":[
        "Bori"
    ],
    "name:kor_x_preferred":[
        "\ubcf4\ub9ac"
    ],
    "name:por_x_preferred":[
        "Bori"
    ],
    "name:swe_x_preferred":[
        "Bori"
    ],
    "name:vie_x_preferred":[
        "Bori"
    ],
    "wof:name":"Bori",
    "wof:placetype":"locality"
},
  "geometry": {"coordinates":[13.36667,6.46667],"type":"Point"}
}