{
  "type": "Feature",
  "properties": {
    "gn:admin1_code":"12.0",
    "gn:asciiname":"Vaza",
    "gn:country_code":"CM",
    "gn:dem":417,
    "gn:feature_class":"P",
    "gn:feature_code":"PPL",
    "gn:name":"Vaza",
    "gn:population":0,
    "gn:timezone":"Africa/Douala",
    "iso:country":"CM",
    "name:und_x_variant":[
        "Waza",
        "Vaza"
    ],
    "wof:name":"Vaza",
    "wof:placetype":"locality"
},
  "geometry": {"coordinates":[14.3301,10.35498],"type":"Point"}
}