{
  "type": "Feature",
  "properties": {
    "gn:admin1_code":"12.0",
    "gn:asciiname":"Koudoukoura",
    "gn:country_code":"CM",
    "gn:dem":857,
    "gn:feature_class":"P",
    "gn:feature_code":"PPL",
    "gn:name":"Koudoukoura",
    "gn:population":0,
    "gn:timezone":"Africa/Douala",
    "iso:country":"CM",
    "wof:name":"Koudoukoura",
    "wof:placetype":"locality"
},
  "geometry": {"coordinates":[13.44814,10.07769],"type":"Point"}
}