{
  "type": "Feature",
  "properties": {
    "gn:admin1_code":"9.0",
    "gn:asciiname":"Mosongo",
    "gn:country_code":"CM",
    "gn:dem":636,
    "gn:feature_class":"P",
    "gn:feature_code":"PPL",
    "gn:name":"Mosongo",
    "gn:population":0,
    "gn:timezone":"Africa/Douala",
    "iso:country":"CM",
    "wof:name":"Mosongo",
    "wof:placetype":"locality"
},
  "geometry": {"coordinates":[9.0398,5.0456],"type":"Point"}
}