{
  "type": "Feature",
  "properties": {
    "gn:admin1_code":"12.0",
    "gn:asciiname":"Mozogoy",
    "gn:country_code":"CM",
    "gn:dem":504,
    "gn:feature_class":"P",
    "gn:feature_code":"PPL",
    "gn:name":"Mozogoy",
    "gn:population":0,
    "gn:timezone":"Africa/Douala",
    "iso:country":"CM",
    "wof:name":"Mozogoy",
    "wof:placetype":"locality"
},
  "geometry": {"coordinates":[14.21243,10.64764],"type":"Point"}
}