{
  "type": "Feature",
  "properties": {
    "gn:admin1_code":"8.0",
    "gn:asciiname":"Ngang",
    "gn:country_code":"CM",
    "gn:dem":1611,
    "gn:feature_class":"P",
    "gn:feature_code":"PPL",
    "gn:name":"Ngang",
    "gn:population":0,
    "gn:timezone":"Africa/Douala",
    "iso:country":"CM",
    "name:fra_x_preferred":[
        "Bangang"
    ],
    "wof:name":"Ngang",
    "wof:placetype":"locality"
},
  "geometry": {"coordinates":[10.17435,5.56747],"type":"Point"}
}