{
  "type": "Feature",
  "properties": {
    "gn:admin1_code":"10.0",
    "gn:asciiname":"Mandourou",
    "gn:country_code":"CM",
    "gn:dem":993,
    "gn:feature_class":"P",
    "gn:feature_code":"PPL",
    "gn:name":"Mandourou",
    "gn:population":0,
    "gn:timezone":"Africa/Douala",
    "iso:country":"CM",
    "wof:name":"Mandourou",
    "wof:placetype":"locality"
},
  "geometry": {"coordinates":[13.25,7.48333],"type":"Point"}
}