{
  "type": "Feature",
  "properties": {
    "gn:admin1_code":"12.0",
    "gn:asciiname":"Kubura Lufa",
    "gn:country_code":"CM",
    "gn:dem":474,
    "gn:feature_class":"P",
    "gn:feature_code":"PPL",
    "gn:name":"Kubura Lufa",
    "gn:population":0,
    "gn:timezone":"Africa/Douala",
    "iso:country":"CM",
    "wof:name":"Kubura Lufa",
    "wof:placetype":"locality"
},
  "geometry": {"coordinates":[13.98333,10.93333],"type":"Point"}
}