{
  "type": "Feature",
  "properties": {
    "gn:admin1_code":"13.0",
    "gn:asciiname":"Bangay",
    "gn:country_code":"CM",
    "gn:dem":467,
    "gn:feature_class":"P",
    "gn:feature_code":"PPL",
    "gn:name":"Bangay",
    "gn:population":0,
    "gn:timezone":"Africa/Douala",
    "iso:country":"CM",
    "wof:name":"Bangay",
    "wof:placetype":"locality"
},
  "geometry": {"coordinates":[13.76008,10.09462],"type":"Point"}
}