{
  "type": "Feature",
  "properties": {
    "gn:admin1_code":"11.0",
    "gn:asciiname":"Mengor",
    "gn:country_code":"CM",
    "gn:dem":605,
    "gn:feature_class":"P",
    "gn:feature_code":"PPL",
    "gn:name":"Mengor",
    "gn:population":0,
    "gn:timezone":"Africa/Douala",
    "iso:country":"CM",
    "wof:name":"Mengor",
    "wof:placetype":"locality"
},
  "geometry": {"coordinates":[12.01667,5.05],"type":"Point"}
}