{
  "type": "Feature",
  "properties": {
    "gn:admin1_code":"14.0",
    "gn:asciiname":"Angale",
    "gn:country_code":"CM",
    "gn:dem":77,
    "gn:feature_class":"P",
    "gn:feature_code":"PPL",
    "gn:name":"Angal\u00e9",
    "gn:population":0,
    "gn:timezone":"Africa/Douala",
    "iso:country":"CM",
    "wof:name":"Angale",
    "wof:placetype":"locality"
},
  "geometry": {"coordinates":[10.05,2.55],"type":"Point"}
}