{
  "type": "Feature",
  "properties": {
    "gn:admin1_code":"8.0",
    "gn:asciiname":"Makam",
    "gn:country_code":"CM",
    "gn:dem":1128,
    "gn:feature_class":"P",
    "gn:feature_code":"PPL",
    "gn:name":"Makam",
    "gn:population":0,
    "gn:timezone":"Africa/Douala",
    "iso:country":"CM",
    "name:fra_x_preferred":[
        "Makam"
    ],
    "wof:name":"Makam",
    "wof:placetype":"locality"
},
  "geometry": {"coordinates":[10.95956,5.89501],"type":"Point"}
}