{
  "type": "Feature",
  "properties": {
    "gn:admin1_code":"12.0",
    "gn:asciiname":"Wodbao",
    "gn:country_code":"CM",
    "gn:dem":723,
    "gn:feature_class":"P",
    "gn:feature_code":"PPL",
    "gn:name":"Wodbao",
    "gn:population":0,
    "gn:timezone":"Africa/Douala",
    "iso:country":"CM",
    "wof:name":"Wodbao",
    "wof:placetype":"locality"
},
  "geometry": {"coordinates":[13.9125,10.73954],"type":"Point"}
}