{
  "type": "Feature",
  "properties": {
    "gn:admin1_code":"5.0",
    "gn:asciiname":"Konbe",
    "gn:country_code":"CM",
    "gn:dem":60,
    "gn:feature_class":"P",
    "gn:feature_code":"PPL",
    "gn:name":"Konb\u00e9",
    "gn:population":0,
    "gn:timezone":"Africa/Douala",
    "iso:country":"CM",
    "wof:name":"Konbe",
    "wof:placetype":"locality"
},
  "geometry": {"coordinates":[9.92111,3.575],"type":"Point"}
}