{
  "type": "Feature",
  "properties": {
    "gn:admin1_code":"11.0",
    "gn:asciiname":"Indinding",
    "gn:country_code":"CM",
    "gn:dem":610,
    "gn:feature_class":"P",
    "gn:feature_code":"PPL",
    "gn:name":"Indinding",
    "gn:population":0,
    "gn:timezone":"Africa/Douala",
    "iso:country":"CM",
    "name:und_x_variant":[
        "Endingding",
        "Indinding"
    ],
    "wof:name":"Indinding",
    "wof:placetype":"locality"
},
  "geometry": {"coordinates":[11.48333,4.11667],"type":"Point"}
}