{
  "type": "Feature",
  "properties": {
    "gn:admin1_code":"7.0",
    "gn:asciiname":"Menda Nkwe",
    "gn:country_code":"CM",
    "gn:dem":1676,
    "gn:feature_class":"P",
    "gn:feature_code":"PPL",
    "gn:name":"Menda Nkwe",
    "gn:population":0,
    "gn:timezone":"Africa/Douala",
    "iso:country":"CM",
    "wof:name":"Menda Nkwe",
    "wof:placetype":"locality"
},
  "geometry": {"coordinates":[10.19795,5.93581],"type":"Point"}
}