{
  "type": "Feature",
  "properties": {
    "gn:admin1_code":"13.0",
    "gn:asciiname":"Babandji",
    "gn:country_code":"CM",
    "gn:dem":313,
    "gn:feature_class":"P",
    "gn:feature_code":"PPL",
    "gn:name":"Babandji",
    "gn:population":0,
    "gn:timezone":"Africa/Douala",
    "iso:country":"CM",
    "wof:name":"Babandji",
    "wof:placetype":"locality"
},
  "geometry": {"coordinates":[13.45044,9.45535],"type":"Point"}
}