{
  "type": "Feature",
  "properties": {
    "gn:admin1_code":"12.0",
    "gn:asciiname":"Madek",
    "gn:country_code":"CM",
    "gn:dem":289,
    "gn:feature_class":"P",
    "gn:feature_code":"PPL",
    "gn:name":"Mad\u00e8k",
    "gn:population":0,
    "gn:timezone":"Africa/Douala",
    "iso:country":"CM",
    "name:und_x_variant":[
        "B\u00e9derk",
        "Madaik",
        "Mad\u00e9ik",
        "Mad\u00e8k"
    ],
    "wof:name":"Madek",
    "wof:placetype":"locality"
},
  "geometry": {"coordinates":[14.56084,12.7015],"type":"Point"}
}