{
  "type": "Feature",
  "properties": {
    "gn:admin1_code":"8.0",
    "gn:asciiname":"Nkoutenke",
    "gn:country_code":"CM",
    "gn:dem":1184,
    "gn:feature_class":"P",
    "gn:feature_code":"PPL",
    "gn:name":"Nkoutenk\u00e9",
    "gn:population":0,
    "gn:timezone":"Africa/Douala",
    "iso:country":"CM",
    "wof:name":"Nkoutenke",
    "wof:placetype":"locality"
},
  "geometry": {"coordinates":[10.81709,5.65754],"type":"Point"}
}