{
  "type": "Feature",
  "properties": {
    "gn:admin1_code":"13.0",
    "gn:asciiname":"Mouroum",
    "gn:country_code":"CM",
    "gn:dem":440,
    "gn:feature_class":"P",
    "gn:feature_code":"PPL",
    "gn:name":"Mouroum",
    "gn:population":0,
    "gn:timezone":"Africa/Douala",
    "iso:country":"CM",
    "wof:name":"Mouroum",
    "wof:placetype":"locality"
},
  "geometry": {"coordinates":[13.64744,9.87928],"type":"Point"}
}