{
  "type": "Feature",
  "properties": {
    "gn:admin1_code":"12.0",
    "gn:asciiname":"Sabongari",
    "gn:country_code":"CM",
    "gn:dem":581,
    "gn:feature_class":"P",
    "gn:feature_code":"PPL",
    "gn:name":"Sabongari",
    "gn:population":0,
    "gn:timezone":"Africa/Douala",
    "iso:country":"CM",
    "wof:name":"Sabongari",
    "wof:placetype":"locality"
},
  "geometry": {"coordinates":[13.92352,10.5553],"type":"Point"}
}