{
  "type": "Feature",
  "properties": {
    "gn:admin1_code":"13.0",
    "gn:asciiname":"Bideng",
    "gn:country_code":"CM",
    "gn:dem":213,
    "gn:feature_class":"P",
    "gn:feature_code":"PPL",
    "gn:name":"Bideng",
    "gn:population":0,
    "gn:timezone":"Africa/Douala",
    "iso:country":"CM",
    "name:und_x_variant":[
        "Biding"
    ],
    "wof:name":"Bideng",
    "wof:placetype":"locality"
},
  "geometry": {"coordinates":[13.99994,8.78182],"type":"Point"}
}