{
  "type": "Feature",
  "properties": {
    "gn:admin1_code":"12.0",
    "gn:asciiname":"Ndoufgay",
    "gn:country_code":"CM",
    "gn:dem":742,
    "gn:feature_class":"P",
    "gn:feature_code":"PPL",
    "gn:name":"Ndoufgay",
    "gn:population":0,
    "gn:timezone":"Africa/Douala",
    "iso:country":"CM",
    "wof:name":"Ndoufgay",
    "wof:placetype":"locality"
},
  "geometry": {"coordinates":[13.83926,10.8387],"type":"Point"}
}