{
  "type": "Feature",
  "properties": {
    "gn:country":"CM",
    "gn:fcode":"PPL",
    "gn:pop":7560,
    "iso:country":"CM",
    "name:eng_x_preferred":[
        "Bangou"
    ],
    "name:fra_x_preferred":[
        "Ngou"
    ],
    "name:fra_x_variant":[
        "Bangou",
        "Banjou"
    ],
    "name:msa_x_preferred":[
        "Bangou"
    ],
    "name:nan_x_preferred":[
        "Bangou"
    ],
    "name:nld_x_preferred":[
        "Bangou"
    ],
    "name:unk_x_variant":[
        "Banjou"
    ],
    "qs:name":"Ngou",
    "qs:photos_9r":0,
    "qs:photos_sr":0,
    "qs:pop_sr":"5",
    "wof:name":"Ngou",
    "wof:placetype":"locality",
    "wof:population":7560
},
  "geometry": {"coordinates":[10.38441,5.1959],"type":"Point"}
}