{
  "type": "Feature",
  "properties": {
    "gn:admin1_code":"12.0",
    "gn:asciiname":"Zidim",
    "gn:country_code":"CM",
    "gn:dem":920,
    "gn:feature_class":"P",
    "gn:feature_code":"PPL",
    "gn:name":"Zidim",
    "gn:population":0,
    "gn:timezone":"Africa/Douala",
    "iso:country":"CM",
    "name:und_x_variant":[
        "Sidim",
        "Zidim"
    ],
    "wof:name":"Zidim",
    "wof:placetype":"locality"
},
  "geometry": {"coordinates":[13.48361,10.4702],"type":"Point"}
}