{
  "type": "Feature",
  "properties": {
    "gn:admin1_code":"4.0",
    "gn:asciiname":"Bakoissie",
    "gn:country_code":"CM",
    "gn:dem":913,
    "gn:feature_class":"P",
    "gn:feature_code":"PPL",
    "gn:name":"Bakoissi\u00e9",
    "gn:population":0,
    "gn:timezone":"Africa/Douala",
    "iso:country":"CM",
    "name:und_x_variant":[
        "Bakossi",
        "Bakoissi\u00e9"
    ],
    "wof:name":"Bakoissie",
    "wof:placetype":"locality"
},
  "geometry": {"coordinates":[14.43333,5.98333],"type":"Point"}
}