{
  "type": "Feature",
  "properties": {
    "gn:admin1_code":"9.0",
    "gn:asciiname":"Isangele",
    "gn:country_code":"CM",
    "gn:dem":31,
    "gn:feature_class":"P",
    "gn:feature_code":"PPL",
    "gn:name":"Isangele",
    "gn:population":0,
    "gn:timezone":"Africa/Douala",
    "iso:country":"CM",
    "wof:name":"Isangele",
    "wof:placetype":"locality"
},
  "geometry": {"coordinates":[8.68,4.7804],"type":"Point"}
}