{
  "type": "Feature",
  "properties": {
    "gn:admin1_code":"12.0",
    "gn:asciiname":"Cheloba",
    "gn:country_code":"CM",
    "gn:dem":296,
    "gn:feature_class":"P",
    "gn:feature_code":"PPL",
    "gn:name":"Ch\u00e9loba",
    "gn:population":0,
    "gn:timezone":"Africa/Douala",
    "iso:country":"CM",
    "name:und_x_variant":[
        "Cheloba I",
        "Ch\u00e9loba"
    ],
    "wof:name":"Cheloba",
    "wof:placetype":"locality"
},
  "geometry": {"coordinates":[14.85389,12.24828],"type":"Point"}
}