{
  "type": "Feature",
  "properties": {
    "gn:admin1_code":"13.0",
    "gn:asciiname":"Djakva",
    "gn:country_code":"CM",
    "gn:dem":1299,
    "gn:feature_class":"P",
    "gn:feature_code":"PPL",
    "gn:name":"Djakva",
    "gn:population":0,
    "gn:timezone":"Africa/Douala",
    "iso:country":"CM",
    "name:und_x_variant":[
        "Diara",
        "Djakva"
    ],
    "wof:name":"Djakva",
    "wof:placetype":"locality"
},
  "geometry": {"coordinates":[14.51667,7.21667],"type":"Point"}
}