{
  "type": "Feature",
  "properties": {
    "gn:admin1_code":"8.0",
    "gn:asciiname":"Pouo'che",
    "gn:country_code":"CM",
    "gn:dem":929,
    "gn:feature_class":"P",
    "gn:feature_code":"PPL",
    "gn:name":"Pouo\u2019che",
    "gn:population":0,
    "gn:timezone":"Africa/Douala",
    "iso:country":"CM",
    "name:und_x_variant":[
        "Pouo\u2019che",
        "Poueuch"
    ],
    "wof:name":"Pouo'che",
    "wof:placetype":"locality"
},
  "geometry": {"coordinates":[10.89323,5.45943],"type":"Point"}
}