{
  "type": "Feature",
  "properties": {
    "gn:admin1_code":"12.0",
    "gn:asciiname":"Maday",
    "gn:country_code":"CM",
    "gn:dem":661,
    "gn:feature_class":"P",
    "gn:feature_code":"PPL",
    "gn:name":"Maday",
    "gn:population":0,
    "gn:timezone":"Africa/Douala",
    "iso:country":"CM",
    "wof:name":"Maday",
    "wof:placetype":"locality"
},
  "geometry": {"coordinates":[13.61372,10.20018],"type":"Point"}
}