{
  "type": "Feature",
  "properties": {
    "gn:admin1_code":"7.0",
    "gn:asciiname":"Badjine",
    "gn:country_code":"CM",
    "gn:dem":422,
    "gn:feature_class":"P",
    "gn:feature_code":"PPL",
    "gn:name":"Badjine",
    "gn:population":0,
    "gn:timezone":"Africa/Douala",
    "iso:country":"CM",
    "wof:name":"Badjine",
    "wof:placetype":"locality"
},
  "geometry": {"coordinates":[9.7304,6.5918],"type":"Point"}
}