{
  "type": "Feature",
  "properties": {
    "gn:admin1_code":"4.0",
    "gn:asciiname":"Lala",
    "gn:country_code":"CM",
    "gn:dem":646,
    "gn:feature_class":"P",
    "gn:feature_code":"PPL",
    "gn:name":"Lala",
    "gn:population":0,
    "gn:timezone":"Africa/Douala",
    "iso:country":"CM",
    "wof:name":"Lala",
    "wof:placetype":"locality"
},
  "geometry": {"coordinates":[14.26667,4.81667],"type":"Point"}
}