{
  "type": "Feature",
  "properties": {
    "gn:admin1_code":"4.0",
    "gn:asciiname":"Lala",
    "gn:country_code":"CM",
    "gn:dem":646,
    "gn:feature_class":"P",
    "gn:feature_code":"PPL",
    "gn:name":"Lala",
    "gn:population":0,
    "gn:timezone":"Africa/Douala",
    "iso:country":"CM",
    "name:bak_x_preferred":[
        "\u041b\u04d9\u043b\u04d9"
    ],
    "name:ceb_x_preferred":[
        "Lala"
    ],
    "name:deu_x_preferred":[
        "Lala"
    ],
    "name:fra_x_preferred":[
        "Lala"
    ],
    "name:ind_x_preferred":[
        "Lala"
    ],
    "name:ita_x_preferred":[
        "Lala"
    ],
    "name:nld_x_preferred":[
        "Lala"
    ],
    "name:rus_x_preferred":[
        "\u041b\u044f\u043b\u044f"
    ],
    "name:spa_x_preferred":[
        "Lala"
    ],
    "name:swe_x_preferred":[
        "Lala"
    ],
    "wof:name":"Lala",
    "wof:placetype":"locality"
},
  "geometry": {"coordinates":[14.26667,4.81667],"type":"Point"}
}