{
  "type": "Feature",
  "properties": {
    "gn:admin1_code":"12.0",
    "gn:asciiname":"Oualamay",
    "gn:country_code":"CM",
    "gn:dem":672,
    "gn:feature_class":"P",
    "gn:feature_code":"PPL",
    "gn:name":"Oualamay",
    "gn:population":0,
    "gn:timezone":"Africa/Douala",
    "iso:country":"CM",
    "wof:name":"Oualamay",
    "wof:placetype":"locality"
},
  "geometry": {"coordinates":[13.9833,10.7914],"type":"Point"}
}