{
  "type": "Feature",
  "properties": {
    "gn:admin1_code":"4.0",
    "gn:asciiname":"Ndandenge",
    "gn:country_code":"CM",
    "gn:dem":781,
    "gn:feature_class":"P",
    "gn:feature_code":"PPL",
    "gn:name":"Ndandeng\u00e9",
    "gn:population":0,
    "gn:timezone":"Africa/Douala",
    "iso:country":"CM",
    "wof:name":"Ndandenge",
    "wof:placetype":"locality"
},
  "geometry": {"coordinates":[13.93333,4.95],"type":"Point"}
}