{
  "type": "Feature",
  "properties": {
    "gn:admin1_code":"8.0",
    "gn:asciiname":"Toula' Dezong",
    "gn:country_code":"CM",
    "gn:dem":1520,
    "gn:feature_class":"P",
    "gn:feature_code":"PPL",
    "gn:name":"Toula\u2019 Dezong",
    "gn:population":0,
    "gn:timezone":"Africa/Douala",
    "iso:country":"CM",
    "wof:name":"Toula' Dezong",
    "wof:placetype":"locality"
},
  "geometry": {"coordinates":[10.09587,5.46368],"type":"Point"}
}