{
  "type": "Feature",
  "properties": {
    "gn:admin1_code":"7.0",
    "gn:asciiname":"Baba I",
    "gn:country_code":"CM",
    "gn:dem":1165,
    "gn:feature_class":"P",
    "gn:feature_code":"PPL",
    "gn:name":"Baba I",
    "gn:population":0,
    "gn:timezone":"Africa/Douala",
    "iso:country":"CM",
    "name:fra_x_preferred":[
        "Baba"
    ],
    "name:und_x_variant":[
        "Baba I"
    ],
    "wof:name":"Baba I",
    "wof:placetype":"locality"
},
  "geometry": {"coordinates":[10.46667,6.03333],"type":"Point"}
}