{
  "type": "Feature",
  "properties": {
    "gn:admin1_code":"11.0",
    "gn:asciiname":"Biwawe",
    "gn:country_code":"CM",
    "gn:dem":813,
    "gn:feature_class":"P",
    "gn:feature_code":"PPL",
    "gn:name":"Biwaw\u00e9",
    "gn:population":0,
    "gn:timezone":"Africa/Douala",
    "iso:country":"CM",
    "wof:name":"Biwawe",
    "wof:placetype":"locality"
},
  "geometry": {"coordinates":[11.58333,5.85],"type":"Point"}
}