{
  "type": "Feature",
  "properties": {
    "gn:admin1_code":"12.0",
    "gn:asciiname":"Ouro Daye",
    "gn:country_code":"CM",
    "gn:dem":340,
    "gn:feature_class":"P",
    "gn:feature_code":"PPL",
    "gn:name":"Ouro Day\u00e9",
    "gn:population":0,
    "gn:timezone":"Africa/Douala",
    "iso:country":"CM",
    "wof:name":"Ouro Daye",
    "wof:placetype":"locality"
},
  "geometry": {"coordinates":[14.62845,10.61722],"type":"Point"}
}