{
  "type": "Feature",
  "properties": {
    "gn:admin1_code":"5.0",
    "gn:asciiname":"Bomono Ba Mbengue",
    "gn:country_code":"CM",
    "gn:dem":40,
    "gn:feature_class":"P",
    "gn:feature_code":"PPL",
    "gn:name":"Bomono Ba Mbengu\u00e9",
    "gn:population":0,
    "gn:timezone":"Africa/Douala",
    "iso:country":"CM",
    "wof:name":"Bomono Ba Mbengue",
    "wof:placetype":"locality"
},
  "geometry": {"coordinates":[9.5913,4.1406],"type":"Point"}
}