{
  "type": "Feature",
  "properties": {
    "gn:admin1_code":"7.0",
    "gn:asciiname":"Abunde",
    "gn:country_code":"CM",
    "gn:dem":462,
    "gn:feature_class":"P",
    "gn:feature_code":"PPL",
    "gn:name":"Abunde",
    "gn:population":0,
    "gn:timezone":"Africa/Douala",
    "iso:country":"CM",
    "wof:name":"Abunde",
    "wof:placetype":"locality"
},
  "geometry": {"coordinates":[9.856,6.3501],"type":"Point"}
}