{
  "type": "Feature",
  "properties": {
    "gn:admin1_code":"5.0",
    "gn:asciiname":"Lebe",
    "gn:country_code":"CM",
    "gn:dem":8,
    "gn:feature_class":"P",
    "gn:feature_code":"PPL",
    "gn:name":"L\u00e9b\u00e9",
    "gn:population":0,
    "gn:timezone":"Africa/Douala",
    "iso:country":"CM",
    "wof:name":"Lebe",
    "wof:placetype":"locality"
},
  "geometry": {"coordinates":[9.6508,4.0969],"type":"Point"}
}