{
  "type": "Feature",
  "properties": {
    "gn:admin1_code":"11.0",
    "gn:asciiname":"Nkolakono I",
    "gn:country_code":"CM",
    "gn:dem":667,
    "gn:feature_class":"P",
    "gn:feature_code":"PPL",
    "gn:name":"Nkolakono I",
    "gn:population":0,
    "gn:timezone":"Africa/Douala",
    "iso:country":"CM",
    "wof:name":"Nkolakono I",
    "wof:placetype":"locality"
},
  "geometry": {"coordinates":[11.33333,3.55],"type":"Point"}
}