{
  "type": "Feature",
  "properties": {
    "gn:admin1_code":"12.0",
    "gn:asciiname":"Boulatani",
    "gn:country_code":"CM",
    "gn:dem":365,
    "gn:feature_class":"P",
    "gn:feature_code":"PPL",
    "gn:name":"Boulatani",
    "gn:population":0,
    "gn:timezone":"Africa/Douala",
    "iso:country":"CM",
    "wof:name":"Boulatani",
    "wof:placetype":"locality"
},
  "geometry": {"coordinates":[13.95012,11.19992],"type":"Point"}
}