{
  "type": "Feature",
  "properties": {
    "gn:admin1_code":"13.0",
    "gn:asciiname":"Kobosi",
    "gn:country_code":"CM",
    "gn:dem":562,
    "gn:feature_class":"P",
    "gn:feature_code":"PPL",
    "gn:name":"Kobosi",
    "gn:population":0,
    "gn:timezone":"Africa/Douala",
    "iso:country":"CM",
    "name:und_x_variant":[
        "Bind\u00e9 Sagali",
        "Kobosi"
    ],
    "wof:name":"Kobosi",
    "wof:placetype":"locality"
},
  "geometry": {"coordinates":[13.31667,9.95],"type":"Point"}
}