{
  "type": "Feature",
  "properties": {
    "gn:admin1_code":"12.0",
    "gn:asciiname":"Dougoumbra",
    "gn:country_code":"CM",
    "gn:dem":302,
    "gn:feature_class":"P",
    "gn:feature_code":"PPL",
    "gn:name":"Dougoumbra",
    "gn:population":0,
    "gn:timezone":"Africa/Douala",
    "iso:country":"CM",
    "wof:name":"Dougoumbra",
    "wof:placetype":"locality"
},
  "geometry": {"coordinates":[14.92581,11.51277],"type":"Point"}
}