{
  "type": "Feature",
  "properties": {
    "gn:admin1_code":"14.0",
    "gn:asciiname":"Amwam",
    "gn:country_code":"CM",
    "gn:dem":630,
    "gn:feature_class":"P",
    "gn:feature_code":"PPL",
    "gn:name":"Amwam",
    "gn:population":0,
    "gn:timezone":"Africa/Douala",
    "iso:country":"CM",
    "wof:name":"Amwam",
    "wof:placetype":"locality"
},
  "geometry": {"coordinates":[11.21667,2.75],"type":"Point"}
}