{
  "type": "Feature",
  "properties": {
    "gn:admin1_code":"4.0",
    "gn:asciiname":"Daligene",
    "gn:country_code":"CM",
    "gn:dem":632,
    "gn:feature_class":"P",
    "gn:feature_code":"PPL",
    "gn:name":"Dalig\u00e9n\u00e9",
    "gn:population":0,
    "gn:timezone":"Africa/Douala",
    "iso:country":"CM",
    "name:und_x_variant":[
        "Daligu\u00e9n\u00e9",
        "Dalig\u00e9n\u00e9"
    ],
    "wof:name":"Daligene",
    "wof:placetype":"locality"
},
  "geometry": {"coordinates":[14.16667,4.43333],"type":"Point"}
}