{
  "type": "Feature",
  "properties": {
    "gn:admin1_code":"8.0",
    "gn:asciiname":"Mefou",
    "gn:country_code":"CM",
    "gn:dem":1546,
    "gn:feature_class":"P",
    "gn:feature_code":"PPL",
    "gn:name":"Mefou",
    "gn:population":0,
    "gn:timezone":"Africa/Douala",
    "iso:country":"CM",
    "wof:name":"Mefou",
    "wof:placetype":"locality"
},
  "geometry": {"coordinates":[10.19332,5.55261],"type":"Point"}
}