{
  "type": "Feature",
  "properties": {
    "gn:admin1_code":"9.0",
    "gn:asciiname":"Fuinya",
    "gn:country_code":"CM",
    "gn:dem":355,
    "gn:feature_class":"P",
    "gn:feature_code":"PPL",
    "gn:name":"Fuinya",
    "gn:population":0,
    "gn:timezone":"Africa/Douala",
    "iso:country":"CM",
    "wof:name":"Fuinya",
    "wof:placetype":"locality"
},
  "geometry": {"coordinates":[9.7151,5.2519],"type":"Point"}
}