{
  "type": "Feature",
  "properties": {
    "gn:admin1_code":"14.0",
    "gn:asciiname":"Mleboo",
    "gn:country_code":"CM",
    "gn:dem":735,
    "gn:feature_class":"P",
    "gn:feature_code":"PPL",
    "gn:name":"Ml\u00e9boo",
    "gn:population":0,
    "gn:timezone":"Africa/Douala",
    "iso:country":"CM",
    "wof:name":"Mleboo",
    "wof:placetype":"locality"
},
  "geometry": {"coordinates":[11.98333,2.56667],"type":"Point"}
}