{
  "type": "Feature",
  "properties": {
    "gn:admin1_code":"13.0",
    "gn:asciiname":"Kodeala",
    "gn:country_code":"CM",
    "gn:dem":517,
    "gn:feature_class":"P",
    "gn:feature_code":"PPL",
    "gn:name":"Kod\u00e9ala",
    "gn:population":0,
    "gn:timezone":"Africa/Douala",
    "iso:country":"CM",
    "wof:name":"Kodeala",
    "wof:placetype":"locality"
},
  "geometry": {"coordinates":[13.26667,8.23333],"type":"Point"}
}