{
  "type": "Feature",
  "properties": {
    "gn:admin1_code":"8.0",
    "gn:asciiname":"Louh",
    "gn:country_code":"CM",
    "gn:dem":1461,
    "gn:feature_class":"P",
    "gn:feature_code":"PPL",
    "gn:name":"Louh",
    "gn:population":0,
    "gn:timezone":"Africa/Douala",
    "iso:country":"CM",
    "wof:name":"Louh",
    "wof:placetype":"locality"
},
  "geometry": {"coordinates":[10.42552,5.16117],"type":"Point"}
}