{
  "type": "Feature",
  "properties": {
    "gn:admin1_code":"12.0",
    "gn:asciiname":"Medegouer",
    "gn:country_code":"CM",
    "gn:dem":488,
    "gn:feature_class":"P",
    "gn:feature_code":"PPL",
    "gn:name":"M\u00e9d\u00e9gouer",
    "gn:population":0,
    "gn:timezone":"Africa/Douala",
    "iso:country":"CM",
    "name:und_x_variant":[
        "M\u00e9d\u00e9gwer",
        "M\u00e9d\u00e9gouer",
        "M\u00e9d\u00e9gou\u00e8r"
    ],
    "wof:name":"Medegouer",
    "wof:placetype":"locality"
},
  "geometry": {"coordinates":[13.87026,10.94734],"type":"Point"}
}