{
  "type": "Feature",
  "properties": {
    "iso:country":"CM",
    "name:deu_x_preferred":[
        "Ngambe"
    ],
    "name:eng_x_preferred":[
        "Ngamb\u00e9"
    ],
    "name:fra_x_preferred":[
        "Ngambe"
    ],
    "name:nan_x_preferred":[
        "Ngambe"
    ],
    "name:nld_x_preferred":[
        "Ngamb\u00e9"
    ],
    "name:spa_x_preferred":[
        "Ngambe"
    ],
    "name:und_x_variant":[
        "Babimbi"
    ],
    "qs:gn_country":"CM",
    "qs:gn_fcode":"PPL",
    "qs:gn_pop":6414,
    "qs:name":"Ngamb\u00e9",
    "qs:name_adm0":"Cameroun",
    "qs:name_adm1":"Littoral",
    "qs:photos":0,
    "qs:photos_1k":0,
    "qs:photos_9k":0,
    "qs:photos_9r":0,
    "qs:photos_all":0,
    "qs:photos_sr":0,
    "qs:placetype":"Town",
    "qs:pop_sr":"5",
    "qs:woe_adm0":23424785,
    "wd:wordcount":85,
    "wof:name":"Ngamb\u00e9",
    "wof:placetype":"locality",
    "wof:population":6414
},
  "geometry": {"coordinates":[10.61667,4.23333],"type":"Point"}
}