{
  "type": "Feature",
  "properties": {
    "gn:admin1_code":"11.0",
    "gn:asciiname":"Awae Fala",
    "gn:country_code":"CM",
    "gn:dem":688,
    "gn:feature_class":"P",
    "gn:feature_code":"PPL",
    "gn:name":"Awa\u00e9 Fala",
    "gn:population":0,
    "gn:timezone":"Africa/Douala",
    "iso:country":"CM",
    "wof:name":"Awae Fala",
    "wof:placetype":"locality"
},
  "geometry": {"coordinates":[11.53333,3.16667],"type":"Point"}
}