{
  "type": "Feature",
  "properties": {
    "gn:admin1_code":"12.0",
    "gn:asciiname":"Kessagana",
    "gn:country_code":"CM",
    "gn:dem":315,
    "gn:feature_class":"P",
    "gn:feature_code":"PPL",
    "gn:name":"K\u00e9ssagana",
    "gn:population":0,
    "gn:timezone":"Africa/Douala",
    "iso:country":"CM",
    "wof:name":"Kessagana",
    "wof:placetype":"locality"
},
  "geometry": {"coordinates":[14.3886,11.14346],"type":"Point"}
}