{
  "type": "Feature",
  "properties": {
    "gn:admin1_code":"13.0",
    "gn:asciiname":"Metadiam",
    "gn:country_code":"CM",
    "gn:dem":375,
    "gn:feature_class":"P",
    "gn:feature_code":"PPL",
    "gn:name":"M\u00e9tadiam",
    "gn:population":0,
    "gn:timezone":"Africa/Douala",
    "iso:country":"CM",
    "wof:name":"Metadiam",
    "wof:placetype":"locality"
},
  "geometry": {"coordinates":[13.06315,8.24995],"type":"Point"}
}