{
  "type": "Feature",
  "properties": {
    "gn:admin1_code":"4.0",
    "gn:asciiname":"Nyimbe",
    "gn:country_code":"CM",
    "gn:dem":693,
    "gn:feature_class":"P",
    "gn:feature_code":"PPL",
    "gn:name":"Nyimb\u00e9",
    "gn:population":0,
    "gn:timezone":"Africa/Douala",
    "iso:country":"CM",
    "wof:name":"Nyimbe",
    "wof:placetype":"locality"
},
  "geometry": {"coordinates":[12.95,3.98333],"type":"Point"}
}