{
  "type": "Feature",
  "properties": {
    "gn:admin1_code":"5.0",
    "gn:asciiname":"Ndokok",
    "gn:country_code":"CM",
    "gn:dem":143,
    "gn:feature_class":"P",
    "gn:feature_code":"PPL",
    "gn:name":"Ndokok",
    "gn:population":0,
    "gn:timezone":"Africa/Douala",
    "iso:country":"CM",
    "name:und_x_variant":[
        "Dokko",
        "Ndokok"
    ],
    "wof:name":"Ndokok",
    "wof:placetype":"locality"
},
  "geometry": {"coordinates":[10.28333,3.83333],"type":"Point"}
}