{
  "type": "Feature",
  "properties": {
    "gn:admin1_code":"4.0",
    "gn:asciiname":"Efoulan",
    "gn:country_code":"CM",
    "gn:dem":669,
    "gn:feature_class":"P",
    "gn:feature_code":"PPL",
    "gn:name":"Efoulan",
    "gn:population":0,
    "gn:timezone":"Africa/Douala",
    "iso:country":"CM",
    "name:fra_x_preferred":[
        "Efoulan"
    ],
    "name:msa_x_preferred":[
        "Efoulan"
    ],
    "name:spa_x_preferred":[
        "Efoulan"
    ],
    "wof:name":"Efoulan",
    "wof:placetype":"locality"
},
  "geometry": {"coordinates":[12.81667,4.13333],"type":"Point"}
}