{
  "type": "Feature",
  "properties": {
    "gn:admin1_code":"9.0",
    "gn:asciiname":"Fomanji",
    "gn:country_code":"CM",
    "gn:dem":1835,
    "gn:feature_class":"P",
    "gn:feature_code":"PPL",
    "gn:name":"Fomanji",
    "gn:population":0,
    "gn:timezone":"Africa/Douala",
    "iso:country":"CM",
    "name:fra_x_preferred":[
        "Fomanji"
    ],
    "wof:name":"Fomanji",
    "wof:placetype":"locality"
},
  "geometry": {"coordinates":[10.00447,5.70709],"type":"Point"}
}