{
  "type": "Feature",
  "properties": {
    "gn:admin1_code":"8.0",
    "gn:asciiname":"Makia Mezoung",
    "gn:country_code":"CM",
    "gn:dem":1478,
    "gn:feature_class":"P",
    "gn:feature_code":"PPL",
    "gn:name":"Makia Mezoung",
    "gn:population":0,
    "gn:timezone":"Africa/Douala",
    "iso:country":"CM",
    "wof:name":"Makia Mezoung",
    "wof:placetype":"locality"
},
  "geometry": {"coordinates":[10.13001,5.40991],"type":"Point"}
}