{
  "type": "Feature",
  "properties": {
    "gn:admin1_code":"12.0",
    "gn:asciiname":"Membeng",
    "gn:country_code":"CM",
    "gn:dem":552,
    "gn:feature_class":"P",
    "gn:feature_code":"PPL",
    "gn:name":"Membeng",
    "gn:population":0,
    "gn:timezone":"Africa/Douala",
    "iso:country":"CM",
    "name:und_x_variant":[
        "Minbing"
    ],
    "wof:name":"Membeng",
    "wof:placetype":"locality"
},
  "geometry": {"coordinates":[13.93663,10.43062],"type":"Point"}
}