{
  "type": "Feature",
  "properties": {
    "gn:admin1_code":"8.0",
    "gn:asciiname":"Fotsemlesseng",
    "gn:country_code":"CM",
    "gn:dem":1443,
    "gn:feature_class":"P",
    "gn:feature_code":"PPL",
    "gn:name":"Fotsemlesseng",
    "gn:population":0,
    "gn:timezone":"Africa/Douala",
    "iso:country":"CM",
    "name:fra_x_preferred":[
        "Folessing"
    ],
    "name:fra_x_variant":[
        "Fotsemlessing"
    ],
    "wof:name":"Fotsemlesseng",
    "wof:placetype":"locality"
},
  "geometry": {"coordinates":[10.07348,5.35467],"type":"Point"}
}