{
  "type": "Feature",
  "properties": {
    "gn:admin1_code":"13.0",
    "gn:asciiname":"Perni",
    "gn:country_code":"CM",
    "gn:dem":568,
    "gn:feature_class":"P",
    "gn:feature_code":"PPL",
    "gn:name":"Perni",
    "gn:population":0,
    "gn:timezone":"Africa/Douala",
    "iso:country":"CM",
    "wof:name":"Perni",
    "wof:placetype":"locality"
},
  "geometry": {"coordinates":[13.57544,10.03311],"type":"Point"}
}