{
  "type": "Feature",
  "properties": {
    "gn:admin1_code":"14.0",
    "gn:asciiname":"Bernbe",
    "gn:country_code":"CM",
    "gn:dem":612,
    "gn:feature_class":"P",
    "gn:feature_code":"PPL",
    "gn:name":"Bernb\u00e9",
    "gn:population":0,
    "gn:timezone":"Africa/Douala",
    "iso:country":"CM",
    "wof:name":"Bernbe",
    "wof:placetype":"locality"
},
  "geometry": {"coordinates":[11.25,2.93333],"type":"Point"}
}