{
  "type": "Feature",
  "properties": {
    "gn:admin1_code":"8.0",
    "gn:asciiname":"Bandjisso II",
    "gn:country_code":"CM",
    "gn:dem":1279,
    "gn:feature_class":"P",
    "gn:feature_code":"PPL",
    "gn:name":"Bandjisso II",
    "gn:population":0,
    "gn:timezone":"Africa/Douala",
    "iso:country":"CM",
    "name:fra_x_preferred":[
        "Bajinso"
    ],
    "wof:name":"Bandjisso II",
    "wof:placetype":"locality"
},
  "geometry": {"coordinates":[10.31605,5.59143],"type":"Point"}
}