{
  "type": "Feature",
  "properties": {
    "gn:admin1_code":"12.0",
    "gn:asciiname":"Nsoro",
    "gn:country_code":"CM",
    "gn:dem":288,
    "gn:feature_class":"P",
    "gn:feature_code":"PPL",
    "gn:name":"Nsoro",
    "gn:population":0,
    "gn:timezone":"Africa/Douala",
    "iso:country":"CM",
    "wof:name":"Nsoro",
    "wof:placetype":"locality"
},
  "geometry": {"coordinates":[14.68382,12.55338],"type":"Point"}
}