{
  "type": "Feature",
  "properties": {
    "gn:admin1_code":"8.0",
    "gn:asciiname":"Fonegom",
    "gn:country_code":"CM",
    "gn:dem":1497,
    "gn:feature_class":"P",
    "gn:feature_code":"PPL",
    "gn:name":"Fonegom",
    "gn:population":0,
    "gn:timezone":"Africa/Douala",
    "iso:country":"CM",
    "name:fra_x_preferred":[
        "Fo Negom"
    ],
    "wof:name":"Fonegom",
    "wof:placetype":"locality"
},
  "geometry": {"coordinates":[10.4672,5.35505],"type":"Point"}
}