{
  "type": "Feature",
  "properties": {
    "gn:admin1_code":"4.0",
    "gn:asciiname":"Lelo",
    "gn:country_code":"CM",
    "gn:dem":630,
    "gn:feature_class":"P",
    "gn:feature_code":"PPL",
    "gn:name":"L\u00e9lo",
    "gn:population":0,
    "gn:timezone":"Africa/Douala",
    "iso:country":"CM",
    "name:ceb_x_preferred":[
        "Lelo"
    ],
    "name:fra_x_preferred":[
        "Lelo"
    ],
    "name:swe_x_preferred":[
        "Lelo"
    ],
    "wof:name":"Lelo",
    "wof:placetype":"locality"
},
  "geometry": {"coordinates":[14.11667,4.33333],"type":"Point"}
}