{
  "type": "Feature",
  "properties": {
    "gn:admin1_code":"8.0",
    "gn:asciiname":"Toula",
    "gn:country_code":"CM",
    "gn:dem":1442,
    "gn:feature_class":"P",
    "gn:feature_code":"PPL",
    "gn:name":"Toula",
    "gn:population":0,
    "gn:timezone":"Africa/Douala",
    "iso:country":"CM",
    "name:ceb_x_preferred":[
        "Toula"
    ],
    "name:fra_x_preferred":[
        "Toula"
    ],
    "name:swe_x_preferred":[
        "Toula"
    ],
    "wof:name":"Toula",
    "wof:placetype":"locality"
},
  "geometry": {"coordinates":[10.47189,5.2775],"type":"Point"}
}