{
  "type": "Feature",
  "properties": {
    "gn:admin1_code":"8.0",
    "gn:asciiname":"Nzenkop",
    "gn:country_code":"CM",
    "gn:dem":1514,
    "gn:feature_class":"P",
    "gn:feature_code":"PPL",
    "gn:name":"Nzenkop",
    "gn:population":0,
    "gn:timezone":"Africa/Douala",
    "iso:country":"CM",
    "name:und_x_variant":[
        "Nzenkop II"
    ],
    "wof:name":"Nzenkop",
    "wof:placetype":"locality"
},
  "geometry": {"coordinates":[10.10815,5.48193],"type":"Point"}
}