{
  "type": "Feature",
  "properties": {
    "gn:admin1_code":"5.0",
    "gn:asciiname":"Kangue",
    "gn:country_code":"CM",
    "gn:dem":1,
    "gn:feature_class":"P",
    "gn:feature_code":"PPL",
    "gn:name":"Kangu\u00e9",
    "gn:population":0,
    "gn:timezone":"Africa/Douala",
    "iso:country":"CM",
    "wof:name":"Kangue",
    "wof:placetype":"locality"
},
  "geometry": {"coordinates":[9.34732,3.90911],"type":"Point"}
}