{
  "type": "Feature",
  "properties": {
    "gn:admin1_code":"10.0",
    "gn:asciiname":"Gankoumbol",
    "gn:country_code":"CM",
    "gn:dem":957,
    "gn:feature_class":"P",
    "gn:feature_code":"PPL",
    "gn:name":"Gankoumbol",
    "gn:population":0,
    "gn:timezone":"Africa/Douala",
    "iso:country":"CM",
    "name:und_x_variant":[
        "Gaukumbal",
        "Gaukoumboum",
        "Gamkoumbon",
        "Gankoumbol"
    ],
    "wof:name":"Gankoumbol",
    "wof:placetype":"locality"
},
  "geometry": {"coordinates":[14.36667,6.26667],"type":"Point"}
}