{
  "type": "Feature",
  "properties": {
    "gn:admin1_code":"8.0",
    "gn:asciiname":"Nkwetkwet",
    "gn:country_code":"CM",
    "gn:dem":1100,
    "gn:feature_class":"P",
    "gn:feature_code":"PPL",
    "gn:name":"Nkwetkwet",
    "gn:population":0,
    "gn:timezone":"Africa/Douala",
    "iso:country":"CM",
    "wof:name":"Nkwetkwet",
    "wof:placetype":"locality"
},
  "geometry": {"coordinates":[10.62216,5.54383],"type":"Point"}
}