{
  "type": "Feature",
  "properties": {
    "gn:admin1_code":"5.0",
    "gn:asciiname":"Bonepoupa II",
    "gn:country_code":"CM",
    "gn:dem":31,
    "gn:feature_class":"P",
    "gn:feature_code":"PPL",
    "gn:name":"Bon\u00e9poupa II",
    "gn:population":0,
    "gn:timezone":"Africa/Douala",
    "iso:country":"CM",
    "wof:name":"Bonepoupa II",
    "wof:placetype":"locality"
},
  "geometry": {"coordinates":[9.9957,4.1532],"type":"Point"}
}