{
  "type": "Feature",
  "properties": {
    "gn:admin1_code":"12.0",
    "gn:asciiname":"Markanday",
    "gn:country_code":"CM",
    "gn:dem":852,
    "gn:feature_class":"P",
    "gn:feature_code":"PPL",
    "gn:name":"Markanday",
    "gn:population":0,
    "gn:timezone":"Africa/Douala",
    "iso:country":"CM",
    "name:und_x_variant":[
        "Makanday",
        "Markanday"
    ],
    "wof:name":"Markanday",
    "wof:placetype":"locality"
},
  "geometry": {"coordinates":[13.841,10.81875],"type":"Point"}
}