{
  "type": "Feature",
  "properties": {
    "gn:admin1_code":"5.0",
    "gn:asciiname":"Bossamba",
    "gn:country_code":"CM",
    "gn:dem":41,
    "gn:feature_class":"P",
    "gn:feature_code":"PPL",
    "gn:name":"Bossamba",
    "gn:population":0,
    "gn:timezone":"Africa/Douala",
    "iso:country":"CM",
    "wof:name":"Bossamba",
    "wof:placetype":"locality"
},
  "geometry": {"coordinates":[9.754,4.2221],"type":"Point"}
}