{
  "type": "Feature",
  "properties": {
    "gn:admin1_code":"13.0",
    "gn:asciiname":"Siti",
    "gn:country_code":"CM",
    "gn:dem":344,
    "gn:feature_class":"P",
    "gn:feature_code":"PPL",
    "gn:name":"Siti",
    "gn:population":0,
    "gn:timezone":"Africa/Douala",
    "iso:country":"CM",
    "wof:name":"Siti",
    "wof:placetype":"locality"
},
  "geometry": {"coordinates":[13.43852,8.491],"type":"Point"}
}