{
  "type": "Feature",
  "properties": {
    "gn:admin1_code":"4.0",
    "gn:asciiname":"Gwonepoum",
    "gn:country_code":"CM",
    "gn:dem":620,
    "gn:feature_class":"P",
    "gn:feature_code":"PPL",
    "gn:name":"Gwonepoum",
    "gn:population":0,
    "gn:timezone":"Africa/Douala",
    "iso:country":"CM",
    "name:und_x_variant":[
        "Ss\u00e9ke\u2019s",
        "Goamiboum",
        "Goaningpoum",
        "Goaningpum",
        "Gwonepoum"
    ],
    "wof:name":"Gwonepoum",
    "wof:placetype":"locality"
},
  "geometry": {"coordinates":[14.63333,2.76667],"type":"Point"}
}