{
  "type": "Feature",
  "properties": {
    "gn:admin1_code":"13.0",
    "gn:asciiname":"Barkao",
    "gn:country_code":"CM",
    "gn:dem":445,
    "gn:feature_class":"P",
    "gn:feature_code":"PPL",
    "gn:name":"Barkao",
    "gn:population":0,
    "gn:timezone":"Africa/Douala",
    "iso:country":"CM",
    "wof:name":"Barkao",
    "wof:placetype":"locality"
},
  "geometry": {"coordinates":[13.78585,10.07836],"type":"Point"}
}