{
  "type": "Feature",
  "properties": {
    "gn:admin1_code":"13.0",
    "gn:asciiname":"Donka",
    "gn:country_code":"CM",
    "gn:dem":986,
    "gn:feature_class":"P",
    "gn:feature_code":"PPL",
    "gn:name":"Donka",
    "gn:population":0,
    "gn:timezone":"Africa/Douala",
    "iso:country":"CM",
    "wof:name":"Donka",
    "wof:placetype":"locality"
},
  "geometry": {"coordinates":[13.3448,10.04675],"type":"Point"}
}