{
  "type": "Feature",
  "properties": {
    "gn:admin1_code":"8.0",
    "gn:asciiname":"Kem",
    "gn:country_code":"CM",
    "gn:dem":1762,
    "gn:feature_class":"P",
    "gn:feature_code":"PPL",
    "gn:name":"Kem",
    "gn:population":0,
    "gn:timezone":"Africa/Douala",
    "iso:country":"CM",
    "wof:name":"Kem",
    "wof:placetype":"locality"
},
  "geometry": {"coordinates":[10.33596,5.25727],"type":"Point"}
}