{
  "type": "Feature",
  "properties": {
    "gn:admin1_code":"8.0",
    "gn:asciiname":"Kem",
    "gn:country_code":"CM",
    "gn:dem":1762,
    "gn:feature_class":"P",
    "gn:feature_code":"PPL",
    "gn:name":"Kem",
    "gn:population":0,
    "gn:timezone":"Africa/Douala",
    "iso:country":"CM",
    "name:ara_x_preferred":[
        "\u0643\u064a\u0645"
    ],
    "name:bel_x_preferred":[
        "\u041a\u0435\u043c"
    ],
    "name:ben_x_preferred":[
        "\u0995\u09c7\u09ae"
    ],
    "name:ces_x_preferred":[
        "Kem"
    ],
    "name:ell_x_preferred":[
        "\u039a\u03b5\u03bc"
    ],
    "name:fin_x_preferred":[
        "Kem"
    ],
    "name:fra_x_preferred":[
        "Kem"
    ],
    "name:heb_x_preferred":[
        "\u05e7\u05b6\u05dd"
    ],
    "name:hin_x_preferred":[
        "\u0915\u0947\u092e"
    ],
    "name:hsb_x_preferred":[
        "Kem"
    ],
    "name:hun_x_preferred":[
        "Kem"
    ],
    "name:ind_x_preferred":[
        "Kem"
    ],
    "name:ita_x_preferred":[
        "Kem'"
    ],
    "name:kor_x_preferred":[
        "\ucf10"
    ],
    "name:nld_x_preferred":[
        "Kem"
    ],
    "name:nor_x_preferred":[
        "KEM"
    ],
    "name:pol_x_preferred":[
        "Kem"
    ],
    "name:por_x_preferred":[
        "Kem"
    ],
    "name:rus_x_preferred":[
        "\u041a\u0435\u043c\u044c"
    ],
    "name:sco_x_preferred":[
        "Kem"
    ],
    "name:spa_x_preferred":[
        "Kem"
    ],
    "name:tur_x_preferred":[
        "Kem"
    ],
    "name:urd_x_preferred":[
        "\u06a9\u06cc\u0645"
    ],
    "name:vep_x_preferred":[
        "Kem'"
    ],
    "name:vie_x_preferred":[
        "S\u00f4ng Kem"
    ],
    "name:vie_x_variant":[
        "Kem"
    ],
    "wof:name":"Kem",
    "wof:placetype":"locality"
},
  "geometry": {"coordinates":[10.33596,5.25727],"type":"Point"}
}