{
  "type": "Feature",
  "properties": {
    "gn:admin1_code":"14.0",
    "gn:asciiname":"Azem",
    "gn:country_code":"CM",
    "gn:dem":590,
    "gn:feature_class":"P",
    "gn:feature_code":"PPL",
    "gn:name":"Azem",
    "gn:population":0,
    "gn:timezone":"Africa/Douala",
    "iso:country":"CM",
    "wof:name":"Azem",
    "wof:placetype":"locality"
},
  "geometry": {"coordinates":[11.15,2.86667],"type":"Point"}
}