{
  "type": "Feature",
  "properties": {
    "gn:admin1_code":"7.0",
    "gn:asciiname":"Ntopeli",
    "gn:country_code":"CM",
    "gn:dem":1175,
    "gn:feature_class":"P",
    "gn:feature_code":"PPL",
    "gn:name":"Ntopeli",
    "gn:population":0,
    "gn:timezone":"Africa/Douala",
    "iso:country":"CM",
    "name:fra_x_preferred":[
        "Ntopeli"
    ],
    "wof:name":"Ntopeli",
    "wof:placetype":"locality"
},
  "geometry": {"coordinates":[10.50929,5.89432],"type":"Point"}
}