{
  "type": "Feature",
  "properties": {
    "gn:admin1_code":"12.0",
    "gn:asciiname":"Petchime",
    "gn:country_code":"CM",
    "gn:dem":679,
    "gn:feature_class":"P",
    "gn:feature_code":"PPL",
    "gn:name":"Petchim\u00e9",
    "gn:population":0,
    "gn:timezone":"Africa/Douala",
    "iso:country":"CM",
    "wof:name":"Petchime",
    "wof:placetype":"locality"
},
  "geometry": {"coordinates":[13.85932,10.84368],"type":"Point"}
}