{
  "type": "Feature",
  "properties": {
    "gn:admin1_code":"11.0",
    "gn:asciiname":"Nyenge",
    "gn:country_code":"CM",
    "gn:dem":679,
    "gn:feature_class":"P",
    "gn:feature_code":"PPL",
    "gn:name":"Nyeng\u00e9",
    "gn:population":0,
    "gn:timezone":"Africa/Douala",
    "iso:country":"CM",
    "wof:name":"Nyenge",
    "wof:placetype":"locality"
},
  "geometry": {"coordinates":[11.13333,3.43333],"type":"Point"}
}