{
  "type": "Feature",
  "properties": {
    "gn:admin1_code":"12.0",
    "gn:asciiname":"Marafil",
    "gn:country_code":"CM",
    "gn:dem":293,
    "gn:feature_class":"P",
    "gn:feature_code":"PPL",
    "gn:name":"Marafil",
    "gn:population":0,
    "gn:timezone":"Africa/Douala",
    "iso:country":"CM",
    "wof:name":"Marafil",
    "wof:placetype":"locality"
},
  "geometry": {"coordinates":[14.71607,12.37437],"type":"Point"}
}