{
  "type": "Feature",
  "properties": {
    "gn:admin1_code":"9.0",
    "gn:asciiname":"Kombo a Janea",
    "gn:country_code":"CM",
    "gn:dem":15,
    "gn:feature_class":"P",
    "gn:feature_code":"PPL",
    "gn:name":"Kombo a Janea",
    "gn:population":0,
    "gn:timezone":"Africa/Douala",
    "iso:country":"CM",
    "wof:name":"Kombo a Janea",
    "wof:placetype":"locality"
},
  "geometry": {"coordinates":[8.5567,4.5996],"type":"Point"}
}