{
  "type": "Feature",
  "properties": {
    "gn:admin1_code":"11.0",
    "gn:asciiname":"Ebebda I",
    "gn:country_code":"CM",
    "gn:dem":404,
    "gn:feature_class":"P",
    "gn:feature_code":"PPL",
    "gn:name":"\u00c9bebda I",
    "gn:population":0,
    "gn:timezone":"Africa/Douala",
    "iso:country":"CM",
    "wof:name":"Ebebda I",
    "wof:placetype":"locality"
},
  "geometry": {"coordinates":[11.28333,4.33333],"type":"Point"}
}