{
  "type": "Feature",
  "properties": {
    "gn:admin1_code":"11.0",
    "gn:asciiname":"Ngat",
    "gn:country_code":"CM",
    "gn:dem":709,
    "gn:feature_class":"P",
    "gn:feature_code":"PPL",
    "gn:name":"Ngat",
    "gn:population":0,
    "gn:timezone":"Africa/Douala",
    "iso:country":"CM",
    "wof:name":"Ngat",
    "wof:placetype":"locality"
},
  "geometry": {"coordinates":[11.98333,3.85],"type":"Point"}
}