{
  "type": "Feature",
  "properties": {
    "gn:admin1_code":"12.0",
    "gn:asciiname":"Rouva",
    "gn:country_code":"CM",
    "gn:dem":809,
    "gn:feature_class":"P",
    "gn:feature_code":"PPL",
    "gn:name":"Rouva",
    "gn:population":0,
    "gn:timezone":"Africa/Douala",
    "iso:country":"CM",
    "name:und_x_variant":[
        "Ouva",
        "Rouva",
        "Kouva"
    ],
    "wof:name":"Rouva",
    "wof:placetype":"locality"
},
  "geometry": {"coordinates":[13.82354,10.81929],"type":"Point"}
}