{
  "type": "Feature",
  "properties": {
    "gn:admin1_code":"12.0",
    "gn:asciiname":"Larie",
    "gn:country_code":"CM",
    "gn:dem":401,
    "gn:feature_class":"P",
    "gn:feature_code":"PPL",
    "gn:name":"Lari\u00e9",
    "gn:population":0,
    "gn:timezone":"Africa/Douala",
    "iso:country":"CM",
    "name:und_x_variant":[
        "Laari\u00e9",
        "Lari\u00e9"
    ],
    "wof:name":"Larie",
    "wof:placetype":"locality"
},
  "geometry": {"coordinates":[14.43407,10.47699],"type":"Point"}
}