{
  "type": "Feature",
  "properties": {
    "gn:admin1_code":"12.0",
    "gn:asciiname":"Nogagueyguey",
    "gn:country_code":"CM",
    "gn:dem":392,
    "gn:feature_class":"P",
    "gn:feature_code":"PPL",
    "gn:name":"Nogagu\u00e9ygu\u00e9y",
    "gn:population":0,
    "gn:timezone":"Africa/Douala",
    "iso:country":"CM",
    "wof:name":"Nogagueyguey",
    "wof:placetype":"locality"
},
  "geometry": {"coordinates":[13.93696,11.11473],"type":"Point"}
}