{
  "type": "Feature",
  "properties": {
    "gn:admin1_code":"8.0",
    "gn:asciiname":"Nka'ndepa'",
    "gn:country_code":"CM",
    "gn:dem":1807,
    "gn:feature_class":"P",
    "gn:feature_code":"PPL",
    "gn:name":"Nka\u2019ndepa\u2019",
    "gn:population":0,
    "gn:timezone":"Africa/Douala",
    "iso:country":"CM",
    "wof:name":"Nka'ndepa'",
    "wof:placetype":"locality"
},
  "geometry": {"coordinates":[10.40592,5.26882],"type":"Point"}
}