{
  "type": "Feature",
  "properties": {
    "gn:admin1_code":"7.0",
    "gn:asciiname":"Bwotong",
    "gn:country_code":"CM",
    "gn:dem":693,
    "gn:feature_class":"P",
    "gn:feature_code":"PPL",
    "gn:name":"Bwotong",
    "gn:population":0,
    "gn:timezone":"Africa/Douala",
    "iso:country":"CM",
    "wof:name":"Bwotong",
    "wof:placetype":"locality"
},
  "geometry": {"coordinates":[9.9595,6.3306],"type":"Point"}
}