{
  "type": "Feature",
  "properties": {
    "gn:admin1_code":"12.0",
    "gn:asciiname":"Mokola",
    "gn:country_code":"CM",
    "gn:dem":786,
    "gn:feature_class":"P",
    "gn:feature_code":"PPL",
    "gn:name":"Mokola",
    "gn:population":0,
    "gn:timezone":"Africa/Douala",
    "iso:country":"CM",
    "wof:name":"Mokola",
    "wof:placetype":"locality"
},
  "geometry": {"coordinates":[13.83447,10.75893],"type":"Point"}
}