{
  "type": "Feature",
  "properties": {
    "gn:admin1_code":"14.0",
    "gn:asciiname":"Mfem",
    "gn:country_code":"CM",
    "gn:dem":635,
    "gn:feature_class":"P",
    "gn:feature_code":"PPL",
    "gn:name":"Mfem",
    "gn:population":0,
    "gn:timezone":"Africa/Douala",
    "iso:country":"CM",
    "wof:name":"Mfem",
    "wof:placetype":"locality"
},
  "geometry": {"coordinates":[12.66667,2.53333],"type":"Point"}
}