{
  "type": "Feature",
  "properties": {
    "gn:admin1_code":"12.0",
    "gn:asciiname":"Goulouri",
    "gn:country_code":"CM",
    "gn:dem":307,
    "gn:feature_class":"P",
    "gn:feature_code":"PPL",
    "gn:name":"Goulouri",
    "gn:population":0,
    "gn:timezone":"Africa/Douala",
    "iso:country":"CM",
    "wof:name":"Goulouri",
    "wof:placetype":"locality"
},
  "geometry": {"coordinates":[14.41832,11.38084],"type":"Point"}
}