{
  "type": "Feature",
  "properties": {
    "gn:admin1_code":"13.0",
    "gn:asciiname":"Ouro Bah",
    "gn:country_code":"CM",
    "gn:dem":284,
    "gn:feature_class":"P",
    "gn:feature_code":"PPL",
    "gn:name":"Ouro Bah",
    "gn:population":0,
    "gn:timezone":"Africa/Douala",
    "iso:country":"CM",
    "wof:name":"Ouro Bah",
    "wof:placetype":"locality"
},
  "geometry": {"coordinates":[13.83451,9.13232],"type":"Point"}
}