{
  "type": "Feature",
  "properties": {
    "gn:admin1_code":"11.0",
    "gn:asciiname":"Mbeyinge",
    "gn:country_code":"CM",
    "gn:dem":708,
    "gn:feature_class":"P",
    "gn:feature_code":"PPL",
    "gn:name":"Mb\u00e9ying\u00e9",
    "gn:population":0,
    "gn:timezone":"Africa/Douala",
    "iso:country":"CM",
    "wof:name":"Mbeyinge",
    "wof:placetype":"locality"
},
  "geometry": {"coordinates":[11.31667,3.71667],"type":"Point"}
}