{
  "type": "Feature",
  "properties": {
    "gn:admin1_code":"8.0",
    "gn:asciiname":"Kekem",
    "gn:country_code":"CM",
    "gn:dem":714,
    "gn:feature_class":"P",
    "gn:feature_code":"PPL",
    "gn:name":"Kekem",
    "gn:population":0,
    "gn:timezone":"Africa/Douala",
    "iso:country":"CM",
    "name:ceb_x_preferred":[
        "Kekem"
    ],
    "name:fra_x_preferred":[
        "Kekem"
    ],
    "name:ita_x_preferred":[
        "K\u00e9kem"
    ],
    "name:msa_x_preferred":[
        "K\u00e9kem"
    ],
    "name:pol_x_preferred":[
        "K\u00e9kem"
    ],
    "name:spa_x_preferred":[
        "K\u00e9kem"
    ],
    "name:swe_x_preferred":[
        "Kekem"
    ],
    "wof:name":"Kekem",
    "wof:placetype":"locality"
},
  "geometry": {"coordinates":[10.01996,5.15689],"type":"Point"}
}